Workbook

Sheet 素材需求
A1: 网梗收容：奶龙失效｜美术素材需求
A2: 按当前实现与用户美术指南整理 · 先看「生成规范」，再按 P0 和依赖顺序生产
A4: 需求组 | B4: =COUNTA(A8:A112) -> 105 | D4: 独立 PNG / 单姿势图 | E4: =SUM(L8:L112) -> 288 | G4: P0 生成需求组 | H4: =COUNTIFS(B8:B112,"P0",L8:L112,">0") -> 64 | J4: 程序保留组 | K4: =COUNTIF(L8:L112,0) -> 3
A5: 查看列 D–H 获取命名、要求和参考对象；O 列为可填写进度。详细导出/轴点/来源见右侧列。
A7: 需求ID | B7: 优先级 | C7: 素材类别 | D7: 素材命名（组） | E7: 中文名称 | F7: 状态 / 用途 | G7: 素材生成要求 | H7: 素材参考对象 / 借鉴点 | I7: 参考图ID | J7: 建议生成画布 | K7: 交付类型 | L7: 文件数 | M7: 前置需求ID | N7: 策划 / 美术验收 | O7: 生产状态（填写） | P7: 导出 / 后处理 | Q7: 轴点 / 对齐 | R7: 当前实现来源 | S7: 特有禁止项 | T7: 备注 / 复用说明
A8: STA_001 | B8: P0 | C8: 员工/形体定稿 | D8: agent_base_idle_01 | E8: 员工通用基型定稿 | F8: IDLE | G8: 原创怪诞手绘收容风：不均匀粗墨外轮廓、较细结构线、局部不对称、平涂和少量排线；轮廓在游戏缩小尺寸仍清楚。 约 3 头身，大头、小而窄的工业外套躯干、细长四肢和厚底短靴；头略前倾、肩线不对称、神经质但仍是可工作的普通员工。灰绿制服 #68716c、旧纸肤色 #d9c6a5、少量铁锈/米白；不画英雄盔甲。用一位中性员工确定标准头颅、颈、肩、髋与手掌比例，服装含翻领、细领带和小工牌。 | H8: 当前 E01–E06 的共用身体及怪诞手绘指南 | I8: REF_STAFF | J8: 1024 × 1024 px | K8: 定稿 | L8: 1 | M8: — | N8: 缩到约 66 世界像素高仍能辨认头、躯干、双臂双腿；脚底与注册线一致；黑白剪影可读；与五物相比体量较小。 | O8: 待生成 | P8: 单个 RGBA 透明 PNG，sRGB，无底色和阴影背景，保留透明边距。 | Q8: 脚底地面中心；1024 × 1024 定稿统一注册点 (512, 896)，朝右；左向由引擎镜像。 | R8: src/scenes/facility/actors.ts :: drawHuman / SKIN / UNIFORM；用户提供《美术替换指南》 | S8: 不要照片、3D 渲染、像素风、光滑矢量图标风或高饱和日漫；不要复制现成游戏的角色、脸型或官方 IP 素材；不要背景、文字、水印、UI、血条、黄色选中圈或攻击范围；不要以红色滤镜代替形变。 | T8: 只定一种可复用身体；六名员工不做六套全身图。制服 A00 和基础脸型属于此基型，发型与面部在后续拆件中独立。
A9: STA_002 | B9: P0 | C9: 员工/通用拆件 | D9: agent_base_parts_01 | E9: 员工共用身体与基础工作道具拆件 | F9: 通用 | G9: 承接 STA_001，交付 14 个身体件：无发无表情头 1、含制服躯干 1、上臂左右 2、前臂左右 2、手左右 2、大腿左右 2、小腿左右 2、鞋左右 2；另交制式短棍 W00 1、观察夹板 1，共 16 件。关节内侧补全被遮区域，袖口与手掌连接清楚。夹板为旧纸矩形、金属夹和两道手写痕，不生成可读字。短棍是朴素铁灰/锈色棍，不带能量核心。 以上为整套构成；每次只生成 「逐张提示词」本张范围 指定的一个独立件，不画整套平铺图。 | H9: 已批准的员工基型；当前 OBSERVE 夹板和 W00 | I9: REF_STAFF | J9: 身体装配母版 1024 × 1024 px；各身体件与手持物在相同坐标画布分别导出 | K9: 拆件 | L9: 16 | M9: STA_001 | N9: 零件数量和清单一致；手臂/腿弯曲时关节无白缝；同一骨架能组回基型；无需重画身体即可换发型、武器、防具。 | O9: 待生成 | P9: 16 个独立透明 PNG；同坐标母版导出，不自动裁切；另附可编辑分层源文件和挂点 JSON/表格（附属文件不另计素材数）。 分层源文件与挂点记录由后处理制作，不要求图像模型直接生成。 | Q9: 装配根为脚底 (512, 896)；头颈、肩、肘、腕、髋、膝、踝分别记录像素挂点；两道具记录握柄点。 | R9: src/scenes/facility/actors.ts :: drawHuman / drawWeapon(W00) | S9: 不要照片、3D 渲染、像素风、光滑矢量图标风或高饱和日漫；不要复制现成游戏的角色、脸型或官方 IP 素材；不要背景、文字、水印、UI、血条、黄色选中圈或攻击范围；不要以红色滤镜代替形变。 | T9: 14 个身体件 + 2 个基础道具。只交拆件不宣称已有骨骼动画；选中圈、阴影、受击射线仍由引擎绘制。
A10: STA_003 | B10: P0 | C10: 员工/发型 | D10: agent_hair_quiff_01 | E10: E01 向上尖束 | F10: 通用 | G10: 原创怪诞手绘收容风：不均匀粗墨外轮廓、较细结构线、局部不对称、平涂和少量排线；轮廓在游戏缩小尺寸仍清楚。 深灰发，前额一束不等长尖峰向上偏前，后脑轮廓压低；不要对称刺猬头。 所有发型套用同一头颅，不改变脸长、颈部或眼位；发色低饱和。 | H10: 当前 E01 对应发型和已批准共用头颅 | I10: REF_STAFF | J10: 1024 × 1024 px（沿用员工装配母版）；实际内容仅头部附近 | K10: 拆件 | L10: 1 | M10: STA_001 / STA_002 | N10: 只看剪影可区分其他五种发型；约 66 世界像素员工缩放下不遮眼，不用编号或颜色作为唯一差别。 | O10: 待生成 | P10: 1 个 RGBA 透明 PNG，保持与员工头件的注册坐标；不含头皮、脸、身体或背景。 | Q10: 跟随共用头骨/颈部挂点；保留母版像素位置，头部旋转时不滑离头皮。 | R10: src/scenes/facility/actors.ts :: drawHair(index=0) / HAIR | S10: 不要照片、3D 渲染、像素风、光滑矢量图标风或高饱和日漫；不要复制现成游戏的角色、脸型或官方 IP 素材；不要背景、文字、水印、UI、血条、黄色选中圈或攻击范围；不要以红色滤镜代替形变。 | T10: 不额外生产六套完整员工；后层头发与脸前配件由装配层级决定。
A11: STA_004 | B11: P0 | C11: 员工/发型 | D11: agent_hair_side_fringe_01 | E11: E02 侧扫斜刘海 | F11: 通用 | G11: 原创怪诞手绘收容风：不均匀粗墨外轮廓、较细结构线、局部不对称、平涂和少量排线；轮廓在游戏缩小尺寸仍清楚。 棕锈发，大块斜刘海由高侧扫到低侧，另一侧耳根露出；长度短，不盖住双眼和眼镜挂点。 所有发型套用同一头颅，不改变脸长、颈部或眼位；发色低饱和。 | H11: 当前 E02 对应发型和已批准共用头颅 | I11: REF_STAFF | J11: 1024 × 1024 px（沿用员工装配母版）；实际内容仅头部附近 | K11: 拆件 | L11: 1 | M11: STA_001 / STA_002 | N11: 只看剪影可区分其他五种发型；约 66 世界像素员工缩放下不遮眼，不用编号或颜色作为唯一差别。 | O11: 待生成 | P11: 1 个 RGBA 透明 PNG，保持与员工头件的注册坐标；不含头皮、脸、身体或背景。 | Q11: 跟随共用头骨/颈部挂点；保留母版像素位置，头部旋转时不滑离头皮。 | R11: src/scenes/facility/actors.ts :: drawHair(index=1) / HAIR | S11: 不要照片、3D 渲染、像素风、光滑矢量图标风或高饱和日漫；不要复制现成游戏的角色、脸型或官方 IP 素材；不要背景、文字、水印、UI、血条、黄色选中圈或攻击范围；不要以红色滤镜代替形变。 | T11: 不额外生产六套完整员工；后层头发与脸前配件由装配层级决定。
A12: STA_010 | B12: P0 | C12: 员工/动作参考 | D12: agent_locomotion_reference_01 | E12: 员工待机、行走与攀爬参考 | F12: IDLE / MOVING / TRANSIT | G12: 分别生成六个独立单姿参考：待机呼气/吸气 2 姿；行走左脚接触/右脚接触 2 姿；攀爬左手高/右手高 2 姿。保持大头小身与前倾；行走手脚反向、短而清楚的脚步；攀爬手脚沿竖直连接设施交替，不画跳跃、飞行或瞬移。每姿使用相同地面基线，攀爬显示参考握点。 每个独立交付文件只能含一个姿势；按 「逐张提示词」本张范围 逐张生成。 | H12: 批准的共用员工拆件及实际 moving/climbing/stride | I12: REF_STAFF | J12: 1024 × 1024 px / 姿势，全部统一比例与注册点 | K12: 动作参考 | L12: 6 | M12: STA_001 / STA_002 | N12: 同一个员工比例不漂移；左右支撑脚和握点明确；能指导拆件旋转与位移，但不以这些独立参考宣称已完成动画。 | O12: 待生成 | P12: 6 个独立透明 PNG，每个只含一个完整角色姿势；不拼 sheet、不画文字注释；挂点和姿势名另存文本。 | Q12: 每格脚底基准相同；攀爬显示根节点与握点，不能烘焙相机或楼梯背景。 | R12: src/scenes/facility/actors.ts :: HumanPose / drawHuman（moving / climbing / stride） | S12: 不要照片、3D 渲染、像素风、光滑矢量图标风或高饱和日漫；不要复制现成游戏的角色、脸型或官方 IP 素材；不要背景、文字、水印、UI、血条、黄色选中圈或攻击范围；不要以红色滤镜代替形变。 | T12: 此项是动画制作参考图组，不是已完成的 sprite 动画或图集；拆件、骨骼装配和循环制作仍需另行接入。动作只能读取模拟 time/stride/状态，暂停冻结。
A13: STA_011 | B13: P0 | C13: 员工/动作参考 | D13: agent_work_reference_01 | E13: 员工三类工作手势参考 | F13: OBSERVE / INTERACT / SOOTHE | G13: 分别生成六个独立单姿参考，每类起/落两姿：观察将夹板靠胸或举至面前、视线落在样本；互动一手试探前伸再收回、上身小幅靠近；安抚双手低位缓慢张开、身体略后倾。用不同手势节奏区别工作，不增加法杖、扫描枪、仪式或魔法。作业双脚留在相同工作点。 每个独立交付文件只能含一个姿势；按 「逐张提示词」本张范围 逐张生成。 | H13: drawHuman 的 workType 和原有夹板 | I13: REF_STAFF | J13: 1024 × 1024 px / 姿势，全部统一比例与注册点 | K13: 动作参考 | L13: 6 | M13: STA_001 / STA_002 | N13: 不依靠标题也能区分观察持板、互动探手、安抚双手；手掌不穿夹板，头发和躯干体积一致。 | O13: 待生成 | P13: 6 个独立透明 PNG，每个只含一个完整角色姿势；不拼 sheet、不画文字注释；挂点和姿势名另存文本。 | Q13: 每格相同脚底根节点；夹板挂腕/手掌，前伸只改变肢体局部，不改变工作点。 | R13: src/scenes/facility/actors.ts :: drawHuman（workType OBSERVE / INTERACT / SOOTHE） | S13: 不要照片、3D 渲染、像素风、光滑矢量图标风或高饱和日漫；不要复制现成游戏的角色、脸型或官方 IP 素材；不要背景、文字、水印、UI、血条、黄色选中圈或攻击范围；不要以红色滤镜代替形变。 | T13: 此项是动画制作参考图组，不是已完成的 sprite 动画或图集；拆件、骨骼装配和循环制作仍需另行接入。动作只能读取模拟 time/stride/状态，暂停冻结。
A14: STA_012 | B14: P0 | C14: 员工/动作参考 | D14: agent_distress_reference_01 | E14: 员工恐慌、受伤与本日倒地参考 | F14: PANICKED / HURT / LOW_HP / INCAPACITATED | G14: 分别生成六个独立单姿参考：恐慌站立和踉跄行走 2 姿（夸张张口、护头手、步态不协调）；受击瞬间回缩 1 姿；低 HP 弯腰护身但保持可移动 1 姿；本日重伤倒地的落姿与稳定倒地 2 姿。仅用少量抽象墨痕和衣物皱折；倒地身体卧倒在脚底注册点附近。不要把低 HP 画成拄杖或新增爬行状态。 每个独立交付文件只能含一个姿势；按 「逐张提示词」本张范围 逐张生成。 | H14: 当前真实员工 panic、hurt、hp<40%、INCAPACITATED 绘制 | I14: REF_STAFF | J14: 1024 × 1024 px / 姿势，全部统一比例与注册点 | K14: 动作参考 | L14: 6 | M14: STA_001 / STA_002 / STA_009 | N14: 恐慌、受击、低 HP、倒地从姿态上可区分；倒地不出现墓碑、灵魂、尸解或复活动作；低 HP 仅外观变化。 | O14: 待生成 | P14: 6 个独立透明 PNG，每个只含一个完整角色姿势；不拼 sheet、不画文字注释；挂点和姿势名另存文本。 | Q14: 倒地仍围绕原脚底根节点；直立姿与落姿保持同一坐标基准，不横向传送。 | R14: src/scenes/facility/actors.ts :: drawHuman（panic / injured / impact / INCAPACITATED） | S14: 不要照片、3D 渲染、像素风、光滑矢量图标风或高饱和日漫；不要复制现成游戏的角色、脸型或官方 IP 素材；不要背景、文字、水印、UI、血条、黄色选中圈或攻击范围；不要以红色滤镜代替形变。 不要永久死亡、自动医疗复活、血腥内脏、以低血量动画改变真实移动速度。 | T14: 此项是动画制作参考图组，不是已完成的 sprite 动画或图集；拆件、骨骼装配和循环制作仍需另行接入。动作只能读取模拟 time/stride/状态，暂停冻结。 游戏已有 INCAPACITATED 为本日离场，重试/下一日恢复；低 HP 受伤姿不修改数值速度。
A15: STA_013 | B15: P0 | C15: 员工/动作参考 | D15: agent_weapon_attack_reference_01 | E15: 员工统一持械与攻击挂点参考 | F15: SUPPRESSING / WINDUP / IMPACT | G15: 分别生成四个独立单姿参考：持械准备、前摇收臂、命中前送、收势。以制式短棍示范手、肘、肩的共用结构；爪套、喇叭与共振器的握点由拆件元数据说明，不再画五套完整人形。保持头部不突变、脚底不脱离实际位置，攻击动作不能暗示冲刺或位移技能。 每个独立交付文件只能含一个姿势；按 「逐张提示词」本张范围 逐张生成。 | H15: drawHuman 攻击分支与 drawWeapon 的 hand/facing/angle | I15: REF_STAFF | J15: 1024 × 1024 px / 姿势，全部统一比例与注册点 | K15: 动作参考 | L15: 4 | M15: STA_002 | N15: 前摇和命中姿势差异可读；同一腕点可替换五专属武器；无新增攻击距离、子弹或技能特效。 | O15: 待生成 | P15: 4 个独立透明 PNG，每个只含一个完整角色姿势；不拼 sheet、不画文字注释；挂点和姿势名另存文本。 | Q15: 全身根=脚底；武器根=握柄点；前后手层级明确。 | R15: src/scenes/facility/actors.ts :: drawHuman（attackPhase / windupEnd）/ drawWeapon | S15: 不要照片、3D 渲染、像素风、光滑矢量图标风或高饱和日漫；不要复制现成游戏的角色、脸型或官方 IP 素材；不要背景、文字、水印、UI、血条、黄色选中圈或攻击范围；不要以红色滤镜代替形变。 | T15: 此项是动画制作参考图组，不是已完成的 sprite 动画或图集；拆件、骨骼装配和循环制作仍需另行接入。动作只能读取模拟 time/stride/状态，暂停冻结。 时长、射程和伤害由现有 config/模拟决定，单姿参考图组不给固定帧率或命中时间。
A16: ABN_N01_01 | B16: P0 | C16: 五物/平静定稿 | D16: abn_nailong_idle_01 | E16: N01 奶龙 平静定稿 | F16: CONTAINED / IDLE | G16: 原创怪诞手绘收容风：不均匀粗墨外轮廓、较细结构线、局部不对称、平涂和少量排线；轮廓在游戏缩小尺寸仍清楚。 软黄梨形身体、奶油色圆肚、短手、宽扁脚、不对称短尾；头颈连成柔软长弧，两个小角一高一低，眼睛大小不一、口鼻略突出。主色黄 #d9b854、奶油 #e9d38c 和土黄阴影，呆软而非写实恐龙。 侧视略带正脸可读性，所有部位围绕单一脚底根节点，不画房间。 | H16: 当前 奶龙 室内未作业形态 | I16: REF_N01_CALM | J16: 1024 × 1024 px | K16: 定稿 | L16: 1 | M16: — | N16: 缩至约 100 世界像素高（大狗约 1.06 倍）仍可凭轮廓认出 奶龙；与其他四物的头、肢体、外形不混同；不超出已有脚底对齐逻辑。 | O16: 待生成 | P16: 1 个透明 RGBA PNG 定稿；主体完整、无底座、无环境阴影；附三色主色票说明。 | Q16: 脚底地面中心；母版 (512, 896)，朝右；全部形态共享同一根节点。 | R16: src/art/characters/abnormalities.ts :: drawCreature / nailong；config/anomalies.json :: N01 | S16: 不要照片、3D 渲染、像素风、光滑矢量图标风或高饱和日漫；不要复制现成游戏的角色、脸型或官方 IP 素材；不要背景、文字、水印、UI、血条、黄色选中圈或攻击范围；不要以红色滤镜代替形变。 | T16: 平静定稿是所有衍生姿态的形体基准。主样本与两只分身复用同一素材，分身仅由引擎按 0.76 缩放并调色；不新增分身专用图、不让分身产生更多分身。
A17: ABN_N01_03 | B17: P0 | C17: 五物/失控定稿 | D17: abn_nailong_breach_01 | E17: N01 奶龙 失控定稿 | F17: BREACHED | G17: 原创怪诞手绘收容风：不均匀粗墨外轮廓、较细结构线、局部不对称、平涂和少量排线；轮廓在游戏缩小尺寸仍清楚。 保留软黄肚子与短尾识别点，头颈明显拉长，大小不等的实黑空眼；嘴裂成斜向大黑开口、稀疏奶油三角齿，嘴角延伸至颈部；身体有轻微被拉扁的视频帧错位感。相比平静形态，空眼、裂嘴、长颈三项都必须明确，不能仅涂红或加烟。 | H17: 当前 奶龙 真实 enemy 形态，对照其平静定稿 | I17: REF_N01_CALM / REF_N01_BREACH | J17: 1024 × 1024 px | K17: 定稿 | L17: 1 | M17: ABN_N01_01 | N17: 平静/失控灰度对比时，仅看剪影与脸部也可分辨；不增加肢体数量、不改变角色物种；主体轮廓不被残影盖没。 | O17: 待生成 | P17: 1 个透明 RGBA PNG 主体定稿；虚影/错帧效果仅放附属说明，实际主体不带不可拆多重残像。 | Q17: 脚底地面中心；母版 (512, 896)，朝右；全部形态共享同一根节点。 | R17: src/art/characters/abnormalities.ts :: drawCreature / nailong；config/anomalies.json :: N01（m.breached） | S17: 不要照片、3D 渲染、像素风、光滑矢量图标风或高饱和日漫；不要复制现成游戏的角色、脸型或官方 IP 素材；不要背景、文字、水印、UI、血条、黄色选中圈或攻击范围；不要以红色滤镜代替形变。 | T17: 失控以实际 enemy 存在为准。主样本与两只分身复用同一素材，分身仅由引擎按 0.76 缩放并调色；不新增分身专用图、不让分身产生更多分身。
A18: ABN_N01_04 | B18: P0 | C18: 五物/角色拆件 | D18: abn_nailong_parts_01 | E18: N01 奶龙 双形态共用拆件 | F18: IDLE / WORKING / BREACHED | G18: 躯干 1、平静头颈 1、失控头颈 1、平静口鼻 1、失控裂嘴 1、常态/空眼两组眼部 2、左右短臂 2、左右脚 2、尾 1，共 12 件。头颈、眼、口分层，裂嘴不与选中圈或残影合并。 沿用两份已批准定稿的线宽与体积，关节背面补全；可复用部位只交一份，不为每个动作复制整身。完整定稿仅作组合校对，不额外计独立交付单位。 以上为整套构成；每次只生成 「逐张提示词」本张范围 指定的一个独立件，不画整套平铺图。 | H18: 奶龙 已批准平静与失控定稿 | I18: REF_N01_CALM / REF_N01_BREACH | J18: 1024 × 1024 px 装配母版；全部零件沿用原坐标透明导出 | K18: 拆件 | L18: 12 | M18: ABN_N01_01 / ABN_N01_03 | N18: 独立 PNG 恰为 12 件，能无缝组回两形态；旋转连接处有遮盖余量；缩小后细线不糊为一团。 | O18: 待生成 | P18: 12 个独立 RGBA 透明 PNG + 关联分层源文件/挂点清单；不裁去各件共同定位信息；同名件不可合层。 分层源文件与挂点记录由后处理制作，不要求图像模型直接生成。 | Q18: 脚底地面中心；母版 (512, 896)，朝右；全部形态共享同一根节点。 另记录头颈、四肢、口部或钟针等实际旋转挂点。 | R18: src/art/characters/abnormalities.ts :: drawCreature / nailong；config/anomalies.json :: N01 | S18: 不要照片、3D 渲染、像素风、光滑矢量图标风或高饱和日漫；不要复制现成游戏的角色、脸型或官方 IP 素材；不要背景、文字、水印、UI、血条、黄色选中圈或攻击范围；不要以红色滤镜代替形变。 | T18: 此清单只申请绘制需要的最小拆件；引擎仍须接入素材装配。阴影、选中圈、受击射线、受控星标、故障残影继续复用程序绘制，不重复生成静态图。
A19: ABN_N01_05 | B19: P0 | C19: 五物/战斗参考 | D19: abn_nailong_combat_reference_01 | E19: N01 奶龙 失控行动与攻击参考 | F19: MOVING / WINDUP / IMPACT / HURT | G19: 分别生成六个独立单姿：失控行走左右支撑 2 姿、前摇抬臂/后仰 1 姿、裂嘴前送命中 1 姿、收势 1 姿、短促受击回缩 1 姿。拉长颈部但脚底不瞬移；所有姿态使用同一裂嘴造型。 每个独立交付文件只能含一个姿势；按 「逐张提示词」本张范围 逐张生成。 | H19: 奶龙 已批准失控定稿与实际 attackPhase/impactRemaining/hurt | I19: REF_N01_CALM / REF_N01_BREACH | J19: 1024 × 1024 px，每张单独姿势/零件，共用 (512, 896) 根 | K19: 动作参考 | L19: 6 | M19: ABN_N01_03 / ABN_N01_04 | N19: 可清楚判断准备、前摇、释放、收势；受击与主动攻击不混淆；前摇不靠字幕才成立。参考不承诺未制作的动画帧数。 | O19: 待生成 | P19: 6 个独立透明 RGBA PNG，每张仅一个完整角色姿势；不拼 sheet、无文字、无重复实体/残影。 | Q19: 每个主要姿势保持同一脚底注册点；行走仅示足部接触关系，不烘焙移动距离。 | R19: src/art/characters/abnormalities.ts :: drawCreature / nailong；config/anomalies.json :: N01（windup / impact / walk / hurt） | S19: 不要照片、3D 渲染、像素风、光滑矢量图标风或高饱和日漫；不要复制现成游戏的角色、脸型或官方 IP 素材；不要背景、文字、水印、UI、血条、黄色选中圈或攻击范围；不要以红色滤镜代替形变。 | T19: 此项是动画制作独立参考图组，不是已完成的 sprite 动画或图集；拆件、骨骼装配和循环制作仍需另行接入。动作只能读取模拟 time/stride/状态，暂停冻结。 主样本与两只分身复用同一素材，分身仅由引擎按 0.76 缩放并调色；不新增分身专用图、不让分身产生更多分身。
... A112: ENV_028 | B112: P2 | C112: 低优先背景 | D112: facility_distant_framework_a | E112: 远景支柱与交叉撑架 | F112: 静态远景装饰 | G112: 二维正交侧视、怪诞手绘工业收容风；深墨外轮廓略歪但整体结构清楚，大块低饱和平涂，仅局部刻线阴影。长竖柱与横向联梁一件、对角撑架一件，黑灰蓝剪影、少量低对比边线，形状比可走结构更暗更简略。无门窗、扶梯、地板标线、文字或亮色检修灯。 | H112: 总览暗空腔中的稀疏钢骨架；对齐现有drawVoid装饰层。 | I112: REF_OVERVIEW | J112: 竖柱联梁512×2048 px；对角撑架1024×1024 px。 | K112: 背景 | L112: 2 | M112: ENV_027 | N112: 在Home总览下只形成设施纵深，不与真实可走地板争抢视觉；画在所有真实房间/走廊之后，不遮住A/B/C井。 | O112: 待生成 | P112: 透明PNG两件，竖柱纵向可延伸拼接。 | Q112: 柱件中轴下端；撑架左下连接点。 | R112: src/scenes/facility/architecture.ts#drawVoid/drawArchitecture（房间下方撑架） | S112: 不画员工、收容物、HUD、可读文字或水印；不做俯视/等距透视、写实金属、高饱和霓虹、密集污渍或其他游戏的标志图案；不要把整间房与设备烘焙成一张不可拆大图。 | T112: 远景架不是额外楼层或可探索区域，不能据此修改导航图。 建议画布尺寸是生成纹理的像素数，不修改现有3600×2500逻辑地图。每件单独生成和导出，不要求图像模型一次输出连续序列帧；quantity是独立交付文件数，不是地图中的摆放次数。

Sheet 逐张提示词
A1: 逐张提示词｜一行一张独立素材
A2: 复制 D 列完整提示词，并附上 F 列对应参考图；拆件先附已确认的本组定稿图，勿直接批量生成全套
A4: 出图任务 | B4: =COUNTA(B8:B295) -> 288 | D4: 提示词随主表要求与「生成规范」统一风格更新；建议先试做一名员工 + 奶龙平静/失效，再批量。
A5: 参考图在本工作簿内。回传目录是建议生产目录，不是当前游戏自动加载路径。每次仅处理一行。
A7: 需求ID | B7: 单件文件名 | C7: 本张生成对象 | D7: 完整生成提示词（复制本格） | E7: 负面要求（也已含于提示词） | F7: 参考图ID | G7: 优先级 | H7: 本张画布 | I7: 本张范围 / 只画此件 | J7: 输出与后处理 | K7: 轴点 / 对齐 | L7: 建议回传目录 | M7: 出图状态（填写） | N7: 前置需求ID
A8: STA_001 | B8: agent_base_idle_01_approved.png | C8: 员工基型定稿 | D8: ="【唯一交付文件】"&B8&CHAR(10)&"【对象】"&C8&CHAR(10)&生成规范!$B$8&CHAR(10)&"【同组设计标准，仅作一致性约束】"&素材需求!G8&CHAR(10)&"【本次只画】"&I8&"；本次只交付这一件/一个姿势，不把同组其他素材、姿势或裁切线画进本图，不拼成多格图集。"&CHAR(10)&"【状态】"&素材需求!F8&CHAR(10)&"【参考】附图 "&F8&"。"&素材需求!H8&"。如有前置定稿，必须保持同一造型、比例、线宽、服装和配色；拆件需另附已确认整身定稿图。"&CHAR(10)&"【画布】"&H8&"；尺寸不支持时保持比例生成，再后处理到目标尺寸。"&CHAR(10)&"【输出】"&J8&"。只输出当前这一张；套组其余部分由其他任务分别完成。透明须为真实Alpha，禁止棋盘格。"&CHAR(10)&"【对齐】"&K8&CHAR(10)&"【禁止】"&E8 -> 【唯一交付文件】agent_base_idle_01_approved.png 【对象】员工基型定稿 原创二维地下工业收容设施游戏美术；怪诞手绘收容风，受手绘怪诞生存童话的表现原则启发。hand-drawn, ink-outline, slightly grotesque, whimsical horror, 2D cutout-friendly。粗细有变化的深墨轮廓，轻微不规则手绘线，大面积低饱和平涂，少量刻线阴影；剪影与动作优先于纹理。正交二维侧视角色/设施，UI为正视平面。保留对象身份，统一视觉语言，不复制其他作品具体资产。 【同组设计标准，仅作一致性约束】原创怪诞手绘收容风：不均匀粗墨外轮廓、较细结构线、局部不对称、平涂和少量排线；轮廓在游戏缩小尺寸仍清楚。 约 3 头身，大头、小而窄的工业外套躯干、细长四肢和厚底短靴；头略前倾、肩线不对称、神经质但仍是可工作的普通员工。灰绿制服 #68716c、旧纸肤色 #d9c6a5、少量铁锈/米白；不画英雄盔甲。用一位中性员工确定标准头颅、颈、肩、髋与手掌比例，服装含翻领、细领带和小工牌。 【本次只画】本次只画一名完整的中性工业员工，待机站立，约三头身、神经质前倾，大头细长四肢；发型以 E01 为示意，不带专属装备；只交这一独立单元，不画其他零件、对照姿、sheet、文字或背景。保持主表指定造型、朝向与挂点。；本次只交付这一件/一个姿势，不把同组其他素材、姿势或裁切线画进本图，不拼成多格图集。 【状态】IDLE 【参考】附图 REF_STAFF。当前 E01–E06 的共用身体及怪诞手绘指南。如有前置定稿，必须保持同一造型、比例、线宽、服装和配色；拆件需另附已确认整身定稿图。 【画布】1024 × 1024 px；尺寸不支持时保持比例生成，再后处理到目标尺寸。 【输出】单个 RGBA 透明 PNG，sRGB，无底色和阴影背景，保留透明边距。。只输出当前这一张；套组其余部分由其他任务分别完成。透明须为真实Alpha，禁止棋盘格。 【对齐】脚底地面中心；1024 × 1024 定稿统一注册点 (512, 896)，朝右；左向由引擎镜像。 【禁止】不做 3D、照片写实、厚涂油画、等距俯视、高饱和二次元、霓虹光污染、密集脏污；不加文字、数字、二维码、水印、游戏界面或棋盘格背景；不把动态状态、血条、范围、路径烘焙进图。 不要照片、3D 渲染、像素风、光滑矢量图标风或高饱和日漫；不要复制现成游戏的角色、脸型或官方 IP 素材；不要背景、文字、水印、UI、血条、黄色选中圈或攻击范围；不要以红色滤镜代替形变。 | E8: =生成规范!$B$9&CHAR(10)&素材需求!S8 -> 不做 3D、照片写实、厚涂油画、等距俯视、高饱和二次元、霓虹光污染、密集脏污；不加文字、数字、二维码、水印、游戏界面或棋盘格背景；不把动态状态、血条、范围、路径烘焙进图。 不要照片、3D 渲染、像素风、光滑矢量图标风或高饱和日漫；不要复制现成游戏的角色、脸型或官方 IP 素材；不要背景、文字、水印、UI、血条、黄色选中圈或攻击范围；不要以红色滤镜代替形变。 | F8: REF_STAFF | G8: =素材需求!B8 -> P0 | H8: 1024 × 1024 px | I8: 本次只画一名完整的中性工业员工，待机站立，约三头身、神经质前倾，大头细长四肢；发型以 E01 为示意，不带专属装备；只交这一独立单元，不画其他零件、对照姿、sheet、文字或背景。保持主表指定造型、朝向与挂点。 | J8: 单个 RGBA 透明 PNG，sRGB，无底色和阴影背景，保留透明边距。 | K8: 脚底地面中心；1024 × 1024 定稿统一注册点 (512, 896)，朝右；左向由引擎镜像。 | L8: art_delivery/v1/characters/ | M8: 待生成 | N8: —
A9: STA_002 | B9: agent_base_parts_01_head.png | C9: 无发无表情头 | D9: ="【唯一交付文件】"&B9&CHAR(10)&"【对象】"&C9&CHAR(10)&生成规范!$B$8&CHAR(10)&"【同组设计标准，仅作一致性约束】"&素材需求!G9&CHAR(10)&"【本次只画】"&I9&"；本次只交付这一件/一个姿势，不把同组其他素材、姿势或裁切线画进本图，不拼成多格图集。"&CHAR(10)&"【状态】"&素材需求!F9&CHAR(10)&"【参考】附图 "&F9&"。"&素材需求!H9&"。如有前置定稿，必须保持同一造型、比例、线宽、服装和配色；拆件需另附已确认整身定稿图。"&CHAR(10)&"【画布】"&H9&"；尺寸不支持时保持比例生成，再后处理到目标尺寸。"&CHAR(10)&"【输出】"&J9&"。只输出当前这一张；套组其余部分由其他任务分别完成。透明须为真实Alpha，禁止棋盘格。"&CHAR(10)&"【对齐】"&K9&CHAR(10)&"【禁止】"&E9 -> 【唯一交付文件】agent_base_parts_01_head.png 【对象】无发无表情头 原创二维地下工业收容设施游戏美术；怪诞手绘收容风，受手绘怪诞生存童话的表现原则启发。hand-drawn, ink-outline, slightly grotesque, whimsical horror, 2D cutout-friendly。粗细有变化的深墨轮廓，轻微不规则手绘线，大面积低饱和平涂，少量刻线阴影；剪影与动作优先于纹理。正交二维侧视角色/设施，UI为正视平面。保留对象身份，统一视觉语言，不复制其他作品具体资产。 【同组设计标准，仅作一致性约束】承接 STA_001，交付 14 个身体件：无发无表情头 1、含制服躯干 1、上臂左右 2、前臂左右 2、手左右 2、大腿左右 2、小腿左右 2、鞋左右 2；另交制式短棍 W00 1、观察夹板 1，共 16 件。关节内侧补全被遮区域，袖口与手掌连接清楚。夹板为旧纸矩形、金属夹和两道手写痕，不生成可读字。短棍是朴素铁灰/锈色棍，不带能量核心。 以上为整套构成；每次只生成 「逐张提示词」本张范围 指定的一个独立件，不画整套平铺图。 【本次只画】本次只画共用员工的无发、无眉眼嘴头部，含耳与颈连接余量，完整补齐头皮；只交这一独立单元，不画其他零件、对照姿、sheet、文字或背景。保持主表指定造型、朝向与挂点。；本次只交付这一件/一个姿势，不把同组其他素材、姿势或裁切线画进本图，不拼成多格图集。 【状态】通用 【参考】附图 REF_STAFF。已批准的员工基型；当前 OBSERVE 夹板和 W00。如有前置定稿，必须保持同一造型、比例、线宽、服装和配色；拆件需另附已确认整身定稿图。 【画布】身体装配母版 1024 × 1024 px；各身体件与手持物在相同坐标画布分别导出；尺寸不支持时保持比例生成，再后处理到目标尺寸。 【输出】本次仅一张单件 PNG，sRGB；真实 Alpha 透明背景；沿用装配母版位置，不自动裁切；尺寸修正、边缘清理、分层源文件及轴点记录由后处理制作。。只输出当前这一张；套组其余部分由其他任务分别完成。透明须为真实Alpha，禁止棋盘格。 【对齐】装配根为脚底 (512, 896)；头颈、肩、肘、腕、髋、膝、踝分别记录像素挂点；两道具记录握柄点。 【禁止】不做 3D、照片写实、厚涂油画、等距俯视、高饱和二次元、霓虹光污染、密集脏污；不加文字、数字、二维码、水印、游戏界面或棋盘格背景；不把动态状态、血条、范围、路径烘焙进图。 不要照片、3D 渲染、像素风、光滑矢量图标风或高饱和日漫；不要复制现成游戏的角色、脸型或官方 IP 素材；不要背景、文字、水印、UI、血条、黄色选中圈或攻击范围；不要以红色滤镜代替形变。 | E9: =生成规范!$B$9&CHAR(10)&素材需求!S9 -> 不做 3D、照片写实、厚涂油画、等距俯视、高饱和二次元、霓虹光污染、密集脏污；不加文字、数字、二维码、水印、游戏界面或棋盘格背景；不把动态状态、血条、范围、路径烘焙进图。 不要照片、3D 渲染、像素风、光滑矢量图标风或高饱和日漫；不要复制现成游戏的角色、脸型或官方 IP 素材；不要背景、文字、水印、UI、血条、黄色选中圈或攻击范围；不要以红色滤镜代替形变。 | F9: REF_STAFF | G9: =素材需求!B9 -> P0 | H9: 身体装配母版 1024 × 1024 px；各身体件与手持物在相同坐标画布分别导出 | I9: 本次只画共用员工的无发、无眉眼嘴头部，含耳与颈连接余量，完整补齐头皮；只交这一独立单元，不画其他零件、对照姿、sheet、文字或背景。保持主表指定造型、朝向与挂点。 | J9: 本次仅一张单件 PNG，sRGB；真实 Alpha 透明背景；沿用装配母版位置，不自动裁切；尺寸修正、边缘清理、分层源文件及轴点记录由后处理制作。 | K9: 装配根为脚底 (512, 896)；头颈、肩、肘、腕、髋、膝、踝分别记录像素挂点；两道具记录握柄点。 | L9: art_delivery/v1/characters/ | M9: 待生成 | N9: STA_001
A10: STA_002 | B10: agent_base_parts_01_torso.png | C10: 制服躯干 | D10: ="【唯一交付文件】"&B10&CHAR(10)&"【对象】"&C10&CHAR(10)&生成规范!$B$8&CHAR(10)&"【同组设计标准，仅作一致性约束】"&素材需求!G9&CHAR(10)&"【本次只画】"&I10&"；本次只交付这一件/一个姿势，不把同组其他素材、姿势或裁切线画进本图，不拼成多格图集。"&CHAR(10)&"【状态】"&素材需求!F9&CHAR(10)&"【参考】附图 "&F10&"。"&素材需求!H9&"。如有前置定稿，必须保持同一造型、比例、线宽、服装和配色；拆件需另附已确认整身定稿图。"&CHAR(10)&"【画布】"&H10&"；尺寸不支持时保持比例生成，再后处理到目标尺寸。"&CHAR(10)&"【输出】"&J10&"。只输出当前这一张；套组其余部分由其他任务分别完成。透明须为真实Alpha，禁止棋盘格。"&CHAR(10)&"【对齐】"&K10&CHAR(10)&"【禁止】"&E10 -> 【唯一交付文件】agent_base_parts_01_torso.png 【对象】制服躯干 原创二维地下工业收容设施游戏美术；怪诞手绘收容风，受手绘怪诞生存童话的表现原则启发。hand-drawn, ink-outline, slightly grotesque, whimsical horror, 2D cutout-friendly。粗细有变化的深墨轮廓，轻微不规则手绘线，大面积低饱和平涂，少量刻线阴影；剪影与动作优先于纹理。正交二维侧视角色/设施，UI为正视平面。保留对象身份，统一视觉语言，不复制其他作品具体资产。 【同组设计标准，仅作一致性约束】承接 STA_001，交付 14 个身体件：无发无表情头 1、含制服躯干 1、上臂左右 2、前臂左右 2、手左右 2、大腿左右 2、小腿左右 2、鞋左右 2；另交制式短棍 W00 1、观察夹板 1，共 16 件。关节内侧补全被遮区域，袖口与手掌连接清楚。夹板为旧纸矩形、金属夹和两道手写痕，不生成可读字。短棍是朴素铁灰/锈色棍，不带能量核心。 以上为整套构成；每次只生成 「逐张提示词」本张范围 指定的一个独立件，不画整套平铺图。 【本次只画】本次只画共用员工的灰绿制服躯干，含翻领、领带、工牌和衣摆，不含头及四肢；只交这一独立单元，不画其他零件、对照姿、sheet、文字或背景。保持主表指定造型、朝向与挂点。；本次只交付这一件/一个姿势，不把同组其他素材、姿势或裁切线画进本图，不拼成多格图集。 【状态】通用 【参考】附图 REF_STAFF。已批准的员工基型；当前 OBSERVE 夹板和 W00。如有前置定稿，必须保持同一造型、比例、线宽、服装和配色；拆件需另附已确认整身定稿图。 【画布】身体装配母版 1024 × 1024 px；各身体件与手持物在相同坐标画布分别导出；尺寸不支持时保持比例生成，再后处理到目标尺寸。 【输出】本次仅一张单件 PNG，sRGB；真实 Alpha 透明背景；沿用装配母版位置，不自动裁切；尺寸修正、边缘清理、分层源文件及轴点记录由后处理制作。。只输出当前这一张；套组其余部分由其他任务分别完成。透明须为真实Alpha，禁止棋盘格。 【对齐】装配根为脚底 (512, 896)；头颈、肩、肘、腕、髋、膝、踝分别记录像素挂点；两道具记录握柄点。 【禁止】不做 3D、照片写实、厚涂油画、等距俯视、高饱和二次元、霓虹光污染、密集脏污；不加文字、数字、二维码、水印、游戏界面或棋盘格背景；不把动态状态、血条、范围、路径烘焙进图。 不要照片、3D 渲染、像素风、光滑矢量图标风或高饱和日漫；不要复制现成游戏的角色、脸型或官方 IP 素材；不要背景、文字、水印、UI、血条、黄色选中圈或攻击范围；不要以红色滤镜代替形变。 | E10: =生成规范!$B$9&CHAR(10)&素材需求!S9 -> 不做 3D、照片写实、厚涂油画、等距俯视、高饱和二次元、霓虹光污染、密集脏污；不加文字、数字、二维码、水印、游戏界面或棋盘格背景；不把动态状态、血条、范围、路径烘焙进图。 不要照片、3D 渲染、像素风、光滑矢量图标风或高饱和日漫；不要复制现成游戏的角色、脸型或官方 IP 素材；不要背景、文字、水印、UI、血条、黄色选中圈或攻击范围；不要以红色滤镜代替形变。 | F10: REF_STAFF | G10: =素材需求!B9 -> P0 | H10: 身体装配母版 1024 × 1024 px；各身体件与手持物在相同坐标画布分别导出 | I10: 本次只画共用员工的灰绿制服躯干，含翻领、领带、工牌和衣摆，不含头及四肢；只交这一独立单元，不画其他零件、对照姿、sheet、文字或背景。保持主表指定造型、朝向与挂点。 | J10: 本次仅一张单件 PNG，sRGB；真实 Alpha 透明背景；沿用装配母版位置，不自动裁切；尺寸修正、边缘清理、分层源文件及轴点记录由后处理制作。 | K10: 装配根为脚底 (512, 896)；头颈、肩、肘、腕、髋、膝、踝分别记录像素挂点；两道具记录握柄点。 | L10: art_delivery/v1/characters/ | M10: 待生成 | N10: STA_001
A11: STA_002 | B11: agent_base_parts_01_upper_arm_left.png | C11: 左上臂 | D11: ="【唯一交付文件】"&B11&CHAR(10)&"【对象】"&C11&CHAR(10)&生成规范!$B$8&CHAR(10)&"【同组设计标准，仅作一致性约束】"&素材需求!G9&CHAR(10)&"【本次只画】"&I11&"；本次只交付这一件/一个姿势，不把同组其他素材、姿势或裁切线画进本图，不拼成多格图集。"&CHAR(10)&"【状态】"&素材需求!F9&CHAR(10)&"【参考】附图 "&F11&"。"&素材需求!H9&"。如有前置定稿，必须保持同一造型、比例、线宽、服装和配色；拆件需另附已确认整身定稿图。"&CHAR(10)&"【画布】"&H11&"；尺寸不支持时保持比例生成，再后处理到目标尺寸。"&CHAR(10)&"【输出】"&J11&"。只输出当前这一张；套组其余部分由其他任务分别完成。透明须为真实Alpha，禁止棋盘格。"&CHAR(10)&"【对齐】"&K11&CHAR(10)&"【禁止】"&E11 -> 【唯一交付文件】agent_base_parts_01_upper_arm_left.png 【对象】左上臂 原创二维地下工业收容设施游戏美术；怪诞手绘收容风，受手绘怪诞生存童话的表现原则启发。hand-drawn, ink-outline, slightly grotesque, whimsical horror, 2D cutout-friendly。粗细有变化的深墨轮廓，轻微不规则手绘线，大面积低饱和平涂，少量刻线阴影；剪影与动作优先于纹理。正交二维侧视角色/设施，UI为正视平面。保留对象身份，统一视觉语言，不复制其他作品具体资产。 【同组设计标准，仅作一致性约束】承接 STA_001，交付 14 个身体件：无发无表情头 1、含制服躯干 1、上臂左右 2、前臂左右 2、手左右 2、大腿左右 2、小腿左右 2、鞋左右 2；另交制式短棍 W00 1、观察夹板 1，共 16 件。关节内侧补全被遮区域，袖口与手掌连接清楚。夹板为旧纸矩形、金属夹和两道手写痕，不生成可读字。短棍是朴素铁灰/锈色棍，不带能量核心。 以上为整套构成；每次只生成 「逐张提示词」本张范围 指定的一个独立件，不画整套平铺图。 【本次只画】本次只画左上臂制服袖件，从肩根到肘，补齐连接区；只交这一独立单元，不画其他零件、对照姿、sheet、文字或背景。保持主表指定造型、朝向与挂点。；本次只交付这一件/一个姿势，不把同组其他素材、姿势或裁切线画进本图，不拼成多格图集。 【状态】通用 【参考】附图 REF_STAFF。已批准的员工基型；当前 OBSERVE 夹板和 W00。如有前置定稿，必须保持同一造型、比例、线宽、服装和配色；拆件需另附已确认整身定稿图。 【画布】身体装配母版 1024 × 1024 px；各身体件与手持物在相同坐标画布分别导出；尺寸不支持时保持比例生成，再后处理到目标尺寸。 【输出】本次仅一张单件 PNG，sRGB；真实 Alpha 透明背景；沿用装配母版位置，不自动裁切；尺寸修正、边缘清理、分层源文件及轴点记录由后处理制作。。只输出当前这一张；套组其余部分由其他任务分别完成。透明须为真实Alpha，禁止棋盘格。 【对齐】装配根为脚底 (512, 896)；头颈、肩、肘、腕、髋、膝、踝分别记录像素挂点；两道具记录握柄点。 【禁止】不做 3D、照片写实、厚涂油画、等距俯视、高饱和二次元、霓虹光污染、密集脏污；不加文字、数字、二维码、水印、游戏界面或棋盘格背景；不把动态状态、血条、范围、路径烘焙进图。 不要照片、3D 渲染、像素风、光滑矢量图标风或高饱和日漫；不要复制现成游戏的角色、脸型或官方 IP 素材；不要背景、文字、水印、UI、血条、黄色选中圈或攻击范围；不要以红色滤镜代替形变。 | E11: =生成规范!$B$9&CHAR(10)&素材需求!S9 -> 不做 3D、照片写实、厚涂油画、等距俯视、高饱和二次元、霓虹光污染、密集脏污；不加文字、数字、二维码、水印、游戏界面或棋盘格背景；不把动态状态、血条、范围、路径烘焙进图。 不要照片、3D 渲染、像素风、光滑矢量图标风或高饱和日漫；不要复制现成游戏的角色、脸型或官方 IP 素材；不要背景、文字、水印、UI、血条、黄色选中圈或攻击范围；不要以红色滤镜代替形变。 | F11: REF_STAFF | G11: =素材需求!B9 -> P0 | H11: 身体装配母版 1024 × 1024 px；各身体件与手持物在相同坐标画布分别导出 | I11: 本次只画左上臂制服袖件，从肩根到肘，补齐连接区；只交这一独立单元，不画其他零件、对照姿、sheet、文字或背景。保持主表指定造型、朝向与挂点。 | J11: 本次仅一张单件 PNG，sRGB；真实 Alpha 透明背景；沿用装配母版位置，不自动裁切；尺寸修正、边缘清理、分层源文件及轴点记录由后处理制作。 | K11: 装配根为脚底 (512, 896)；头颈、肩、肘、腕、髋、膝、踝分别记录像素挂点；两道具记录握柄点。 | L11: art_delivery/v1/characters/ | M11: 待生成 | N11: STA_001
A12: STA_002 | B12: agent_base_parts_01_upper_arm_right.png | C12: 右上臂 | D12: ="【唯一交付文件】"&B12&CHAR(10)&"【对象】"&C12&CHAR(10)&生成规范!$B$8&CHAR(10)&"【同组设计标准，仅作一致性约束】"&素材需求!G9&CHAR(10)&"【本次只画】"&I12&"；本次只交付这一件/一个姿势，不把同组其他素材、姿势或裁切线画进本图，不拼成多格图集。"&CHAR(10)&"【状态】"&素材需求!F9&CHAR(10)&"【参考】附图 "&F12&"。"&素材需求!H9&"。如有前置定稿，必须保持同一造型、比例、线宽、服装和配色；拆件需另附已确认整身定稿图。"&CHAR(10)&"【画布】"&H12&"；尺寸不支持时保持比例生成，再后处理到目标尺寸。"&CHAR(10)&"【输出】"&J12&"。只输出当前这一张；套组其余部分由其他任务分别完成。透明须为真实Alpha，禁止棋盘格。"&CHAR(10)&"【对齐】"&K12&CHAR(10)&"【禁止】"&E12 -> 【唯一交付文件】agent_base_parts_01_upper_arm_right.png 【对象】右上臂 原创二维地下工业收容设施游戏美术；怪诞手绘收容风，受手绘怪诞生存童话的表现原则启发。hand-drawn, ink-outline, slightly grotesque, whimsical horror, 2D cutout-friendly。粗细有变化的深墨轮廓，轻微不规则手绘线，大面积低饱和平涂，少量刻线阴影；剪影与动作优先于纹理。正交二维侧视角色/设施，UI为正视平面。保留对象身份，统一视觉语言，不复制其他作品具体资产。 【同组设计标准，仅作一致性约束】承接 STA_001，交付 14 个身体件：无发无表情头 1、含制服躯干 1、上臂左右 2、前臂左右 2、手左右 2、大腿左右 2、小腿左右 2、鞋左右 2；另交制式短棍 W00 1、观察夹板 1，共 16 件。关节内侧补全被遮区域，袖口与手掌连接清楚。夹板为旧纸矩形、金属夹和两道手写痕，不生成可读字。短棍是朴素铁灰/锈色棍，不带能量核心。 以上为整套构成；每次只生成 「逐张提示词」本张范围 指定的一个独立件，不画整套平铺图。 【本次只画】本次只画右上臂制服袖件，从肩根到肘，补齐连接区；只交这一独立单元，不画其他零件、对照姿、sheet、文字或背景。保持主表指定造型、朝向与挂点。；本次只交付这一件/一个姿势，不把同组其他素材、姿势或裁切线画进本图，不拼成多格图集。 【状态】通用 【参考】附图 REF_STAFF。已批准的员工基型；当前 OBSERVE 夹板和 W00。如有前置定稿，必须保持同一造型、比例、线宽、服装和配色；拆件需另附已确认整身定稿图。 【画布】身体装配母版 1024 × 1024 px；各身体件与手持物在相同坐标画布分别导出；尺寸不支持时保持比例生成，再后处理到目标尺寸。 【输出】本次仅一张单件 PNG，sRGB；真实 Alpha 透明背景；沿用装配母版位置，不自动裁切；尺寸修正、边缘清理、分层源文件及轴点记录由后处理制作。。只输出当前这一张；套组其余部分由其他任务分别完成。透明须为真实Alpha，禁止棋盘格。 【对齐】装配根为脚底 (512, 896)；头颈、肩、肘、腕、髋、膝、踝分别记录像素挂点；两道具记录握柄点。 【禁止】不做 3D、照片写实、厚涂油画、等距俯视、高饱和二次元、霓虹光污染、密集脏污；不加文字、数字、二维码、水印、游戏界面或棋盘格背景；不把动态状态、血条、范围、路径烘焙进图。 不要照片、3D 渲染、像素风、光滑矢量图标风或高饱和日漫；不要复制现成游戏的角色、脸型或官方 IP 素材；不要背景、文字、水印、UI、血条、黄色选中圈或攻击范围；不要以红色滤镜代替形变。 | E12: =生成规范!$B$9&CHAR(10)&素材需求!S9 -> 不做 3D、照片写实、厚涂油画、等距俯视、高饱和二次元、霓虹光污染、密集脏污；不加文字、数字、二维码、水印、游戏界面或棋盘格背景；不把动态状态、血条、范围、路径烘焙进图。 不要照片、3D 渲染、像素风、光滑矢量图标风或高饱和日漫；不要复制现成游戏的角色、脸型或官方 IP 素材；不要背景、文字、水印、UI、血条、黄色选中圈或攻击范围；不要以红色滤镜代替形变。 | F12: REF_STAFF | G12: =素材需求!B9 -> P0 | H12: 身体装配母版 1024 × 1024 px；各身体件与手持物在相同坐标画布分别导出 | I12: 本次只画右上臂制服袖件，从肩根到肘，补齐连接区；只交这一独立单元，不画其他零件、对照姿、sheet、文字或背景。保持主表指定造型、朝向与挂点。 | J12: 本次仅一张单件 PNG，sRGB；真实 Alpha 透明背景；沿用装配母版位置，不自动裁切；尺寸修正、边缘清理、分层源文件及轴点记录由后处理制作。 | K12: 装配根为脚底 (512, 896)；头颈、肩、肘、腕、髋、膝、踝分别记录像素挂点；两道具记录握柄点。 | L12: art_delivery/v1/characters/ | M12: 待生成 | N12: STA_001
A13: STA_002 | B13: agent_base_parts_01_forearm_left.png | C13: 左前臂 | D13: ="【唯一交付文件】"&B13&CHAR(10)&"【对象】"&C13&CHAR(10)&生成规范!$B$8&CHAR(10)&"【同组设计标准，仅作一致性约束】"&素材需求!G9&CHAR(10)&"【本次只画】"&I13&"；本次只交付这一件/一个姿势，不把同组其他素材、姿势或裁切线画进本图，不拼成多格图集。"&CHAR(10)&"【状态】"&素材需求!F9&CHAR(10)&"【参考】附图 "&F13&"。"&素材需求!H9&"。如有前置定稿，必须保持同一造型、比例、线宽、服装和配色；拆件需另附已确认整身定稿图。"&CHAR(10)&"【画布】"&H13&"；尺寸不支持时保持比例生成，再后处理到目标尺寸。"&CHAR(10)&"【输出】"&J13&"。只输出当前这一张；套组其余部分由其他任务分别完成。透明须为真实Alpha，禁止棋盘格。"&CHAR(10)&"【对齐】"&K13&CHAR(10)&"【禁止】"&E13 -> 【唯一交付文件】agent_base_parts_01_forearm_left.png 【对象】左前臂 原创二维地下工业收容设施游戏美术；怪诞手绘收容风，受手绘怪诞生存童话的表现原则启发。hand-drawn, ink-outline, slightly grotesque, whimsical horror, 2D cutout-friendly。粗细有变化的深墨轮廓，轻微不规则手绘线，大面积低饱和平涂，少量刻线阴影；剪影与动作优先于纹理。正交二维侧视角色/设施，UI为正视平面。保留对象身份，统一视觉语言，不复制其他作品具体资产。 【同组设计标准，仅作一致性约束】承接 STA_001，交付 14 个身体件：无发无表情头 1、含制服躯干 1、上臂左右 2、前臂左右 2、手左右 2、大腿左右 2、小腿左右 2、鞋左右 2；另交制式短棍 W00 1、观察夹板 1，共 16 件。关节内侧补全被遮区域，袖口与手掌连接清楚。夹板为旧纸矩形、金属夹和两道手写痕，不生成可读字。短棍是朴素铁灰/锈色棍，不带能量核心。 以上为整套构成；每次只生成 「逐张提示词」本张范围 指定的一个独立件，不画整套平铺图。 【本次只画】本次只画左前臂袖件，从肘到腕，保留袖口；只交这一独立单元，不画其他零件、对照姿、sheet、文字或背景。保持主表指定造型、朝向与挂点。；本次只交付这一件/一个姿势，不把同组其他素材、姿势或裁切线画进本图，不拼成多格图集。 【状态】通用 【参考】附图 REF_STAFF。已批准的员工基型；当前 OBSERVE 夹板和 W00。如有前置定稿，必须保持同一造型、比例、线宽、服装和配色；拆件需另附已确认整身定稿图。 【画布】身体装配母版 1024 × 1024 px；各身体件与手持物在相同坐标画布分别导出；尺寸不支持时保持比例生成，再后处理到目标尺寸。 【输出】本次仅一张单件 PNG，sRGB；真实 Alpha 透明背景；沿用装配母版位置，不自动裁切；尺寸修正、边缘清理、分层源文件及轴点记录由后处理制作。。只输出当前这一张；套组其余部分由其他任务分别完成。透明须为真实Alpha，禁止棋盘格。 【对齐】装配根为脚底 (512, 896)；头颈、肩、肘、腕、髋、膝、踝分别记录像素挂点；两道具记录握柄点。 【禁止】不做 3D、照片写实、厚涂油画、等距俯视、高饱和二次元、霓虹光污染、密集脏污；不加文字、数字、二维码、水印、游戏界面或棋盘格背景；不把动态状态、血条、范围、路径烘焙进图。 不要照片、3D 渲染、像素风、光滑矢量图标风或高饱和日漫；不要复制现成游戏的角色、脸型或官方 IP 素材；不要背景、文字、水印、UI、血条、黄色选中圈或攻击范围；不要以红色滤镜代替形变。 | E13: =生成规范!$B$9&CHAR(10)&素材需求!S9 -> 不做 3D、照片写实、厚涂油画、等距俯视、高饱和二次元、霓虹光污染、密集脏污；不加文字、数字、二维码、水印、游戏界面或棋盘格背景；不把动态状态、血条、范围、路径烘焙进图。 不要照片、3D 渲染、像素风、光滑矢量图标风或高饱和日漫；不要复制现成游戏的角色、脸型或官方 IP 素材；不要背景、文字、水印、UI、血条、黄色选中圈或攻击范围；不要以红色滤镜代替形变。 | F13: REF_STAFF | G13: =素材需求!B9 -> P0 | H13: 身体装配母版 1024 × 1024 px；各身体件与手持物在相同坐标画布分别导出 | I13: 本次只画左前臂袖件，从肘到腕，保留袖口；只交这一独立单元，不画其他零件、对照姿、sheet、文字或背景。保持主表指定造型、朝向与挂点。 | J13: 本次仅一张单件 PNG，sRGB；真实 Alpha 透明背景；沿用装配母版位置，不自动裁切；尺寸修正、边缘清理、分层源文件及轴点记录由后处理制作。 | K13: 装配根为脚底 (512, 896)；头颈、肩、肘、腕、髋、膝、踝分别记录像素挂点；两道具记录握柄点。 | L13: art_delivery/v1/characters/ | M13: 待生成 | N13: STA_001
A14: STA_002 | B14: agent_base_parts_01_forearm_right.png | C14: 右前臂 | D14: ="【唯一交付文件】"&B14&CHAR(10)&"【对象】"&C14&CHAR(10)&生成规范!$B$8&CHAR(10)&"【同组设计标准，仅作一致性约束】"&素材需求!G9&CHAR(10)&"【本次只画】"&I14&"；本次只交付这一件/一个姿势，不把同组其他素材、姿势或裁切线画进本图，不拼成多格图集。"&CHAR(10)&"【状态】"&素材需求!F9&CHAR(10)&"【参考】附图 "&F14&"。"&素材需求!H9&"。如有前置定稿，必须保持同一造型、比例、线宽、服装和配色；拆件需另附已确认整身定稿图。"&CHAR(10)&"【画布】"&H14&"；尺寸不支持时保持比例生成，再后处理到目标尺寸。"&CHAR(10)&"【输出】"&J14&"。只输出当前这一张；套组其余部分由其他任务分别完成。透明须为真实Alpha，禁止棋盘格。"&CHAR(10)&"【对齐】"&K14&CHAR(10)&"【禁止】"&E14 -> 【唯一交付文件】agent_base_parts_01_forearm_right.png 【对象】右前臂 原创二维地下工业收容设施游戏美术；怪诞手绘收容风，受手绘怪诞生存童话的表现原则启发。hand-drawn, ink-outline, slightly grotesque, whimsical horror, 2D cutout-friendly。粗细有变化的深墨轮廓，轻微不规则手绘线，大面积低饱和平涂，少量刻线阴影；剪影与动作优先于纹理。正交二维侧视角色/设施，UI为正视平面。保留对象身份，统一视觉语言，不复制其他作品具体资产。 【同组设计标准，仅作一致性约束】承接 STA_001，交付 14 个身体件：无发无表情头 1、含制服躯干 1、上臂左右 2、前臂左右 2、手左右 2、大腿左右 2、小腿左右 2、鞋左右 2；另交制式短棍 W00 1、观察夹板 1，共 16 件。关节内侧补全被遮区域，袖口与手掌连接清楚。夹板为旧纸矩形、金属夹和两道手写痕，不生成可读字。短棍是朴素铁灰/锈色棍，不带能量核心。 以上为整套构成；每次只生成 「逐张提示词」本张范围 指定的一个独立件，不画整套平铺图。 【本次只画】本次只画右前臂袖件，从肘到腕，保留袖口；只交这一独立单元，不画其他零件、对照姿、sheet、文字或背景。保持主表指定造型、朝向与挂点。；本次只交付这一件/一个姿势，不把同组其他素材、姿势或裁切线画进本图，不拼成多格图集。 【状态】通用 【参考】附图 REF_STAFF。已批准的员工基型；当前 OBSERVE 夹板和 W00。如有前置定稿，必须保持同一造型、比例、线宽、服装和配色；拆件需另附已确认整身定稿图。 【画布】身体装配母版 1024 × 1024 px；各身体件与手持物在相同坐标画布分别导出；尺寸不支持时保持比例生成，再后处理到目标尺寸。 【输出】本次仅一张单件 PNG，sRGB；真实 Alpha 透明背景；沿用装配母版位置，不自动裁切；尺寸修正、边缘清理、分层源文件及轴点记录由后处理制作。。只输出当前这一张；套组其余部分由其他任务分别完成。透明须为真实Alpha，禁止棋盘格。 【对齐】装配根为脚底 (512, 896)；头颈、肩、肘、腕、髋、膝、踝分别记录像素挂点；两道具记录握柄点。 【禁止】不做 3D、照片写实、厚涂油画、等距俯视、高饱和二次元、霓虹光污染、密集脏污；不加文字、数字、二维码、水印、游戏界面或棋盘格背景；不把动态状态、血条、范围、路径烘焙进图。 不要照片、3D 渲染、像素风、光滑矢量图标风或高饱和日漫；不要复制现成游戏的角色、脸型或官方 IP 素材；不要背景、文字、水印、UI、血条、黄色选中圈或攻击范围；不要以红色滤镜代替形变。 | E14: =生成规范!$B$9&CHAR(10)&素材需求!S9 -> 不做 3D、照片写实、厚涂油画、等距俯视、高饱和二次元、霓虹光污染、密集脏污；不加文字、数字、二维码、水印、游戏界面或棋盘格背景；不把动态状态、血条、范围、路径烘焙进图。 不要照片、3D 渲染、像素风、光滑矢量图标风或高饱和日漫；不要复制现成游戏的角色、脸型或官方 IP 素材；不要背景、文字、水印、UI、血条、黄色选中圈或攻击范围；不要以红色滤镜代替形变。 | F14: REF_STAFF | G14: =素材需求!B9 -> P0 | H14: 身体装配母版 1024 × 1024 px；各身体件与手持物在相同坐标画布分别导出 | I14: 本次只画右前臂袖件，从肘到腕，保留袖口；只交这一独立单元，不画其他零件、对照姿、sheet、文字或背景。保持主表指定造型、朝向与挂点。 | J14: 本次仅一张单件 PNG，sRGB；真实 Alpha 透明背景；沿用装配母版位置，不自动裁切；尺寸修正、边缘清理、分层源文件及轴点记录由后处理制作。 | K14: 装配根为脚底 (512, 896)；头颈、肩、肘、腕、髋、膝、踝分别记录像素挂点；两道具记录握柄点。 | L14: art_delivery/v1/characters/ | M14: 待生成 | N14: STA_001
A15: STA_002 | B15: agent_base_parts_01_hand_left.png | C15: 左手 | D15: ="【唯一交付文件】"&B15&CHAR(10)&"【对象】"&C15&CHAR(10)&生成规范!$B$8&CHAR(10)&"【同组设计标准，仅作一致性约束】"&素材需求!G9&CHAR(10)&"【本次只画】"&I15&"；本次只交付这一件/一个姿势，不把同组其他素材、姿势或裁切线画进本图，不拼成多格图集。"&CHAR(10)&"【状态】"&素材需求!F9&CHAR(10)&"【参考】附图 "&F15&"。"&素材需求!H9&"。如有前置定稿，必须保持同一造型、比例、线宽、服装和配色；拆件需另附已确认整身定稿图。"&CHAR(10)&"【画布】"&H15&"；尺寸不支持时保持比例生成，再后处理到目标尺寸。"&CHAR(10)&"【输出】"&J15&"。只输出当前这一张；套组其余部分由其他任务分别完成。透明须为真实Alpha，禁止棋盘格。"&CHAR(10)&"【对齐】"&K15&CHAR(10)&"【禁止】"&E15 -> 【唯一交付文件】agent_base_parts_01_hand_left.png 【对象】左手 原创二维地下工业收容设施游戏美术；怪诞手绘收容风，受手绘怪诞生存童话的表现原则启发。hand-drawn, ink-outline, slightly grotesque, whimsical horror, 2D cutout-friendly。粗细有变化的深墨轮廓，轻微不规则手绘线，大面积低饱和平涂，少量刻线阴影；剪影与动作优先于纹理。正交二维侧视角色/设施，UI为正视平面。保留对象身份，统一视觉语言，不复制其他作品具体资产。 【同组设计标准，仅作一致性约束】承接 STA_001，交付 14 个身体件：无发无表情头 1、含制服躯干 1、上臂左右 2、前臂左右 2、手左右 2、大腿左右 2、小腿左右 2、鞋左右 2；另交制式短棍 W00 1、观察夹板 1，共 16 件。关节内侧补全被遮区域，袖口与手掌连接清楚。夹板为旧纸矩形、金属夹和两道手写痕，不生成可读字。短棍是朴素铁灰/锈色棍，不带能量核心。 以上为整套构成；每次只生成 「逐张提示词」本张范围 指定的一个独立件，不画整套平铺图。 【本次只画】本次只画左手简化手掌，保持可握持姿态和腕根，不附带道具；只交这一独立单元，不画其他零件、对照姿、sheet、文字或背景。保持主表指定造型、朝向与挂点。；本次只交付这一件/一个姿势，不把同组其他素材、姿势或裁切线画进本图，不拼成多格图集。 【状态】通用 【参考】附图 REF_STAFF。已批准的员工基型；当前 OBSERVE 夹板和 W00。如有前置定稿，必须保持同一造型、比例、线宽、服装和配色；拆件需另附已确认整身定稿图。 【画布】身体装配母版 1024 × 1024 px；各身体件与手持物在相同坐标画布分别导出；尺寸不支持时保持比例生成，再后处理到目标尺寸。 【输出】本次仅一张单件 PNG，sRGB；真实 Alpha 透明背景；沿用装配母版位置，不自动裁切；尺寸修正、边缘清理、分层源文件及轴点记录由后处理制作。。只输出当前这一张；套组其余部分由其他任务分别完成。透明须为真实Alpha，禁止棋盘格。 【对齐】装配根为脚底 (512, 896)；头颈、肩、肘、腕、髋、膝、踝分别记录像素挂点；两道具记录握柄点。 【禁止】不做 3D、照片写实、厚涂油画、等距俯视、高饱和二次元、霓虹光污染、密集脏污；不加文字、数字、二维码、水印、游戏界面或棋盘格背景；不把动态状态、血条、范围、路径烘焙进图。 不要照片、3D 渲染、像素风、光滑矢量图标风或高饱和日漫；不要复制现成游戏的角色、脸型或官方 IP 素材；不要背景、文字、水印、UI、血条、黄色选中圈或攻击范围；不要以红色滤镜代替形变。 | E15: =生成规范!$B$9&CHAR(10)&素材需求!S9 -> 不做 3D、照片写实、厚涂油画、等距俯视、高饱和二次元、霓虹光污染、密集脏污；不加文字、数字、二维码、水印、游戏界面或棋盘格背景；不把动态状态、血条、范围、路径烘焙进图。 不要照片、3D 渲染、像素风、光滑矢量图标风或高饱和日漫；不要复制现成游戏的角色、脸型或官方 IP 素材；不要背景、文字、水印、UI、血条、黄色选中圈或攻击范围；不要以红色滤镜代替形变。 | F15: REF_STAFF | G15: =素材需求!B9 -> P0 | H15: 身体装配母版 1024 × 1024 px；各身体件与手持物在相同坐标画布分别导出 | I15: 本次只画左手简化手掌，保持可握持姿态和腕根，不附带道具；只交这一独立单元，不画其他零件、对照姿、sheet、文字或背景。保持主表指定造型、朝向与挂点。 | J15: 本次仅一张单件 PNG，sRGB；真实 Alpha 透明背景；沿用装配母版位置，不自动裁切；尺寸修正、边缘清理、分层源文件及轴点记录由后处理制作。 | K15: 装配根为脚底 (512, 896)；头颈、肩、肘、腕、髋、膝、踝分别记录像素挂点；两道具记录握柄点。 | L15: art_delivery/v1/characters/ | M15: 待生成 | N15: STA_001
A16: STA_002 | B16: agent_base_parts_01_hand_right.png | C16: 右手 | D16: ="【唯一交付文件】"&B16&CHAR(10)&"【对象】"&C16&CHAR(10)&生成规范!$B$8&CHAR(10)&"【同组设计标准，仅作一致性约束】"&素材需求!G9&CHAR(10)&"【本次只画】"&I16&"；本次只交付这一件/一个姿势，不把同组其他素材、姿势或裁切线画进本图，不拼成多格图集。"&CHAR(10)&"【状态】"&素材需求!F9&CHAR(10)&"【参考】附图 "&F16&"。"&素材需求!H9&"。如有前置定稿，必须保持同一造型、比例、线宽、服装和配色；拆件需另附已确认整身定稿图。"&CHAR(10)&"【画布】"&H16&"；尺寸不支持时保持比例生成，再后处理到目标尺寸。"&CHAR(10)&"【输出】"&J16&"。只输出当前这一张；套组其余部分由其他任务分别完成。透明须为真实Alpha，禁止棋盘格。"&CHAR(10)&"【对齐】"&K16&CHAR(10)&"【禁止】"&E16 -> 【唯一交付文件】agent_base_parts_01_hand_right.png 【对象】右手 原创二维地下工业收容设施游戏美术；怪诞手绘收容风，受手绘怪诞生存童话的表现原则启发。hand-drawn, ink-outline, slightly grotesque, whimsical horror, 2D cutout-friendly。粗细有变化的深墨轮廓，轻微不规则手绘线，大面积低饱和平涂，少量刻线阴影；剪影与动作优先于纹理。正交二维侧视角色/设施，UI为正视平面。保留对象身份，统一视觉语言，不复制其他作品具体资产。 【同组设计标准，仅作一致性约束】承接 STA_001，交付 14 个身体件：无发无表情头 1、含制服躯干 1、上臂左右 2、前臂左右 2、手左右 2、大腿左右 2、小腿左右 2、鞋左右 2；另交制式短棍 W00 1、观察夹板 1，共 16 件。关节内侧补全被遮区域，袖口与手掌连接清楚。夹板为旧纸矩形、金属夹和两道手写痕，不生成可读字。短棍是朴素铁灰/锈色棍，不带能量核心。 以上为整套构成；每次只生成 「逐张提示词」本张范围 指定的一个独立件，不画整套平铺图。 【本次只画】本次只画右手简化手掌，保持可握持姿态和腕根，不附带道具；只交这一独立单元，不画其他零件、对照姿、sheet、文字或背景。保持主表指定造型、朝向与挂点。；本次只交付这一件/一个姿势，不把同组其他素材、姿势或裁切线画进本图，不拼成多格图集。 【状态】通用 【参考】附图 REF_STAFF。已批准的员工基型；当前 OBSERVE 夹板和 W00。如有前置定稿，必须保持同一造型、比例、线宽、服装和配色；拆件需另附已确认整身定稿图。 【画布】身体装配母版 1024 × 1024 px；各身体件与手持物在相同坐标画布分别导出；尺寸不支持时保持比例生成，再后处理到目标尺寸。 【输出】本次仅一张单件 PNG，sRGB；真实 Alpha 透明背景；沿用装配母版位置，不自动裁切；尺寸修正、边缘清理、分层源文件及轴点记录由后处理制作。。只输出当前这一张；套组其余部分由其他任务分别完成。透明须为真实Alpha，禁止棋盘格。 【对齐】装配根为脚底 (512, 896)；头颈、肩、肘、腕、髋、膝、踝分别记录像素挂点；两道具记录握柄点。 【禁止】不做 3D、照片写实、厚涂油画、等距俯视、高饱和二次元、霓虹光污染、密集脏污；不加文字、数字、二维码、水印、游戏界面或棋盘格背景；不把动态状态、血条、范围、路径烘焙进图。 不要照片、3D 渲染、像素风、光滑矢量图标风或高饱和日漫；不要复制现成游戏的角色、脸型或官方 IP 素材；不要背景、文字、水印、UI、血条、黄色选中圈或攻击范围；不要以红色滤镜代替形变。 | E16: =生成规范!$B$9&CHAR(10)&素材需求!S9 -> 不做 3D、照片写实、厚涂油画、等距俯视、高饱和二次元、霓虹光污染、密集脏污；不加文字、数字、二维码、水印、游戏界面或棋盘格背景；不把动态状态、血条、范围、路径烘焙进图。 不要照片、3D 渲染、像素风、光滑矢量图标风或高饱和日漫；不要复制现成游戏的角色、脸型或官方 IP 素材；不要背景、文字、水印、UI、血条、黄色选中圈或攻击范围；不要以红色滤镜代替形变。 | F16: REF_STAFF | G16: =素材需求!B9 -> P0 | H16: 身体装配母版 1024 × 1024 px；各身体件与手持物在相同坐标画布分别导出 | I16: 本次只画右手简化手掌，保持可握持姿态和腕根，不附带道具；只交这一独立单元，不画其他零件、对照姿、sheet、文字或背景。保持主表指定造型、朝向与挂点。 | J16: 本次仅一张单件 PNG，sRGB；真实 Alpha 透明背景；沿用装配母版位置，不自动裁切；尺寸修正、边缘清理、分层源文件及轴点记录由后处理制作。 | K16: 装配根为脚底 (512, 896)；头颈、肩、肘、腕、髋、膝、踝分别记录像素挂点；两道具记录握柄点。 | L16: art_delivery/v1/characters/ | M16: 待生成 | N16: STA_001
A17: STA_002 | B17: agent_base_parts_01_thigh_left.png | C17: 左大腿 | D17: ="【唯一交付文件】"&B17&CHAR(10)&"【对象】"&C17&CHAR(10)&生成规范!$B$8&CHAR(10)&"【同组设计标准，仅作一致性约束】"&素材需求!G9&CHAR(10)&"【本次只画】"&I17&"；本次只交付这一件/一个姿势，不把同组其他素材、姿势或裁切线画进本图，不拼成多格图集。"&CHAR(10)&"【状态】"&素材需求!F9&CHAR(10)&"【参考】附图 "&F17&"。"&素材需求!H9&"。如有前置定稿，必须保持同一造型、比例、线宽、服装和配色；拆件需另附已确认整身定稿图。"&CHAR(10)&"【画布】"&H17&"；尺寸不支持时保持比例生成，再后处理到目标尺寸。"&CHAR(10)&"【输出】"&J17&"。只输出当前这一张；套组其余部分由其他任务分别完成。透明须为真实Alpha，禁止棋盘格。"&CHAR(10)&"【对齐】"&K17&CHAR(10)&"【禁止】"&E17 -> 【唯一交付文件】agent_base_parts_01_thigh_left.png 【对象】左大腿 原创二维地下工业收容设施游戏美术；怪诞手绘收容风，受手绘怪诞生存童话的表现原则启发。hand-drawn, ink-outline, slightly grotesque, whimsical horror, 2D cutout-friendly。粗细有变化的深墨轮廓，轻微不规则手绘线，大面积低饱和平涂，少量刻线阴影；剪影与动作优先于纹理。正交二维侧视角色/设施，UI为正视平面。保留对象身份，统一视觉语言，不复制其他作品具体资产。 【同组设计标准，仅作一致性约束】承接 STA_001，交付 14 个身体件：无发无表情头 1、含制服躯干 1、上臂左右 2、前臂左右 2、手左右 2、大腿左右 2、小腿左右 2、鞋左右 2；另交制式短棍 W00 1、观察夹板 1，共 16 件。关节内侧补全被遮区域，袖口与手掌连接清楚。夹板为旧纸矩形、金属夹和两道手写痕，不生成可读字。短棍是朴素铁灰/锈色棍，不带能量核心。 以上为整套构成；每次只生成 「逐张提示词」本张范围 指定的一个独立件，不画整套平铺图。 【本次只画】本次只画左大腿制服裤件，髋到膝的细长轮廓；只交这一独立单元，不画其他零件、对照姿、sheet、文字或背景。保持主表指定造型、朝向与挂点。；本次只交付这一件/一个姿势，不把同组其他素材、姿势或裁切线画进本图，不拼成多格图集。 【状态】通用 【参考】附图 REF_STAFF。已批准的员工基型；当前 OBSERVE 夹板和 W00。如有前置定稿，必须保持同一造型、比例、线宽、服装和配色；拆件需另附已确认整身定稿图。 【画布】身体装配母版 1024 × 1024 px；各身体件与手持物在相同坐标画布分别导出；尺寸不支持时保持比例生成，再后处理到目标尺寸。 【输出】本次仅一张单件 PNG，sRGB；真实 Alpha 透明背景；沿用装配母版位置，不自动裁切；尺寸修正、边缘清理、分层源文件及轴点记录由后处理制作。。只输出当前这一张；套组其余部分由其他任务分别完成。透明须为真实Alpha，禁止棋盘格。 【对齐】装配根为脚底 (512, 896)；头颈、肩、肘、腕、髋、膝、踝分别记录像素挂点；两道具记录握柄点。 【禁止】不做 3D、照片写实、厚涂油画、等距俯视、高饱和二次元、霓虹光污染、密集脏污；不加文字、数字、二维码、水印、游戏界面或棋盘格背景；不把动态状态、血条、范围、路径烘焙进图。 不要照片、3D 渲染、像素风、光滑矢量图标风或高饱和日漫；不要复制现成游戏的角色、脸型或官方 IP 素材；不要背景、文字、水印、UI、血条、黄色选中圈或攻击范围；不要以红色滤镜代替形变。 | E17: =生成规范!$B$9&CHAR(10)&素材需求!S9 -> 不做 3D、照片写实、厚涂油画、等距俯视、高饱和二次元、霓虹光污染、密集脏污；不加文字、数字、二维码、水印、游戏界面或棋盘格背景；不把动态状态、血条、范围、路径烘焙进图。 不要照片、3D 渲染、像素风、光滑矢量图标风或高饱和日漫；不要复制现成游戏的角色、脸型或官方 IP 素材；不要背景、文字、水印、UI、血条、黄色选中圈或攻击范围；不要以红色滤镜代替形变。 | F17: REF_STAFF | G17: =素材需求!B9 -> P0 | H17: 身体装配母版 1024 × 1024 px；各身体件与手持物在相同坐标画布分别导出 | I17: 本次只画左大腿制服裤件，髋到膝的细长轮廓；只交这一独立单元，不画其他零件、对照姿、sheet、文字或背景。保持主表指定造型、朝向与挂点。 | J17: 本次仅一张单件 PNG，sRGB；真实 Alpha 透明背景；沿用装配母版位置，不自动裁切；尺寸修正、边缘清理、分层源文件及轴点记录由后处理制作。 | K17: 装配根为脚底 (512, 896)；头颈、肩、肘、腕、髋、膝、踝分别记录像素挂点；两道具记录握柄点。 | L17: art_delivery/v1/characters/ | M17: 待生成 | N17: STA_001
A18: STA_002 | B18: agent_base_parts_01_thigh_right.png | C18: 右大腿 | D18: ="【唯一交付文件】"&B18&CHAR(10)&"【对象】"&C18&CHAR(10)&生成规范!$B$8&CHAR(10)&"【同组设计标准，仅作一致性约束】"&素材需求!G9&CHAR(10)&"【本次只画】"&I18&"；本次只交付这一件/一个姿势，不把同组其他素材、姿势或裁切线画进本图，不拼成多格图集。"&CHAR(10)&"【状态】"&素材需求!F9&CHAR(10)&"【参考】附图 "&F18&"。"&素材需求!H9&"。如有前置定稿，必须保持同一造型、比例、线宽、服装和配色；拆件需另附已确认整身定稿图。"&CHAR(10)&"【画布】"&H18&"；尺寸不支持时保持比例生成，再后处理到目标尺寸。"&CHAR(10)&"【输出】"&J18&"。只输出当前这一张；套组其余部分由其他任务分别完成。透明须为真实Alpha，禁止棋盘格。"&CHAR(10)&"【对齐】"&K18&CHAR(10)&"【禁止】"&E18 -> 【唯一交付文件】agent_base_parts_01_thigh_right.png 【对象】右大腿 原创二维地下工业收容设施游戏美术；怪诞手绘收容风，受手绘怪诞生存童话的表现原则启发。hand-drawn, ink-outline, slightly grotesque, whimsical horror, 2D cutout-friendly。粗细有变化的深墨轮廓，轻微不规则手绘线，大面积低饱和平涂，少量刻线阴影；剪影与动作优先于纹理。正交二维侧视角色/设施，UI为正视平面。保留对象身份，统一视觉语言，不复制其他作品具体资产。 【同组设计标准，仅作一致性约束】承接 STA_001，交付 14 个身体件：无发无表情头 1、含制服躯干 1、上臂左右 2、前臂左右 2、手左右 2、大腿左右 2、小腿左右 2、鞋左右 2；另交制式短棍 W00 1、观察夹板 1，共 16 件。关节内侧补全被遮区域，袖口与手掌连接清楚。夹板为旧纸矩形、金属夹和两道手写痕，不生成可读字。短棍是朴素铁灰/锈色棍，不带能量核心。 以上为整套构成；每次只生成 「逐张提示词」本张范围 指定的一个独立件，不画整套平铺图。 【本次只画】本次只画右大腿制服裤件，髋到膝的细长轮廓；只交这一独立单元，不画其他零件、对照姿、sheet、文字或背景。保持主表指定造型、朝向与挂点。；本次只交付这一件/一个姿势，不把同组其他素材、姿势或裁切线画进本图，不拼成多格图集。 【状态】通用 【参考】附图 REF_STAFF。已批准的员工基型；当前 OBSERVE 夹板和 W00。如有前置定稿，必须保持同一造型、比例、线宽、服装和配色；拆件需另附已确认整身定稿图。 【画布】身体装配母版 1024 × 1024 px；各身体件与手持物在相同坐标画布分别导出；尺寸不支持时保持比例生成，再后处理到目标尺寸。 【输出】本次仅一张单件 PNG，sRGB；真实 Alpha 透明背景；沿用装配母版位置，不自动裁切；尺寸修正、边缘清理、分层源文件及轴点记录由后处理制作。。只输出当前这一张；套组其余部分由其他任务分别完成。透明须为真实Alpha，禁止棋盘格。 【对齐】装配根为脚底 (512, 896)；头颈、肩、肘、腕、髋、膝、踝分别记录像素挂点；两道具记录握柄点。 【禁止】不做 3D、照片写实、厚涂油画、等距俯视、高饱和二次元、霓虹光污染、密集脏污；不加文字、数字、二维码、水印、游戏界面或棋盘格背景；不把动态状态、血条、范围、路径烘焙进图。 不要照片、3D 渲染、像素风、光滑矢量图标风或高饱和日漫；不要复制现成游戏的角色、脸型或官方 IP 素材；不要背景、文字、水印、UI、血条、黄色选中圈或攻击范围；不要以红色滤镜代替形变。 | E18: =生成规范!$B$9&CHAR(10)&素材需求!S9 -> 不做 3D、照片写实、厚涂油画、等距俯视、高饱和二次元、霓虹光污染、密集脏污；不加文字、数字、二维码、水印、游戏界面或棋盘格背景；不把动态状态、血条、范围、路径烘焙进图。 不要照片、3D 渲染、像素风、光滑矢量图标风或高饱和日漫；不要复制现成游戏的角色、脸型或官方 IP 素材；不要背景、文字、水印、UI、血条、黄色选中圈或攻击范围；不要以红色滤镜代替形变。 | F18: REF_STAFF | G18: =素材需求!B9 -> P0 | H18: 身体装配母版 1024 × 1024 px；各身体件与手持物在相同坐标画布分别导出 | I18: 本次只画右大腿制服裤件，髋到膝的细长轮廓；只交这一独立单元，不画其他零件、对照姿、sheet、文字或背景。保持主表指定造型、朝向与挂点。 | J18: 本次仅一张单件 PNG，sRGB；真实 Alpha 透明背景；沿用装配母版位置，不自动裁切；尺寸修正、边缘清理、分层源文件及轴点记录由后处理制作。 | K18: 装配根为脚底 (512, 896)；头颈、肩、肘、腕、髋、膝、踝分别记录像素挂点；两道具记录握柄点。 | L18: art_delivery/v1/characters/ | M18: 待生成 | N18: STA_001
A19: STA_002 | B19: agent_base_parts_01_shin_left.png | C19: 左小腿 | D19: ="【唯一交付文件】"&B19&CHAR(10)&"【对象】"&C19&CHAR(10)&生成规范!$B$8&CHAR(10)&"【同组设计标准，仅作一致性约束】"&素材需求!G9&CHAR(10)&"【本次只画】"&I19&"；本次只交付这一件/一个姿势，不把同组其他素材、姿势或裁切线画进本图，不拼成多格图集。"&CHAR(10)&"【状态】"&素材需求!F9&CHAR(10)&"【参考】附图 "&F19&"。"&素材需求!H9&"。如有前置定稿，必须保持同一造型、比例、线宽、服装和配色；拆件需另附已确认整身定稿图。"&CHAR(10)&"【画布】"&H19&"；尺寸不支持时保持比例生成，再后处理到目标尺寸。"&CHAR(10)&"【输出】"&J19&"。只输出当前这一张；套组其余部分由其他任务分别完成。透明须为真实Alpha，禁止棋盘格。"&CHAR(10)&"【对齐】"&K19&CHAR(10)&"【禁止】"&E19 -> 【唯一交付文件】agent_base_parts_01_shin_left.png 【对象】左小腿 原创二维地下工业收容设施游戏美术；怪诞手绘收容风，受手绘怪诞生存童话的表现原则启发。hand-drawn, ink-outline, slightly grotesque, whimsical horror, 2D cutout-friendly。粗细有变化的深墨轮廓，轻微不规则手绘线，大面积低饱和平涂，少量刻线阴影；剪影与动作优先于纹理。正交二维侧视角色/设施，UI为正视平面。保留对象身份，统一视觉语言，不复制其他作品具体资产。 【同组设计标准，仅作一致性约束】承接 STA_001，交付 14 个身体件：无发无表情头 1、含制服躯干 1、上臂左右 2、前臂左右 2、手左右 2、大腿左右 2、小腿左右 2、鞋左右 2；另交制式短棍 W00 1、观察夹板 1，共 16 件。关节内侧补全被遮区域，袖口与手掌连接清楚。夹板为旧纸矩形、金属夹和两道手写痕，不生成可读字。短棍是朴素铁灰/锈色棍，不带能量核心。 以上为整套构成；每次只生成 「逐张提示词」本张范围 指定的一个独立件，不画整套平铺图。 【本次只画】本次只画左小腿制服裤件，膝到踝，保留膝连接余量；只交这一独立单元，不画其他零件、对照姿、sheet、文字或背景。保持主表指定造型、朝向与挂点。；本次只交付这一件/一个姿势，不把同组其他素材、姿势或裁切线画进本图，不拼成多格图集。 【状态】通用 【参考】附图 REF_STAFF。已批准的员工基型；当前 OBSERVE 夹板和 W00。如有前置定稿，必须保持同一造型、比例、线宽、服装和配色；拆件需另附已确认整身定稿图。 【画布】身体装配母版 1024 × 1024 px；各身体件与手持物在相同坐标画布分别导出；尺寸不支持时保持比例生成，再后处理到目标尺寸。 【输出】本次仅一张单件 PNG，sRGB；真实 Alpha 透明背景；沿用装配母版位置，不自动裁切；尺寸修正、边缘清理、分层源文件及轴点记录由后处理制作。。只输出当前这一张；套组其余部分由其他任务分别完成。透明须为真实Alpha，禁止棋盘格。 【对齐】装配根为脚底 (512, 896)；头颈、肩、肘、腕、髋、膝、踝分别记录像素挂点；两道具记录握柄点。 【禁止】不做 3D、照片写实、厚涂油画、等距俯视、高饱和二次元、霓虹光污染、密集脏污；不加文字、数字、二维码、水印、游戏界面或棋盘格背景；不把动态状态、血条、范围、路径烘焙进图。 不要照片、3D 渲染、像素风、光滑矢量图标风或高饱和日漫；不要复制现成游戏的角色、脸型或官方 IP 素材；不要背景、文字、水印、UI、血条、黄色选中圈或攻击范围；不要以红色滤镜代替形变。 | E19: =生成规范!$B$9&CHAR(10)&素材需求!S9 -> 不做 3D、照片写实、厚涂油画、等距俯视、高饱和二次元、霓虹光污染、密集脏污；不加文字、数字、二维码、水印、游戏界面或棋盘格背景；不把动态状态、血条、范围、路径烘焙进图。 不要照片、3D 渲染、像素风、光滑矢量图标风或高饱和日漫；不要复制现成游戏的角色、脸型或官方 IP 素材；不要背景、文字、水印、UI、血条、黄色选中圈或攻击范围；不要以红色滤镜代替形变。 | F19: REF_STAFF | G19: =素材需求!B9 -> P0 | H19: 身体装配母版 1024 × 1024 px；各身体件与手持物在相同坐标画布分别导出 | I19: 本次只画左小腿制服裤件，膝到踝，保留膝连接余量；只交这一独立单元，不画其他零件、对照姿、sheet、文字或背景。保持主表指定造型、朝向与挂点。 | J19: 本次仅一张单件 PNG，sRGB；真实 Alpha 透明背景；沿用装配母版位置，不自动裁切；尺寸修正、边缘清理、分层源文件及轴点记录由后处理制作。 | K19: 装配根为脚底 (512, 896)；头颈、肩、肘、腕、髋、膝、踝分别记录像素挂点；两道具记录握柄点。 | L19: art_delivery/v1/characters/ | M19: 待生成 | N19: STA_001
A20: STA_002 | B20: agent_base_parts_01_shin_right.png | C20: 右小腿 | D20: ="【唯一交付文件】"&B20&CHAR(10)&"【对象】"&C20&CHAR(10)&生成规范!$B$8&CHAR(10)&"【同组设计标准，仅作一致性约束】"&素材需求!G9&CHAR(10)&"【本次只画】"&I20&"；本次只交付这一件/一个姿势，不把同组其他素材、姿势或裁切线画进本图，不拼成多格图集。"&CHAR(10)&"【状态】"&素材需求!F9&CHAR(10)&"【参考】附图 "&F20&"。"&素材需求!H9&"。如有前置定稿，必须保持同一造型、比例、线宽、服装和配色；拆件需另附已确认整身定稿图。"&CHAR(10)&"【画布】"&H20&"；尺寸不支持时保持比例生成，再后处理到目标尺寸。"&CHAR(10)&"【输出】"&J20&"。只输出当前这一张；套组其余部分由其他任务分别完成。透明须为真实Alpha，禁止棋盘格。"&CHAR(10)&"【对齐】"&K20&CHAR(10)&"【禁止】"&E20 -> 【唯一交付文件】agent_base_parts_01_shin_right.png 【对象】右小腿 原创二维地下工业收容设施游戏美术；怪诞手绘收容风，受手绘怪诞生存童话的表现原则启发。hand-drawn, ink-outline, slightly grotesque, whimsical horror, 2D cutout-friendly。粗细有变化的深墨轮廓，轻微不规则手绘线，大面积低饱和平涂，少量刻线阴影；剪影与动作优先于纹理。正交二维侧视角色/设施，UI为正视平面。保留对象身份，统一视觉语言，不复制其他作品具体资产。 【同组设计标准，仅作一致性约束】承接 STA_001，交付 14 个身体件：无发无表情头 1、含制服躯干 1、上臂左右 2、前臂左右 2、手左右 2、大腿左右 2、小腿左右 2、鞋左右 2；另交制式短棍 W00 1、观察夹板 1，共 16 件。关节内侧补全被遮区域，袖口与手掌连接清楚。夹板为旧纸矩形、金属夹和两道手写痕，不生成可读字。短棍是朴素铁灰/锈色棍，不带能量核心。 以上为整套构成；每次只生成 「逐张提示词」本张范围 指定的一个独立件，不画整套平铺图。 【本次只画】本次只画右小腿制服裤件，膝到踝，保留膝连接余量；只交这一独立单元，不画其他零件、对照姿、sheet、文字或背景。保持主表指定造型、朝向与挂点。；本次只交付这一件/一个姿势，不把同组其他素材、姿势或裁切线画进本图，不拼成多格图集。 【状态】通用 【参考】附图 REF_STAFF。已批准的员工基型；当前 OBSERVE 夹板和 W00。如有前置定稿，必须保持同一造型、比例、线宽、服装和配色；拆件需另附已确认整身定稿图。 【画布】身体装配母版 1024 × 1024 px；各身体件与手持物在相同坐标画布分别导出；尺寸不支持时保持比例生成，再后处理到目标尺寸。 【输出】本次仅一张单件 PNG，sRGB；真实 Alpha 透明背景；沿用装配母版位置，不自动裁切；尺寸修正、边缘清理、分层源文件及轴点记录由后处理制作。。只输出当前这一张；套组其余部分由其他任务分别完成。透明须为真实Alpha，禁止棋盘格。 【对齐】装配根为脚底 (512, 896)；头颈、肩、肘、腕、髋、膝、踝分别记录像素挂点；两道具记录握柄点。 【禁止】不做 3D、照片写实、厚涂油画、等距俯视、高饱和二次元、霓虹光污染、密集脏污；不加文字、数字、二维码、水印、游戏界面或棋盘格背景；不把动态状态、血条、范围、路径烘焙进图。 不要照片、3D 渲染、像素风、光滑矢量图标风或高饱和日漫；不要复制现成游戏的角色、脸型或官方 IP 素材；不要背景、文字、水印、UI、血条、黄色选中圈或攻击范围；不要以红色滤镜代替形变。 | E20: =生成规范!$B$9&CHAR(10)&素材需求!S9 -> 不做 3D、照片写实、厚涂油画、等距俯视、高饱和二次元、霓虹光污染、密集脏污；不加文字、数字、二维码、水印、游戏界面或棋盘格背景；不把动态状态、血条、范围、路径烘焙进图。 不要照片、3D 渲染、像素风、光滑矢量图标风或高饱和日漫；不要复制现成游戏的角色、脸型或官方 IP 素材；不要背景、文字、水印、UI、血条、黄色选中圈或攻击范围；不要以红色滤镜代替形变。 | F20: REF_STAFF | G20: =素材需求!B9 -> P0 | H20: 身体装配母版 1024 × 1024 px；各身体件与手持物在相同坐标画布分别导出 | I20: 本次只画右小腿制服裤件，膝到踝，保留膝连接余量；只交这一独立单元，不画其他零件、对照姿、sheet、文字或背景。保持主表指定造型、朝向与挂点。 | J20: 本次仅一张单件 PNG，sRGB；真实 Alpha 透明背景；沿用装配母版位置，不自动裁切；尺寸修正、边缘清理、分层源文件及轴点记录由后处理制作。 | K20: 装配根为脚底 (512, 896)；头颈、肩、肘、腕、髋、膝、踝分别记录像素挂点；两道具记录握柄点。 | L20: art_delivery/v1/characters/ | M20: 待生成 | N20: STA_001
A21: STA_002 | B21: agent_base_parts_01_boot_left.png | C21: 左鞋 | D21: ="【唯一交付文件】"&B21&CHAR(10)&"【对象】"&C21&CHAR(10)&生成规范!$B$8&CHAR(10)&"【同组设计标准，仅作一致性约束】"&素材需求!G9&CHAR(10)&"【本次只画】"&I21&"；本次只交付这一件/一个姿势，不把同组其他素材、姿势或裁切线画进本图，不拼成多格图集。"&CHAR(10)&"【状态】"&素材需求!F9&CHAR(10)&"【参考】附图 "&F21&"。"&素材需求!H9&"。如有前置定稿，必须保持同一造型、比例、线宽、服装和配色；拆件需另附已确认整身定稿图。"&CHAR(10)&"【画布】"&H21&"；尺寸不支持时保持比例生成，再后处理到目标尺寸。"&CHAR(10)&"【输出】"&J21&"。只输出当前这一张；套组其余部分由其他任务分别完成。透明须为真实Alpha，禁止棋盘格。"&CHAR(10)&"【对齐】"&K21&CHAR(10)&"【禁止】"&E21 -> 【唯一交付文件】agent_base_parts_01_boot_left.png 【对象】左鞋 原创二维地下工业收容设施游戏美术；怪诞手绘收容风，受手绘怪诞生存童话的表现原则启发。hand-drawn, ink-outline, slightly grotesque, whimsical horror, 2D cutout-friendly。粗细有变化的深墨轮廓，轻微不规则手绘线，大面积低饱和平涂，少量刻线阴影；剪影与动作优先于纹理。正交二维侧视角色/设施，UI为正视平面。保留对象身份，统一视觉语言，不复制其他作品具体资产。 【同组设计标准，仅作一致性约束】承接 STA_001，交付 14 个身体件：无发无表情头 1、含制服躯干 1、上臂左右 2、前臂左右 2、手左右 2、大腿左右 2、小腿左右 2、鞋左右 2；另交制式短棍 W00 1、观察夹板 1，共 16 件。关节内侧补全被遮区域，袖口与手掌连接清楚。夹板为旧纸矩形、金属夹和两道手写痕，不生成可读字。短棍是朴素铁灰/锈色棍，不带能量核心。 以上为整套构成；每次只生成 「逐张提示词」本张范围 指定的一个独立件，不画整套平铺图。 【本次只画】本次只画左脚厚底工业短靴，脚底水平，保留踝挂点；只交这一独立单元，不画其他零件、对照姿、sheet、文字或背景。保持主表指定造型、朝向与挂点。；本次只交付这一件/一个姿势，不把同组其他素材、姿势或裁切线画进本图，不拼成多格图集。 【状态】通用 【参考】附图 REF_STAFF。已批准的员工基型；当前 OBSERVE 夹板和 W00。如有前置定稿，必须保持同一造型、比例、线宽、服装和配色；拆件需另附已确认整身定稿图。 【画布】身体装配母版 1024 × 1024 px；各身体件与手持物在相同坐标画布分别导出；尺寸不支持时保持比例生成，再后处理到目标尺寸。 【输出】本次仅一张单件 PNG，sRGB；真实 Alpha 透明背景；沿用装配母版位置，不自动裁切；尺寸修正、边缘清理、分层源文件及轴点记录由后处理制作。。只输出当前这一张；套组其余部分由其他任务分别完成。透明须为真实Alpha，禁止棋盘格。 【对齐】装配根为脚底 (512, 896)；头颈、肩、肘、腕、髋、膝、踝分别记录像素挂点；两道具记录握柄点。 【禁止】不做 3D、照片写实、厚涂油画、等距俯视、高饱和二次元、霓虹光污染、密集脏污；不加文字、数字、二维码、水印、游戏界面或棋盘格背景；不把动态状态、血条、范围、路径烘焙进图。 不要照片、3D 渲染、像素风、光滑矢量图标风或高饱和日漫；不要复制现成游戏的角色、脸型或官方 IP 素材；不要背景、文字、水印、UI、血条、黄色选中圈或攻击范围；不要以红色滤镜代替形变。 | E21: =生成规范!$B$9&CHAR(10)&素材需求!S9 -> 不做 3D、照片写实、厚涂油画、等距俯视、高饱和二次元、霓虹光污染、密集脏污；不加文字、数字、二维码、水印、游戏界面或棋盘格背景；不把动态状态、血条、范围、路径烘焙进图。 不要照片、3D 渲染、像素风、光滑矢量图标风或高饱和日漫；不要复制现成游戏的角色、脸型或官方 IP 素材；不要背景、文字、水印、UI、血条、黄色选中圈或攻击范围；不要以红色滤镜代替形变。 | F21: REF_STAFF | G21: =素材需求!B9 -> P0 | H21: 身体装配母版 1024 × 1024 px；各身体件与手持物在相同坐标画布分别导出 | I21: 本次只画左脚厚底工业短靴，脚底水平，保留踝挂点；只交这一独立单元，不画其他零件、对照姿、sheet、文字或背景。保持主表指定造型、朝向与挂点。 | J21: 本次仅一张单件 PNG，sRGB；真实 Alpha 透明背景；沿用装配母版位置，不自动裁切；尺寸修正、边缘清理、分层源文件及轴点记录由后处理制作。 | K21: 装配根为脚底 (512, 896)；头颈、肩、肘、腕、髋、膝、踝分别记录像素挂点；两道具记录握柄点。 | L21: art_delivery/v1/characters/ | M21: 待生成 | N21: STA_001
A22: STA_002 | B22: agent_base_parts_01_boot_right.png | C22: 右鞋 | D22: ="【唯一交付文件】"&B22&CHAR(10)&"【对象】"&C22&CHAR(10)&生成规范!$B$8&CHAR(10)&"【同组设计标准，仅作一致性约束】"&素材需求!G9&CHAR(10)&"【本次只画】"&I22&"；本次只交付这一件/一个姿势，不把同组其他素材、姿势或裁切线画进本图，不拼成多格图集。"&CHAR(10)&"【状态】"&素材需求!F9&CHAR(10)&"【参考】附图 "&F22&"。"&素材需求!H9&"。如有前置定稿，必须保持同一造型、比例、线宽、服装和配色；拆件需另附已确认整身定稿图。"&CHAR(10)&"【画布】"&H22&"；尺寸不支持时保持比例生成，再后处理到目标尺寸。"&CHAR(10)&"【输出】"&J22&"。只输出当前这一张；套组其余部分由其他任务分别完成。透明须为真实Alpha，禁止棋盘格。"&CHAR(10)&"【对齐】"&K22&CHAR(10)&"【禁止】"&E22 -> 【唯一交付文件】agent_base_parts_01_boot_right.png 【对象】右鞋 原创二维地下工业收容设施游戏美术；怪诞手绘收容风，受手绘怪诞生存童话的表现原则启发。hand-drawn, ink-outline, slightly grotesque, whimsical horror, 2D cutout-friendly。粗细有变化的深墨轮廓，轻微不规则手绘线，大面积低饱和平涂，少量刻线阴影；剪影与动作优先于纹理。正交二维侧视角色/设施，UI为正视平面。保留对象身份，统一视觉语言，不复制其他作品具体资产。 【同组设计标准，仅作一致性约束】承接 STA_001，交付 14 个身体件：无发无表情头 1、含制服躯干 1、上臂左右 2、前臂左右 2、手左右 2、大腿左右 2、小腿左右 2、鞋左右 2；另交制式短棍 W00 1、观察夹板 1，共 16 件。关节内侧补全被遮区域，袖口与手掌连接清楚。夹板为旧纸矩形、金属夹和两道手写痕，不生成可读字。短棍是朴素铁灰/锈色棍，不带能量核心。 以上为整套构成；每次只生成 「逐张提示词」本张范围 指定的一个独立件，不画整套平铺图。 【本次只画】本次只画右脚厚底工业短靴，脚底水平，保留踝挂点；只交这一独立单元，不画其他零件、对照姿、sheet、文字或背景。保持主表指定造型、朝向与挂点。；本次只交付这一件/一个姿势，不把同组其他素材、姿势或裁切线画进本图，不拼成多格图集。 【状态】通用 【参考】附图 REF_STAFF。已批准的员工基型；当前 OBSERVE 夹板和 W00。如有前置定稿，必须保持同一造型、比例、线宽、服装和配色；拆件需另附已确认整身定稿图。 【画布】身体装配母版 1024 × 1024 px；各身体件与手持物在相同坐标画布分别导出；尺寸不支持时保持比例生成，再后处理到目标尺寸。 【输出】本次仅一张单件 PNG，sRGB；真实 Alpha 透明背景；沿用装配母版位置，不自动裁切；尺寸修正、边缘清理、分层源文件及轴点记录由后处理制作。。只输出当前这一张；套组其余部分由其他任务分别完成。透明须为真实Alpha，禁止棋盘格。 【对齐】装配根为脚底 (512, 896)；头颈、肩、肘、腕、髋、膝、踝分别记录像素挂点；两道具记录握柄点。 【禁止】不做 3D、照片写实、厚涂油画、等距俯视、高饱和二次元、霓虹光污染、密集脏污；不加文字、数字、二维码、水印、游戏界面或棋盘格背景；不把动态状态、血条、范围、路径烘焙进图。 不要照片、3D 渲染、像素风、光滑矢量图标风或高饱和日漫；不要复制现成游戏的角色、脸型或官方 IP 素材；不要背景、文字、水印、UI、血条、黄色选中圈或攻击范围；不要以红色滤镜代替形变。 | E22: =生成规范!$B$9&CHAR(10)&素材需求!S9 -> 不做 3D、照片写实、厚涂油画、等距俯视、高饱和二次元、霓虹光污染、密集脏污；不加文字、数字、二维码、水印、游戏界面或棋盘格背景；不把动态状态、血条、范围、路径烘焙进图。 不要照片、3D 渲染、像素风、光滑矢量图标风或高饱和日漫；不要复制现成游戏的角色、脸型或官方 IP 素材；不要背景、文字、水印、UI、血条、黄色选中圈或攻击范围；不要以红色滤镜代替形变。 | F22: REF_STAFF | G22: =素材需求!B9 -> P0 | H22: 身体装配母版 1024 × 1024 px；各身体件与手持物在相同坐标画布分别导出 | I22: 本次只画右脚厚底工业短靴，脚底水平，保留踝挂点；只交这一独立单元，不画其他零件、对照姿、sheet、文字或背景。保持主表指定造型、朝向与挂点。 | J22: 本次仅一张单件 PNG，sRGB；真实 Alpha 透明背景；沿用装配母版位置，不自动裁切；尺寸修正、边缘清理、分层源文件及轴点记录由后处理制作。 | K22: 装配根为脚底 (512, 896)；头颈、肩、肘、腕、髋、膝、踝分别记录像素挂点；两道具记录握柄点。 | L22: art_delivery/v1/characters/ | M22: 待生成 | N22: STA_001
A23: STA_002 | B23: agent_base_parts_01_starter_baton.png | C23: 制式短棍 W00 | D23: ="【唯一交付文件】"&B23&CHAR(10)&"【对象】"&C23&CHAR(10)&生成规范!$B$8&CHAR(10)&"【同组设计标准，仅作一致性约束】"&素材需求!G9&CHAR(10)&"【本次只画】"&I23&"；本次只交付这一件/一个姿势，不把同组其他素材、姿势或裁切线画进本图，不拼成多格图集。"&CHAR(10)&"【状态】"&素材需求!F9&CHAR(10)&"【参考】附图 "&F23&"。"&素材需求!H9&"。如有前置定稿，必须保持同一造型、比例、线宽、服装和配色；拆件需另附已确认整身定稿图。"&CHAR(10)&"【画布】"&H23&"；尺寸不支持时保持比例生成，再后处理到目标尺寸。"&CHAR(10)&"【输出】"&J23&"。只输出当前这一张；套组其余部分由其他任务分别完成。透明须为真实Alpha，禁止棋盘格。"&CHAR(10)&"【对齐】"&K23&CHAR(10)&"【禁止】"&E23 -> 【唯一交付文件】agent_base_parts_01_starter_baton.png 【对象】制式短棍 W00 原创二维地下工业收容设施游戏美术；怪诞手绘收容风，受手绘怪诞生存童话的表现原则启发。hand-drawn, ink-outline, slightly grotesque, whimsical horror, 2D cutout-friendly。粗细有变化的深墨轮廓，轻微不规则手绘线，大面积低饱和平涂，少量刻线阴影；剪影与动作优先于纹理。正交二维侧视角色/设施，UI为正视平面。保留对象身份，统一视觉语言，不复制其他作品具体资产。 【同组设计标准，仅作一致性约束】承接 STA_001，交付 14 个身体件：无发无表情头 1、含制服躯干 1、上臂左右 2、前臂左右 2、手左右 2、大腿左右 2、小腿左右 2、鞋左右 2；另交制式短棍 W00 1、观察夹板 1，共 16 件。关节内侧补全被遮区域，袖口与手掌连接清楚。夹板为旧纸矩形、金属夹和两道手写痕，不生成可读字。短棍是朴素铁灰/锈色棍，不带能量核心。 以上为整套构成；每次只生成 「逐张提示词」本张范围 指定的一个独立件，不画整套平铺图。 【本次只画】本次只画朴素铁灰和锈色制式短棍，不含手和发光效果；只交这一独立单元，不画其他零件、对照姿、sheet、文字或背景。保持主表指定造型、朝向与挂点。；本次只交付这一件/一个姿势，不把同组其他素材、姿势或裁切线画进本图，不拼成多格图集。 【状态】通用 【参考】附图 REF_STAFF。已批准的员工基型；当前 OBSERVE 夹板和 W00。如有前置定稿，必须保持同一造型、比例、线宽、服装和配色；拆件需另附已确认整身定稿图。 【画布】身体装配母版 1024 × 1024 px；各身体件与手持物在相同坐标画布分别导出；尺寸不支持时保持比例生成，再后处理到目标尺寸。 【输出】本次仅一张单件 PNG，sRGB；真实 Alpha 透明背景；沿用装配母版位置，不自动裁切；尺寸修正、边缘清理、分层源文件及轴点记录由后处理制作。。只输出当前这一张；套组其余部分由其他任务分别完成。透明须为真实Alpha，禁止棋盘格。 【对齐】装配根为脚底 (512, 896)；头颈、肩、肘、腕、髋、膝、踝分别记录像素挂点；两道具记录握柄点。 【禁止】不做 3D、照片写实、厚涂油画、等距俯视、高饱和二次元、霓虹光污染、密集脏污；不加文字、数字、二维码、水印、游戏界面或棋盘格背景；不把动态状态、血条、范围、路径烘焙进图。 不要照片、3D 渲染、像素风、光滑矢量图标风或高饱和日漫；不要复制现成游戏的角色、脸型或官方 IP 素材；不要背景、文字、水印、UI、血条、黄色选中圈或攻击范围；不要以红色滤镜代替形变。 | E23: =生成规范!$B$9&CHAR(10)&素材需求!S9 -> 不做 3D、照片写实、厚涂油画、等距俯视、高饱和二次元、霓虹光污染、密集脏污；不加文字、数字、二维码、水印、游戏界面或棋盘格背景；不把动态状态、血条、范围、路径烘焙进图。 不要照片、3D 渲染、像素风、光滑矢量图标风或高饱和日漫；不要复制现成游戏的角色、脸型或官方 IP 素材；不要背景、文字、水印、UI、血条、黄色选中圈或攻击范围；不要以红色滤镜代替形变。 | F23: REF_STAFF | G23: =素材需求!B9 -> P0 | H23: 身体装配母版 1024 × 1024 px；各身体件与手持物在相同坐标画布分别导出 | I23: 本次只画朴素铁灰和锈色制式短棍，不含手和发光效果；只交这一独立单元，不画其他零件、对照姿、sheet、文字或背景。保持主表指定造型、朝向与挂点。 | J23: 本次仅一张单件 PNG，sRGB；真实 Alpha 透明背景；沿用装配母版位置，不自动裁切；尺寸修正、边缘清理、分层源文件及轴点记录由后处理制作。 | K23: 装配根为脚底 (512, 896)；头颈、肩、肘、腕、髋、膝、踝分别记录像素挂点；两道具记录握柄点。 | L23: art_delivery/v1/characters/ | M23: 待生成 | N23: STA_001
A24: STA_002 | B24: agent_base_parts_01_clipboard.png | C24: 观察夹板 | D24: ="【唯一交付文件】"&B24&CHAR(10)&"【对象】"&C24&CHAR(10)&生成规范!$B$8&CHAR(10)&"【同组设计标准，仅作一致性约束】"&素材需求!G9&CHAR(10)&"【本次只画】"&I24&"；本次只交付这一件/一个姿势，不把同组其他素材、姿势或裁切线画进本图，不拼成多格图集。"&CHAR(10)&"【状态】"&素材需求!F9&CHAR(10)&"【参考】附图 "&F24&"。"&素材需求!H9&"。如有前置定稿，必须保持同一造型、比例、线宽、服装和配色；拆件需另附已确认整身定稿图。"&CHAR(10)&"【画布】"&H24&"；尺寸不支持时保持比例生成，再后处理到目标尺寸。"&CHAR(10)&"【输出】"&J24&"。只输出当前这一张；套组其余部分由其他任务分别完成。透明须为真实Alpha，禁止棋盘格。"&CHAR(10)&"【对齐】"&K24&CHAR(10)&"【禁止】"&E24 -> 【唯一交付文件】agent_base_parts_01_clipboard.png 【对象】观察夹板 原创二维地下工业收容设施游戏美术；怪诞手绘收容风，受手绘怪诞生存童话的表现原则启发。hand-drawn, ink-outline, slightly grotesque, whimsical horror, 2D cutout-friendly。粗细有变化的深墨轮廓，轻微不规则手绘线，大面积低饱和平涂，少量刻线阴影；剪影与动作优先于纹理。正交二维侧视角色/设施，UI为正视平面。保留对象身份，统一视觉语言，不复制其他作品具体资产。 【同组设计标准，仅作一致性约束】承接 STA_001，交付 14 个身体件：无发无表情头 1、含制服躯干 1、上臂左右 2、前臂左右 2、手左右 2、大腿左右 2、小腿左右 2、鞋左右 2；另交制式短棍 W00 1、观察夹板 1，共 16 件。关节内侧补全被遮区域，袖口与手掌连接清楚。夹板为旧纸矩形、金属夹和两道手写痕，不生成可读字。短棍是朴素铁灰/锈色棍，不带能量核心。 以上为整套构成；每次只生成 「逐张提示词」本张范围 指定的一个独立件，不画整套平铺图。 【本次只画】本次只画旧纸夹板、金属夹和两道不可读笔迹，不含手和可读文字；只交这一独立单元，不画其他零件、对照姿、sheet、文字或背景。保持主表指定造型、朝向与挂点。；本次只交付这一件/一个姿势，不把同组其他素材、姿势或裁切线画进本图，不拼成多格图集。 【状态】通用 【参考】附图 REF_STAFF。已批准的员工基型；当前 OBSERVE 夹板和 W00。如有前置定稿，必须保持同一造型、比例、线宽、服装和配色；拆件需另附已确认整身定稿图。 【画布】身体装配母版 1024 × 1024 px；各身体件与手持物在相同坐标画布分别导出；尺寸不支持时保持比例生成，再后处理到目标尺寸。 【输出】本次仅一张单件 PNG，sRGB；真实 Alpha 透明背景；沿用装配母版位置，不自动裁切；尺寸修正、边缘清理、分层源文件及轴点记录由后处理制作。。只输出当前这一张；套组其余部分由其他任务分别完成。透明须为真实Alpha，禁止棋盘格。 【对齐】装配根为脚底 (512, 896)；头颈、肩、肘、腕、髋、膝、踝分别记录像素挂点；两道具记录握柄点。 【禁止】不做 3D、照片写实、厚涂油画、等距俯视、高饱和二次元、霓虹光污染、密集脏污；不加文字、数字、二维码、水印、游戏界面或棋盘格背景；不把动态状态、血条、范围、路径烘焙进图。 不要照片、3D 渲染、像素风、光滑矢量图标风或高饱和日漫；不要复制现成游戏的角色、脸型或官方 IP 素材；不要背景、文字、水印、UI、血条、黄色选中圈或攻击范围；不要以红色滤镜代替形变。 | E24: =生成规范!$B$9&CHAR(10)&素材需求!S9 -> 不做 3D、照片写实、厚涂油画、等距俯视、高饱和二次元、霓虹光污染、密集脏污；不加文字、数字、二维码、水印、游戏界面或棋盘格背景；不把动态状态、血条、范围、路径烘焙进图。 不要照片、3D 渲染、像素风、光滑矢量图标风或高饱和日漫；不要复制现成游戏的角色、脸型或官方 IP 素材；不要背景、文字、水印、UI、血条、黄色选中圈或攻击范围；不要以红色滤镜代替形变。 | F24: REF_STAFF | G24: =素材需求!B9 -> P0 | H24: 身体装配母版 1024 × 1024 px；各身体件与手持物在相同坐标画布分别导出 | I24: 本次只画旧纸夹板、金属夹和两道不可读笔迹，不含手和可读文字；只交这一独立单元，不画其他零件、对照姿、sheet、文字或背景。保持主表指定造型、朝向与挂点。 | J24: 本次仅一张单件 PNG，sRGB；真实 Alpha 透明背景；沿用装配母版位置，不自动裁切；尺寸修正、边缘清理、分层源文件及轴点记录由后处理制作。 | K24: 装配根为脚底 (512, 896)；头颈、肩、肘、腕、髋、膝、踝分别记录像素挂点；两道具记录握柄点。 | L24: art_delivery/v1/characters/ | M24: 待生成 | N24: STA_001
A25: STA_003 | B25: agent_hair_quiff_01_hair.png | C25: E01 向上尖束 | D25: ="【唯一交付文件】"&B25&CHAR(10)&"【对象】"&C25&CHAR(10)&生成规范!$B$8&CHAR(10)&"【同组设计标准，仅作一致性约束】"&素材需求!G10&CHAR(10)&"【本次只画】"&I25&"；本次只交付这一件/一个姿势，不把同组其他素材、姿势或裁切线画进本图，不拼成多格图集。"&CHAR(10)&"【状态】"&素材需求!F10&CHAR(10)&"【参考】附图 "&F25&"。"&素材需求!H10&"。如有前置定稿，必须保持同一造型、比例、线宽、服装和配色；拆件需另附已确认整身定稿图。"&CHAR(10)&"【画布】"&H25&"；尺寸不支持时保持比例生成，再后处理到目标尺寸。"&CHAR(10)&"【输出】"&J25&"。只输出当前这一张；套组其余部分由其他任务分别完成。透明须为真实Alpha，禁止棋盘格。"&CHAR(10)&"【对齐】"&K25&CHAR(10)&"【禁止】"&E25 -> 【唯一交付文件】agent_hair_quiff_01_hair.png 【对象】E01 向上尖束 原创二维地下工业收容设施游戏美术；怪诞手绘收容风，受手绘怪诞生存童话的表现原则启发。hand-drawn, ink-outline, slightly grotesque, whimsical horror, 2D cutout-friendly。粗细有变化的深墨轮廓，轻微不规则手绘线，大面积低饱和平涂，少量刻线阴影；剪影与动作优先于纹理。正交二维侧视角色/设施，UI为正视平面。保留对象身份，统一视觉语言，不复制其他作品具体资产。 【同组设计标准，仅作一致性约束】原创怪诞手绘收容风：不均匀粗墨外轮廓、较细结构线、局部不对称、平涂和少量排线；轮廓在游戏缩小尺寸仍清楚。 深灰发，前额一束不等长尖峰向上偏前，后脑轮廓压低；不要对称刺猬头。 所有发型套用同一头颅，不改变脸长、颈部或眼位；发色低饱和。 【本次只画】本次只画E01 一整片前高后低的深灰向上尖束头发，不含头和脸；只交这一独立单元，不画其他零件、对照姿、sheet、文字或背景。保持主表指定造型、朝向与挂点。；本次只交付这一件/一个姿势，不把同组其他素材、姿势或裁切线画进本图，不拼成多格图集。 【状态】通用 【参考】附图 REF_STAFF。当前 E01 对应发型和已批准共用头颅。如有前置定稿，必须保持同一造型、比例、线宽、服装和配色；拆件需另附已确认整身定稿图。 【画布】1024 × 1024 px（沿用员工装配母版）；实际内容仅头部附近；尺寸不支持时保持比例生成，再后处理到目标尺寸。 【输出】1 个 RGBA 透明 PNG，保持与员工头件的注册坐标；不含头皮、脸、身体或背景。。只输出当前这一张；套组其余部分由其他任务分别完成。透明须为真实Alpha，禁止棋盘格。 【对齐】跟随共用头骨/颈部挂点；保留母版像素位置，头部旋转时不滑离头皮。 【禁止】不做 3D、照片写实、厚涂油画、等距俯视、高饱和二次元、霓虹光污染、密集脏污；不加文字、数字、二维码、水印、游戏界面或棋盘格背景；不把动态状态、血条、范围、路径烘焙进图。 不要照片、3D 渲染、像素风、光滑矢量图标风或高饱和日漫；不要复制现成游戏的角色、脸型或官方 IP 素材；不要背景、文字、水印、UI、血条、黄色选中圈或攻击范围；不要以红色滤镜代替形变。 | E25: =生成规范!$B$9&CHAR(10)&素材需求!S10 -> 不做 3D、照片写实、厚涂油画、等距俯视、高饱和二次元、霓虹光污染、密集脏污；不加文字、数字、二维码、水印、游戏界面或棋盘格背景；不把动态状态、血条、范围、路径烘焙进图。 不要照片、3D 渲染、像素风、光滑矢量图标风或高饱和日漫；不要复制现成游戏的角色、脸型或官方 IP 素材；不要背景、文字、水印、UI、血条、黄色选中圈或攻击范围；不要以红色滤镜代替形变。 | F25: REF_STAFF | G25: =素材需求!B10 -> P0 | H25: 1024 × 1024 px（沿用员工装配母版）；实际内容仅头部附近 | I25: 本次只画E01 一整片前高后低的深灰向上尖束头发，不含头和脸；只交这一独立单元，不画其他零件、对照姿、sheet、文字或背景。保持主表指定造型、朝向与挂点。 | J25: 1 个 RGBA 透明 PNG，保持与员工头件的注册坐标；不含头皮、脸、身体或背景。 | K25: 跟随共用头骨/颈部挂点；保留母版像素位置，头部旋转时不滑离头皮。 | L25: art_delivery/v1/characters/ | M25: 待生成 | N25: STA_001 / STA_002
A26: STA_004 | B26: agent_hair_side_fringe_01_hair.png | C26: E02 侧扫斜刘海 | D26: ="【唯一交付文件】"&B26&CHAR(10)&"【对象】"&C26&CHAR(10)&生成规范!$B$8&CHAR(10)&"【同组设计标准，仅作一致性约束】"&素材需求!G11&CHAR(10)&"【本次只画】"&I26&"；本次只交付这一件/一个姿势，不把同组其他素材、姿势或裁切线画进本图，不拼成多格图集。"&CHAR(10)&"【状态】"&素材需求!F11&CHAR(10)&"【参考】附图 "&F26&"。"&素材需求!H11&"。如有前置定稿，必须保持同一造型、比例、线宽、服装和配色；拆件需另附已确认整身定稿图。"&CHAR(10)&"【画布】"&H26&"；尺寸不支持时保持比例生成，再后处理到目标尺寸。"&CHAR(10)&"【输出】"&J26&"。只输出当前这一张；套组其余部分由其他任务分别完成。透明须为真实Alpha，禁止棋盘格。"&CHAR(10)&"【对齐】"&K26&CHAR(10)&"【禁止】"&E26 -> 【唯一交付文件】agent_hair_side_fringe_01_hair.png 【对象】E02 侧扫斜刘海 原创二维地下工业收容设施游戏美术；怪诞手绘收容风，受手绘怪诞生存童话的表现原则启发。hand-drawn, ink-outline, slightly grotesque, whimsical horror, 2D cutout-friendly。粗细有变化的深墨轮廓，轻微不规则手绘线，大面积低饱和平涂，少量刻线阴影；剪影与动作优先于纹理。正交二维侧视角色/设施，UI为正视平面。保留对象身份，统一视觉语言，不复制其他作品具体资产。 【同组设计标准，仅作一致性约束】原创怪诞手绘收容风：不均匀粗墨外轮廓、较细结构线、局部不对称、平涂和少量排线；轮廓在游戏缩小尺寸仍清楚。 棕锈发，大块斜刘海由高侧扫到低侧，另一侧耳根露出；长度短，不盖住双眼和眼镜挂点。 所有发型套用同一头颅，不改变脸长、颈部或眼位；发色低饱和。 【本次只画】本次只画E02 棕锈色侧扫斜刘海整体发片，不含头和脸；只交这一独立单元，不画其他零件、对照姿、sheet、文字或背景。保持主表指定造型、朝向与挂点。；本次只交付这一件/一个姿势，不把同组其他素材、姿势或裁切线画进本图，不拼成多格图集。 【状态】通用 【参考】附图 REF_STAFF。当前 E02 对应发型和已批准共用头颅。如有前置定稿，必须保持同一造型、比例、线宽、服装和配色；拆件需另附已确认整身定稿图。 【画布】1024 × 1024 px（沿用员工装配母版）；实际内容仅头部附近；尺寸不支持时保持比例生成，再后处理到目标尺寸。 【输出】1 个 RGBA 透明 PNG，保持与员工头件的注册坐标；不含头皮、脸、身体或背景。。只输出当前这一张；套组其余部分由其他任务分别完成。透明须为真实Alpha，禁止棋盘格。 【对齐】跟随共用头骨/颈部挂点；保留母版像素位置，头部旋转时不滑离头皮。 【禁止】不做 3D、照片写实、厚涂油画、等距俯视、高饱和二次元、霓虹光污染、密集脏污；不加文字、数字、二维码、水印、游戏界面或棋盘格背景；不把动态状态、血条、范围、路径烘焙进图。 不要照片、3D 渲染、像素风、光滑矢量图标风或高饱和日漫；不要复制现成游戏的角色、脸型或官方 IP 素材；不要背景、文字、水印、UI、血条、黄色选中圈或攻击范围；不要以红色滤镜代替形变。 | E26: =生成规范!$B$9&CHAR(10)&素材需求!S11 -> 不做 3D、照片写实、厚涂油画、等距俯视、高饱和二次元、霓虹光污染、密集脏污；不加文字、数字、二维码、水印、游戏界面或棋盘格背景；不把动态状态、血条、范围、路径烘焙进图。 不要照片、3D 渲染、像素风、光滑矢量图标风或高饱和日漫；不要复制现成游戏的角色、脸型或官方 IP 素材；不要背景、文字、水印、UI、血条、黄色选中圈或攻击范围；不要以红色滤镜代替形变。 | F26: REF_STAFF | G26: =素材需求!B11 -> P0 | H26: 1024 × 1024 px（沿用员工装配母版）；实际内容仅头部附近 | I26: 本次只画E02 棕锈色侧扫斜刘海整体发片，不含头和脸；只交这一独立单元，不画其他零件、对照姿、sheet、文字或背景。保持主表指定造型、朝向与挂点。 | J26: 1 个 RGBA 透明 PNG，保持与员工头件的注册坐标；不含头皮、脸、身体或背景。 | K26: 跟随共用头骨/颈部挂点；保留母版像素位置，头部旋转时不滑离头皮。 | L26: art_delivery/v1/characters/ | M26: 待生成 | N26: STA_001 / STA_002
A27: STA_010 | B27: agent_locomotion_reference_01_idle_exhale.png | C27: 待机呼气 | D27: ="【唯一交付文件】"&B27&CHAR(10)&"【对象】"&C27&CHAR(10)&生成规范!$B$8&CHAR(10)&"【同组设计标准，仅作一致性约束】"&素材需求!G12&CHAR(10)&"【本次只画】"&I27&"；本次只交付这一件/一个姿势，不把同组其他素材、姿势或裁切线画进本图，不拼成多格图集。"&CHAR(10)&"【状态】"&素材需求!F12&CHAR(10)&"【参考】附图 "&F27&"。"&素材需求!H12&"。如有前置定稿，必须保持同一造型、比例、线宽、服装和配色；拆件需另附已确认整身定稿图。"&CHAR(10)&"【画布】"&H27&"；尺寸不支持时保持比例生成，再后处理到目标尺寸。"&CHAR(10)&"【输出】"&J27&"。只输出当前这一张；套组其余部分由其他任务分别完成。透明须为真实Alpha，禁止棋盘格。"&CHAR(10)&"【对齐】"&K27&CHAR(10)&"【禁止】"&E27 -> 【唯一交付文件】agent_locomotion_reference_01_idle_exhale.png 【对象】待机呼气 原创二维地下工业收容设施游戏美术；怪诞手绘收容风，受手绘怪诞生存童话的表现原则启发。hand-drawn, ink-outline, slightly grotesque, whimsical horror, 2D cutout-friendly。粗细有变化的深墨轮廓，轻微不规则手绘线，大面积低饱和平涂，少量刻线阴影；剪影与动作优先于纹理。正交二维侧视角色/设施，UI为正视平面。保留对象身份，统一视觉语言，不复制其他作品具体资产。 【同组设计标准，仅作一致性约束】分别生成六个独立单姿参考：待机呼气/吸气 2 姿；行走左脚接触/右脚接触 2 姿；攀爬左手高/右手高 2 姿。保持大头小身与前倾；行走手脚反向、短而清楚的脚步；攀爬手脚沿竖直连接设施交替，不画跳跃、飞行或瞬移。每姿使用相同地面基线，攀爬显示参考握点。 每个独立交付文件只能含一个姿势；按 「逐张提示词」本张范围 逐张生成。 【本次只画】本次只画完整员工待机呼气姿，肩稍落、身体轻前倾，双脚站稳；只交这一独立单元，不画其他零件、对照姿、sheet、文字或背景。保持主表指定造型、朝向与挂点。；本次只交付这一件/一个姿势，不把同组其他素材、姿势或裁切线画进本图，不拼成多格图集。 【状态】IDLE / MOVING / TRANSIT 【参考】附图 REF_STAFF。批准的共用员工拆件及实际 moving/climbing/stride。如有前置定稿，必须保持同一造型、比例、线宽、服装和配色；拆件需另附已确认整身定稿图。 【画布】1024 × 1024 px，每个姿势独立一张，统一脚底 (512, 896)；尺寸不支持时保持比例生成，再后处理到目标尺寸。 【输出】本次仅一张单件 PNG，sRGB；真实 Alpha 透明背景；保持足够安全边距；尺寸修正、边缘清理、分层源文件及轴点记录由后处理制作。。只输出当前这一张；套组其余部分由其他任务分别完成。透明须为真实Alpha，禁止棋盘格。 【对齐】每格脚底基准相同；攀爬显示根节点与握点，不能烘焙相机或楼梯背景。 【禁止】不做 3D、照片写实、厚涂油画、等距俯视、高饱和二次元、霓虹光污染、密集脏污；不加文字、数字、二维码、水印、游戏界面或棋盘格背景；不把动态状态、血条、范围、路径烘焙进图。 不要照片、3D 渲染、像素风、光滑矢量图标风或高饱和日漫；不要复制现成游戏的角色、脸型或官方 IP 素材；不要背景、文字、水印、UI、血条、黄色选中圈或攻击范围；不要以红色滤镜代替形变。 | E27: =生成规范!$B$9&CHAR(10)&素材需求!S12 -> 不做 3D、照片写实、厚涂油画、等距俯视、高饱和二次元、霓虹光污染、密集脏污；不加文字、数字、二维码、水印、游戏界面或棋盘格背景；不把动态状态、血条、范围、路径烘焙进图。 不要照片、3D 渲染、像素风、光滑矢量图标风或高饱和日漫；不要复制现成游戏的角色、脸型或官方 IP 素材；不要背景、文字、水印、UI、血条、黄色选中圈或攻击范围；不要以红色滤镜代替形变。 | F27: REF_STAFF | G27: =素材需求!B12 -> P0 | H27: 1024 × 1024 px，每个姿势独立一张，统一脚底 (512, 896) | I27: 本次只画完整员工待机呼气姿，肩稍落、身体轻前倾，双脚站稳；只交这一独立单元，不画其他零件、对照姿、sheet、文字或背景。保持主表指定造型、朝向与挂点。 | J27: 本次仅一张单件 PNG，sRGB；真实 Alpha 透明背景；保持足够安全边距；尺寸修正、边缘清理、分层源文件及轴点记录由后处理制作。 | K27: 每格脚底基准相同；攀爬显示根节点与握点，不能烘焙相机或楼梯背景。 | L27: art_delivery/v1/characters/ | M27: 待生成 | N27: STA_001 / STA_002
A28: STA_010 | B28: agent_locomotion_reference_01_idle_inhale.png | C28: 待机吸气 | D28: ="【唯一交付文件】"&B28&CHAR(10)&"【对象】"&C28&CHAR(10)&生成规范!$B$8&CHAR(10)&"【同组设计标准，仅作一致性约束】"&素材需求!G12&CHAR(10)&"【本次只画】"&I28&"；本次只交付这一件/一个姿势，不把同组其他素材、姿势或裁切线画进本图，不拼成多格图集。"&CHAR(10)&"【状态】"&素材需求!F12&CHAR(10)&"【参考】附图 "&F28&"。"&素材需求!H12&"。如有前置定稿，必须保持同一造型、比例、线宽、服装和配色；拆件需另附已确认整身定稿图。"&CHAR(10)&"【画布】"&H28&"；尺寸不支持时保持比例生成，再后处理到目标尺寸。"&CHAR(10)&"【输出】"&J28&"。只输出当前这一张；套组其余部分由其他任务分别完成。透明须为真实Alpha，禁止棋盘格。"&CHAR(10)&"【对齐】"&K28&CHAR(10)&"【禁止】"&E28 -> 【唯一交付文件】agent_locomotion_reference_01_idle_inhale.png 【对象】待机吸气 原创二维地下工业收容设施游戏美术；怪诞手绘收容风，受手绘怪诞生存童话的表现原则启发。hand-drawn, ink-outline, slightly grotesque, whimsical horror, 2D cutout-friendly。粗细有变化的深墨轮廓，轻微不规则手绘线，大面积低饱和平涂，少量刻线阴影；剪影与动作优先于纹理。正交二维侧视角色/设施，UI为正视平面。保留对象身份，统一视觉语言，不复制其他作品具体资产。 【同组设计标准，仅作一致性约束】分别生成六个独立单姿参考：待机呼气/吸气 2 姿；行走左脚接触/右脚接触 2 姿；攀爬左手高/右手高 2 姿。保持大头小身与前倾；行走手脚反向、短而清楚的脚步；攀爬手脚沿竖直连接设施交替，不画跳跃、飞行或瞬移。每姿使用相同地面基线，攀爬显示参考握点。 每个独立交付文件只能含一个姿势；按 「逐张提示词」本张范围 逐张生成。 【本次只画】本次只画同一完整员工待机吸气姿，胸部和头部仅小幅抬高，双脚不移；只交这一独立单元，不画其他零件、对照姿、sheet、文字或背景。保持主表指定造型、朝向与挂点。；本次只交付这一件/一个姿势，不把同组其他素材、姿势或裁切线画进本图，不拼成多格图集。 【状态】IDLE / MOVING / TRANSIT 【参考】附图 REF_STAFF。批准的共用员工拆件及实际 moving/climbing/stride。如有前置定稿，必须保持同一造型、比例、线宽、服装和配色；拆件需另附已确认整身定稿图。 【画布】1024 × 1024 px，每个姿势独立一张，统一脚底 (512, 896)；尺寸不支持时保持比例生成，再后处理到目标尺寸。 【输出】本次仅一张单件 PNG，sRGB；真实 Alpha 透明背景；保持足够安全边距；尺寸修正、边缘清理、分层源文件及轴点记录由后处理制作。。只输出当前这一张；套组其余部分由其他任务分别完成。透明须为真实Alpha，禁止棋盘格。 【对齐】每格脚底基准相同；攀爬显示根节点与握点，不能烘焙相机或楼梯背景。 【禁止】不做 3D、照片写实、厚涂油画、等距俯视、高饱和二次元、霓虹光污染、密集脏污；不加文字、数字、二维码、水印、游戏界面或棋盘格背景；不把动态状态、血条、范围、路径烘焙进图。 不要照片、3D 渲染、像素风、光滑矢量图标风或高饱和日漫；不要复制现成游戏的角色、脸型或官方 IP 素材；不要背景、文字、水印、UI、血条、黄色选中圈或攻击范围；不要以红色滤镜代替形变。 | E28: =生成规范!$B$9&CHAR(10)&素材需求!S12 -> 不做 3D、照片写实、厚涂油画、等距俯视、高饱和二次元、霓虹光污染、密集脏污；不加文字、数字、二维码、水印、游戏界面或棋盘格背景；不把动态状态、血条、范围、路径烘焙进图。 不要照片、3D 渲染、像素风、光滑矢量图标风或高饱和日漫；不要复制现成游戏的角色、脸型或官方 IP 素材；不要背景、文字、水印、UI、血条、黄色选中圈或攻击范围；不要以红色滤镜代替形变。 | F28: REF_STAFF | G28: =素材需求!B12 -> P0 | H28: 1024 × 1024 px，每个姿势独立一张，统一脚底 (512, 896) | I28: 本次只画同一完整员工待机吸气姿，胸部和头部仅小幅抬高，双脚不移；只交这一独立单元，不画其他零件、对照姿、sheet、文字或背景。保持主表指定造型、朝向与挂点。 | J28: 本次仅一张单件 PNG，sRGB；真实 Alpha 透明背景；保持足够安全边距；尺寸修正、边缘清理、分层源文件及轴点记录由后处理制作。 | K28: 每格脚底基准相同；攀爬显示根节点与握点，不能烘焙相机或楼梯背景。 | L28: art_delivery/v1/characters/ | M28: 待生成 | N28: STA_001 / STA_002
A29: STA_010 | B29: agent_locomotion_reference_01_walk_left_contact.png | C29: 行走左脚接触 | D29: ="【唯一交付文件】"&B29&CHAR(10)&"【对象】"&C29&CHAR(10)&生成规范!$B$8&CHAR(10)&"【同组设计标准，仅作一致性约束】"&素材需求!G12&CHAR(10)&"【本次只画】"&I29&"；本次只交付这一件/一个姿势，不把同组其他素材、姿势或裁切线画进本图，不拼成多格图集。"&CHAR(10)&"【状态】"&素材需求!F12&CHAR(10)&"【参考】附图 "&F29&"。"&素材需求!H12&"。如有前置定稿，必须保持同一造型、比例、线宽、服装和配色；拆件需另附已确认整身定稿图。"&CHAR(10)&"【画布】"&H29&"；尺寸不支持时保持比例生成，再后处理到目标尺寸。"&CHAR(10)&"【输出】"&J29&"。只输出当前这一张；套组其余部分由其他任务分别完成。透明须为真实Alpha，禁止棋盘格。"&CHAR(10)&"【对齐】"&K29&CHAR(10)&"【禁止】"&E29 -> 【唯一交付文件】agent_locomotion_reference_01_walk_left_contact.png 【对象】行走左脚接触 原创二维地下工业收容设施游戏美术；怪诞手绘收容风，受手绘怪诞生存童话的表现原则启发。hand-drawn, ink-outline, slightly grotesque, whimsical horror, 2D cutout-friendly。粗细有变化的深墨轮廓，轻微不规则手绘线，大面积低饱和平涂，少量刻线阴影；剪影与动作优先于纹理。正交二维侧视角色/设施，UI为正视平面。保留对象身份，统一视觉语言，不复制其他作品具体资产。 【同组设计标准，仅作一致性约束】分别生成六个独立单姿参考：待机呼气/吸气 2 姿；行走左脚接触/右脚接触 2 姿；攀爬左手高/右手高 2 姿。保持大头小身与前倾；行走手脚反向、短而清楚的脚步；攀爬手脚沿竖直连接设施交替，不画跳跃、飞行或瞬移。每姿使用相同地面基线，攀爬显示参考握点。 每个独立交付文件只能含一个姿势；按 「逐张提示词」本张范围 逐张生成。 【本次只画】本次只画完整员工行走的左脚接触姿，右臂前摆、右脚准备提起；只交这一独立单元，不画其他零件、对照姿、sheet、文字或背景。保持主表指定造型、朝向与挂点。；本次只交付这一件/一个姿势，不把同组其他素材、姿势或裁切线画进本图，不拼成多格图集。 【状态】IDLE / MOVING / TRANSIT 【参考】附图 REF_STAFF。批准的共用员工拆件及实际 moving/climbing/stride。如有前置定稿，必须保持同一造型、比例、线宽、服装和配色；拆件需另附已确认整身定稿图。 【画布】1024 × 1024 px，每个姿势独立一张，统一脚底 (512, 896)；尺寸不支持时保持比例生成，再后处理到目标尺寸。 【输出】本次仅一张单件 PNG，sRGB；真实 Alpha 透明背景；保持足够安全边距；尺寸修正、边缘清理、分层源文件及轴点记录由后处理制作。。只输出当前这一张；套组其余部分由其他任务分别完成。透明须为真实Alpha，禁止棋盘格。 【对齐】每格脚底基准相同；攀爬显示根节点与握点，不能烘焙相机或楼梯背景。 【禁止】不做 3D、照片写实、厚涂油画、等距俯视、高饱和二次元、霓虹光污染、密集脏污；不加文字、数字、二维码、水印、游戏界面或棋盘格背景；不把动态状态、血条、范围、路径烘焙进图。 不要照片、3D 渲染、像素风、光滑矢量图标风或高饱和日漫；不要复制现成游戏的角色、脸型或官方 IP 素材；不要背景、文字、水印、UI、血条、黄色选中圈或攻击范围；不要以红色滤镜代替形变。 | E29: =生成规范!$B$9&CHAR(10)&素材需求!S12 -> 不做 3D、照片写实、厚涂油画、等距俯视、高饱和二次元、霓虹光污染、密集脏污；不加文字、数字、二维码、水印、游戏界面或棋盘格背景；不把动态状态、血条、范围、路径烘焙进图。 不要照片、3D 渲染、像素风、光滑矢量图标风或高饱和日漫；不要复制现成游戏的角色、脸型或官方 IP 素材；不要背景、文字、水印、UI、血条、黄色选中圈或攻击范围；不要以红色滤镜代替形变。 | F29: REF_STAFF | G29: =素材需求!B12 -> P0 | H29: 1024 × 1024 px，每个姿势独立一张，统一脚底 (512, 896) | I29: 本次只画完整员工行走的左脚接触姿，右臂前摆、右脚准备提起；只交这一独立单元，不画其他零件、对照姿、sheet、文字或背景。保持主表指定造型、朝向与挂点。 | J29: 本次仅一张单件 PNG，sRGB；真实 Alpha 透明背景；保持足够安全边距；尺寸修正、边缘清理、分层源文件及轴点记录由后处理制作。 | K29: 每格脚底基准相同；攀爬显示根节点与握点，不能烘焙相机或楼梯背景。 | L29: art_delivery/v1/characters/ | M29: 待生成 | N29: STA_001 / STA_002
A30: STA_010 | B30: agent_locomotion_reference_01_walk_right_contact.png | C30: 行走右脚接触 | D30: ="【唯一交付文件】"&B30&CHAR(10)&"【对象】"&C30&CHAR(10)&生成规范!$B$8&CHAR(10)&"【同组设计标准，仅作一致性约束】"&素材需求!G12&CHAR(10)&"【本次只画】"&I30&"；本次只交付这一件/一个姿势，不把同组其他素材、姿势或裁切线画进本图，不拼成多格图集。"&CHAR(10)&"【状态】"&素材需求!F12&CHAR(10)&"【参考】附图 "&F30&"。"&素材需求!H12&"。如有前置定稿，必须保持同一造型、比例、线宽、服装和配色；拆件需另附已确认整身定稿图。"&CHAR(10)&"【画布】"&H30&"；尺寸不支持时保持比例生成，再后处理到目标尺寸。"&CHAR(10)&"【输出】"&J30&"。只输出当前这一张；套组其余部分由其他任务分别完成。透明须为真实Alpha，禁止棋盘格。"&CHAR(10)&"【对齐】"&K30&CHAR(10)&"【禁止】"&E30 -> 【唯一交付文件】agent_locomotion_reference_01_walk_right_contact.png 【对象】行走右脚接触 原创二维地下工业收容设施游戏美术；怪诞手绘收容风，受手绘怪诞生存童话的表现原则启发。hand-drawn, ink-outline, slightly grotesque, whimsical horror, 2D cutout-friendly。粗细有变化的深墨轮廓，轻微不规则手绘线，大面积低饱和平涂，少量刻线阴影；剪影与动作优先于纹理。正交二维侧视角色/设施，UI为正视平面。保留对象身份，统一视觉语言，不复制其他作品具体资产。 【同组设计标准，仅作一致性约束】分别生成六个独立单姿参考：待机呼气/吸气 2 姿；行走左脚接触/右脚接触 2 姿；攀爬左手高/右手高 2 姿。保持大头小身与前倾；行走手脚反向、短而清楚的脚步；攀爬手脚沿竖直连接设施交替，不画跳跃、飞行或瞬移。每姿使用相同地面基线，攀爬显示参考握点。 每个独立交付文件只能含一个姿势；按 「逐张提示词」本张范围 逐张生成。 【本次只画】本次只画完整员工行走的右脚接触姿，左臂前摆、左脚准备提起；只交这一独立单元，不画其他零件、对照姿、sheet、文字或背景。保持主表指定造型、朝向与挂点。；本次只交付这一件/一个姿势，不把同组其他素材、姿势或裁切线画进本图，不拼成多格图集。 【状态】IDLE / MOVING / TRANSIT 【参考】附图 REF_STAFF。批准的共用员工拆件及实际 moving/climbing/stride。如有前置定稿，必须保持同一造型、比例、线宽、服装和配色；拆件需另附已确认整身定稿图。 【画布】1024 × 1024 px，每个姿势独立一张，统一脚底 (512, 896)；尺寸不支持时保持比例生成，再后处理到目标尺寸。 【输出】本次仅一张单件 PNG，sRGB；真实 Alpha 透明背景；保持足够安全边距；尺寸修正、边缘清理、分层源文件及轴点记录由后处理制作。。只输出当前这一张；套组其余部分由其他任务分别完成。透明须为真实Alpha，禁止棋盘格。 【对齐】每格脚底基准相同；攀爬显示根节点与握点，不能烘焙相机或楼梯背景。 【禁止】不做 3D、照片写实、厚涂油画、等距俯视、高饱和二次元、霓虹光污染、密集脏污；不加文字、数字、二维码、水印、游戏界面或棋盘格背景；不把动态状态、血条、范围、路径烘焙进图。 不要照片、3D 渲染、像素风、光滑矢量图标风或高饱和日漫；不要复制现成游戏的角色、脸型或官方 IP 素材；不要背景、文字、水印、UI、血条、黄色选中圈或攻击范围；不要以红色滤镜代替形变。 | E30: =生成规范!$B$9&CHAR(10)&素材需求!S12 -> 不做 3D、照片写实、厚涂油画、等距俯视、高饱和二次元、霓虹光污染、密集脏污；不加文字、数字、二维码、水印、游戏界面或棋盘格背景；不把动态状态、血条、范围、路径烘焙进图。 不要照片、3D 渲染、像素风、光滑矢量图标风或高饱和日漫；不要复制现成游戏的角色、脸型或官方 IP 素材；不要背景、文字、水印、UI、血条、黄色选中圈或攻击范围；不要以红色滤镜代替形变。 | F30: REF_STAFF | G30: =素材需求!B12 -> P0 | H30: 1024 × 1024 px，每个姿势独立一张，统一脚底 (512, 896) | I30: 本次只画完整员工行走的右脚接触姿，左臂前摆、左脚准备提起；只交这一独立单元，不画其他零件、对照姿、sheet、文字或背景。保持主表指定造型、朝向与挂点。 | J30: 本次仅一张单件 PNG，sRGB；真实 Alpha 透明背景；保持足够安全边距；尺寸修正、边缘清理、分层源文件及轴点记录由后处理制作。 | K30: 每格脚底基准相同；攀爬显示根节点与握点，不能烘焙相机或楼梯背景。 | L30: art_delivery/v1/characters/ | M30: 待生成 | N30: STA_001 / STA_002
A31: STA_010 | B31: agent_locomotion_reference_01_climb_left_high.png | C31: 攀爬左手高 | D31: ="【唯一交付文件】"&B31&CHAR(10)&"【对象】"&C31&CHAR(10)&生成规范!$B$8&CHAR(10)&"【同组设计标准，仅作一致性约束】"&素材需求!G12&CHAR(10)&"【本次只画】"&I31&"；本次只交付这一件/一个姿势，不把同组其他素材、姿势或裁切线画进本图，不拼成多格图集。"&CHAR(10)&"【状态】"&素材需求!F12&CHAR(10)&"【参考】附图 "&F31&"。"&素材需求!H12&"。如有前置定稿，必须保持同一造型、比例、线宽、服装和配色；拆件需另附已确认整身定稿图。"&CHAR(10)&"【画布】"&H31&"；尺寸不支持时保持比例生成，再后处理到目标尺寸。"&CHAR(10)&"【输出】"&J31&"。只输出当前这一张；套组其余部分由其他任务分别完成。透明须为真实Alpha，禁止棋盘格。"&CHAR(10)&"【对齐】"&K31&CHAR(10)&"【禁止】"&E31 -> 【唯一交付文件】agent_locomotion_reference_01_climb_left_high.png 【对象】攀爬左手高 原创二维地下工业收容设施游戏美术；怪诞手绘收容风，受手绘怪诞生存童话的表现原则启发。hand-drawn, ink-outline, slightly grotesque, whimsical horror, 2D cutout-friendly。粗细有变化的深墨轮廓，轻微不规则手绘线，大面积低饱和平涂，少量刻线阴影；剪影与动作优先于纹理。正交二维侧视角色/设施，UI为正视平面。保留对象身份，统一视觉语言，不复制其他作品具体资产。 【同组设计标准，仅作一致性约束】分别生成六个独立单姿参考：待机呼气/吸气 2 姿；行走左脚接触/右脚接触 2 姿；攀爬左手高/右手高 2 姿。保持大头小身与前倾；行走手脚反向、短而清楚的脚步；攀爬手脚沿竖直连接设施交替，不画跳跃、飞行或瞬移。每姿使用相同地面基线，攀爬显示参考握点。 每个独立交付文件只能含一个姿势；按 「逐张提示词」本张范围 逐张生成。 【本次只画】本次只画完整员工攀爬姿，左手高握、右手低握、腿交替支撑；不画梯子；只交这一独立单元，不画其他零件、对照姿、sheet、文字或背景。保持主表指定造型、朝向与挂点。；本次只交付这一件/一个姿势，不把同组其他素材、姿势或裁切线画进本图，不拼成多格图集。 【状态】IDLE / MOVING / TRANSIT 【参考】附图 REF_STAFF。批准的共用员工拆件及实际 moving/climbing/stride。如有前置定稿，必须保持同一造型、比例、线宽、服装和配色；拆件需另附已确认整身定稿图。 【画布】1024 × 1024 px，每个姿势独立一张，统一脚底 (512, 896)；尺寸不支持时保持比例生成，再后处理到目标尺寸。 【输出】本次仅一张单件 PNG，sRGB；真实 Alpha 透明背景；保持足够安全边距；尺寸修正、边缘清理、分层源文件及轴点记录由后处理制作。。只输出当前这一张；套组其余部分由其他任务分别完成。透明须为真实Alpha，禁止棋盘格。 【对齐】每格脚底基准相同；攀爬显示根节点与握点，不能烘焙相机或楼梯背景。 【禁止】不做 3D、照片写实、厚涂油画、等距俯视、高饱和二次元、霓虹光污染、密集脏污；不加文字、数字、二维码、水印、游戏界面或棋盘格背景；不把动态状态、血条、范围、路径烘焙进图。 不要照片、3D 渲染、像素风、光滑矢量图标风或高饱和日漫；不要复制现成游戏的角色、脸型或官方 IP 素材；不要背景、文字、水印、UI、血条、黄色选中圈或攻击范围；不要以红色滤镜代替形变。 | E31: =生成规范!$B$9&CHAR(10)&素材需求!S12 -> 不做 3D、照片写实、厚涂油画、等距俯视、高饱和二次元、霓虹光污染、密集脏污；不加文字、数字、二维码、水印、游戏界面或棋盘格背景；不把动态状态、血条、范围、路径烘焙进图。 不要照片、3D 渲染、像素风、光滑矢量图标风或高饱和日漫；不要复制现成游戏的角色、脸型或官方 IP 素材；不要背景、文字、水印、UI、血条、黄色选中圈或攻击范围；不要以红色滤镜代替形变。 | F31: REF_STAFF | G31: =素材需求!B12 -> P0 | H31: 1024 × 1024 px，每个姿势独立一张，统一脚底 (512, 896) | I31: 本次只画完整员工攀爬姿，左手高握、右手低握、腿交替支撑；不画梯子；只交这一独立单元，不画其他零件、对照姿、sheet、文字或背景。保持主表指定造型、朝向与挂点。 | J31: 本次仅一张单件 PNG，sRGB；真实 Alpha 透明背景；保持足够安全边距；尺寸修正、边缘清理、分层源文件及轴点记录由后处理制作。 | K31: 每格脚底基准相同；攀爬显示根节点与握点，不能烘焙相机或楼梯背景。 | L31: art_delivery/v1/characters/ | M31: 待生成 | N31: STA_001 / STA_002
A32: STA_010 | B32: agent_locomotion_reference_01_climb_right_high.png | C32: 攀爬右手高 | D32: ="【唯一交付文件】"&B32&CHAR(10)&"【对象】"&C32&CHAR(10)&生成规范!$B$8&CHAR(10)&"【同组设计标准，仅作一致性约束】"&素材需求!G12&CHAR(10)&"【本次只画】"&I32&"；本次只交付这一件/一个姿势，不把同组其他素材、姿势或裁切线画进本图，不拼成多格图集。"&CHAR(10)&"【状态】"&素材需求!F12&CHAR(10)&"【参考】附图 "&F32&"。"&素材需求!H12&"。如有前置定稿，必须保持同一造型、比例、线宽、服装和配色；拆件需另附已确认整身定稿图。"&CHAR(10)&"【画布】"&H32&"；尺寸不支持时保持比例生成，再后处理到目标尺寸。"&CHAR(10)&"【输出】"&J32&"。只输出当前这一张；套组其余部分由其他任务分别完成。透明须为真实Alpha，禁止棋盘格。"&CHAR(10)&"【对齐】"&K32&CHAR(10)&"【禁止】"&E32 -> 【唯一交付文件】agent_locomotion_reference_01_climb_right_high.png 【对象】攀爬右手高 原创二维地下工业收容设施游戏美术；怪诞手绘收容风，受手绘怪诞生存童话的表现原则启发。hand-drawn, ink-outline, slightly grotesque, whimsical horror, 2D cutout-friendly。粗细有变化的深墨轮廓，轻微不规则手绘线，大面积低饱和平涂，少量刻线阴影；剪影与动作优先于纹理。正交二维侧视角色/设施，UI为正视平面。保留对象身份，统一视觉语言，不复制其他作品具体资产。 【同组设计标准，仅作一致性约束】分别生成六个独立单姿参考：待机呼气/吸气 2 姿；行走左脚接触/右脚接触 2 姿；攀爬左手高/右手高 2 姿。保持大头小身与前倾；行走手脚反向、短而清楚的脚步；攀爬手脚沿竖直连接设施交替，不画跳跃、飞行或瞬移。每姿使用相同地面基线，攀爬显示参考握点。 每个独立交付文件只能含一个姿势；按 「逐张提示词」本张范围 逐张生成。 【本次只画】本次只画完整员工攀爬姿，右手高握、左手低握、腿交替支撑；不画梯子；只交这一独立单元，不画其他零件、对照姿、sheet、文字或背景。保持主表指定造型、朝向与挂点。；本次只交付这一件/一个姿势，不把同组其他素材、姿势或裁切线画进本图，不拼成多格图集。 【状态】IDLE / MOVING / TRANSIT 【参考】附图 REF_STAFF。批准的共用员工拆件及实际 moving/climbing/stride。如有前置定稿，必须保持同一造型、比例、线宽、服装和配色；拆件需另附已确认整身定稿图。 【画布】1024 × 1024 px，每个姿势独立一张，统一脚底 (512, 896)；尺寸不支持时保持比例生成，再后处理到目标尺寸。 【输出】本次仅一张单件 PNG，sRGB；真实 Alpha 透明背景；保持足够安全边距；尺寸修正、边缘清理、分层源文件及轴点记录由后处理制作。。只输出当前这一张；套组其余部分由其他任务分别完成。透明须为真实Alpha，禁止棋盘格。 【对齐】每格脚底基准相同；攀爬显示根节点与握点，不能烘焙相机或楼梯背景。 【禁止】不做 3D、照片写实、厚涂油画、等距俯视、高饱和二次元、霓虹光污染、密集脏污；不加文字、数字、二维码、水印、游戏界面或棋盘格背景；不把动态状态、血条、范围、路径烘焙进图。 不要照片、3D 渲染、像素风、光滑矢量图标风或高饱和日漫；不要复制现成游戏的角色、脸型或官方 IP 素材；不要背景、文字、水印、UI、血条、黄色选中圈或攻击范围；不要以红色滤镜代替形变。 | E32: =生成规范!$B$9&CHAR(10)&素材需求!S12 -> 不做 3D、照片写实、厚涂油画、等距俯视、高饱和二次元、霓虹光污染、密集脏污；不加文字、数字、二维码、水印、游戏界面或棋盘格背景；不把动态状态、血条、范围、路径烘焙进图。 不要照片、3D 渲染、像素风、光滑矢量图标风或高饱和日漫；不要复制现成游戏的角色、脸型或官方 IP 素材；不要背景、文字、水印、UI、血条、黄色选中圈或攻击范围；不要以红色滤镜代替形变。 | F32: REF_STAFF | G32: =素材需求!B12 -> P0 | H32: 1024 × 1024 px，每个姿势独立一张，统一脚底 (512, 896) | I32: 本次只画完整员工攀爬姿，右手高握、左手低握、腿交替支撑；不画梯子；只交这一独立单元，不画其他零件、对照姿、sheet、文字或背景。保持主表指定造型、朝向与挂点。 | J32: 本次仅一张单件 PNG，sRGB；真实 Alpha 透明背景；保持足够安全边距；尺寸修正、边缘清理、分层源文件及轴点记录由后处理制作。 | K32: 每格脚底基准相同；攀爬显示根节点与握点，不能烘焙相机或楼梯背景。 | L32: art_delivery/v1/characters/ | M32: 待生成 | N32: STA_001 / STA_002
A33: STA_011 | B33: agent_work_reference_01_observe_raise.png | C33: 观察举板 | D33: ="【唯一交付文件】"&B33&CHAR(10)&"【对象】"&C33&CHAR(10)&生成规范!$B$8&CHAR(10)&"【同组设计标准，仅作一致性约束】"&素材需求!G13&CHAR(10)&"【本次只画】"&I33&"；本次只交付这一件/一个姿势，不把同组其他素材、姿势或裁切线画进本图，不拼成多格图集。"&CHAR(10)&"【状态】"&素材需求!F13&CHAR(10)&"【参考】附图 "&F33&"。"&素材需求!H13&"。如有前置定稿，必须保持同一造型、比例、线宽、服装和配色；拆件需另附已确认整身定稿图。"&CHAR(10)&"【画布】"&H33&"；尺寸不支持时保持比例生成，再后处理到目标尺寸。"&CHAR(10)&"【输出】"&J33&"。只输出当前这一张；套组其余部分由其他任务分别完成。透明须为真实Alpha，禁止棋盘格。"&CHAR(10)&"【对齐】"&K33&CHAR(10)&"【禁止】"&E33 -> 【唯一交付文件】agent_work_reference_01_observe_raise.png 【对象】观察举板 原创二维地下工业收容设施游戏美术；怪诞手绘收容风，受手绘怪诞生存童话的表现原则启发。hand-drawn, ink-outline, slightly grotesque, whimsical horror, 2D cutout-friendly。粗细有变化的深墨轮廓，轻微不规则手绘线，大面积低饱和平涂，少量刻线阴影；剪影与动作优先于纹理。正交二维侧视角色/设施，UI为正视平面。保留对象身份，统一视觉语言，不复制其他作品具体资产。 【同组设计标准，仅作一致性约束】分别生成六个独立单姿参考，每类起/落两姿：观察将夹板靠胸或举至面前、视线落在样本；互动一手试探前伸再收回、上身小幅靠近；安抚双手低位缓慢张开、身体略后倾。用不同手势节奏区别工作，不增加法杖、扫描枪、仪式或魔法。作业双脚留在相同工作点。 每个独立交付文件只能含一个姿势；按 「逐张提示词」本张范围 逐张生成。 【本次只画】本次只画完整员工观察举板姿，夹板在胸前接近视线，目光落在夹板或样本方向；只交这一独立单元，不画其他零件、对照姿、sheet、文字或背景。保持主表指定造型、朝向与挂点。；本次只交付这一件/一个姿势，不把同组其他素材、姿势或裁切线画进本图，不拼成多格图集。 【状态】OBSERVE / INTERACT / SOOTHE 【参考】附图 REF_STAFF。drawHuman 的 workType 和原有夹板。如有前置定稿，必须保持同一造型、比例、线宽、服装和配色；拆件需另附已确认整身定稿图。 【画布】1024 × 1024 px，每个姿势独立一张，统一脚底 (512, 896)；尺寸不支持时保持比例生成，再后处理到目标尺寸。 【输出】本次仅一张单件 PNG，sRGB；真实 Alpha 透明背景；保持足够安全边距；尺寸修正、边缘清理、分层源文件及轴点记录由后处理制作。。只输出当前这一张；套组其余部分由其他任务分别完成。透明须为真实Alpha，禁止棋盘格。 【对齐】每格相同脚底根节点；夹板挂腕/手掌，前伸只改变肢体局部，不改变工作点。 【禁止】不做 3D、照片写实、厚涂油画、等距俯视、高饱和二次元、霓虹光污染、密集脏污；不加文字、数字、二维码、水印、游戏界面或棋盘格背景；不把动态状态、血条、范围、路径烘焙进图。 不要照片、3D 渲染、像素风、光滑矢量图标风或高饱和日漫；不要复制现成游戏的角色、脸型或官方 IP 素材；不要背景、文字、水印、UI、血条、黄色选中圈或攻击范围；不要以红色滤镜代替形变。 | E33: =生成规范!$B$9&CHAR(10)&素材需求!S13 -> 不做 3D、照片写实、厚涂油画、等距俯视、高饱和二次元、霓虹光污染、密集脏污；不加文字、数字、二维码、水印、游戏界面或棋盘格背景；不把动态状态、血条、范围、路径烘焙进图。 不要照片、3D 渲染、像素风、光滑矢量图标风或高饱和日漫；不要复制现成游戏的角色、脸型或官方 IP 素材；不要背景、文字、水印、UI、血条、黄色选中圈或攻击范围；不要以红色滤镜代替形变。 | F33: REF_STAFF | G33: =素材需求!B13 -> P0 | H33: 1024 × 1024 px，每个姿势独立一张，统一脚底 (512, 896) | I33: 本次只画完整员工观察举板姿，夹板在胸前接近视线，目光落在夹板或样本方向；只交这一独立单元，不画其他零件、对照姿、sheet、文字或背景。保持主表指定造型、朝向与挂点。 | J33: 本次仅一张单件 PNG，sRGB；真实 Alpha 透明背景；保持足够安全边距；尺寸修正、边缘清理、分层源文件及轴点记录由后处理制作。 | K33: 每格相同脚底根节点；夹板挂腕/手掌，前伸只改变肢体局部，不改变工作点。 | L33: art_delivery/v1/characters/ | M33: 待生成 | N33: STA_001 / STA_002
A34: STA_011 | B34: agent_work_reference_01_observe_rest.png | C34: 观察收板 | D34: ="【唯一交付文件】"&B34&CHAR(10)&"【对象】"&C34&CHAR(10)&生成规范!$B$8&CHAR(10)&"【同组设计标准，仅作一致性约束】"&素材需求!G13&CHAR(10)&"【本次只画】"&I34&"；本次只交付这一件/一个姿势，不把同组其他素材、姿势或裁切线画进本图，不拼成多格图集。"&CHAR(10)&"【状态】"&素材需求!F13&CHAR(10)&"【参考】附图 "&F34&"。"&素材需求!H13&"。如有前置定稿，必须保持同一造型、比例、线宽、服装和配色；拆件需另附已确认整身定稿图。"&CHAR(10)&"【画布】"&H34&"；尺寸不支持时保持比例生成，再后处理到目标尺寸。"&CHAR(10)&"【输出】"&J34&"。只输出当前这一张；套组其余部分由其他任务分别完成。透明须为真实Alpha，禁止棋盘格。"&CHAR(10)&"【对齐】"&K34&CHAR(10)&"【禁止】"&E34 -> 【唯一交付文件】agent_work_reference_01_observe_rest.png 【对象】观察收板 原创二维地下工业收容设施游戏美术；怪诞手绘收容风，受手绘怪诞生存童话的表现原则启发。hand-drawn, ink-outline, slightly grotesque, whimsical horror, 2D cutout-friendly。粗细有变化的深墨轮廓，轻微不规则手绘线，大面积低饱和平涂，少量刻线阴影；剪影与动作优先于纹理。正交二维侧视角色/设施，UI为正视平面。保留对象身份，统一视觉语言，不复制其他作品具体资产。 【同组设计标准，仅作一致性约束】分别生成六个独立单姿参考，每类起/落两姿：观察将夹板靠胸或举至面前、视线落在样本；互动一手试探前伸再收回、上身小幅靠近；安抚双手低位缓慢张开、身体略后倾。用不同手势节奏区别工作，不增加法杖、扫描枪、仪式或魔法。作业双脚留在相同工作点。 每个独立交付文件只能含一个姿势；按 「逐张提示词」本张范围 逐张生成。 【本次只画】本次只画同一完整员工观察收板姿，夹板略降、头轻微偏向样本方向；只交这一独立单元，不画其他零件、对照姿、sheet、文字或背景。保持主表指定造型、朝向与挂点。；本次只交付这一件/一个姿势，不把同组其他素材、姿势或裁切线画进本图，不拼成多格图集。 【状态】OBSERVE / INTERACT / SOOTHE 【参考】附图 REF_STAFF。drawHuman 的 workType 和原有夹板。如有前置定稿，必须保持同一造型、比例、线宽、服装和配色；拆件需另附已确认整身定稿图。 【画布】1024 × 1024 px，每个姿势独立一张，统一脚底 (512, 896)；尺寸不支持时保持比例生成，再后处理到目标尺寸。 【输出】本次仅一张单件 PNG，sRGB；真实 Alpha 透明背景；保持足够安全边距；尺寸修正、边缘清理、分层源文件及轴点记录由后处理制作。。只输出当前这一张；套组其余部分由其他任务分别完成。透明须为真实Alpha，禁止棋盘格。 【对齐】每格相同脚底根节点；夹板挂腕/手掌，前伸只改变肢体局部，不改变工作点。 【禁止】不做 3D、照片写实、厚涂油画、等距俯视、高饱和二次元、霓虹光污染、密集脏污；不加文字、数字、二维码、水印、游戏界面或棋盘格背景；不把动态状态、血条、范围、路径烘焙进图。 不要照片、3D 渲染、像素风、光滑矢量图标风或高饱和日漫；不要复制现成游戏的角色、脸型或官方 IP 素材；不要背景、文字、水印、UI、血条、黄色选中圈或攻击范围；不要以红色滤镜代替形变。 | E34: =生成规范!$B$9&CHAR(10)&素材需求!S13 -> 不做 3D、照片写实、厚涂油画、等距俯视、高饱和二次元、霓虹光污染、密集脏污；不加文字、数字、二维码、水印、游戏界面或棋盘格背景；不把动态状态、血条、范围、路径烘焙进图。 不要照片、3D 渲染、像素风、光滑矢量图标风或高饱和日漫；不要复制现成游戏的角色、脸型或官方 IP 素材；不要背景、文字、水印、UI、血条、黄色选中圈或攻击范围；不要以红色滤镜代替形变。 | F34: REF_STAFF | G34: =素材需求!B13 -> P0 | H34: 1024 × 1024 px，每个姿势独立一张，统一脚底 (512, 896) | I34: 本次只画同一完整员工观察收板姿，夹板略降、头轻微偏向样本方向；只交这一独立单元，不画其他零件、对照姿、sheet、文字或背景。保持主表指定造型、朝向与挂点。 | J34: 本次仅一张单件 PNG，sRGB；真实 Alpha 透明背景；保持足够安全边距；尺寸修正、边缘清理、分层源文件及轴点记录由后处理制作。 | K34: 每格相同脚底根节点；夹板挂腕/手掌，前伸只改变肢体局部，不改变工作点。 | L34: art_delivery/v1/characters/ | M34: 待生成 | N34: STA_001 / STA_002
A35: STA_011 | B35: agent_work_reference_01_interact_reach.png | C35: 互动探手 | D35: ="【唯一交付文件】"&B35&CHAR(10)&"【对象】"&C35&CHAR(10)&生成规范!$B$8&CHAR(10)&"【同组设计标准，仅作一致性约束】"&素材需求!G13&CHAR(10)&"【本次只画】"&I35&"；本次只交付这一件/一个姿势，不把同组其他素材、姿势或裁切线画进本图，不拼成多格图集。"&CHAR(10)&"【状态】"&素材需求!F13&CHAR(10)&"【参考】附图 "&F35&"。"&素材需求!H13&"。如有前置定稿，必须保持同一造型、比例、线宽、服装和配色；拆件需另附已确认整身定稿图。"&CHAR(10)&"【画布】"&H35&"；尺寸不支持时保持比例生成，再后处理到目标尺寸。"&CHAR(10)&"【输出】"&J35&"。只输出当前这一张；套组其余部分由其他任务分别完成。透明须为真实Alpha，禁止棋盘格。"&CHAR(10)&"【对齐】"&K35&CHAR(10)&"【禁止】"&E35 -> 【唯一交付文件】agent_work_reference_01_interact_reach.png 【对象】互动探手 原创二维地下工业收容设施游戏美术；怪诞手绘收容风，受手绘怪诞生存童话的表现原则启发。hand-drawn, ink-outline, slightly grotesque, whimsical horror, 2D cutout-friendly。粗细有变化的深墨轮廓，轻微不规则手绘线，大面积低饱和平涂，少量刻线阴影；剪影与动作优先于纹理。正交二维侧视角色/设施，UI为正视平面。保留对象身份，统一视觉语言，不复制其他作品具体资产。 【同组设计标准，仅作一致性约束】分别生成六个独立单姿参考，每类起/落两姿：观察将夹板靠胸或举至面前、视线落在样本；互动一手试探前伸再收回、上身小幅靠近；安抚双手低位缓慢张开、身体略后倾。用不同手势节奏区别工作，不增加法杖、扫描枪、仪式或魔法。作业双脚留在相同工作点。 每个独立交付文件只能含一个姿势；按 「逐张提示词」本张范围 逐张生成。 【本次只画】本次只画完整员工互动探手姿，一手试探前伸、上身略靠近，双脚不移；只交这一独立单元，不画其他零件、对照姿、sheet、文字或背景。保持主表指定造型、朝向与挂点。；本次只交付这一件/一个姿势，不把同组其他素材、姿势或裁切线画进本图，不拼成多格图集。 【状态】OBSERVE / INTERACT / SOOTHE 【参考】附图 REF_STAFF。drawHuman 的 workType 和原有夹板。如有前置定稿，必须保持同一造型、比例、线宽、服装和配色；拆件需另附已确认整身定稿图。 【画布】1024 × 1024 px，每个姿势独立一张，统一脚底 (512, 896)；尺寸不支持时保持比例生成，再后处理到目标尺寸。 【输出】本次仅一张单件 PNG，sRGB；真实 Alpha 透明背景；保持足够安全边距；尺寸修正、边缘清理、分层源文件及轴点记录由后处理制作。。只输出当前这一张；套组其余部分由其他任务分别完成。透明须为真实Alpha，禁止棋盘格。 【对齐】每格相同脚底根节点；夹板挂腕/手掌，前伸只改变肢体局部，不改变工作点。 【禁止】不做 3D、照片写实、厚涂油画、等距俯视、高饱和二次元、霓虹光污染、密集脏污；不加文字、数字、二维码、水印、游戏界面或棋盘格背景；不把动态状态、血条、范围、路径烘焙进图。 不要照片、3D 渲染、像素风、光滑矢量图标风或高饱和日漫；不要复制现成游戏的角色、脸型或官方 IP 素材；不要背景、文字、水印、UI、血条、黄色选中圈或攻击范围；不要以红色滤镜代替形变。 | E35: =生成规范!$B$9&CHAR(10)&素材需求!S13 -> 不做 3D、照片写实、厚涂油画、等距俯视、高饱和二次元、霓虹光污染、密集脏污；不加文字、数字、二维码、水印、游戏界面或棋盘格背景；不把动态状态、血条、范围、路径烘焙进图。 不要照片、3D 渲染、像素风、光滑矢量图标风或高饱和日漫；不要复制现成游戏的角色、脸型或官方 IP 素材；不要背景、文字、水印、UI、血条、黄色选中圈或攻击范围；不要以红色滤镜代替形变。 | F35: REF_STAFF | G35: =素材需求!B13 -> P0 | H35: 1024 × 1024 px，每个姿势独立一张，统一脚底 (512, 896) | I35: 本次只画完整员工互动探手姿，一手试探前伸、上身略靠近，双脚不移；只交这一独立单元，不画其他零件、对照姿、sheet、文字或背景。保持主表指定造型、朝向与挂点。 | J35: 本次仅一张单件 PNG，sRGB；真实 Alpha 透明背景；保持足够安全边距；尺寸修正、边缘清理、分层源文件及轴点记录由后处理制作。 | K35: 每格相同脚底根节点；夹板挂腕/手掌，前伸只改变肢体局部，不改变工作点。 | L35: art_delivery/v1/characters/ | M35: 待生成 | N35: STA_001 / STA_002
A36: STA_011 | B36: agent_work_reference_01_interact_retract.png | C36: 互动收手 | D36: ="【唯一交付文件】"&B36&CHAR(10)&"【对象】"&C36&CHAR(10)&生成规范!$B$8&CHAR(10)&"【同组设计标准，仅作一致性约束】"&素材需求!G13&CHAR(10)&"【本次只画】"&I36&"；本次只交付这一件/一个姿势，不把同组其他素材、姿势或裁切线画进本图，不拼成多格图集。"&CHAR(10)&"【状态】"&素材需求!F13&CHAR(10)&"【参考】附图 "&F36&"。"&素材需求!H13&"。如有前置定稿，必须保持同一造型、比例、线宽、服装和配色；拆件需另附已确认整身定稿图。"&CHAR(10)&"【画布】"&H36&"；尺寸不支持时保持比例生成，再后处理到目标尺寸。"&CHAR(10)&"【输出】"&J36&"。只输出当前这一张；套组其余部分由其他任务分别完成。透明须为真实Alpha，禁止棋盘格。"&CHAR(10)&"【对齐】"&K36&CHAR(10)&"【禁止】"&E36 -> 【唯一交付文件】agent_work_reference_01_interact_retract.png 【对象】互动收手 原创二维地下工业收容设施游戏美术；怪诞手绘收容风，受手绘怪诞生存童话的表现原则启发。hand-drawn, ink-outline, slightly grotesque, whimsical horror, 2D cutout-friendly。粗细有变化的深墨轮廓，轻微不规则手绘线，大面积低饱和平涂，少量刻线阴影；剪影与动作优先于纹理。正交二维侧视角色/设施，UI为正视平面。保留对象身份，统一视觉语言，不复制其他作品具体资产。 【同组设计标准，仅作一致性约束】分别生成六个独立单姿参考，每类起/落两姿：观察将夹板靠胸或举至面前、视线落在样本；互动一手试探前伸再收回、上身小幅靠近；安抚双手低位缓慢张开、身体略后倾。用不同手势节奏区别工作，不增加法杖、扫描枪、仪式或魔法。作业双脚留在相同工作点。 每个独立交付文件只能含一个姿势；按 「逐张提示词」本张范围 逐张生成。 【本次只画】本次只画完整员工互动收手姿，前伸手收回胸前，双脚不移；只交这一独立单元，不画其他零件、对照姿、sheet、文字或背景。保持主表指定造型、朝向与挂点。；本次只交付这一件/一个姿势，不把同组其他素材、姿势或裁切线画进本图，不拼成多格图集。 【状态】OBSERVE / INTERACT / SOOTHE 【参考】附图 REF_STAFF。drawHuman 的 workType 和原有夹板。如有前置定稿，必须保持同一造型、比例、线宽、服装和配色；拆件需另附已确认整身定稿图。 【画布】1024 × 1024 px，每个姿势独立一张，统一脚底 (512, 896)；尺寸不支持时保持比例生成，再后处理到目标尺寸。 【输出】本次仅一张单件 PNG，sRGB；真实 Alpha 透明背景；保持足够安全边距；尺寸修正、边缘清理、分层源文件及轴点记录由后处理制作。。只输出当前这一张；套组其余部分由其他任务分别完成。透明须为真实Alpha，禁止棋盘格。 【对齐】每格相同脚底根节点；夹板挂腕/手掌，前伸只改变肢体局部，不改变工作点。 【禁止】不做 3D、照片写实、厚涂油画、等距俯视、高饱和二次元、霓虹光污染、密集脏污；不加文字、数字、二维码、水印、游戏界面或棋盘格背景；不把动态状态、血条、范围、路径烘焙进图。 不要照片、3D 渲染、像素风、光滑矢量图标风或高饱和日漫；不要复制现成游戏的角色、脸型或官方 IP 素材；不要背景、文字、水印、UI、血条、黄色选中圈或攻击范围；不要以红色滤镜代替形变。 | E36: =生成规范!$B$9&CHAR(10)&素材需求!S13 -> 不做 3D、照片写实、厚涂油画、等距俯视、高饱和二次元、霓虹光污染、密集脏污；不加文字、数字、二维码、水印、游戏界面或棋盘格背景；不把动态状态、血条、范围、路径烘焙进图。 不要照片、3D 渲染、像素风、光滑矢量图标风或高饱和日漫；不要复制现成游戏的角色、脸型或官方 IP 素材；不要背景、文字、水印、UI、血条、黄色选中圈或攻击范围；不要以红色滤镜代替形变。 | F36: REF_STAFF | G36: =素材需求!B13 -> P0 | H36: 1024 × 1024 px，每个姿势独立一张，统一脚底 (512, 896) | I36: 本次只画完整员工互动收手姿，前伸手收回胸前，双脚不移；只交这一独立单元，不画其他零件、对照姿、sheet、文字或背景。保持主表指定造型、朝向与挂点。 | J36: 本次仅一张单件 PNG，sRGB；真实 Alpha 透明背景；保持足够安全边距；尺寸修正、边缘清理、分层源文件及轴点记录由后处理制作。 | K36: 每格相同脚底根节点；夹板挂腕/手掌，前伸只改变肢体局部，不改变工作点。 | L36: art_delivery/v1/characters/ | M36: 待生成 | N36: STA_001 / STA_002
A37: STA_011 | B37: agent_work_reference_01_soothe_open.png | C37: 安抚张手 | D37: ="【唯一交付文件】"&B37&CHAR(10)&"【对象】"&C37&CHAR(10)&生成规范!$B$8&CHAR(10)&"【同组设计标准，仅作一致性约束】"&素材需求!G13&CHAR(10)&"【本次只画】"&I37&"；本次只交付这一件/一个姿势，不把同组其他素材、姿势或裁切线画进本图，不拼成多格图集。"&CHAR(10)&"【状态】"&素材需求!F13&CHAR(10)&"【参考】附图 "&F37&"。"&素材需求!H13&"。如有前置定稿，必须保持同一造型、比例、线宽、服装和配色；拆件需另附已确认整身定稿图。"&CHAR(10)&"【画布】"&H37&"；尺寸不支持时保持比例生成，再后处理到目标尺寸。"&CHAR(10)&"【输出】"&J37&"。只输出当前这一张；套组其余部分由其他任务分别完成。透明须为真实Alpha，禁止棋盘格。"&CHAR(10)&"【对齐】"&K37&CHAR(10)&"【禁止】"&E37 -> 【唯一交付文件】agent_work_reference_01_soothe_open.png 【对象】安抚张手 原创二维地下工业收容设施游戏美术；怪诞手绘收容风，受手绘怪诞生存童话的表现原则启发。hand-drawn, ink-outline, slightly grotesque, whimsical horror, 2D cutout-friendly。粗细有变化的深墨轮廓，轻微不规则手绘线，大面积低饱和平涂，少量刻线阴影；剪影与动作优先于纹理。正交二维侧视角色/设施，UI为正视平面。保留对象身份，统一视觉语言，不复制其他作品具体资产。 【同组设计标准，仅作一致性约束】分别生成六个独立单姿参考，每类起/落两姿：观察将夹板靠胸或举至面前、视线落在样本；互动一手试探前伸再收回、上身小幅靠近；安抚双手低位缓慢张开、身体略后倾。用不同手势节奏区别工作，不增加法杖、扫描枪、仪式或魔法。作业双脚留在相同工作点。 每个独立交付文件只能含一个姿势；按 「逐张提示词」本张范围 逐张生成。 【本次只画】本次只画完整员工安抚张手姿，双手低位缓慢打开、身体略后倾；只交这一独立单元，不画其他零件、对照姿、sheet、文字或背景。保持主表指定造型、朝向与挂点。；本次只交付这一件/一个姿势，不把同组其他素材、姿势或裁切线画进本图，不拼成多格图集。 【状态】OBSERVE / INTERACT / SOOTHE 【参考】附图 REF_STAFF。drawHuman 的 workType 和原有夹板。如有前置定稿，必须保持同一造型、比例、线宽、服装和配色；拆件需另附已确认整身定稿图。 【画布】1024 × 1024 px，每个姿势独立一张，统一脚底 (512, 896)；尺寸不支持时保持比例生成，再后处理到目标尺寸。 【输出】本次仅一张单件 PNG，sRGB；真实 Alpha 透明背景；保持足够安全边距；尺寸修正、边缘清理、分层源文件及轴点记录由后处理制作。。只输出当前这一张；套组其余部分由其他任务分别完成。透明须为真实Alpha，禁止棋盘格。 【对齐】每格相同脚底根节点；夹板挂腕/手掌，前伸只改变肢体局部，不改变工作点。 【禁止】不做 3D、照片写实、厚涂油画、等距俯视、高饱和二次元、霓虹光污染、密集脏污；不加文字、数字、二维码、水印、游戏界面或棋盘格背景；不把动态状态、血条、范围、路径烘焙进图。 不要照片、3D 渲染、像素风、光滑矢量图标风或高饱和日漫；不要复制现成游戏的角色、脸型或官方 IP 素材；不要背景、文字、水印、UI、血条、黄色选中圈或攻击范围；不要以红色滤镜代替形变。 | E37: =生成规范!$B$9&CHAR(10)&素材需求!S13 -> 不做 3D、照片写实、厚涂油画、等距俯视、高饱和二次元、霓虹光污染、密集脏污；不加文字、数字、二维码、水印、游戏界面或棋盘格背景；不把动态状态、血条、范围、路径烘焙进图。 不要照片、3D 渲染、像素风、光滑矢量图标风或高饱和日漫；不要复制现成游戏的角色、脸型或官方 IP 素材；不要背景、文字、水印、UI、血条、黄色选中圈或攻击范围；不要以红色滤镜代替形变。 | F37: REF_STAFF | G37: =素材需求!B13 -> P0 | H37: 1024 × 1024 px，每个姿势独立一张，统一脚底 (512, 896) | I37: 本次只画完整员工安抚张手姿，双手低位缓慢打开、身体略后倾；只交这一独立单元，不画其他零件、对照姿、sheet、文字或背景。保持主表指定造型、朝向与挂点。 | J37: 本次仅一张单件 PNG，sRGB；真实 Alpha 透明背景；保持足够安全边距；尺寸修正、边缘清理、分层源文件及轴点记录由后处理制作。 | K37: 每格相同脚底根节点；夹板挂腕/手掌，前伸只改变肢体局部，不改变工作点。 | L37: art_delivery/v1/characters/ | M37: 待生成 | N37: STA_001 / STA_002
A38: STA_011 | B38: agent_work_reference_01_soothe_settle.png | C38: 安抚落手 | D38: ="【唯一交付文件】"&B38&CHAR(10)&"【对象】"&C38&CHAR(10)&生成规范!$B$8&CHAR(10)&"【同组设计标准，仅作一致性约束】"&素材需求!G13&CHAR(10)&"【本次只画】"&I38&"；本次只交付这一件/一个姿势，不把同组其他素材、姿势或裁切线画进本图，不拼成多格图集。"&CHAR(10)&"【状态】"&素材需求!F13&CHAR(10)&"【参考】附图 "&F38&"。"&素材需求!H13&"。如有前置定稿，必须保持同一造型、比例、线宽、服装和配色；拆件需另附已确认整身定稿图。"&CHAR(10)&"【画布】"&H38&"；尺寸不支持时保持比例生成，再后处理到目标尺寸。"&CHAR(10)&"【输出】"&J38&"。只输出当前这一张；套组其余部分由其他任务分别完成。透明须为真实Alpha，禁止棋盘格。"&CHAR(10)&"【对齐】"&K38&CHAR(10)&"【禁止】"&E38 -> 【唯一交付文件】agent_work_reference_01_soothe_settle.png 【对象】安抚落手 原创二维地下工业收容设施游戏美术；怪诞手绘收容风，受手绘怪诞生存童话的表现原则启发。hand-drawn, ink-outline, slightly grotesque, whimsical horror, 2D cutout-friendly。粗细有变化的深墨轮廓，轻微不规则手绘线，大面积低饱和平涂，少量刻线阴影；剪影与动作优先于纹理。正交二维侧视角色/设施，UI为正视平面。保留对象身份，统一视觉语言，不复制其他作品具体资产。 【同组设计标准，仅作一致性约束】分别生成六个独立单姿参考，每类起/落两姿：观察将夹板靠胸或举至面前、视线落在样本；互动一手试探前伸再收回、上身小幅靠近；安抚双手低位缓慢张开、身体略后倾。用不同手势节奏区别工作，不增加法杖、扫描枪、仪式或魔法。作业双脚留在相同工作点。 每个独立交付文件只能含一个姿势；按 「逐张提示词」本张范围 逐张生成。 【本次只画】本次只画完整员工安抚落手姿，双手降低并收拢，肩线放松但仍紧张；只交这一独立单元，不画其他零件、对照姿、sheet、文字或背景。保持主表指定造型、朝向与挂点。；本次只交付这一件/一个姿势，不把同组其他素材、姿势或裁切线画进本图，不拼成多格图集。 【状态】OBSERVE / INTERACT / SOOTHE 【参考】附图 REF_STAFF。drawHuman 的 workType 和原有夹板。如有前置定稿，必须保持同一造型、比例、线宽、服装和配色；拆件需另附已确认整身定稿图。 【画布】1024 × 1024 px，每个姿势独立一张，统一脚底 (512, 896)；尺寸不支持时保持比例生成，再后处理到目标尺寸。 【输出】本次仅一张单件 PNG，sRGB；真实 Alpha 透明背景；保持足够安全边距；尺寸修正、边缘清理、分层源文件及轴点记录由后处理制作。。只输出当前这一张；套组其余部分由其他任务分别完成。透明须为真实Alpha，禁止棋盘格。 【对齐】每格相同脚底根节点；夹板挂腕/手掌，前伸只改变肢体局部，不改变工作点。 【禁止】不做 3D、照片写实、厚涂油画、等距俯视、高饱和二次元、霓虹光污染、密集脏污；不加文字、数字、二维码、水印、游戏界面或棋盘格背景；不把动态状态、血条、范围、路径烘焙进图。 不要照片、3D 渲染、像素风、光滑矢量图标风或高饱和日漫；不要复制现成游戏的角色、脸型或官方 IP 素材；不要背景、文字、水印、UI、血条、黄色选中圈或攻击范围；不要以红色滤镜代替形变。 | E38: =生成规范!$B$9&CHAR(10)&素材需求!S13 -> 不做 3D、照片写实、厚涂油画、等距俯视、高饱和二次元、霓虹光污染、密集脏污；不加文字、数字、二维码、水印、游戏界面或棋盘格背景；不把动态状态、血条、范围、路径烘焙进图。 不要照片、3D 渲染、像素风、光滑矢量图标风或高饱和日漫；不要复制现成游戏的角色、脸型或官方 IP 素材；不要背景、文字、水印、UI、血条、黄色选中圈或攻击范围；不要以红色滤镜代替形变。 | F38: REF_STAFF | G38: =素材需求!B13 -> P0 | H38: 1024 × 1024 px，每个姿势独立一张，统一脚底 (512, 896) | I38: 本次只画完整员工安抚落手姿，双手降低并收拢，肩线放松但仍紧张；只交这一独立单元，不画其他零件、对照姿、sheet、文字或背景。保持主表指定造型、朝向与挂点。 | J38: 本次仅一张单件 PNG，sRGB；真实 Alpha 透明背景；保持足够安全边距；尺寸修正、边缘清理、分层源文件及轴点记录由后处理制作。 | K38: 每格相同脚底根节点；夹板挂腕/手掌，前伸只改变肢体局部，不改变工作点。 | L38: art_delivery/v1/characters/ | M38: 待生成 | N38: STA_001 / STA_002
A39: STA_012 | B39: agent_distress_reference_01_panic_idle.png | C39: 恐慌站立 | D39: ="【唯一交付文件】"&B39&CHAR(10)&"【对象】"&C39&CHAR(10)&生成规范!$B$8&CHAR(10)&"【同组设计标准，仅作一致性约束】"&素材需求!G14&CHAR(10)&"【本次只画】"&I39&"；本次只交付这一件/一个姿势，不把同组其他素材、姿势或裁切线画进本图，不拼成多格图集。"&CHAR(10)&"【状态】"&素材需求!F14&CHAR(10)&"【参考】附图 "&F39&"。"&素材需求!H14&"。如有前置定稿，必须保持同一造型、比例、线宽、服装和配色；拆件需另附已确认整身定稿图。"&CHAR(10)&"【画布】"&H39&"；尺寸不支持时保持比例生成，再后处理到目标尺寸。"&CHAR(10)&"【输出】"&J39&"。只输出当前这一张；套组其余部分由其他任务分别完成。透明须为真实Alpha，禁止棋盘格。"&CHAR(10)&"【对齐】"&K39&CHAR(10)&"【禁止】"&E39 -> 【唯一交付文件】agent_distress_reference_01_panic_idle.png 【对象】恐慌站立 原创二维地下工业收容设施游戏美术；怪诞手绘收容风，受手绘怪诞生存童话的表现原则启发。hand-drawn, ink-outline, slightly grotesque, whimsical horror, 2D cutout-friendly。粗细有变化的深墨轮廓，轻微不规则手绘线，大面积低饱和平涂，少量刻线阴影；剪影与动作优先于纹理。正交二维侧视角色/设施，UI为正视平面。保留对象身份，统一视觉语言，不复制其他作品具体资产。 【同组设计标准，仅作一致性约束】分别生成六个独立单姿参考：恐慌站立和踉跄行走 2 姿（夸张张口、护头手、步态不协调）；受击瞬间回缩 1 姿；低 HP 弯腰护身但保持可移动 1 姿；本日重伤倒地的落姿与稳定倒地 2 姿。仅用少量抽象墨痕和衣物皱折；倒地身体卧倒在脚底注册点附近。不要把低 HP 画成拄杖或新增爬行状态。 每个独立交付文件只能含一个姿势；按 「逐张提示词」本张范围 逐张生成。 【本次只画】本次只画完整员工恐慌站立姿，歪斜大眼、张口、一手护头，双脚不协调但仍接地；只交这一独立单元，不画其他零件、对照姿、sheet、文字或背景。保持主表指定造型、朝向与挂点。；本次只交付这一件/一个姿势，不把同组其他素材、姿势或裁切线画进本图，不拼成多格图集。 【状态】PANICKED / HURT / LOW_HP / INCAPACITATED 【参考】附图 REF_STAFF。当前真实员工 panic、hurt、hp<40%、INCAPACITATED 绘制。如有前置定稿，必须保持同一造型、比例、线宽、服装和配色；拆件需另附已确认整身定稿图。 【画布】1024 × 1024 px，每个姿势独立一张，统一脚底 (512, 896)；尺寸不支持时保持比例生成，再后处理到目标尺寸。 【输出】本次仅一张单件 PNG，sRGB；真实 Alpha 透明背景；保持足够安全边距；尺寸修正、边缘清理、分层源文件及轴点记录由后处理制作。。只输出当前这一张；套组其余部分由其他任务分别完成。透明须为真实Alpha，禁止棋盘格。 【对齐】倒地仍围绕原脚底根节点；直立姿与落姿保持同一坐标基准，不横向传送。 【禁止】不做 3D、照片写实、厚涂油画、等距俯视、高饱和二次元、霓虹光污染、密集脏污；不加文字、数字、二维码、水印、游戏界面或棋盘格背景；不把动态状态、血条、范围、路径烘焙进图。 不要照片、3D 渲染、像素风、光滑矢量图标风或高饱和日漫；不要复制现成游戏的角色、脸型或官方 IP 素材；不要背景、文字、水印、UI、血条、黄色选中圈或攻击范围；不要以红色滤镜代替形变。 不要永久死亡、自动医疗复活、血腥内脏、以低血量动画改变真实移动速度。 | E39: =生成规范!$B$9&CHAR(10)&素材需求!S14 -> 不做 3D、照片写实、厚涂油画、等距俯视、高饱和二次元、霓虹光污染、密集脏污；不加文字、数字、二维码、水印、游戏界面或棋盘格背景；不把动态状态、血条、范围、路径烘焙进图。 不要照片、3D 渲染、像素风、光滑矢量图标风或高饱和日漫；不要复制现成游戏的角色、脸型或官方 IP 素材；不要背景、文字、水印、UI、血条、黄色选中圈或攻击范围；不要以红色滤镜代替形变。 不要永久死亡、自动医疗复活、血腥内脏、以低血量动画改变真实移动速度。 | F39: REF_STAFF | G39: =素材需求!B14 -> P0 | H39: 1024 × 1024 px，每个姿势独立一张，统一脚底 (512, 896) | I39: 本次只画完整员工恐慌站立姿，歪斜大眼、张口、一手护头，双脚不协调但仍接地；只交这一独立单元，不画其他零件、对照姿、sheet、文字或背景。保持主表指定造型、朝向与挂点。 | J39: 本次仅一张单件 PNG，sRGB；真实 Alpha 透明背景；保持足够安全边距；尺寸修正、边缘清理、分层源文件及轴点记录由后处理制作。 | K39: 倒地仍围绕原脚底根节点；直立姿与落姿保持同一坐标基准，不横向传送。 | L39: art_delivery/v1/characters/ | M39: 待生成 | N39: STA_001 / STA_002 / STA_009
A40: STA_012 | B40: agent_distress_reference_01_panic_walk.png | C40: 恐慌踉跄 | D40: ="【唯一交付文件】"&B40&CHAR(10)&"【对象】"&C40&CHAR(10)&生成规范!$B$8&CHAR(10)&"【同组设计标准，仅作一致性约束】"&素材需求!G14&CHAR(10)&"【本次只画】"&I40&"；本次只交付这一件/一个姿势，不把同组其他素材、姿势或裁切线画进本图，不拼成多格图集。"&CHAR(10)&"【状态】"&素材需求!F14&CHAR(10)&"【参考】附图 "&F40&"。"&素材需求!H14&"。如有前置定稿，必须保持同一造型、比例、线宽、服装和配色；拆件需另附已确认整身定稿图。"&CHAR(10)&"【画布】"&H40&"；尺寸不支持时保持比例生成，再后处理到目标尺寸。"&CHAR(10)&"【输出】"&J40&"。只输出当前这一张；套组其余部分由其他任务分别完成。透明须为真实Alpha，禁止棋盘格。"&CHAR(10)&"【对齐】"&K40&CHAR(10)&"【禁止】"&E40 -> 【唯一交付文件】agent_distress_reference_01_panic_walk.png 【对象】恐慌踉跄 原创二维地下工业收容设施游戏美术；怪诞手绘收容风，受手绘怪诞生存童话的表现原则启发。hand-drawn, ink-outline, slightly grotesque, whimsical horror, 2D cutout-friendly。粗细有变化的深墨轮廓，轻微不规则手绘线，大面积低饱和平涂，少量刻线阴影；剪影与动作优先于纹理。正交二维侧视角色/设施，UI为正视平面。保留对象身份，统一视觉语言，不复制其他作品具体资产。 【同组设计标准，仅作一致性约束】分别生成六个独立单姿参考：恐慌站立和踉跄行走 2 姿（夸张张口、护头手、步态不协调）；受击瞬间回缩 1 姿；低 HP 弯腰护身但保持可移动 1 姿；本日重伤倒地的落姿与稳定倒地 2 姿。仅用少量抽象墨痕和衣物皱折；倒地身体卧倒在脚底注册点附近。不要把低 HP 画成拄杖或新增爬行状态。 每个独立交付文件只能含一个姿势；按 「逐张提示词」本张范围 逐张生成。 【本次只画】本次只画完整员工恐慌行走的单个踉跄姿，四肢不协调，不能新增爬行或实际减速；只交这一独立单元，不画其他零件、对照姿、sheet、文字或背景。保持主表指定造型、朝向与挂点。；本次只交付这一件/一个姿势，不把同组其他素材、姿势或裁切线画进本图，不拼成多格图集。 【状态】PANICKED / HURT / LOW_HP / INCAPACITATED 【参考】附图 REF_STAFF。当前真实员工 panic、hurt、hp<40%、INCAPACITATED 绘制。如有前置定稿，必须保持同一造型、比例、线宽、服装和配色；拆件需另附已确认整身定稿图。 【画布】1024 × 1024 px，每个姿势独立一张，统一脚底 (512, 896)；尺寸不支持时保持比例生成，再后处理到目标尺寸。 【输出】本次仅一张单件 PNG，sRGB；真实 Alpha 透明背景；保持足够安全边距；尺寸修正、边缘清理、分层源文件及轴点记录由后处理制作。。只输出当前这一张；套组其余部分由其他任务分别完成。透明须为真实Alpha，禁止棋盘格。 【对齐】倒地仍围绕原脚底根节点；直立姿与落姿保持同一坐标基准，不横向传送。 【禁止】不做 3D、照片写实、厚涂油画、等距俯视、高饱和二次元、霓虹光污染、密集脏污；不加文字、数字、二维码、水印、游戏界面或棋盘格背景；不把动态状态、血条、范围、路径烘焙进图。 不要照片、3D 渲染、像素风、光滑矢量图标风或高饱和日漫；不要复制现成游戏的角色、脸型或官方 IP 素材；不要背景、文字、水印、UI、血条、黄色选中圈或攻击范围；不要以红色滤镜代替形变。 不要永久死亡、自动医疗复活、血腥内脏、以低血量动画改变真实移动速度。 | E40: =生成规范!$B$9&CHAR(10)&素材需求!S14 -> 不做 3D、照片写实、厚涂油画、等距俯视、高饱和二次元、霓虹光污染、密集脏污；不加文字、数字、二维码、水印、游戏界面或棋盘格背景；不把动态状态、血条、范围、路径烘焙进图。 不要照片、3D 渲染、像素风、光滑矢量图标风或高饱和日漫；不要复制现成游戏的角色、脸型或官方 IP 素材；不要背景、文字、水印、UI、血条、黄色选中圈或攻击范围；不要以红色滤镜代替形变。 不要永久死亡、自动医疗复活、血腥内脏、以低血量动画改变真实移动速度。 | F40: REF_STAFF | G40: =素材需求!B14 -> P0 | H40: 1024 × 1024 px，每个姿势独立一张，统一脚底 (512, 896) | I40: 本次只画完整员工恐慌行走的单个踉跄姿，四肢不协调，不能新增爬行或实际减速；只交这一独立单元，不画其他零件、对照姿、sheet、文字或背景。保持主表指定造型、朝向与挂点。 | J40: 本次仅一张单件 PNG，sRGB；真实 Alpha 透明背景；保持足够安全边距；尺寸修正、边缘清理、分层源文件及轴点记录由后处理制作。 | K40: 倒地仍围绕原脚底根节点；直立姿与落姿保持同一坐标基准，不横向传送。 | L40: art_delivery/v1/characters/ | M40: 待生成 | N40: STA_001 / STA_002 / STA_009
A41: STA_012 | B41: agent_distress_reference_01_hit_recoil.png | C41: 受击回缩 | D41: ="【唯一交付文件】"&B41&CHAR(10)&"【对象】"&C41&CHAR(10)&生成规范!$B$8&CHAR(10)&"【同组设计标准，仅作一致性约束】"&素材需求!G14&CHAR(10)&"【本次只画】"&I41&"；本次只交付这一件/一个姿势，不把同组其他素材、姿势或裁切线画进本图，不拼成多格图集。"&CHAR(10)&"【状态】"&素材需求!F14&CHAR(10)&"【参考】附图 "&F41&"。"&素材需求!H14&"。如有前置定稿，必须保持同一造型、比例、线宽、服装和配色；拆件需另附已确认整身定稿图。"&CHAR(10)&"【画布】"&H41&"；尺寸不支持时保持比例生成，再后处理到目标尺寸。"&CHAR(10)&"【输出】"&J41&"。只输出当前这一张；套组其余部分由其他任务分别完成。透明须为真实Alpha，禁止棋盘格。"&CHAR(10)&"【对齐】"&K41&CHAR(10)&"【禁止】"&E41 -> 【唯一交付文件】agent_distress_reference_01_hit_recoil.png 【对象】受击回缩 原创二维地下工业收容设施游戏美术；怪诞手绘收容风，受手绘怪诞生存童话的表现原则启发。hand-drawn, ink-outline, slightly grotesque, whimsical horror, 2D cutout-friendly。粗细有变化的深墨轮廓，轻微不规则手绘线，大面积低饱和平涂，少量刻线阴影；剪影与动作优先于纹理。正交二维侧视角色/设施，UI为正视平面。保留对象身份，统一视觉语言，不复制其他作品具体资产。 【同组设计标准，仅作一致性约束】分别生成六个独立单姿参考：恐慌站立和踉跄行走 2 姿（夸张张口、护头手、步态不协调）；受击瞬间回缩 1 姿；低 HP 弯腰护身但保持可移动 1 姿；本日重伤倒地的落姿与稳定倒地 2 姿。仅用少量抽象墨痕和衣物皱折；倒地身体卧倒在脚底注册点附近。不要把低 HP 画成拄杖或新增爬行状态。 每个独立交付文件只能含一个姿势；按 「逐张提示词」本张范围 逐张生成。 【本次只画】本次只画完整员工受击瞬间回缩姿，上身后撤、手臂收紧，以少量墨痕辅助；只交这一独立单元，不画其他零件、对照姿、sheet、文字或背景。保持主表指定造型、朝向与挂点。；本次只交付这一件/一个姿势，不把同组其他素材、姿势或裁切线画进本图，不拼成多格图集。 【状态】PANICKED / HURT / LOW_HP / INCAPACITATED 【参考】附图 REF_STAFF。当前真实员工 panic、hurt、hp<40%、INCAPACITATED 绘制。如有前置定稿，必须保持同一造型、比例、线宽、服装和配色；拆件需另附已确认整身定稿图。 【画布】1024 × 1024 px，每个姿势独立一张，统一脚底 (512, 896)；尺寸不支持时保持比例生成，再后处理到目标尺寸。 【输出】本次仅一张单件 PNG，sRGB；真实 Alpha 透明背景；保持足够安全边距；尺寸修正、边缘清理、分层源文件及轴点记录由后处理制作。。只输出当前这一张；套组其余部分由其他任务分别完成。透明须为真实Alpha，禁止棋盘格。 【对齐】倒地仍围绕原脚底根节点；直立姿与落姿保持同一坐标基准，不横向传送。 【禁止】不做 3D、照片写实、厚涂油画、等距俯视、高饱和二次元、霓虹光污染、密集脏污；不加文字、数字、二维码、水印、游戏界面或棋盘格背景；不把动态状态、血条、范围、路径烘焙进图。 不要照片、3D 渲染、像素风、光滑矢量图标风或高饱和日漫；不要复制现成游戏的角色、脸型或官方 IP 素材；不要背景、文字、水印、UI、血条、黄色选中圈或攻击范围；不要以红色滤镜代替形变。 不要永久死亡、自动医疗复活、血腥内脏、以低血量动画改变真实移动速度。 | E41: =生成规范!$B$9&CHAR(10)&素材需求!S14 -> 不做 3D、照片写实、厚涂油画、等距俯视、高饱和二次元、霓虹光污染、密集脏污；不加文字、数字、二维码、水印、游戏界面或棋盘格背景；不把动态状态、血条、范围、路径烘焙进图。 不要照片、3D 渲染、像素风、光滑矢量图标风或高饱和日漫；不要复制现成游戏的角色、脸型或官方 IP 素材；不要背景、文字、水印、UI、血条、黄色选中圈或攻击范围；不要以红色滤镜代替形变。 不要永久死亡、自动医疗复活、血腥内脏、以低血量动画改变真实移动速度。 | F41: REF_STAFF | G41: =素材需求!B14 -> P0 | H41: 1024 × 1024 px，每个姿势独立一张，统一脚底 (512, 896) | I41: 本次只画完整员工受击瞬间回缩姿，上身后撤、手臂收紧，以少量墨痕辅助；只交这一独立单元，不画其他零件、对照姿、sheet、文字或背景。保持主表指定造型、朝向与挂点。 | J41: 本次仅一张单件 PNG，sRGB；真实 Alpha 透明背景；保持足够安全边距；尺寸修正、边缘清理、分层源文件及轴点记录由后处理制作。 | K41: 倒地仍围绕原脚底根节点；直立姿与落姿保持同一坐标基准，不横向传送。 | L41: art_delivery/v1/characters/ | M41: 待生成 | N41: STA_001 / STA_002 / STA_009
A42: STA_012 | B42: agent_distress_reference_01_low_hp_guard.png | C42: 低 HP 护身 | D42: ="【唯一交付文件】"&B42&CHAR(10)&"【对象】"&C42&CHAR(10)&生成规范!$B$8&CHAR(10)&"【同组设计标准，仅作一致性约束】"&素材需求!G14&CHAR(10)&"【本次只画】"&I42&"；本次只交付这一件/一个姿势，不把同组其他素材、姿势或裁切线画进本图，不拼成多格图集。"&CHAR(10)&"【状态】"&素材需求!F14&CHAR(10)&"【参考】附图 "&F42&"。"&素材需求!H14&"。如有前置定稿，必须保持同一造型、比例、线宽、服装和配色；拆件需另附已确认整身定稿图。"&CHAR(10)&"【画布】"&H42&"；尺寸不支持时保持比例生成，再后处理到目标尺寸。"&CHAR(10)&"【输出】"&J42&"。只输出当前这一张；套组其余部分由其他任务分别完成。透明须为真实Alpha，禁止棋盘格。"&CHAR(10)&"【对齐】"&K42&CHAR(10)&"【禁止】"&E42 -> 【唯一交付文件】agent_distress_reference_01_low_hp_guard.png 【对象】低 HP 护身 原创二维地下工业收容设施游戏美术；怪诞手绘收容风，受手绘怪诞生存童话的表现原则启发。hand-drawn, ink-outline, slightly grotesque, whimsical horror, 2D cutout-friendly。粗细有变化的深墨轮廓，轻微不规则手绘线，大面积低饱和平涂，少量刻线阴影；剪影与动作优先于纹理。正交二维侧视角色/设施，UI为正视平面。保留对象身份，统一视觉语言，不复制其他作品具体资产。 【同组设计标准，仅作一致性约束】分别生成六个独立单姿参考：恐慌站立和踉跄行走 2 姿（夸张张口、护头手、步态不协调）；受击瞬间回缩 1 姿；低 HP 弯腰护身但保持可移动 1 姿；本日重伤倒地的落姿与稳定倒地 2 姿。仅用少量抽象墨痕和衣物皱折；倒地身体卧倒在脚底注册点附近。不要把低 HP 画成拄杖或新增爬行状态。 每个独立交付文件只能含一个姿势；按 「逐张提示词」本张范围 逐张生成。 【本次只画】本次只画完整员工低 HP 弯腰护身姿，仍可站立行走，不能增加拐杖或暗示速度变慢；只交这一独立单元，不画其他零件、对照姿、sheet、文字或背景。保持主表指定造型、朝向与挂点。；本次只交付这一件/一个姿势，不把同组其他素材、姿势或裁切线画进本图，不拼成多格图集。 【状态】PANICKED / HURT / LOW_HP / INCAPACITATED 【参考】附图 REF_STAFF。当前真实员工 panic、hurt、hp<40%、INCAPACITATED 绘制。如有前置定稿，必须保持同一造型、比例、线宽、服装和配色；拆件需另附已确认整身定稿图。 【画布】1024 × 1024 px，每个姿势独立一张，统一脚底 (512, 896)；尺寸不支持时保持比例生成，再后处理到目标尺寸。 【输出】本次仅一张单件 PNG，sRGB；真实 Alpha 透明背景；保持足够安全边距；尺寸修正、边缘清理、分层源文件及轴点记录由后处理制作。。只输出当前这一张；套组其余部分由其他任务分别完成。透明须为真实Alpha，禁止棋盘格。 【对齐】倒地仍围绕原脚底根节点；直立姿与落姿保持同一坐标基准，不横向传送。 【禁止】不做 3D、照片写实、厚涂油画、等距俯视、高饱和二次元、霓虹光污染、密集脏污；不加文字、数字、二维码、水印、游戏界面或棋盘格背景；不把动态状态、血条、范围、路径烘焙进图。 不要照片、3D 渲染、像素风、光滑矢量图标风或高饱和日漫；不要复制现成游戏的角色、脸型或官方 IP 素材；不要背景、文字、水印、UI、血条、黄色选中圈或攻击范围；不要以红色滤镜代替形变。 不要永久死亡、自动医疗复活、血腥内脏、以低血量动画改变真实移动速度。 | E42: =生成规范!$B$9&CHAR(10)&素材需求!S14 -> 不做 3D、照片写实、厚涂油画、等距俯视、高饱和二次元、霓虹光污染、密集脏污；不加文字、数字、二维码、水印、游戏界面或棋盘格背景；不把动态状态、血条、范围、路径烘焙进图。 不要照片、3D 渲染、像素风、光滑矢量图标风或高饱和日漫；不要复制现成游戏的角色、脸型或官方 IP 素材；不要背景、文字、水印、UI、血条、黄色选中圈或攻击范围；不要以红色滤镜代替形变。 不要永久死亡、自动医疗复活、血腥内脏、以低血量动画改变真实移动速度。 | F42: REF_STAFF | G42: =素材需求!B14 -> P0 | H42: 1024 × 1024 px，每个姿势独立一张，统一脚底 (512, 896) | I42: 本次只画完整员工低 HP 弯腰护身姿，仍可站立行走，不能增加拐杖或暗示速度变慢；只交这一独立单元，不画其他零件、对照姿、sheet、文字或背景。保持主表指定造型、朝向与挂点。 | J42: 本次仅一张单件 PNG，sRGB；真实 Alpha 透明背景；保持足够安全边距；尺寸修正、边缘清理、分层源文件及轴点记录由后处理制作。 | K42: 倒地仍围绕原脚底根节点；直立姿与落姿保持同一坐标基准，不横向传送。 | L42: art_delivery/v1/characters/ | M42: 待生成 | N42: STA_001 / STA_002 / STA_009
A43: STA_012 | B43: agent_distress_reference_01_incapacitated_fall.png | C43: 本日重伤落姿 | D43: ="【唯一交付文件】"&B43&CHAR(10)&"【对象】"&C43&CHAR(10)&生成规范!$B$8&CHAR(10)&"【同组设计标准，仅作一致性约束】"&素材需求!G14&CHAR(10)&"【本次只画】"&I43&"；本次只交付这一件/一个姿势，不把同组其他素材、姿势或裁切线画进本图，不拼成多格图集。"&CHAR(10)&"【状态】"&素材需求!F14&CHAR(10)&"【参考】附图 "&F43&"。"&素材需求!H14&"。如有前置定稿，必须保持同一造型、比例、线宽、服装和配色；拆件需另附已确认整身定稿图。"&CHAR(10)&"【画布】"&H43&"；尺寸不支持时保持比例生成，再后处理到目标尺寸。"&CHAR(10)&"【输出】"&J43&"。只输出当前这一张；套组其余部分由其他任务分别完成。透明须为真实Alpha，禁止棋盘格。"&CHAR(10)&"【对齐】"&K43&CHAR(10)&"【禁止】"&E43 -> 【唯一交付文件】agent_distress_reference_01_incapacitated_fall.png 【对象】本日重伤落姿 原创二维地下工业收容设施游戏美术；怪诞手绘收容风，受手绘怪诞生存童话的表现原则启发。hand-drawn, ink-outline, slightly grotesque, whimsical horror, 2D cutout-friendly。粗细有变化的深墨轮廓，轻微不规则手绘线，大面积低饱和平涂，少量刻线阴影；剪影与动作优先于纹理。正交二维侧视角色/设施，UI为正视平面。保留对象身份，统一视觉语言，不复制其他作品具体资产。 【同组设计标准，仅作一致性约束】分别生成六个独立单姿参考：恐慌站立和踉跄行走 2 姿（夸张张口、护头手、步态不协调）；受击瞬间回缩 1 姿；低 HP 弯腰护身但保持可移动 1 姿；本日重伤倒地的落姿与稳定倒地 2 姿。仅用少量抽象墨痕和衣物皱折；倒地身体卧倒在脚底注册点附近。不要把低 HP 画成拄杖或新增爬行状态。 每个独立交付文件只能含一个姿势；按 「逐张提示词」本张范围 逐张生成。 【本次只画】本次只画完整员工重伤倒地的一个落地姿，身体倾倒、四肢收起，无血腥或死亡符号；只交这一独立单元，不画其他零件、对照姿、sheet、文字或背景。保持主表指定造型、朝向与挂点。；本次只交付这一件/一个姿势，不把同组其他素材、姿势或裁切线画进本图，不拼成多格图集。 【状态】PANICKED / HURT / LOW_HP / INCAPACITATED 【参考】附图 REF_STAFF。当前真实员工 panic、hurt、hp<40%、INCAPACITATED 绘制。如有前置定稿，必须保持同一造型、比例、线宽、服装和配色；拆件需另附已确认整身定稿图。 【画布】1024 × 1024 px，每个姿势独立一张，统一脚底 (512, 896)；尺寸不支持时保持比例生成，再后处理到目标尺寸。 【输出】本次仅一张单件 PNG，sRGB；真实 Alpha 透明背景；保持足够安全边距；尺寸修正、边缘清理、分层源文件及轴点记录由后处理制作。。只输出当前这一张；套组其余部分由其他任务分别完成。透明须为真实Alpha，禁止棋盘格。 【对齐】倒地仍围绕原脚底根节点；直立姿与落姿保持同一坐标基准，不横向传送。 【禁止】不做 3D、照片写实、厚涂油画、等距俯视、高饱和二次元、霓虹光污染、密集脏污；不加文字、数字、二维码、水印、游戏界面或棋盘格背景；不把动态状态、血条、范围、路径烘焙进图。 不要照片、3D 渲染、像素风、光滑矢量图标风或高饱和日漫；不要复制现成游戏的角色、脸型或官方 IP 素材；不要背景、文字、水印、UI、血条、黄色选中圈或攻击范围；不要以红色滤镜代替形变。 不要永久死亡、自动医疗复活、血腥内脏、以低血量动画改变真实移动速度。 | E43: =生成规范!$B$9&CHAR(10)&素材需求!S14 -> 不做 3D、照片写实、厚涂油画、等距俯视、高饱和二次元、霓虹光污染、密集脏污；不加文字、数字、二维码、水印、游戏界面或棋盘格背景；不把动态状态、血条、范围、路径烘焙进图。 不要照片、3D 渲染、像素风、光滑矢量图标风或高饱和日漫；不要复制现成游戏的角色、脸型或官方 IP 素材；不要背景、文字、水印、UI、血条、黄色选中圈或攻击范围；不要以红色滤镜代替形变。 不要永久死亡、自动医疗复活、血腥内脏、以低血量动画改变真实移动速度。 | F43: REF_STAFF | G43: =素材需求!B14 -> P0 | H43: 1024 × 1024 px，每个姿势独立一张，统一脚底 (512, 896) | I43: 本次只画完整员工重伤倒地的一个落地姿，身体倾倒、四肢收起，无血腥或死亡符号；只交这一独立单元，不画其他零件、对照姿、sheet、文字或背景。保持主表指定造型、朝向与挂点。 | J43: 本次仅一张单件 PNG，sRGB；真实 Alpha 透明背景；保持足够安全边距；尺寸修正、边缘清理、分层源文件及轴点记录由后处理制作。 | K43: 倒地仍围绕原脚底根节点；直立姿与落姿保持同一坐标基准，不横向传送。 | L43: art_delivery/v1/characters/ | M43: 待生成 | N43: STA_001 / STA_002 / STA_009
A44: STA_012 | B44: agent_distress_reference_01_incapacitated_rest.png | C44: 本日重伤卧倒 | D44: ="【唯一交付文件】"&B44&CHAR(10)&"【对象】"&C44&CHAR(10)&生成规范!$B$8&CHAR(10)&"【同组设计标准，仅作一致性约束】"&素材需求!G14&CHAR(10)&"【本次只画】"&I44&"；本次只交付这一件/一个姿势，不把同组其他素材、姿势或裁切线画进本图，不拼成多格图集。"&CHAR(10)&"【状态】"&素材需求!F14&CHAR(10)&"【参考】附图 "&F44&"。"&素材需求!H14&"。如有前置定稿，必须保持同一造型、比例、线宽、服装和配色；拆件需另附已确认整身定稿图。"&CHAR(10)&"【画布】"&H44&"；尺寸不支持时保持比例生成，再后处理到目标尺寸。"&CHAR(10)&"【输出】"&J44&"。只输出当前这一张；套组其余部分由其他任务分别完成。透明须为真实Alpha，禁止棋盘格。"&CHAR(10)&"【对齐】"&K44&CHAR(10)&"【禁止】"&E44 -> 【唯一交付文件】agent_distress_reference_01_incapacitated_rest.png 【对象】本日重伤卧倒 原创二维地下工业收容设施游戏美术；怪诞手绘收容风，受手绘怪诞生存童话的表现原则启发。hand-drawn, ink-outline, slightly grotesque, whimsical horror, 2D cutout-friendly。粗细有变化的深墨轮廓，轻微不规则手绘线，大面积低饱和平涂，少量刻线阴影；剪影与动作优先于纹理。正交二维侧视角色/设施，UI为正视平面。保留对象身份，统一视觉语言，不复制其他作品具体资产。 【同组设计标准，仅作一致性约束】分别生成六个独立单姿参考：恐慌站立和踉跄行走 2 姿（夸张张口、护头手、步态不协调）；受击瞬间回缩 1 姿；低 HP 弯腰护身但保持可移动 1 姿；本日重伤倒地的落姿与稳定倒地 2 姿。仅用少量抽象墨痕和衣物皱折；倒地身体卧倒在脚底注册点附近。不要把低 HP 画成拄杖或新增爬行状态。 每个独立交付文件只能含一个姿势；按 「逐张提示词」本张范围 逐张生成。 【本次只画】本次只画完整员工本日重伤后稳定卧倒姿，闭眼，身体围绕原脚底根节点，无自动站起效果；只交这一独立单元，不画其他零件、对照姿、sheet、文字或背景。保持主表指定造型、朝向与挂点。；本次只交付这一件/一个姿势，不把同组其他素材、姿势或裁切线画进本图，不拼成多格图集。 【状态】PANICKED / HURT / LOW_HP / INCAPACITATED 【参考】附图 REF_STAFF。当前真实员工 panic、hurt、hp<40%、INCAPACITATED 绘制。如有前置定稿，必须保持同一造型、比例、线宽、服装和配色；拆件需另附已确认整身定稿图。 【画布】1024 × 1024 px，每个姿势独立一张，统一脚底 (512, 896)；尺寸不支持时保持比例生成，再后处理到目标尺寸。 【输出】本次仅一张单件 PNG，sRGB；真实 Alpha 透明背景；保持足够安全边距；尺寸修正、边缘清理、分层源文件及轴点记录由后处理制作。。只输出当前这一张；套组其余部分由其他任务分别完成。透明须为真实Alpha，禁止棋盘格。 【对齐】倒地仍围绕原脚底根节点；直立姿与落姿保持同一坐标基准，不横向传送。 【禁止】不做 3D、照片写实、厚涂油画、等距俯视、高饱和二次元、霓虹光污染、密集脏污；不加文字、数字、二维码、水印、游戏界面或棋盘格背景；不把动态状态、血条、范围、路径烘焙进图。 不要照片、3D 渲染、像素风、光滑矢量图标风或高饱和日漫；不要复制现成游戏的角色、脸型或官方 IP 素材；不要背景、文字、水印、UI、血条、黄色选中圈或攻击范围；不要以红色滤镜代替形变。 不要永久死亡、自动医疗复活、血腥内脏、以低血量动画改变真实移动速度。 | E44: =生成规范!$B$9&CHAR(10)&素材需求!S14 -> 不做 3D、照片写实、厚涂油画、等距俯视、高饱和二次元、霓虹光污染、密集脏污；不加文字、数字、二维码、水印、游戏界面或棋盘格背景；不把动态状态、血条、范围、路径烘焙进图。 不要照片、3D 渲染、像素风、光滑矢量图标风或高饱和日漫；不要复制现成游戏的角色、脸型或官方 IP 素材；不要背景、文字、水印、UI、血条、黄色选中圈或攻击范围；不要以红色滤镜代替形变。 不要永久死亡、自动医疗复活、血腥内脏、以低血量动画改变真实移动速度。 | F44: REF_STAFF | G44: =素材需求!B14 -> P0 | H44: 1024 × 1024 px，每个姿势独立一张，统一脚底 (512, 896) | I44: 本次只画完整员工本日重伤后稳定卧倒姿，闭眼，身体围绕原脚底根节点，无自动站起效果；只交这一独立单元，不画其他零件、对照姿、sheet、文字或背景。保持主表指定造型、朝向与挂点。 | J44: 本次仅一张单件 PNG，sRGB；真实 Alpha 透明背景；保持足够安全边距；尺寸修正、边缘清理、分层源文件及轴点记录由后处理制作。 | K44: 倒地仍围绕原脚底根节点；直立姿与落姿保持同一坐标基准，不横向传送。 | L44: art_delivery/v1/characters/ | M44: 待生成 | N44: STA_001 / STA_002 / STA_009
A45: STA_013 | B45: agent_weapon_attack_reference_01_ready.png | C45: 持械准备 | D45: ="【唯一交付文件】"&B45&CHAR(10)&"【对象】"&C45&CHAR(10)&生成规范!$B$8&CHAR(10)&"【同组设计标准，仅作一致性约束】"&素材需求!G15&CHAR(10)&"【本次只画】"&I45&"；本次只交付这一件/一个姿势，不把同组其他素材、姿势或裁切线画进本图，不拼成多格图集。"&CHAR(10)&"【状态】"&素材需求!F15&CHAR(10)&"【参考】附图 "&F45&"。"&素材需求!H15&"。如有前置定稿，必须保持同一造型、比例、线宽、服装和配色；拆件需另附已确认整身定稿图。"&CHAR(10)&"【画布】"&H45&"；尺寸不支持时保持比例生成，再后处理到目标尺寸。"&CHAR(10)&"【输出】"&J45&"。只输出当前这一张；套组其余部分由其他任务分别完成。透明须为真实Alpha，禁止棋盘格。"&CHAR(10)&"【对齐】"&K45&CHAR(10)&"【禁止】"&E45 -> 【唯一交付文件】agent_weapon_attack_reference_01_ready.png 【对象】持械准备 原创二维地下工业收容设施游戏美术；怪诞手绘收容风，受手绘怪诞生存童话的表现原则启发。hand-drawn, ink-outline, slightly grotesque, whimsical horror, 2D cutout-friendly。粗细有变化的深墨轮廓，轻微不规则手绘线，大面积低饱和平涂，少量刻线阴影；剪影与动作优先于纹理。正交二维侧视角色/设施，UI为正视平面。保留对象身份，统一视觉语言，不复制其他作品具体资产。 【同组设计标准，仅作一致性约束】分别生成四个独立单姿参考：持械准备、前摇收臂、命中前送、收势。以制式短棍示范手、肘、肩的共用结构；爪套、喇叭与共振器的握点由拆件元数据说明，不再画五套完整人形。保持头部不突变、脚底不脱离实际位置，攻击动作不能暗示冲刺或位移技能。 每个独立交付文件只能含一个姿势；按 「逐张提示词」本张范围 逐张生成。 【本次只画】本次只画完整员工持制式短棍的准备姿，握柄和腕根清楚；只交这一独立单元，不画其他零件、对照姿、sheet、文字或背景。保持主表指定造型、朝向与挂点。；本次只交付这一件/一个姿势，不把同组其他素材、姿势或裁切线画进本图，不拼成多格图集。 【状态】SUPPRESSING / WINDUP / IMPACT 【参考】附图 REF_STAFF。drawHuman 攻击分支与 drawWeapon 的 hand/facing/angle。如有前置定稿，必须保持同一造型、比例、线宽、服装和配色；拆件需另附已确认整身定稿图。 【画布】1024 × 1024 px，每个姿势独立一张，统一脚底 (512, 896)；尺寸不支持时保持比例生成，再后处理到目标尺寸。 【输出】本次仅一张单件 PNG，sRGB；真实 Alpha 透明背景；保持足够安全边距；尺寸修正、边缘清理、分层源文件及轴点记录由后处理制作。。只输出当前这一张；套组其余部分由其他任务分别完成。透明须为真实Alpha，禁止棋盘格。 【对齐】全身根=脚底；武器根=握柄点；前后手层级明确。 【禁止】不做 3D、照片写实、厚涂油画、等距俯视、高饱和二次元、霓虹光污染、密集脏污；不加文字、数字、二维码、水印、游戏界面或棋盘格背景；不把动态状态、血条、范围、路径烘焙进图。 不要照片、3D 渲染、像素风、光滑矢量图标风或高饱和日漫；不要复制现成游戏的角色、脸型或官方 IP 素材；不要背景、文字、水印、UI、血条、黄色选中圈或攻击范围；不要以红色滤镜代替形变。 | E45: =生成规范!$B$9&CHAR(10)&素材需求!S15 -> 不做 3D、照片写实、厚涂油画、等距俯视、高饱和二次元、霓虹光污染、密集脏污；不加文字、数字、二维码、水印、游戏界面或棋盘格背景；不把动态状态、血条、范围、路径烘焙进图。 不要照片、3D 渲染、像素风、光滑矢量图标风或高饱和日漫；不要复制现成游戏的角色、脸型或官方 IP 素材；不要背景、文字、水印、UI、血条、黄色选中圈或攻击范围；不要以红色滤镜代替形变。 | F45: REF_STAFF | G45: =素材需求!B15 -> P0 | H45: 1024 × 1024 px，每个姿势独立一张，统一脚底 (512, 896) | I45: 本次只画完整员工持制式短棍的准备姿，握柄和腕根清楚；只交这一独立单元，不画其他零件、对照姿、sheet、文字或背景。保持主表指定造型、朝向与挂点。 | J45: 本次仅一张单件 PNG，sRGB；真实 Alpha 透明背景；保持足够安全边距；尺寸修正、边缘清理、分层源文件及轴点记录由后处理制作。 | K45: 全身根=脚底；武器根=握柄点；前后手层级明确。 | L45: art_delivery/v1/equipment/ | M45: 待生成 | N45: STA_002
A46: STA_013 | B46: agent_weapon_attack_reference_01_windup.png | C46: 攻击前摇 | D46: ="【唯一交付文件】"&B46&CHAR(10)&"【对象】"&C46&CHAR(10)&生成规范!$B$8&CHAR(10)&"【同组设计标准，仅作一致性约束】"&素材需求!G15&CHAR(10)&"【本次只画】"&I46&"；本次只交付这一件/一个姿势，不把同组其他素材、姿势或裁切线画进本图，不拼成多格图集。"&CHAR(10)&"【状态】"&素材需求!F15&CHAR(10)&"【参考】附图 "&F46&"。"&素材需求!H15&"。如有前置定稿，必须保持同一造型、比例、线宽、服装和配色；拆件需另附已确认整身定稿图。"&CHAR(10)&"【画布】"&H46&"；尺寸不支持时保持比例生成，再后处理到目标尺寸。"&CHAR(10)&"【输出】"&J46&"。只输出当前这一张；套组其余部分由其他任务分别完成。透明须为真实Alpha，禁止棋盘格。"&CHAR(10)&"【对齐】"&K46&CHAR(10)&"【禁止】"&E46 -> 【唯一交付文件】agent_weapon_attack_reference_01_windup.png 【对象】攻击前摇 原创二维地下工业收容设施游戏美术；怪诞手绘收容风，受手绘怪诞生存童话的表现原则启发。hand-drawn, ink-outline, slightly grotesque, whimsical horror, 2D cutout-friendly。粗细有变化的深墨轮廓，轻微不规则手绘线，大面积低饱和平涂，少量刻线阴影；剪影与动作优先于纹理。正交二维侧视角色/设施，UI为正视平面。保留对象身份，统一视觉语言，不复制其他作品具体资产。 【同组设计标准，仅作一致性约束】分别生成四个独立单姿参考：持械准备、前摇收臂、命中前送、收势。以制式短棍示范手、肘、肩的共用结构；爪套、喇叭与共振器的握点由拆件元数据说明，不再画五套完整人形。保持头部不突变、脚底不脱离实际位置，攻击动作不能暗示冲刺或位移技能。 每个独立交付文件只能含一个姿势；按 「逐张提示词」本张范围 逐张生成。 【本次只画】本次只画完整员工攻击前摇收臂姿，短棍后收，上身轻后倾，脚底不移；只交这一独立单元，不画其他零件、对照姿、sheet、文字或背景。保持主表指定造型、朝向与挂点。；本次只交付这一件/一个姿势，不把同组其他素材、姿势或裁切线画进本图，不拼成多格图集。 【状态】SUPPRESSING / WINDUP / IMPACT 【参考】附图 REF_STAFF。drawHuman 攻击分支与 drawWeapon 的 hand/facing/angle。如有前置定稿，必须保持同一造型、比例、线宽、服装和配色；拆件需另附已确认整身定稿图。 【画布】1024 × 1024 px，每个姿势独立一张，统一脚底 (512, 896)；尺寸不支持时保持比例生成，再后处理到目标尺寸。 【输出】本次仅一张单件 PNG，sRGB；真实 Alpha 透明背景；保持足够安全边距；尺寸修正、边缘清理、分层源文件及轴点记录由后处理制作。。只输出当前这一张；套组其余部分由其他任务分别完成。透明须为真实Alpha，禁止棋盘格。 【对齐】全身根=脚底；武器根=握柄点；前后手层级明确。 【禁止】不做 3D、照片写实、厚涂油画、等距俯视、高饱和二次元、霓虹光污染、密集脏污；不加文字、数字、二维码、水印、游戏界面或棋盘格背景；不把动态状态、血条、范围、路径烘焙进图。 不要照片、3D 渲染、像素风、光滑矢量图标风或高饱和日漫；不要复制现成游戏的角色、脸型或官方 IP 素材；不要背景、文字、水印、UI、血条、黄色选中圈或攻击范围；不要以红色滤镜代替形变。 | E46: =生成规范!$B$9&CHAR(10)&素材需求!S15 -> 不做 3D、照片写实、厚涂油画、等距俯视、高饱和二次元、霓虹光污染、密集脏污；不加文字、数字、二维码、水印、游戏界面或棋盘格背景；不把动态状态、血条、范围、路径烘焙进图。 不要照片、3D 渲染、像素风、光滑矢量图标风或高饱和日漫；不要复制现成游戏的角色、脸型或官方 IP 素材；不要背景、文字、水印、UI、血条、黄色选中圈或攻击范围；不要以红色滤镜代替形变。 | F46: REF_STAFF | G46: =素材需求!B15 -> P0 | H46: 1024 × 1024 px，每个姿势独立一张，统一脚底 (512, 896) | I46: 本次只画完整员工攻击前摇收臂姿，短棍后收，上身轻后倾，脚底不移；只交这一独立单元，不画其他零件、对照姿、sheet、文字或背景。保持主表指定造型、朝向与挂点。 | J46: 本次仅一张单件 PNG，sRGB；真实 Alpha 透明背景；保持足够安全边距；尺寸修正、边缘清理、分层源文件及轴点记录由后处理制作。 | K46: 全身根=脚底；武器根=握柄点；前后手层级明确。 | L46: art_delivery/v1/equipment/ | M46: 待生成 | N46: STA_002
A47: STA_013 | B47: agent_weapon_attack_reference_01_impact.png | C47: 攻击命中 | D47: ="【唯一交付文件】"&B47&CHAR(10)&"【对象】"&C47&CHAR(10)&生成规范!$B$8&CHAR(10)&"【同组设计标准，仅作一致性约束】"&素材需求!G15&CHAR(10)&"【本次只画】"&I47&"；本次只交付这一件/一个姿势，不把同组其他素材、姿势或裁切线画进本图，不拼成多格图集。"&CHAR(10)&"【状态】"&素材需求!F15&CHAR(10)&"【参考】附图 "&F47&"。"&素材需求!H15&"。如有前置定稿，必须保持同一造型、比例、线宽、服装和配色；拆件需另附已确认整身定稿图。"&CHAR(10)&"【画布】"&H47&"；尺寸不支持时保持比例生成，再后处理到目标尺寸。"&CHAR(10)&"【输出】"&J47&"。只输出当前这一张；套组其余部分由其他任务分别完成。透明须为真实Alpha，禁止棋盘格。"&CHAR(10)&"【对齐】"&K47&CHAR(10)&"【禁止】"&E47 -> 【唯一交付文件】agent_weapon_attack_reference_01_impact.png 【对象】攻击命中 原创二维地下工业收容设施游戏美术；怪诞手绘收容风，受手绘怪诞生存童话的表现原则启发。hand-drawn, ink-outline, slightly grotesque, whimsical horror, 2D cutout-friendly。粗细有变化的深墨轮廓，轻微不规则手绘线，大面积低饱和平涂，少量刻线阴影；剪影与动作优先于纹理。正交二维侧视角色/设施，UI为正视平面。保留对象身份，统一视觉语言，不复制其他作品具体资产。 【同组设计标准，仅作一致性约束】分别生成四个独立单姿参考：持械准备、前摇收臂、命中前送、收势。以制式短棍示范手、肘、肩的共用结构；爪套、喇叭与共振器的握点由拆件元数据说明，不再画五套完整人形。保持头部不突变、脚底不脱离实际位置，攻击动作不能暗示冲刺或位移技能。 每个独立交付文件只能含一个姿势；按 「逐张提示词」本张范围 逐张生成。 【本次只画】本次只画完整员工短棍前送命中姿，肘腕连贯，脚底不移；只交这一独立单元，不画其他零件、对照姿、sheet、文字或背景。保持主表指定造型、朝向与挂点。；本次只交付这一件/一个姿势，不把同组其他素材、姿势或裁切线画进本图，不拼成多格图集。 【状态】SUPPRESSING / WINDUP / IMPACT 【参考】附图 REF_STAFF。drawHuman 攻击分支与 drawWeapon 的 hand/facing/angle。如有前置定稿，必须保持同一造型、比例、线宽、服装和配色；拆件需另附已确认整身定稿图。 【画布】1024 × 1024 px，每个姿势独立一张，统一脚底 (512, 896)；尺寸不支持时保持比例生成，再后处理到目标尺寸。 【输出】本次仅一张单件 PNG，sRGB；真实 Alpha 透明背景；保持足够安全边距；尺寸修正、边缘清理、分层源文件及轴点记录由后处理制作。。只输出当前这一张；套组其余部分由其他任务分别完成。透明须为真实Alpha，禁止棋盘格。 【对齐】全身根=脚底；武器根=握柄点；前后手层级明确。 【禁止】不做 3D、照片写实、厚涂油画、等距俯视、高饱和二次元、霓虹光污染、密集脏污；不加文字、数字、二维码、水印、游戏界面或棋盘格背景；不把动态状态、血条、范围、路径烘焙进图。 不要照片、3D 渲染、像素风、光滑矢量图标风或高饱和日漫；不要复制现成游戏的角色、脸型或官方 IP 素材；不要背景、文字、水印、UI、血条、黄色选中圈或攻击范围；不要以红色滤镜代替形变。 | E47: =生成规范!$B$9&CHAR(10)&素材需求!S15 -> 不做 3D、照片写实、厚涂油画、等距俯视、高饱和二次元、霓虹光污染、密集脏污；不加文字、数字、二维码、水印、游戏界面或棋盘格背景；不把动态状态、血条、范围、路径烘焙进图。 不要照片、3D 渲染、像素风、光滑矢量图标风或高饱和日漫；不要复制现成游戏的角色、脸型或官方 IP 素材；不要背景、文字、水印、UI、血条、黄色选中圈或攻击范围；不要以红色滤镜代替形变。 | F47: REF_STAFF | G47: =素材需求!B15 -> P0 | H47: 1024 × 1024 px，每个姿势独立一张，统一脚底 (512, 896) | I47: 本次只画完整员工短棍前送命中姿，肘腕连贯，脚底不移；只交这一独立单元，不画其他零件、对照姿、sheet、文字或背景。保持主表指定造型、朝向与挂点。 | J47: 本次仅一张单件 PNG，sRGB；真实 Alpha 透明背景；保持足够安全边距；尺寸修正、边缘清理、分层源文件及轴点记录由后处理制作。 | K47: 全身根=脚底；武器根=握柄点；前后手层级明确。 | L47: art_delivery/v1/equipment/ | M47: 待生成 | N47: STA_002
A48: STA_013 | B48: agent_weapon_attack_reference_01_recover.png | C48: 攻击收势 | D48: ="【唯一交付文件】"&B48&CHAR(10)&"【对象】"&C48&CHAR(10)&生成规范!$B$8&CHAR(10)&"【同组设计标准，仅作一致性约束】"&素材需求!G15&CHAR(10)&"【本次只画】"&I48&"；本次只交付这一件/一个姿势，不把同组其他素材、姿势或裁切线画进本图，不拼成多格图集。"&CHAR(10)&"【状态】"&素材需求!F15&CHAR(10)&"【参考】附图 "&F48&"。"&素材需求!H15&"。如有前置定稿，必须保持同一造型、比例、线宽、服装和配色；拆件需另附已确认整身定稿图。"&CHAR(10)&"【画布】"&H48&"；尺寸不支持时保持比例生成，再后处理到目标尺寸。"&CHAR(10)&"【输出】"&J48&"。只输出当前这一张；套组其余部分由其他任务分别完成。透明须为真实Alpha，禁止棋盘格。"&CHAR(10)&"【对齐】"&K48&CHAR(10)&"【禁止】"&E48 -> 【唯一交付文件】agent_weapon_attack_reference_01_recover.png 【对象】攻击收势 原创二维地下工业收容设施游戏美术；怪诞手绘收容风，受手绘怪诞生存童话的表现原则启发。hand-drawn, ink-outline, slightly grotesque, whimsical horror, 2D cutout-friendly。粗细有变化的深墨轮廓，轻微不规则手绘线，大面积低饱和平涂，少量刻线阴影；剪影与动作优先于纹理。正交二维侧视角色/设施，UI为正视平面。保留对象身份，统一视觉语言，不复制其他作品具体资产。 【同组设计标准，仅作一致性约束】分别生成四个独立单姿参考：持械准备、前摇收臂、命中前送、收势。以制式短棍示范手、肘、肩的共用结构；爪套、喇叭与共振器的握点由拆件元数据说明，不再画五套完整人形。保持头部不突变、脚底不脱离实际位置，攻击动作不能暗示冲刺或位移技能。 每个独立交付文件只能含一个姿势；按 「逐张提示词」本张范围 逐张生成。 【本次只画】本次只画完整员工攻击后的回收姿，短棍回到身体侧前，无冲刺效果；只交这一独立单元，不画其他零件、对照姿、sheet、文字或背景。保持主表指定造型、朝向与挂点。；本次只交付这一件/一个姿势，不把同组其他素材、姿势或裁切线画进本图，不拼成多格图集。 【状态】SUPPRESSING / WINDUP / IMPACT 【参考】附图 REF_STAFF。drawHuman 攻击分支与 drawWeapon 的 hand/facing/angle。如有前置定稿，必须保持同一造型、比例、线宽、服装和配色；拆件需另附已确认整身定稿图。 【画布】1024 × 1024 px，每个姿势独立一张，统一脚底 (512, 896)；尺寸不支持时保持比例生成，再后处理到目标尺寸。 【输出】本次仅一张单件 PNG，sRGB；真实 Alpha 透明背景；保持足够安全边距；尺寸修正、边缘清理、分层源文件及轴点记录由后处理制作。。只输出当前这一张；套组其余部分由其他任务分别完成。透明须为真实Alpha，禁止棋盘格。 【对齐】全身根=脚底；武器根=握柄点；前后手层级明确。 【禁止】不做 3D、照片写实、厚涂油画、等距俯视、高饱和二次元、霓虹光污染、密集脏污；不加文字、数字、二维码、水印、游戏界面或棋盘格背景；不把动态状态、血条、范围、路径烘焙进图。 不要照片、3D 渲染、像素风、光滑矢量图标风或高饱和日漫；不要复制现成游戏的角色、脸型或官方 IP 素材；不要背景、文字、水印、UI、血条、黄色选中圈或攻击范围；不要以红色滤镜代替形变。 | E48: =生成规范!$B$9&CHAR(10)&素材需求!S15 -> 不做 3D、照片写实、厚涂油画、等距俯视、高饱和二次元、霓虹光污染、密集脏污；不加文字、数字、二维码、水印、游戏界面或棋盘格背景；不把动态状态、血条、范围、路径烘焙进图。 不要照片、3D 渲染、像素风、光滑矢量图标风或高饱和日漫；不要复制现成游戏的角色、脸型或官方 IP 素材；不要背景、文字、水印、UI、血条、黄色选中圈或攻击范围；不要以红色滤镜代替形变。 | F48: REF_STAFF | G48: =素材需求!B15 -> P0 | H48: 1024 × 1024 px，每个姿势独立一张，统一脚底 (512, 896) | I48: 本次只画完整员工攻击后的回收姿，短棍回到身体侧前，无冲刺效果；只交这一独立单元，不画其他零件、对照姿、sheet、文字或背景。保持主表指定造型、朝向与挂点。 | J48: 本次仅一张单件 PNG，sRGB；真实 Alpha 透明背景；保持足够安全边距；尺寸修正、边缘清理、分层源文件及轴点记录由后处理制作。 | K48: 全身根=脚底；武器根=握柄点；前后手层级明确。 | L48: art_delivery/v1/equipment/ | M48: 待生成 | N48: STA_002
A49: ABN_N01_01 | B49: abn_nailong_idle_01_approved.png | C49: 奶龙 平静定稿 | D49: ="【唯一交付文件】"&B49&CHAR(10)&"【对象】"&C49&CHAR(10)&生成规范!$B$8&CHAR(10)&"【同组设计标准，仅作一致性约束】"&素材需求!G16&CHAR(10)&"【本次只画】"&I49&"；本次只交付这一件/一个姿势，不把同组其他素材、姿势或裁切线画进本图，不拼成多格图集。"&CHAR(10)&"【状态】"&素材需求!F16&CHAR(10)&"【参考】附图 "&F49&"。"&素材需求!H16&"。如有前置定稿，必须保持同一造型、比例、线宽、服装和配色；拆件需另附已确认整身定稿图。"&CHAR(10)&"【画布】"&H49&"；尺寸不支持时保持比例生成，再后处理到目标尺寸。"&CHAR(10)&"【输出】"&J49&"。只输出当前这一张；套组其余部分由其他任务分别完成。透明须为真实Alpha，禁止棋盘格。"&CHAR(10)&"【对齐】"&K49&CHAR(10)&"【禁止】"&E49 -> 【唯一交付文件】abn_nailong_idle_01_approved.png 【对象】奶龙 平静定稿 原创二维地下工业收容设施游戏美术；怪诞手绘收容风，受手绘怪诞生存童话的表现原则启发。hand-drawn, ink-outline, slightly grotesque, whimsical horror, 2D cutout-friendly。粗细有变化的深墨轮廓，轻微不规则手绘线，大面积低饱和平涂，少量刻线阴影；剪影与动作优先于纹理。正交二维侧视角色/设施，UI为正视平面。保留对象身份，统一视觉语言，不复制其他作品具体资产。 【同组设计标准，仅作一致性约束】原创怪诞手绘收容风：不均匀粗墨外轮廓、较细结构线、局部不对称、平涂和少量排线；轮廓在游戏缩小尺寸仍清楚。 软黄梨形身体、奶油色圆肚、短手、宽扁脚、不对称短尾；头颈连成柔软长弧，两个小角一高一低，眼睛大小不一、口鼻略突出。主色黄 #d9b854、奶油 #e9d38c 和土黄阴影，呆软而非写实恐龙。 侧视略带正脸可读性，所有部位围绕单一脚底根节点，不画房间。 【本次只画】本次只画一只完整平静 奶龙，严格采用本行具体形状与三色群，不含动作对照或其他角色；只交这一独立单元，不画其他零件、对照姿、sheet、文字或背景。保持主表指定造型、朝向与挂点。；本次只交付这一件/一个姿势，不把同组其他素材、姿势或裁切线画进本图，不拼成多格图集。 【状态】CONTAINED / IDLE 【参考】附图 REF_N01_CALM。当前 奶龙 室内未作业形态。如有前置定稿，必须保持同一造型、比例、线宽、服装和配色；拆件需另附已确认整身定稿图。 【画布】1024 × 1024 px；尺寸不支持时保持比例生成，再后处理到目标尺寸。 【输出】1 个透明 RGBA PNG 定稿；主体完整、无底座、无环境阴影；附三色主色票说明。。只输出当前这一张；套组其余部分由其他任务分别完成。透明须为真实Alpha，禁止棋盘格。 【对齐】脚底地面中心；母版 (512, 896)，朝右；全部形态共享同一根节点。 【禁止】不做 3D、照片写实、厚涂油画、等距俯视、高饱和二次元、霓虹光污染、密集脏污；不加文字、数字、二维码、水印、游戏界面或棋盘格背景；不把动态状态、血条、范围、路径烘焙进图。 不要照片、3D 渲染、像素风、光滑矢量图标风或高饱和日漫；不要复制现成游戏的角色、脸型或官方 IP 素材；不要背景、文字、水印、UI、血条、黄色选中圈或攻击范围；不要以红色滤镜代替形变。 | E49: =生成规范!$B$9&CHAR(10)&素材需求!S16 -> 不做 3D、照片写实、厚涂油画、等距俯视、高饱和二次元、霓虹光污染、密集脏污；不加文字、数字、二维码、水印、游戏界面或棋盘格背景；不把动态状态、血条、范围、路径烘焙进图。 不要照片、3D 渲染、像素风、光滑矢量图标风或高饱和日漫；不要复制现成游戏的角色、脸型或官方 IP 素材；不要背景、文字、水印、UI、血条、黄色选中圈或攻击范围；不要以红色滤镜代替形变。 | F49: REF_N01_CALM | G49: =素材需求!B16 -> P0 | H49: 1024 × 1024 px | I49: 本次只画一只完整平静 奶龙，严格采用本行具体形状与三色群，不含动作对照或其他角色；只交这一独立单元，不画其他零件、对照姿、sheet、文字或背景。保持主表指定造型、朝向与挂点。 | J49: 1 个透明 RGBA PNG 定稿；主体完整、无底座、无环境阴影；附三色主色票说明。 | K49: 脚底地面中心；母版 (512, 896)，朝右；全部形态共享同一根节点。 | L49: art_delivery/v1/abnormalities/ | M49: 待生成 | N49: —
A50: ABN_N01_03 | B50: abn_nailong_breach_01_approved.png | C50: 奶龙 失控定稿 | D50: ="【唯一交付文件】"&B50&CHAR(10)&"【对象】"&C50&CHAR(10)&生成规范!$B$8&CHAR(10)&"【同组设计标准，仅作一致性约束】"&素材需求!G17&CHAR(10)&"【本次只画】"&I50&"；本次只交付这一件/一个姿势，不把同组其他素材、姿势或裁切线画进本图，不拼成多格图集。"&CHAR(10)&"【状态】"&素材需求!F17&CHAR(10)&"【参考】附图 "&F50&"。"&素材需求!H17&"。如有前置定稿，必须保持同一造型、比例、线宽、服装和配色；拆件需另附已确认整身定稿图。"&CHAR(10)&"【画布】"&H50&"；尺寸不支持时保持比例生成，再后处理到目标尺寸。"&CHAR(10)&"【输出】"&J50&"。只输出当前这一张；套组其余部分由其他任务分别完成。透明须为真实Alpha，禁止棋盘格。"&CHAR(10)&"【对齐】"&K50&CHAR(10)&"【禁止】"&E50 -> 【唯一交付文件】abn_nailong_breach_01_approved.png 【对象】奶龙 失控定稿 原创二维地下工业收容设施游戏美术；怪诞手绘收容风，受手绘怪诞生存童话的表现原则启发。hand-drawn, ink-outline, slightly grotesque, whimsical horror, 2D cutout-friendly。粗细有变化的深墨轮廓，轻微不规则手绘线，大面积低饱和平涂，少量刻线阴影；剪影与动作优先于纹理。正交二维侧视角色/设施，UI为正视平面。保留对象身份，统一视觉语言，不复制其他作品具体资产。 【同组设计标准，仅作一致性约束】原创怪诞手绘收容风：不均匀粗墨外轮廓、较细结构线、局部不对称、平涂和少量排线；轮廓在游戏缩小尺寸仍清楚。 保留软黄肚子与短尾识别点，头颈明显拉长，大小不等的实黑空眼；嘴裂成斜向大黑开口、稀疏奶油三角齿，嘴角延伸至颈部；身体有轻微被拉扁的视频帧错位感。相比平静形态，空眼、裂嘴、长颈三项都必须明确，不能仅涂红或加烟。 【本次只画】本次只画一只完整失控 奶龙 主体，严格体现本行眼口和轮廓变化；不含分身、重影、受控星标或范围；只交这一独立单元，不画其他零件、对照姿、sheet、文字或背景。保持主表指定造型、朝向与挂点。；本次只交付这一件/一个姿势，不把同组其他素材、姿势或裁切线画进本图，不拼成多格图集。 【状态】BREACHED 【参考】附图 REF_N01_CALM / REF_N01_BREACH。当前 奶龙 真实 enemy 形态，对照其平静定稿。如有前置定稿，必须保持同一造型、比例、线宽、服装和配色；拆件需另附已确认整身定稿图。 【画布】1024 × 1024 px；尺寸不支持时保持比例生成，再后处理到目标尺寸。 【输出】1 个透明 RGBA PNG 主体定稿；虚影/错帧效果仅放附属说明，实际主体不带不可拆多重残像。。只输出当前这一张；套组其余部分由其他任务分别完成。透明须为真实Alpha，禁止棋盘格。 【对齐】脚底地面中心；母版 (512, 896)，朝右；全部形态共享同一根节点。 【禁止】不做 3D、照片写实、厚涂油画、等距俯视、高饱和二次元、霓虹光污染、密集脏污；不加文字、数字、二维码、水印、游戏界面或棋盘格背景；不把动态状态、血条、范围、路径烘焙进图。 不要照片、3D 渲染、像素风、光滑矢量图标风或高饱和日漫；不要复制现成游戏的角色、脸型或官方 IP 素材；不要背景、文字、水印、UI、血条、黄色选中圈或攻击范围；不要以红色滤镜代替形变。 | E50: =生成规范!$B$9&CHAR(10)&素材需求!S17 -> 不做 3D、照片写实、厚涂油画、等距俯视、高饱和二次元、霓虹光污染、密集脏污；不加文字、数字、二维码、水印、游戏界面或棋盘格背景；不把动态状态、血条、范围、路径烘焙进图。 不要照片、3D 渲染、像素风、光滑矢量图标风或高饱和日漫；不要复制现成游戏的角色、脸型或官方 IP 素材；不要背景、文字、水印、UI、血条、黄色选中圈或攻击范围；不要以红色滤镜代替形变。 | F50: REF_N01_CALM / REF_N01_BREACH | G50: =素材需求!B17 -> P0 | H50: 1024 × 1024 px | I50: 本次只画一只完整失控 奶龙 主体，严格体现本行眼口和轮廓变化；不含分身、重影、受控星标或范围；只交这一独立单元，不画其他零件、对照姿、sheet、文字或背景。保持主表指定造型、朝向与挂点。 | J50: 1 个透明 RGBA PNG 主体定稿；虚影/错帧效果仅放附属说明，实际主体不带不可拆多重残像。 | K50: 脚底地面中心；母版 (512, 896)，朝右；全部形态共享同一根节点。 | L50: art_delivery/v1/abnormalities/ | M50: 待生成 | N50: ABN_N01_01
A51: ABN_N01_04 | B51: abn_nailong_parts_01_body.png | C51: 奶龙躯干 | D51: ="【唯一交付文件】"&B51&CHAR(10)&"【对象】"&C51&CHAR(10)&生成规范!$B$8&CHAR(10)&"【同组设计标准，仅作一致性约束】"&素材需求!G18&CHAR(10)&"【本次只画】"&I51&"；本次只交付这一件/一个姿势，不把同组其他素材、姿势或裁切线画进本图，不拼成多格图集。"&CHAR(10)&"【状态】"&素材需求!F18&CHAR(10)&"【参考】附图 "&F51&"。"&素材需求!H18&"。如有前置定稿，必须保持同一造型、比例、线宽、服装和配色；拆件需另附已确认整身定稿图。"&CHAR(10)&"【画布】"&H51&"；尺寸不支持时保持比例生成，再后处理到目标尺寸。"&CHAR(10)&"【输出】"&J51&"。只输出当前这一张；套组其余部分由其他任务分别完成。透明须为真实Alpha，禁止棋盘格。"&CHAR(10)&"【对齐】"&K51&CHAR(10)&"【禁止】"&E51 -> 【唯一交付文件】abn_nailong_parts_01_body.png 【对象】奶龙躯干 原创二维地下工业收容设施游戏美术；怪诞手绘收容风，受手绘怪诞生存童话的表现原则启发。hand-drawn, ink-outline, slightly grotesque, whimsical horror, 2D cutout-friendly。粗细有变化的深墨轮廓，轻微不规则手绘线，大面积低饱和平涂，少量刻线阴影；剪影与动作优先于纹理。正交二维侧视角色/设施，UI为正视平面。保留对象身份，统一视觉语言，不复制其他作品具体资产。 【同组设计标准，仅作一致性约束】躯干 1、平静头颈 1、失控头颈 1、平静口鼻 1、失控裂嘴 1、常态/空眼两组眼部 2、左右短臂 2、左右脚 2、尾 1，共 12 件。头颈、眼、口分层，裂嘴不与选中圈或残影合并。 沿用两份已批准定稿的线宽与体积，关节背面补全；可复用部位只交一份，不为每个动作复制整身。完整定稿仅作组合校对，不额外计独立交付单位。 以上为整套构成；每次只生成 「逐张提示词」本张范围 指定的一个独立件，不画整套平铺图。 【本次只画】本次只画奶龙软黄躯干和奶油肚，补全颈肩接口，不含头颈、尾与四肢；只交这一独立单元，不画其他零件、对照姿、sheet、文字或背景。保持主表指定造型、朝向与挂点。；本次只交付这一件/一个姿势，不把同组其他素材、姿势或裁切线画进本图，不拼成多格图集。 【状态】IDLE / WORKING / BREACHED 【参考】附图 REF_N01_CALM / REF_N01_BREACH。奶龙 已批准平静与失控定稿。如有前置定稿，必须保持同一造型、比例、线宽、服装和配色；拆件需另附已确认整身定稿图。 【画布】1024 × 1024 px，每张单独姿势/零件，共用 (512, 896) 根；尺寸不支持时保持比例生成，再后处理到目标尺寸。 【输出】本次仅一张单件 PNG，sRGB；真实 Alpha 透明背景；保持足够安全边距；尺寸修正、边缘清理、分层源文件及轴点记录由后处理制作。。只输出当前这一张；套组其余部分由其他任务分别完成。透明须为真实Alpha，禁止棋盘格。 【对齐】脚底地面中心；母版 (512, 896)，朝右；全部形态共享同一根节点。 另记录头颈、四肢、口部或钟针等实际旋转挂点。 【禁止】不做 3D、照片写实、厚涂油画、等距俯视、高饱和二次元、霓虹光污染、密集脏污；不加文字、数字、二维码、水印、游戏界面或棋盘格背景；不把动态状态、血条、范围、路径烘焙进图。 不要照片、3D 渲染、像素风、光滑矢量图标风或高饱和日漫；不要复制现成游戏的角色、脸型或官方 IP 素材；不要背景、文字、水印、UI、血条、黄色选中圈或攻击范围；不要以红色滤镜代替形变。 | E51: =生成规范!$B$9&CHAR(10)&素材需求!S18 -> 不做 3D、照片写实、厚涂油画、等距俯视、高饱和二次元、霓虹光污染、密集脏污；不加文字、数字、二维码、水印、游戏界面或棋盘格背景；不把动态状态、血条、范围、路径烘焙进图。 不要照片、3D 渲染、像素风、光滑矢量图标风或高饱和日漫；不要复制现成游戏的角色、脸型或官方 IP 素材；不要背景、文字、水印、UI、血条、黄色选中圈或攻击范围；不要以红色滤镜代替形变。 | F51: REF_N01_CALM / REF_N01_BREACH | G51: =素材需求!B18 -> P0 | H51: 1024 × 1024 px，每张单独姿势/零件，共用 (512, 896) 根 | I51: 本次只画奶龙软黄躯干和奶油肚，补全颈肩接口，不含头颈、尾与四肢；只交这一独立单元，不画其他零件、对照姿、sheet、文字或背景。保持主表指定造型、朝向与挂点。 | J51: 本次仅一张单件 PNG，sRGB；真实 Alpha 透明背景；保持足够安全边距；尺寸修正、边缘清理、分层源文件及轴点记录由后处理制作。 | K51: 脚底地面中心；母版 (512, 896)，朝右；全部形态共享同一根节点。 另记录头颈、四肢、口部或钟针等实际旋转挂点。 | L51: art_delivery/v1/abnormalities/ | M51: 待生成 | N51: ABN_N01_01 / ABN_N01_03
A52: ABN_N01_04 | B52: abn_nailong_parts_01_calm_head_neck.png | C52: 奶龙平静头颈 | D52: ="【唯一交付文件】"&B52&CHAR(10)&"【对象】"&C52&CHAR(10)&生成规范!$B$8&CHAR(10)&"【同组设计标准，仅作一致性约束】"&素材需求!G18&CHAR(10)&"【本次只画】"&I52&"；本次只交付这一件/一个姿势，不把同组其他素材、姿势或裁切线画进本图，不拼成多格图集。"&CHAR(10)&"【状态】"&素材需求!F18&CHAR(10)&"【参考】附图 "&F52&"。"&素材需求!H18&"。如有前置定稿，必须保持同一造型、比例、线宽、服装和配色；拆件需另附已确认整身定稿图。"&CHAR(10)&"【画布】"&H52&"；尺寸不支持时保持比例生成，再后处理到目标尺寸。"&CHAR(10)&"【输出】"&J52&"。只输出当前这一张；套组其余部分由其他任务分别完成。透明须为真实Alpha，禁止棋盘格。"&CHAR(10)&"【对齐】"&K52&CHAR(10)&"【禁止】"&E52 -> 【唯一交付文件】abn_nailong_parts_01_calm_head_neck.png 【对象】奶龙平静头颈 原创二维地下工业收容设施游戏美术；怪诞手绘收容风，受手绘怪诞生存童话的表现原则启发。hand-drawn, ink-outline, slightly grotesque, whimsical horror, 2D cutout-friendly。粗细有变化的深墨轮廓，轻微不规则手绘线，大面积低饱和平涂，少量刻线阴影；剪影与动作优先于纹理。正交二维侧视角色/设施，UI为正视平面。保留对象身份，统一视觉语言，不复制其他作品具体资产。 【同组设计标准，仅作一致性约束】躯干 1、平静头颈 1、失控头颈 1、平静口鼻 1、失控裂嘴 1、常态/空眼两组眼部 2、左右短臂 2、左右脚 2、尾 1，共 12 件。头颈、眼、口分层，裂嘴不与选中圈或残影合并。 沿用两份已批准定稿的线宽与体积，关节背面补全；可复用部位只交一份，不为每个动作复制整身。完整定稿仅作组合校对，不额外计独立交付单位。 以上为整套构成；每次只生成 「逐张提示词」本张范围 指定的一个独立件，不画整套平铺图。 【本次只画】本次只画奶龙平静头颈，含不等高小角；预留眼和口鼻，不烘焙五官；只交这一独立单元，不画其他零件、对照姿、sheet、文字或背景。保持主表指定造型、朝向与挂点。；本次只交付这一件/一个姿势，不把同组其他素材、姿势或裁切线画进本图，不拼成多格图集。 【状态】IDLE / WORKING / BREACHED 【参考】附图 REF_N01_CALM / REF_N01_BREACH。奶龙 已批准平静与失控定稿。如有前置定稿，必须保持同一造型、比例、线宽、服装和配色；拆件需另附已确认整身定稿图。 【画布】1024 × 1024 px，每张单独姿势/零件，共用 (512, 896) 根；尺寸不支持时保持比例生成，再后处理到目标尺寸。 【输出】本次仅一张单件 PNG，sRGB；真实 Alpha 透明背景；保持足够安全边距；尺寸修正、边缘清理、分层源文件及轴点记录由后处理制作。。只输出当前这一张；套组其余部分由其他任务分别完成。透明须为真实Alpha，禁止棋盘格。 【对齐】脚底地面中心；母版 (512, 896)，朝右；全部形态共享同一根节点。 另记录头颈、四肢、口部或钟针等实际旋转挂点。 【禁止】不做 3D、照片写实、厚涂油画、等距俯视、高饱和二次元、霓虹光污染、密集脏污；不加文字、数字、二维码、水印、游戏界面或棋盘格背景；不把动态状态、血条、范围、路径烘焙进图。 不要照片、3D 渲染、像素风、光滑矢量图标风或高饱和日漫；不要复制现成游戏的角色、脸型或官方 IP 素材；不要背景、文字、水印、UI、血条、黄色选中圈或攻击范围；不要以红色滤镜代替形变。 | E52: =生成规范!$B$9&CHAR(10)&素材需求!S18 -> 不做 3D、照片写实、厚涂油画、等距俯视、高饱和二次元、霓虹光污染、密集脏污；不加文字、数字、二维码、水印、游戏界面或棋盘格背景；不把动态状态、血条、范围、路径烘焙进图。 不要照片、3D 渲染、像素风、光滑矢量图标风或高饱和日漫；不要复制现成游戏的角色、脸型或官方 IP 素材；不要背景、文字、水印、UI、血条、黄色选中圈或攻击范围；不要以红色滤镜代替形变。 | F52: REF_N01_CALM / REF_N01_BREACH | G52: =素材需求!B18 -> P0 | H52: 1024 × 1024 px，每张单独姿势/零件，共用 (512, 896) 根 | I52: 本次只画奶龙平静头颈，含不等高小角；预留眼和口鼻，不烘焙五官；只交这一独立单元，不画其他零件、对照姿、sheet、文字或背景。保持主表指定造型、朝向与挂点。 | J52: 本次仅一张单件 PNG，sRGB；真实 Alpha 透明背景；保持足够安全边距；尺寸修正、边缘清理、分层源文件及轴点记录由后处理制作。 | K52: 脚底地面中心；母版 (512, 896)，朝右；全部形态共享同一根节点。 另记录头颈、四肢、口部或钟针等实际旋转挂点。 | L52: art_delivery/v1/abnormalities/ | M52: 待生成 | N52: ABN_N01_01 / ABN_N01_03
A53: ABN_N01_04 | B53: abn_nailong_parts_01_breach_head_neck.png | C53: 奶龙失控头颈 | D53: ="【唯一交付文件】"&B53&CHAR(10)&"【对象】"&C53&CHAR(10)&生成规范!$B$8&CHAR(10)&"【同组设计标准，仅作一致性约束】"&素材需求!G18&CHAR(10)&"【本次只画】"&I53&"；本次只交付这一件/一个姿势，不把同组其他素材、姿势或裁切线画进本图，不拼成多格图集。"&CHAR(10)&"【状态】"&素材需求!F18&CHAR(10)&"【参考】附图 "&F53&"。"&素材需求!H18&"。如有前置定稿，必须保持同一造型、比例、线宽、服装和配色；拆件需另附已确认整身定稿图。"&CHAR(10)&"【画布】"&H53&"；尺寸不支持时保持比例生成，再后处理到目标尺寸。"&CHAR(10)&"【输出】"&J53&"。只输出当前这一张；套组其余部分由其他任务分别完成。透明须为真实Alpha，禁止棋盘格。"&CHAR(10)&"【对齐】"&K53&CHAR(10)&"【禁止】"&E53 -> 【唯一交付文件】abn_nailong_parts_01_breach_head_neck.png 【对象】奶龙失控头颈 原创二维地下工业收容设施游戏美术；怪诞手绘收容风，受手绘怪诞生存童话的表现原则启发。hand-drawn, ink-outline, slightly grotesque, whimsical horror, 2D cutout-friendly。粗细有变化的深墨轮廓，轻微不规则手绘线，大面积低饱和平涂，少量刻线阴影；剪影与动作优先于纹理。正交二维侧视角色/设施，UI为正视平面。保留对象身份，统一视觉语言，不复制其他作品具体资产。 【同组设计标准，仅作一致性约束】躯干 1、平静头颈 1、失控头颈 1、平静口鼻 1、失控裂嘴 1、常态/空眼两组眼部 2、左右短臂 2、左右脚 2、尾 1，共 12 件。头颈、眼、口分层，裂嘴不与选中圈或残影合并。 沿用两份已批准定稿的线宽与体积，关节背面补全；可复用部位只交一份，不为每个动作复制整身。完整定稿仅作组合校对，不额外计独立交付单位。 以上为整套构成；每次只生成 「逐张提示词」本张范围 指定的一个独立件，不画整套平铺图。 【本次只画】本次只画奶龙失控拉长头颈，预留空眼与裂嘴，不烘焙五官；只交这一独立单元，不画其他零件、对照姿、sheet、文字或背景。保持主表指定造型、朝向与挂点。；本次只交付这一件/一个姿势，不把同组其他素材、姿势或裁切线画进本图，不拼成多格图集。 【状态】IDLE / WORKING / BREACHED 【参考】附图 REF_N01_CALM / REF_N01_BREACH。奶龙 已批准平静与失控定稿。如有前置定稿，必须保持同一造型、比例、线宽、服装和配色；拆件需另附已确认整身定稿图。 【画布】1024 × 1024 px，每张单独姿势/零件，共用 (512, 896) 根；尺寸不支持时保持比例生成，再后处理到目标尺寸。 【输出】本次仅一张单件 PNG，sRGB；真实 Alpha 透明背景；保持足够安全边距；尺寸修正、边缘清理、分层源文件及轴点记录由后处理制作。。只输出当前这一张；套组其余部分由其他任务分别完成。透明须为真实Alpha，禁止棋盘格。 【对齐】脚底地面中心；母版 (512, 896)，朝右；全部形态共享同一根节点。 另记录头颈、四肢、口部或钟针等实际旋转挂点。 【禁止】不做 3D、照片写实、厚涂油画、等距俯视、高饱和二次元、霓虹光污染、密集脏污；不加文字、数字、二维码、水印、游戏界面或棋盘格背景；不把动态状态、血条、范围、路径烘焙进图。 不要照片、3D 渲染、像素风、光滑矢量图标风或高饱和日漫；不要复制现成游戏的角色、脸型或官方 IP 素材；不要背景、文字、水印、UI、血条、黄色选中圈或攻击范围；不要以红色滤镜代替形变。 | E53: =生成规范!$B$9&CHAR(10)&素材需求!S18 -> 不做 3D、照片写实、厚涂油画、等距俯视、高饱和二次元、霓虹光污染、密集脏污；不加文字、数字、二维码、水印、游戏界面或棋盘格背景；不把动态状态、血条、范围、路径烘焙进图。 不要照片、3D 渲染、像素风、光滑矢量图标风或高饱和日漫；不要复制现成游戏的角色、脸型或官方 IP 素材；不要背景、文字、水印、UI、血条、黄色选中圈或攻击范围；不要以红色滤镜代替形变。 | F53: REF_N01_CALM / REF_N01_BREACH | G53: =素材需求!B18 -> P0 | H53: 1024 × 1024 px，每张单独姿势/零件，共用 (512, 896) 根 | I53: 本次只画奶龙失控拉长头颈，预留空眼与裂嘴，不烘焙五官；只交这一独立单元，不画其他零件、对照姿、sheet、文字或背景。保持主表指定造型、朝向与挂点。 | J53: 本次仅一张单件 PNG，sRGB；真实 Alpha 透明背景；保持足够安全边距；尺寸修正、边缘清理、分层源文件及轴点记录由后处理制作。 | K53: 脚底地面中心；母版 (512, 896)，朝右；全部形态共享同一根节点。 另记录头颈、四肢、口部或钟针等实际旋转挂点。 | L53: art_delivery/v1/abnormalities/ | M53: 待生成 | N53: ABN_N01_01 / ABN_N01_03
A54: ABN_N01_04 | B54: abn_nailong_parts_01_calm_muzzle.png | C54: 奶龙平静口鼻 | D54: ="【唯一交付文件】"&B54&CHAR(10)&"【对象】"&C54&CHAR(10)&生成规范!$B$8&CHAR(10)&"【同组设计标准，仅作一致性约束】"&素材需求!G18&CHAR(10)&"【本次只画】"&I54&"；本次只交付这一件/一个姿势，不把同组其他素材、姿势或裁切线画进本图，不拼成多格图集。"&CHAR(10)&"【状态】"&素材需求!F18&CHAR(10)&"【参考】附图 "&F54&"。"&素材需求!H18&"。如有前置定稿，必须保持同一造型、比例、线宽、服装和配色；拆件需另附已确认整身定稿图。"&CHAR(10)&"【画布】"&H54&"；尺寸不支持时保持比例生成，再后处理到目标尺寸。"&CHAR(10)&"【输出】"&J54&"。只输出当前这一张；套组其余部分由其他任务分别完成。透明须为真实Alpha，禁止棋盘格。"&CHAR(10)&"【对齐】"&K54&CHAR(10)&"【禁止】"&E54 -> 【唯一交付文件】abn_nailong_parts_01_calm_muzzle.png 【对象】奶龙平静口鼻 原创二维地下工业收容设施游戏美术；怪诞手绘收容风，受手绘怪诞生存童话的表现原则启发。hand-drawn, ink-outline, slightly grotesque, whimsical horror, 2D cutout-friendly。粗细有变化的深墨轮廓，轻微不规则手绘线，大面积低饱和平涂，少量刻线阴影；剪影与动作优先于纹理。正交二维侧视角色/设施，UI为正视平面。保留对象身份，统一视觉语言，不复制其他作品具体资产。 【同组设计标准，仅作一致性约束】躯干 1、平静头颈 1、失控头颈 1、平静口鼻 1、失控裂嘴 1、常态/空眼两组眼部 2、左右短臂 2、左右脚 2、尾 1，共 12 件。头颈、眼、口分层，裂嘴不与选中圈或残影合并。 沿用两份已批准定稿的线宽与体积，关节背面补全；可复用部位只交一份，不为每个动作复制整身。完整定稿仅作组合校对，不额外计独立交付单位。 以上为整套构成；每次只生成 「逐张提示词」本张范围 指定的一个独立件，不画整套平铺图。 【本次只画】本次只画奶龙平静的突出口鼻件，奶油色、短抿嘴；只交这一独立单元，不画其他零件、对照姿、sheet、文字或背景。保持主表指定造型、朝向与挂点。；本次只交付这一件/一个姿势，不把同组其他素材、姿势或裁切线画进本图，不拼成多格图集。 【状态】IDLE / WORKING / BREACHED 【参考】附图 REF_N01_CALM / REF_N01_BREACH。奶龙 已批准平静与失控定稿。如有前置定稿，必须保持同一造型、比例、线宽、服装和配色；拆件需另附已确认整身定稿图。 【画布】1024 × 1024 px，每张单独姿势/零件，共用 (512, 896) 根；尺寸不支持时保持比例生成，再后处理到目标尺寸。 【输出】本次仅一张单件 PNG，sRGB；真实 Alpha 透明背景；保持足够安全边距；尺寸修正、边缘清理、分层源文件及轴点记录由后处理制作。。只输出当前这一张；套组其余部分由其他任务分别完成。透明须为真实Alpha，禁止棋盘格。 【对齐】脚底地面中心；母版 (512, 896)，朝右；全部形态共享同一根节点。 另记录头颈、四肢、口部或钟针等实际旋转挂点。 【禁止】不做 3D、照片写实、厚涂油画、等距俯视、高饱和二次元、霓虹光污染、密集脏污；不加文字、数字、二维码、水印、游戏界面或棋盘格背景；不把动态状态、血条、范围、路径烘焙进图。 不要照片、3D 渲染、像素风、光滑矢量图标风或高饱和日漫；不要复制现成游戏的角色、脸型或官方 IP 素材；不要背景、文字、水印、UI、血条、黄色选中圈或攻击范围；不要以红色滤镜代替形变。 | E54: =生成规范!$B$9&CHAR(10)&素材需求!S18 -> 不做 3D、照片写实、厚涂油画、等距俯视、高饱和二次元、霓虹光污染、密集脏污；不加文字、数字、二维码、水印、游戏界面或棋盘格背景；不把动态状态、血条、范围、路径烘焙进图。 不要照片、3D 渲染、像素风、光滑矢量图标风或高饱和日漫；不要复制现成游戏的角色、脸型或官方 IP 素材；不要背景、文字、水印、UI、血条、黄色选中圈或攻击范围；不要以红色滤镜代替形变。 | F54: REF_N01_CALM / REF_N01_BREACH | G54: =素材需求!B18 -> P0 | H54: 1024 × 1024 px，每张单独姿势/零件，共用 (512, 896) 根 | I54: 本次只画奶龙平静的突出口鼻件，奶油色、短抿嘴；只交这一独立单元，不画其他零件、对照姿、sheet、文字或背景。保持主表指定造型、朝向与挂点。 | J54: 本次仅一张单件 PNG，sRGB；真实 Alpha 透明背景；保持足够安全边距；尺寸修正、边缘清理、分层源文件及轴点记录由后处理制作。 | K54: 脚底地面中心；母版 (512, 896)，朝右；全部形态共享同一根节点。 另记录头颈、四肢、口部或钟针等实际旋转挂点。 | L54: art_delivery/v1/abnormalities/ | M54: 待生成 | N54: ABN_N01_01 / ABN_N01_03
A55: ABN_N01_04 | B55: abn_nailong_parts_01_breach_mouth.png | C55: 奶龙失控裂嘴 | D55: ="【唯一交付文件】"&B55&CHAR(10)&"【对象】"&C55&CHAR(10)&生成规范!$B$8&CHAR(10)&"【同组设计标准，仅作一致性约束】"&素材需求!G18&CHAR(10)&"【本次只画】"&I55&"；本次只交付这一件/一个姿势，不把同组其他素材、姿势或裁切线画进本图，不拼成多格图集。"&CHAR(10)&"【状态】"&素材需求!F18&CHAR(10)&"【参考】附图 "&F55&"。"&素材需求!H18&"。如有前置定稿，必须保持同一造型、比例、线宽、服装和配色；拆件需另附已确认整身定稿图。"&CHAR(10)&"【画布】"&H55&"；尺寸不支持时保持比例生成，再后处理到目标尺寸。"&CHAR(10)&"【输出】"&J55&"。只输出当前这一张；套组其余部分由其他任务分别完成。透明须为真实Alpha，禁止棋盘格。"&CHAR(10)&"【对齐】"&K55&CHAR(10)&"【禁止】"&E55 -> 【唯一交付文件】abn_nailong_parts_01_breach_mouth.png 【对象】奶龙失控裂嘴 原创二维地下工业收容设施游戏美术；怪诞手绘收容风，受手绘怪诞生存童话的表现原则启发。hand-drawn, ink-outline, slightly grotesque, whimsical horror, 2D cutout-friendly。粗细有变化的深墨轮廓，轻微不规则手绘线，大面积低饱和平涂，少量刻线阴影；剪影与动作优先于纹理。正交二维侧视角色/设施，UI为正视平面。保留对象身份，统一视觉语言，不复制其他作品具体资产。 【同组设计标准，仅作一致性约束】躯干 1、平静头颈 1、失控头颈 1、平静口鼻 1、失控裂嘴 1、常态/空眼两组眼部 2、左右短臂 2、左右脚 2、尾 1，共 12 件。头颈、眼、口分层，裂嘴不与选中圈或残影合并。 沿用两份已批准定稿的线宽与体积，关节背面补全；可复用部位只交一份，不为每个动作复制整身。完整定稿仅作组合校对，不额外计独立交付单位。 以上为整套构成；每次只生成 「逐张提示词」本张范围 指定的一个独立件，不画整套平铺图。 【本次只画】本次只画奶龙失控的大斜裂嘴及稀疏三角齿，黑口内，无头颈；只交这一独立单元，不画其他零件、对照姿、sheet、文字或背景。保持主表指定造型、朝向与挂点。；本次只交付这一件/一个姿势，不把同组其他素材、姿势或裁切线画进本图，不拼成多格图集。 【状态】IDLE / WORKING / BREACHED 【参考】附图 REF_N01_CALM / REF_N01_BREACH。奶龙 已批准平静与失控定稿。如有前置定稿，必须保持同一造型、比例、线宽、服装和配色；拆件需另附已确认整身定稿图。 【画布】1024 × 1024 px，每张单独姿势/零件，共用 (512, 896) 根；尺寸不支持时保持比例生成，再后处理到目标尺寸。 【输出】本次仅一张单件 PNG，sRGB；真实 Alpha 透明背景；保持足够安全边距；尺寸修正、边缘清理、分层源文件及轴点记录由后处理制作。。只输出当前这一张；套组其余部分由其他任务分别完成。透明须为真实Alpha，禁止棋盘格。 【对齐】脚底地面中心；母版 (512, 896)，朝右；全部形态共享同一根节点。 另记录头颈、四肢、口部或钟针等实际旋转挂点。 【禁止】不做 3D、照片写实、厚涂油画、等距俯视、高饱和二次元、霓虹光污染、密集脏污；不加文字、数字、二维码、水印、游戏界面或棋盘格背景；不把动态状态、血条、范围、路径烘焙进图。 不要照片、3D 渲染、像素风、光滑矢量图标风或高饱和日漫；不要复制现成游戏的角色、脸型或官方 IP 素材；不要背景、文字、水印、UI、血条、黄色选中圈或攻击范围；不要以红色滤镜代替形变。 | E55: =生成规范!$B$9&CHAR(10)&素材需求!S18 -> 不做 3D、照片写实、厚涂油画、等距俯视、高饱和二次元、霓虹光污染、密集脏污；不加文字、数字、二维码、水印、游戏界面或棋盘格背景；不把动态状态、血条、范围、路径烘焙进图。 不要照片、3D 渲染、像素风、光滑矢量图标风或高饱和日漫；不要复制现成游戏的角色、脸型或官方 IP 素材；不要背景、文字、水印、UI、血条、黄色选中圈或攻击范围；不要以红色滤镜代替形变。 | F55: REF_N01_CALM / REF_N01_BREACH | G55: =素材需求!B18 -> P0 | H55: 1024 × 1024 px，每张单独姿势/零件，共用 (512, 896) 根 | I55: 本次只画奶龙失控的大斜裂嘴及稀疏三角齿，黑口内，无头颈；只交这一独立单元，不画其他零件、对照姿、sheet、文字或背景。保持主表指定造型、朝向与挂点。 | J55: 本次仅一张单件 PNG，sRGB；真实 Alpha 透明背景；保持足够安全边距；尺寸修正、边缘清理、分层源文件及轴点记录由后处理制作。 | K55: 脚底地面中心；母版 (512, 896)，朝右；全部形态共享同一根节点。 另记录头颈、四肢、口部或钟针等实际旋转挂点。 | L55: art_delivery/v1/abnormalities/ | M55: 待生成 | N55: ABN_N01_01 / ABN_N01_03
A56: ABN_N01_04 | B56: abn_nailong_parts_01_calm_eyes.png | C56: 奶龙平静眼组 | D56: ="【唯一交付文件】"&B56&CHAR(10)&"【对象】"&C56&CHAR(10)&生成规范!$B$8&CHAR(10)&"【同组设计标准，仅作一致性约束】"&素材需求!G18&CHAR(10)&"【本次只画】"&I56&"；本次只交付这一件/一个姿势，不把同组其他素材、姿势或裁切线画进本图，不拼成多格图集。"&CHAR(10)&"【状态】"&素材需求!F18&CHAR(10)&"【参考】附图 "&F56&"。"&素材需求!H18&"。如有前置定稿，必须保持同一造型、比例、线宽、服装和配色；拆件需另附已确认整身定稿图。"&CHAR(10)&"【画布】"&H56&"；尺寸不支持时保持比例生成，再后处理到目标尺寸。"&CHAR(10)&"【输出】"&J56&"。只输出当前这一张；套组其余部分由其他任务分别完成。透明须为真实Alpha，禁止棋盘格。"&CHAR(10)&"【对齐】"&K56&CHAR(10)&"【禁止】"&E56 -> 【唯一交付文件】abn_nailong_parts_01_calm_eyes.png 【对象】奶龙平静眼组 原创二维地下工业收容设施游戏美术；怪诞手绘收容风，受手绘怪诞生存童话的表现原则启发。hand-drawn, ink-outline, slightly grotesque, whimsical horror, 2D cutout-friendly。粗细有变化的深墨轮廓，轻微不规则手绘线，大面积低饱和平涂，少量刻线阴影；剪影与动作优先于纹理。正交二维侧视角色/设施，UI为正视平面。保留对象身份，统一视觉语言，不复制其他作品具体资产。 【同组设计标准，仅作一致性约束】躯干 1、平静头颈 1、失控头颈 1、平静口鼻 1、失控裂嘴 1、常态/空眼两组眼部 2、左右短臂 2、左右脚 2、尾 1，共 12 件。头颈、眼、口分层，裂嘴不与选中圈或残影合并。 沿用两份已批准定稿的线宽与体积，关节背面补全；可复用部位只交一份，不为每个动作复制整身。完整定稿仅作组合校对，不额外计独立交付单位。 以上为整套构成；每次只生成 「逐张提示词」本张范围 指定的一个独立件，不画整套平铺图。 【本次只画】本次只画奶龙平静的不等大眼组，保留透明眼间区域；只交这一独立单元，不画其他零件、对照姿、sheet、文字或背景。保持主表指定造型、朝向与挂点。；本次只交付这一件/一个姿势，不把同组其他素材、姿势或裁切线画进本图，不拼成多格图集。 【状态】IDLE / WORKING / BREACHED 【参考】附图 REF_N01_CALM / REF_N01_BREACH。奶龙 已批准平静与失控定稿。如有前置定稿，必须保持同一造型、比例、线宽、服装和配色；拆件需另附已确认整身定稿图。 【画布】1024 × 1024 px，每张单独姿势/零件，共用 (512, 896) 根；尺寸不支持时保持比例生成，再后处理到目标尺寸。 【输出】本次仅一张单件 PNG，sRGB；真实 Alpha 透明背景；保持足够安全边距；尺寸修正、边缘清理、分层源文件及轴点记录由后处理制作。。只输出当前这一张；套组其余部分由其他任务分别完成。透明须为真实Alpha，禁止棋盘格。 【对齐】脚底地面中心；母版 (512, 896)，朝右；全部形态共享同一根节点。 另记录头颈、四肢、口部或钟针等实际旋转挂点。 【禁止】不做 3D、照片写实、厚涂油画、等距俯视、高饱和二次元、霓虹光污染、密集脏污；不加文字、数字、二维码、水印、游戏界面或棋盘格背景；不把动态状态、血条、范围、路径烘焙进图。 不要照片、3D 渲染、像素风、光滑矢量图标风或高饱和日漫；不要复制现成游戏的角色、脸型或官方 IP 素材；不要背景、文字、水印、UI、血条、黄色选中圈或攻击范围；不要以红色滤镜代替形变。 | E56: =生成规范!$B$9&CHAR(10)&素材需求!S18 -> 不做 3D、照片写实、厚涂油画、等距俯视、高饱和二次元、霓虹光污染、密集脏污；不加文字、数字、二维码、水印、游戏界面或棋盘格背景；不把动态状态、血条、范围、路径烘焙进图。 不要照片、3D 渲染、像素风、光滑矢量图标风或高饱和日漫；不要复制现成游戏的角色、脸型或官方 IP 素材；不要背景、文字、水印、UI、血条、黄色选中圈或攻击范围；不要以红色滤镜代替形变。 | F56: REF_N01_CALM / REF_N01_BREACH | G56: =素材需求!B18 -> P0 | H56: 1024 × 1024 px，每张单独姿势/零件，共用 (512, 896) 根 | I56: 本次只画奶龙平静的不等大眼组，保留透明眼间区域；只交这一独立单元，不画其他零件、对照姿、sheet、文字或背景。保持主表指定造型、朝向与挂点。 | J56: 本次仅一张单件 PNG，sRGB；真实 Alpha 透明背景；保持足够安全边距；尺寸修正、边缘清理、分层源文件及轴点记录由后处理制作。 | K56: 脚底地面中心；母版 (512, 896)，朝右；全部形态共享同一根节点。 另记录头颈、四肢、口部或钟针等实际旋转挂点。 | L56: art_delivery/v1/abnormalities/ | M56: 待生成 | N56: ABN_N01_01 / ABN_N01_03
A57: ABN_N01_04 | B57: abn_nailong_parts_01_breach_eyes.png | C57: 奶龙空眼组 | D57: ="【唯一交付文件】"&B57&CHAR(10)&"【对象】"&C57&CHAR(10)&生成规范!$B$8&CHAR(10)&"【同组设计标准，仅作一致性约束】"&素材需求!G18&CHAR(10)&"【本次只画】"&I57&"；本次只交付这一件/一个姿势，不把同组其他素材、姿势或裁切线画进本图，不拼成多格图集。"&CHAR(10)&"【状态】"&素材需求!F18&CHAR(10)&"【参考】附图 "&F57&"。"&素材需求!H18&"。如有前置定稿，必须保持同一造型、比例、线宽、服装和配色；拆件需另附已确认整身定稿图。"&CHAR(10)&"【画布】"&H57&"；尺寸不支持时保持比例生成，再后处理到目标尺寸。"&CHAR(10)&"【输出】"&J57&"。只输出当前这一张；套组其余部分由其他任务分别完成。透明须为真实Alpha，禁止棋盘格。"&CHAR(10)&"【对齐】"&K57&CHAR(10)&"【禁止】"&E57 -> 【唯一交付文件】abn_nailong_parts_01_breach_eyes.png 【对象】奶龙空眼组 原创二维地下工业收容设施游戏美术；怪诞手绘收容风，受手绘怪诞生存童话的表现原则启发。hand-drawn, ink-outline, slightly grotesque, whimsical horror, 2D cutout-friendly。粗细有变化的深墨轮廓，轻微不规则手绘线，大面积低饱和平涂，少量刻线阴影；剪影与动作优先于纹理。正交二维侧视角色/设施，UI为正视平面。保留对象身份，统一视觉语言，不复制其他作品具体资产。 【同组设计标准，仅作一致性约束】躯干 1、平静头颈 1、失控头颈 1、平静口鼻 1、失控裂嘴 1、常态/空眼两组眼部 2、左右短臂 2、左右脚 2、尾 1，共 12 件。头颈、眼、口分层，裂嘴不与选中圈或残影合并。 沿用两份已批准定稿的线宽与体积，关节背面补全；可复用部位只交一份，不为每个动作复制整身。完整定稿仅作组合校对，不额外计独立交付单位。 以上为整套构成；每次只生成 「逐张提示词」本张范围 指定的一个独立件，不画整套平铺图。 【本次只画】本次只画奶龙失控的大小不等实黑空眼组，保留透明眼间区域；只交这一独立单元，不画其他零件、对照姿、sheet、文字或背景。保持主表指定造型、朝向与挂点。；本次只交付这一件/一个姿势，不把同组其他素材、姿势或裁切线画进本图，不拼成多格图集。 【状态】IDLE / WORKING / BREACHED 【参考】附图 REF_N01_CALM / REF_N01_BREACH。奶龙 已批准平静与失控定稿。如有前置定稿，必须保持同一造型、比例、线宽、服装和配色；拆件需另附已确认整身定稿图。 【画布】1024 × 1024 px，每张单独姿势/零件，共用 (512, 896) 根；尺寸不支持时保持比例生成，再后处理到目标尺寸。 【输出】本次仅一张单件 PNG，sRGB；真实 Alpha 透明背景；保持足够安全边距；尺寸修正、边缘清理、分层源文件及轴点记录由后处理制作。。只输出当前这一张；套组其余部分由其他任务分别完成。透明须为真实Alpha，禁止棋盘格。 【对齐】脚底地面中心；母版 (512, 896)，朝右；全部形态共享同一根节点。 另记录头颈、四肢、口部或钟针等实际旋转挂点。 【禁止】不做 3D、照片写实、厚涂油画、等距俯视、高饱和二次元、霓虹光污染、密集脏污；不加文字、数字、二维码、水印、游戏界面或棋盘格背景；不把动态状态、血条、范围、路径烘焙进图。 不要照片、3D 渲染、像素风、光滑矢量图标风或高饱和日漫；不要复制现成游戏的角色、脸型或官方 IP 素材；不要背景、文字、水印、UI、血条、黄色选中圈或攻击范围；不要以红色滤镜代替形变。 | E57: =生成规范!$B$9&CHAR(10)&素材需求!S18 -> 不做 3D、照片写实、厚涂油画、等距俯视、高饱和二次元、霓虹光污染、密集脏污；不加文字、数字、二维码、水印、游戏界面或棋盘格背景；不把动态状态、血条、范围、路径烘焙进图。 不要照片、3D 渲染、像素风、光滑矢量图标风或高饱和日漫；不要复制现成游戏的角色、脸型或官方 IP 素材；不要背景、文字、水印、UI、血条、黄色选中圈或攻击范围；不要以红色滤镜代替形变。 | F57: REF_N01_CALM / REF_N01_BREACH | G57: =素材需求!B18 -> P0 | H57: 1024 × 1024 px，每张单独姿势/零件，共用 (512, 896) 根 | I57: 本次只画奶龙失控的大小不等实黑空眼组，保留透明眼间区域；只交这一独立单元，不画其他零件、对照姿、sheet、文字或背景。保持主表指定造型、朝向与挂点。 | J57: 本次仅一张单件 PNG，sRGB；真实 Alpha 透明背景；保持足够安全边距；尺寸修正、边缘清理、分层源文件及轴点记录由后处理制作。 | K57: 脚底地面中心；母版 (512, 896)，朝右；全部形态共享同一根节点。 另记录头颈、四肢、口部或钟针等实际旋转挂点。 | L57: art_delivery/v1/abnormalities/ | M57: 待生成 | N57: ABN_N01_01 / ABN_N01_03
A58: ABN_N01_04 | B58: abn_nailong_parts_01_arm_left.png | C58: 奶龙左短臂 | D58: ="【唯一交付文件】"&B58&CHAR(10)&"【对象】"&C58&CHAR(10)&生成规范!$B$8&CHAR(10)&"【同组设计标准，仅作一致性约束】"&素材需求!G18&CHAR(10)&"【本次只画】"&I58&"；本次只交付这一件/一个姿势，不把同组其他素材、姿势或裁切线画进本图，不拼成多格图集。"&CHAR(10)&"【状态】"&素材需求!F18&CHAR(10)&"【参考】附图 "&F58&"。"&素材需求!H18&"。如有前置定稿，必须保持同一造型、比例、线宽、服装和配色；拆件需另附已确认整身定稿图。"&CHAR(10)&"【画布】"&H58&"；尺寸不支持时保持比例生成，再后处理到目标尺寸。"&CHAR(10)&"【输出】"&J58&"。只输出当前这一张；套组其余部分由其他任务分别完成。透明须为真实Alpha，禁止棋盘格。"&CHAR(10)&"【对齐】"&K58&CHAR(10)&"【禁止】"&E58 -> 【唯一交付文件】abn_nailong_parts_01_arm_left.png 【对象】奶龙左短臂 原创二维地下工业收容设施游戏美术；怪诞手绘收容风，受手绘怪诞生存童话的表现原则启发。hand-drawn, ink-outline, slightly grotesque, whimsical horror, 2D cutout-friendly。粗细有变化的深墨轮廓，轻微不规则手绘线，大面积低饱和平涂，少量刻线阴影；剪影与动作优先于纹理。正交二维侧视角色/设施，UI为正视平面。保留对象身份，统一视觉语言，不复制其他作品具体资产。 【同组设计标准，仅作一致性约束】躯干 1、平静头颈 1、失控头颈 1、平静口鼻 1、失控裂嘴 1、常态/空眼两组眼部 2、左右短臂 2、左右脚 2、尾 1，共 12 件。头颈、眼、口分层，裂嘴不与选中圈或残影合并。 沿用两份已批准定稿的线宽与体积，关节背面补全；可复用部位只交一份，不为每个动作复制整身。完整定稿仅作组合校对，不额外计独立交付单位。 以上为整套构成；每次只生成 「逐张提示词」本张范围 指定的一个独立件，不画整套平铺图。 【本次只画】本次只画奶龙左短臂和小手，补全肩根；只交这一独立单元，不画其他零件、对照姿、sheet、文字或背景。保持主表指定造型、朝向与挂点。；本次只交付这一件/一个姿势，不把同组其他素材、姿势或裁切线画进本图，不拼成多格图集。 【状态】IDLE / WORKING / BREACHED 【参考】附图 REF_N01_CALM / REF_N01_BREACH。奶龙 已批准平静与失控定稿。如有前置定稿，必须保持同一造型、比例、线宽、服装和配色；拆件需另附已确认整身定稿图。 【画布】1024 × 1024 px，每张单独姿势/零件，共用 (512, 896) 根；尺寸不支持时保持比例生成，再后处理到目标尺寸。 【输出】本次仅一张单件 PNG，sRGB；真实 Alpha 透明背景；保持足够安全边距；尺寸修正、边缘清理、分层源文件及轴点记录由后处理制作。。只输出当前这一张；套组其余部分由其他任务分别完成。透明须为真实Alpha，禁止棋盘格。 【对齐】脚底地面中心；母版 (512, 896)，朝右；全部形态共享同一根节点。 另记录头颈、四肢、口部或钟针等实际旋转挂点。 【禁止】不做 3D、照片写实、厚涂油画、等距俯视、高饱和二次元、霓虹光污染、密集脏污；不加文字、数字、二维码、水印、游戏界面或棋盘格背景；不把动态状态、血条、范围、路径烘焙进图。 不要照片、3D 渲染、像素风、光滑矢量图标风或高饱和日漫；不要复制现成游戏的角色、脸型或官方 IP 素材；不要背景、文字、水印、UI、血条、黄色选中圈或攻击范围；不要以红色滤镜代替形变。 | E58: =生成规范!$B$9&CHAR(10)&素材需求!S18 -> 不做 3D、照片写实、厚涂油画、等距俯视、高饱和二次元、霓虹光污染、密集脏污；不加文字、数字、二维码、水印、游戏界面或棋盘格背景；不把动态状态、血条、范围、路径烘焙进图。 不要照片、3D 渲染、像素风、光滑矢量图标风或高饱和日漫；不要复制现成游戏的角色、脸型或官方 IP 素材；不要背景、文字、水印、UI、血条、黄色选中圈或攻击范围；不要以红色滤镜代替形变。 | F58: REF_N01_CALM / REF_N01_BREACH | G58: =素材需求!B18 -> P0 | H58: 1024 × 1024 px，每张单独姿势/零件，共用 (512, 896) 根 | I58: 本次只画奶龙左短臂和小手，补全肩根；只交这一独立单元，不画其他零件、对照姿、sheet、文字或背景。保持主表指定造型、朝向与挂点。 | J58: 本次仅一张单件 PNG，sRGB；真实 Alpha 透明背景；保持足够安全边距；尺寸修正、边缘清理、分层源文件及轴点记录由后处理制作。 | K58: 脚底地面中心；母版 (512, 896)，朝右；全部形态共享同一根节点。 另记录头颈、四肢、口部或钟针等实际旋转挂点。 | L58: art_delivery/v1/abnormalities/ | M58: 待生成 | N58: ABN_N01_01 / ABN_N01_03
A59: ABN_N01_04 | B59: abn_nailong_parts_01_arm_right.png | C59: 奶龙右短臂 | D59: ="【唯一交付文件】"&B59&CHAR(10)&"【对象】"&C59&CHAR(10)&生成规范!$B$8&CHAR(10)&"【同组设计标准，仅作一致性约束】"&素材需求!G18&CHAR(10)&"【本次只画】"&I59&"；本次只交付这一件/一个姿势，不把同组其他素材、姿势或裁切线画进本图，不拼成多格图集。"&CHAR(10)&"【状态】"&素材需求!F18&CHAR(10)&"【参考】附图 "&F59&"。"&素材需求!H18&"。如有前置定稿，必须保持同一造型、比例、线宽、服装和配色；拆件需另附已确认整身定稿图。"&CHAR(10)&"【画布】"&H59&"；尺寸不支持时保持比例生成，再后处理到目标尺寸。"&CHAR(10)&"【输出】"&J59&"。只输出当前这一张；套组其余部分由其他任务分别完成。透明须为真实Alpha，禁止棋盘格。"&CHAR(10)&"【对齐】"&K59&CHAR(10)&"【禁止】"&E59 -> 【唯一交付文件】abn_nailong_parts_01_arm_right.png 【对象】奶龙右短臂 原创二维地下工业收容设施游戏美术；怪诞手绘收容风，受手绘怪诞生存童话的表现原则启发。hand-drawn, ink-outline, slightly grotesque, whimsical horror, 2D cutout-friendly。粗细有变化的深墨轮廓，轻微不规则手绘线，大面积低饱和平涂，少量刻线阴影；剪影与动作优先于纹理。正交二维侧视角色/设施，UI为正视平面。保留对象身份，统一视觉语言，不复制其他作品具体资产。 【同组设计标准，仅作一致性约束】躯干 1、平静头颈 1、失控头颈 1、平静口鼻 1、失控裂嘴 1、常态/空眼两组眼部 2、左右短臂 2、左右脚 2、尾 1，共 12 件。头颈、眼、口分层，裂嘴不与选中圈或残影合并。 沿用两份已批准定稿的线宽与体积，关节背面补全；可复用部位只交一份，不为每个动作复制整身。完整定稿仅作组合校对，不额外计独立交付单位。 以上为整套构成；每次只生成 「逐张提示词」本张范围 指定的一个独立件，不画整套平铺图。 【本次只画】本次只画奶龙右短臂和小手，补全肩根；只交这一独立单元，不画其他零件、对照姿、sheet、文字或背景。保持主表指定造型、朝向与挂点。；本次只交付这一件/一个姿势，不把同组其他素材、姿势或裁切线画进本图，不拼成多格图集。 【状态】IDLE / WORKING / BREACHED 【参考】附图 REF_N01_CALM / REF_N01_BREACH。奶龙 已批准平静与失控定稿。如有前置定稿，必须保持同一造型、比例、线宽、服装和配色；拆件需另附已确认整身定稿图。 【画布】1024 × 1024 px，每张单独姿势/零件，共用 (512, 896) 根；尺寸不支持时保持比例生成，再后处理到目标尺寸。 【输出】本次仅一张单件 PNG，sRGB；真实 Alpha 透明背景；保持足够安全边距；尺寸修正、边缘清理、分层源文件及轴点记录由后处理制作。。只输出当前这一张；套组其余部分由其他任务分别完成。透明须为真实Alpha，禁止棋盘格。 【对齐】脚底地面中心；母版 (512, 896)，朝右；全部形态共享同一根节点。 另记录头颈、四肢、口部或钟针等实际旋转挂点。 【禁止】不做 3D、照片写实、厚涂油画、等距俯视、高饱和二次元、霓虹光污染、密集脏污；不加文字、数字、二维码、水印、游戏界面或棋盘格背景；不把动态状态、血条、范围、路径烘焙进图。 不要照片、3D 渲染、像素风、光滑矢量图标风或高饱和日漫；不要复制现成游戏的角色、脸型或官方 IP 素材；不要背景、文字、水印、UI、血条、黄色选中圈或攻击范围；不要以红色滤镜代替形变。 | E59: =生成规范!$B$9&CHAR(10)&素材需求!S18 -> 不做 3D、照片写实、厚涂油画、等距俯视、高饱和二次元、霓虹光污染、密集脏污；不加文字、数字、二维码、水印、游戏界面或棋盘格背景；不把动态状态、血条、范围、路径烘焙进图。 不要照片、3D 渲染、像素风、光滑矢量图标风或高饱和日漫；不要复制现成游戏的角色、脸型或官方 IP 素材；不要背景、文字、水印、UI、血条、黄色选中圈或攻击范围；不要以红色滤镜代替形变。 | F59: REF_N01_CALM / REF_N01_BREACH | G59: =素材需求!B18 -> P0 | H59: 1024 × 1024 px，每张单独姿势/零件，共用 (512, 896) 根 | I59: 本次只画奶龙右短臂和小手，补全肩根；只交这一独立单元，不画其他零件、对照姿、sheet、文字或背景。保持主表指定造型、朝向与挂点。 | J59: 本次仅一张单件 PNG，sRGB；真实 Alpha 透明背景；保持足够安全边距；尺寸修正、边缘清理、分层源文件及轴点记录由后处理制作。 | K59: 脚底地面中心；母版 (512, 896)，朝右；全部形态共享同一根节点。 另记录头颈、四肢、口部或钟针等实际旋转挂点。 | L59: art_delivery/v1/abnormalities/ | M59: 待生成 | N59: ABN_N01_01 / ABN_N01_03
A60: ABN_N01_04 | B60: abn_nailong_parts_01_foot_left.png | C60: 奶龙左脚 | D60: ="【唯一交付文件】"&B60&CHAR(10)&"【对象】"&C60&CHAR(10)&生成规范!$B$8&CHAR(10)&"【同组设计标准，仅作一致性约束】"&素材需求!G18&CHAR(10)&"【本次只画】"&I60&"；本次只交付这一件/一个姿势，不把同组其他素材、姿势或裁切线画进本图，不拼成多格图集。"&CHAR(10)&"【状态】"&素材需求!F18&CHAR(10)&"【参考】附图 "&F60&"。"&素材需求!H18&"。如有前置定稿，必须保持同一造型、比例、线宽、服装和配色；拆件需另附已确认整身定稿图。"&CHAR(10)&"【画布】"&H60&"；尺寸不支持时保持比例生成，再后处理到目标尺寸。"&CHAR(10)&"【输出】"&J60&"。只输出当前这一张；套组其余部分由其他任务分别完成。透明须为真实Alpha，禁止棋盘格。"&CHAR(10)&"【对齐】"&K60&CHAR(10)&"【禁止】"&E60 -> 【唯一交付文件】abn_nailong_parts_01_foot_left.png 【对象】奶龙左脚 原创二维地下工业收容设施游戏美术；怪诞手绘收容风，受手绘怪诞生存童话的表现原则启发。hand-drawn, ink-outline, slightly grotesque, whimsical horror, 2D cutout-friendly。粗细有变化的深墨轮廓，轻微不规则手绘线，大面积低饱和平涂，少量刻线阴影；剪影与动作优先于纹理。正交二维侧视角色/设施，UI为正视平面。保留对象身份，统一视觉语言，不复制其他作品具体资产。 【同组设计标准，仅作一致性约束】躯干 1、平静头颈 1、失控头颈 1、平静口鼻 1、失控裂嘴 1、常态/空眼两组眼部 2、左右短臂 2、左右脚 2、尾 1，共 12 件。头颈、眼、口分层，裂嘴不与选中圈或残影合并。 沿用两份已批准定稿的线宽与体积，关节背面补全；可复用部位只交一份，不为每个动作复制整身。完整定稿仅作组合校对，不额外计独立交付单位。 以上为整套构成；每次只生成 「逐张提示词」本张范围 指定的一个独立件，不画整套平铺图。 【本次只画】本次只画奶龙左宽扁脚，脚底水平；只交这一独立单元，不画其他零件、对照姿、sheet、文字或背景。保持主表指定造型、朝向与挂点。；本次只交付这一件/一个姿势，不把同组其他素材、姿势或裁切线画进本图，不拼成多格图集。 【状态】IDLE / WORKING / BREACHED 【参考】附图 REF_N01_CALM / REF_N01_BREACH。奶龙 已批准平静与失控定稿。如有前置定稿，必须保持同一造型、比例、线宽、服装和配色；拆件需另附已确认整身定稿图。 【画布】1024 × 1024 px，每张单独姿势/零件，共用 (512, 896) 根；尺寸不支持时保持比例生成，再后处理到目标尺寸。 【输出】本次仅一张单件 PNG，sRGB；真实 Alpha 透明背景；保持足够安全边距；尺寸修正、边缘清理、分层源文件及轴点记录由后处理制作。。只输出当前这一张；套组其余部分由其他任务分别完成。透明须为真实Alpha，禁止棋盘格。 【对齐】脚底地面中心；母版 (512, 896)，朝右；全部形态共享同一根节点。 另记录头颈、四肢、口部或钟针等实际旋转挂点。 【禁止】不做 3D、照片写实、厚涂油画、等距俯视、高饱和二次元、霓虹光污染、密集脏污；不加文字、数字、二维码、水印、游戏界面或棋盘格背景；不把动态状态、血条、范围、路径烘焙进图。 不要照片、3D 渲染、像素风、光滑矢量图标风或高饱和日漫；不要复制现成游戏的角色、脸型或官方 IP 素材；不要背景、文字、水印、UI、血条、黄色选中圈或攻击范围；不要以红色滤镜代替形变。 | E60: =生成规范!$B$9&CHAR(10)&素材需求!S18 -> 不做 3D、照片写实、厚涂油画、等距俯视、高饱和二次元、霓虹光污染、密集脏污；不加文字、数字、二维码、水印、游戏界面或棋盘格背景；不把动态状态、血条、范围、路径烘焙进图。 不要照片、3D 渲染、像素风、光滑矢量图标风或高饱和日漫；不要复制现成游戏的角色、脸型或官方 IP 素材；不要背景、文字、水印、UI、血条、黄色选中圈或攻击范围；不要以红色滤镜代替形变。 | F60: REF_N01_CALM / REF_N01_BREACH | G60: =素材需求!B18 -> P0 | H60: 1024 × 1024 px，每张单独姿势/零件，共用 (512, 896) 根 | I60: 本次只画奶龙左宽扁脚，脚底水平；只交这一独立单元，不画其他零件、对照姿、sheet、文字或背景。保持主表指定造型、朝向与挂点。 | J60: 本次仅一张单件 PNG，sRGB；真实 Alpha 透明背景；保持足够安全边距；尺寸修正、边缘清理、分层源文件及轴点记录由后处理制作。 | K60: 脚底地面中心；母版 (512, 896)，朝右；全部形态共享同一根节点。 另记录头颈、四肢、口部或钟针等实际旋转挂点。 | L60: art_delivery/v1/abnormalities/ | M60: 待生成 | N60: ABN_N01_01 / ABN_N01_03
A61: ABN_N01_04 | B61: abn_nailong_parts_01_foot_right.png | C61: 奶龙右脚 | D61: ="【唯一交付文件】"&B61&CHAR(10)&"【对象】"&C61&CHAR(10)&生成规范!$B$8&CHAR(10)&"【同组设计标准，仅作一致性约束】"&素材需求!G18&CHAR(10)&"【本次只画】"&I61&"；本次只交付这一件/一个姿势，不把同组其他素材、姿势或裁切线画进本图，不拼成多格图集。"&CHAR(10)&"【状态】"&素材需求!F18&CHAR(10)&"【参考】附图 "&F61&"。"&素材需求!H18&"。如有前置定稿，必须保持同一造型、比例、线宽、服装和配色；拆件需另附已确认整身定稿图。"&CHAR(10)&"【画布】"&H61&"；尺寸不支持时保持比例生成，再后处理到目标尺寸。"&CHAR(10)&"【输出】"&J61&"。只输出当前这一张；套组其余部分由其他任务分别完成。透明须为真实Alpha，禁止棋盘格。"&CHAR(10)&"【对齐】"&K61&CHAR(10)&"【禁止】"&E61 -> 【唯一交付文件】abn_nailong_parts_01_foot_right.png 【对象】奶龙右脚 原创二维地下工业收容设施游戏美术；怪诞手绘收容风，受手绘怪诞生存童话的表现原则启发。hand-drawn, ink-outline, slightly grotesque, whimsical horror, 2D cutout-friendly。粗细有变化的深墨轮廓，轻微不规则手绘线，大面积低饱和平涂，少量刻线阴影；剪影与动作优先于纹理。正交二维侧视角色/设施，UI为正视平面。保留对象身份，统一视觉语言，不复制其他作品具体资产。 【同组设计标准，仅作一致性约束】躯干 1、平静头颈 1、失控头颈 1、平静口鼻 1、失控裂嘴 1、常态/空眼两组眼部 2、左右短臂 2、左右脚 2、尾 1，共 12 件。头颈、眼、口分层，裂嘴不与选中圈或残影合并。 沿用两份已批准定稿的线宽与体积，关节背面补全；可复用部位只交一份，不为每个动作复制整身。完整定稿仅作组合校对，不额外计独立交付单位。 以上为整套构成；每次只生成 「逐张提示词」本张范围 指定的一个独立件，不画整套平铺图。 【本次只画】本次只画奶龙右宽扁脚，脚底水平；只交这一独立单元，不画其他零件、对照姿、sheet、文字或背景。保持主表指定造型、朝向与挂点。；本次只交付这一件/一个姿势，不把同组其他素材、姿势或裁切线画进本图，不拼成多格图集。 【状态】IDLE / WORKING / BREACHED 【参考】附图 REF_N01_CALM / REF_N01_BREACH。奶龙 已批准平静与失控定稿。如有前置定稿，必须保持同一造型、比例、线宽、服装和配色；拆件需另附已确认整身定稿图。 【画布】1024 × 1024 px，每张单独姿势/零件，共用 (512, 896) 根；尺寸不支持时保持比例生成，再后处理到目标尺寸。 【输出】本次仅一张单件 PNG，sRGB；真实 Alpha 透明背景；保持足够安全边距；尺寸修正、边缘清理、分层源文件及轴点记录由后处理制作。。只输出当前这一张；套组其余部分由其他任务分别完成。透明须为真实Alpha，禁止棋盘格。 【对齐】脚底地面中心；母版 (512, 896)，朝右；全部形态共享同一根节点。 另记录头颈、四肢、口部或钟针等实际旋转挂点。 【禁止】不做 3D、照片写实、厚涂油画、等距俯视、高饱和二次元、霓虹光污染、密集脏污；不加文字、数字、二维码、水印、游戏界面或棋盘格背景；不把动态状态、血条、范围、路径烘焙进图。 不要照片、3D 渲染、像素风、光滑矢量图标风或高饱和日漫；不要复制现成游戏的角色、脸型或官方 IP 素材；不要背景、文字、水印、UI、血条、黄色选中圈或攻击范围；不要以红色滤镜代替形变。 | E61: =生成规范!$B$9&CHAR(10)&素材需求!S18 -> 不做 3D、照片写实、厚涂油画、等距俯视、高饱和二次元、霓虹光污染、密集脏污；不加文字、数字、二维码、水印、游戏界面或棋盘格背景；不把动态状态、血条、范围、路径烘焙进图。 不要照片、3D 渲染、像素风、光滑矢量图标风或高饱和日漫；不要复制现成游戏的角色、脸型或官方 IP 素材；不要背景、文字、水印、UI、血条、黄色选中圈或攻击范围；不要以红色滤镜代替形变。 | F61: REF_N01_CALM / REF_N01_BREACH | G61: =素材需求!B18 -> P0 | H61: 1024 × 1024 px，每张单独姿势/零件，共用 (512, 896) 根 | I61: 本次只画奶龙右宽扁脚，脚底水平；只交这一独立单元，不画其他零件、对照姿、sheet、文字或背景。保持主表指定造型、朝向与挂点。 | J61: 本次仅一张单件 PNG，sRGB；真实 Alpha 透明背景；保持足够安全边距；尺寸修正、边缘清理、分层源文件及轴点记录由后处理制作。 | K61: 脚底地面中心；母版 (512, 896)，朝右；全部形态共享同一根节点。 另记录头颈、四肢、口部或钟针等实际旋转挂点。 | L61: art_delivery/v1/abnormalities/ | M61: 待生成 | N61: ABN_N01_01 / ABN_N01_03
A62: ABN_N01_04 | B62: abn_nailong_parts_01_tail.png | C62: 奶龙短尾 | D62: ="【唯一交付文件】"&B62&CHAR(10)&"【对象】"&C62&CHAR(10)&生成规范!$B$8&CHAR(10)&"【同组设计标准，仅作一致性约束】"&素材需求!G18&CHAR(10)&"【本次只画】"&I62&"；本次只交付这一件/一个姿势，不把同组其他素材、姿势或裁切线画进本图，不拼成多格图集。"&CHAR(10)&"【状态】"&素材需求!F18&CHAR(10)&"【参考】附图 "&F62&"。"&素材需求!H18&"。如有前置定稿，必须保持同一造型、比例、线宽、服装和配色；拆件需另附已确认整身定稿图。"&CHAR(10)&"【画布】"&H62&"；尺寸不支持时保持比例生成，再后处理到目标尺寸。"&CHAR(10)&"【输出】"&J62&"。只输出当前这一张；套组其余部分由其他任务分别完成。透明须为真实Alpha，禁止棋盘格。"&CHAR(10)&"【对齐】"&K62&CHAR(10)&"【禁止】"&E62 -> 【唯一交付文件】abn_nailong_parts_01_tail.png 【对象】奶龙短尾 原创二维地下工业收容设施游戏美术；怪诞手绘收容风，受手绘怪诞生存童话的表现原则启发。hand-drawn, ink-outline, slightly grotesque, whimsical horror, 2D cutout-friendly。粗细有变化的深墨轮廓，轻微不规则手绘线，大面积低饱和平涂，少量刻线阴影；剪影与动作优先于纹理。正交二维侧视角色/设施，UI为正视平面。保留对象身份，统一视觉语言，不复制其他作品具体资产。 【同组设计标准，仅作一致性约束】躯干 1、平静头颈 1、失控头颈 1、平静口鼻 1、失控裂嘴 1、常态/空眼两组眼部 2、左右短臂 2、左右脚 2、尾 1，共 12 件。头颈、眼、口分层，裂嘴不与选中圈或残影合并。 沿用两份已批准定稿的线宽与体积，关节背面补全；可复用部位只交一份，不为每个动作复制整身。完整定稿仅作组合校对，不额外计独立交付单位。 以上为整套构成；每次只生成 「逐张提示词」本张范围 指定的一个独立件，不画整套平铺图。 【本次只画】本次只画奶龙不对称短尾，带土黄阴影，补全尾根；只交这一独立单元，不画其他零件、对照姿、sheet、文字或背景。保持主表指定造型、朝向与挂点。；本次只交付这一件/一个姿势，不把同组其他素材、姿势或裁切线画进本图，不拼成多格图集。 【状态】IDLE / WORKING / BREACHED 【参考】附图 REF_N01_CALM / REF_N01_BREACH。奶龙 已批准平静与失控定稿。如有前置定稿，必须保持同一造型、比例、线宽、服装和配色；拆件需另附已确认整身定稿图。 【画布】1024 × 1024 px，每张单独姿势/零件，共用 (512, 896) 根；尺寸不支持时保持比例生成，再后处理到目标尺寸。 【输出】本次仅一张单件 PNG，sRGB；真实 Alpha 透明背景；保持足够安全边距；尺寸修正、边缘清理、分层源文件及轴点记录由后处理制作。。只输出当前这一张；套组其余部分由其他任务分别完成。透明须为真实Alpha，禁止棋盘格。 【对齐】脚底地面中心；母版 (512, 896)，朝右；全部形态共享同一根节点。 另记录头颈、四肢、口部或钟针等实际旋转挂点。 【禁止】不做 3D、照片写实、厚涂油画、等距俯视、高饱和二次元、霓虹光污染、密集脏污；不加文字、数字、二维码、水印、游戏界面或棋盘格背景；不把动态状态、血条、范围、路径烘焙进图。 不要照片、3D 渲染、像素风、光滑矢量图标风或高饱和日漫；不要复制现成游戏的角色、脸型或官方 IP 素材；不要背景、文字、水印、UI、血条、黄色选中圈或攻击范围；不要以红色滤镜代替形变。 | E62: =生成规范!$B$9&CHAR(10)&素材需求!S18 -> 不做 3D、照片写实、厚涂油画、等距俯视、高饱和二次元、霓虹光污染、密集脏污；不加文字、数字、二维码、水印、游戏界面或棋盘格背景；不把动态状态、血条、范围、路径烘焙进图。 不要照片、3D 渲染、像素风、光滑矢量图标风或高饱和日漫；不要复制现成游戏的角色、脸型或官方 IP 素材；不要背景、文字、水印、UI、血条、黄色选中圈或攻击范围；不要以红色滤镜代替形变。 | F62: REF_N01_CALM / REF_N01_BREACH | G62: =素材需求!B18 -> P0 | H62: 1024 × 1024 px，每张单独姿势/零件，共用 (512, 896) 根 | I62: 本次只画奶龙不对称短尾，带土黄阴影，补全尾根；只交这一独立单元，不画其他零件、对照姿、sheet、文字或背景。保持主表指定造型、朝向与挂点。 | J62: 本次仅一张单件 PNG，sRGB；真实 Alpha 透明背景；保持足够安全边距；尺寸修正、边缘清理、分层源文件及轴点记录由后处理制作。 | K62: 脚底地面中心；母版 (512, 896)，朝右；全部形态共享同一根节点。 另记录头颈、四肢、口部或钟针等实际旋转挂点。 | L62: art_delivery/v1/abnormalities/ | M62: 待生成 | N62: ABN_N01_01 / ABN_N01_03
A63: ABN_N01_05 | B63: abn_nailong_combat_reference_01_walk_left.png | C63: 奶龙 左足支撑 | D63: ="【唯一交付文件】"&B63&CHAR(10)&"【对象】"&C63&CHAR(10)&生成规范!$B$8&CHAR(10)&"【同组设计标准，仅作一致性约束】"&素材需求!G19&CHAR(10)&"【本次只画】"&I63&"；本次只交付这一件/一个姿势，不把同组其他素材、姿势或裁切线画进本图，不拼成多格图集。"&CHAR(10)&"【状态】"&素材需求!F19&CHAR(10)&"【参考】附图 "&F63&"。"&素材需求!H19&"。如有前置定稿，必须保持同一造型、比例、线宽、服装和配色；拆件需另附已确认整身定稿图。"&CHAR(10)&"【画布】"&H63&"；尺寸不支持时保持比例生成，再后处理到目标尺寸。"&CHAR(10)&"【输出】"&J63&"。只输出当前这一张；套组其余部分由其他任务分别完成。透明须为真实Alpha，禁止棋盘格。"&CHAR(10)&"【对齐】"&K63&CHAR(10)&"【禁止】"&E63 -> 【唯一交付文件】abn_nailong_combat_reference_01_walk_left.png 【对象】奶龙 左足支撑 原创二维地下工业收容设施游戏美术；怪诞手绘收容风，受手绘怪诞生存童话的表现原则启发。hand-drawn, ink-outline, slightly grotesque, whimsical horror, 2D cutout-friendly。粗细有变化的深墨轮廓，轻微不规则手绘线，大面积低饱和平涂，少量刻线阴影；剪影与动作优先于纹理。正交二维侧视角色/设施，UI为正视平面。保留对象身份，统一视觉语言，不复制其他作品具体资产。 【同组设计标准，仅作一致性约束】分别生成六个独立单姿：失控行走左右支撑 2 姿、前摇抬臂/后仰 1 姿、裂嘴前送命中 1 姿、收势 1 姿、短促受击回缩 1 姿。拉长颈部但脚底不瞬移；所有姿态使用同一裂嘴造型。 每个独立交付文件只能含一个姿势；按 「逐张提示词」本张范围 逐张生成。 【本次只画】本次只画完整失控 奶龙 行走的左侧足支撑姿，另一足准备前摆；只交这一独立单元，不画其他零件、对照姿、sheet、文字或背景。保持主表指定造型、朝向与挂点。；本次只交付这一件/一个姿势，不把同组其他素材、姿势或裁切线画进本图，不拼成多格图集。 【状态】MOVING / WINDUP / IMPACT / HURT 【参考】附图 REF_N01_CALM / REF_N01_BREACH。奶龙 已批准失控定稿与实际 attackPhase/impactRemaining/hurt。如有前置定稿，必须保持同一造型、比例、线宽、服装和配色；拆件需另附已确认整身定稿图。 【画布】1024 × 1024 px，每张单独姿势/零件，共用 (512, 896) 根；尺寸不支持时保持比例生成，再后处理到目标尺寸。 【输出】本次仅一张单件 PNG，sRGB；真实 Alpha 透明背景；保持足够安全边距；尺寸修正、边缘清理、分层源文件及轴点记录由后处理制作。。只输出当前这一张；套组其余部分由其他任务分别完成。透明须为真实Alpha，禁止棋盘格。 【对齐】每个主要姿势保持同一脚底注册点；行走仅示足部接触关系，不烘焙移动距离。 【禁止】不做 3D、照片写实、厚涂油画、等距俯视、高饱和二次元、霓虹光污染、密集脏污；不加文字、数字、二维码、水印、游戏界面或棋盘格背景；不把动态状态、血条、范围、路径烘焙进图。 不要照片、3D 渲染、像素风、光滑矢量图标风或高饱和日漫；不要复制现成游戏的角色、脸型或官方 IP 素材；不要背景、文字、水印、UI、血条、黄色选中圈或攻击范围；不要以红色滤镜代替形变。 | E63: =生成规范!$B$9&CHAR(10)&素材需求!S19 -> 不做 3D、照片写实、厚涂油画、等距俯视、高饱和二次元、霓虹光污染、密集脏污；不加文字、数字、二维码、水印、游戏界面或棋盘格背景；不把动态状态、血条、范围、路径烘焙进图。 不要照片、3D 渲染、像素风、光滑矢量图标风或高饱和日漫；不要复制现成游戏的角色、脸型或官方 IP 素材；不要背景、文字、水印、UI、血条、黄色选中圈或攻击范围；不要以红色滤镜代替形变。 | F63: REF_N01_CALM / REF_N01_BREACH | G63: =素材需求!B19 -> P0 | H63: 1024 × 1024 px，每张单独姿势/零件，共用 (512, 896) 根 | I63: 本次只画完整失控 奶龙 行走的左侧足支撑姿，另一足准备前摆；只交这一独立单元，不画其他零件、对照姿、sheet、文字或背景。保持主表指定造型、朝向与挂点。 | J63: 本次仅一张单件 PNG，sRGB；真实 Alpha 透明背景；保持足够安全边距；尺寸修正、边缘清理、分层源文件及轴点记录由后处理制作。 | K63: 每个主要姿势保持同一脚底注册点；行走仅示足部接触关系，不烘焙移动距离。 | L63: art_delivery/v1/abnormalities/ | M63: 待生成 | N63: ABN_N01_03 / ABN_N01_04
A64: ABN_N01_05 | B64: abn_nailong_combat_reference_01_walk_right.png | C64: 奶龙 右足支撑 | D64: ="【唯一交付文件】"&B64&CHAR(10)&"【对象】"&C64&CHAR(10)&生成规范!$B$8&CHAR(10)&"【同组设计标准，仅作一致性约束】"&素材需求!G19&CHAR(10)&"【本次只画】"&I64&"；本次只交付这一件/一个姿势，不把同组其他素材、姿势或裁切线画进本图，不拼成多格图集。"&CHAR(10)&"【状态】"&素材需求!F19&CHAR(10)&"【参考】附图 "&F64&"。"&素材需求!H19&"。如有前置定稿，必须保持同一造型、比例、线宽、服装和配色；拆件需另附已确认整身定稿图。"&CHAR(10)&"【画布】"&H64&"；尺寸不支持时保持比例生成，再后处理到目标尺寸。"&CHAR(10)&"【输出】"&J64&"。只输出当前这一张；套组其余部分由其他任务分别完成。透明须为真实Alpha，禁止棋盘格。"&CHAR(10)&"【对齐】"&K64&CHAR(10)&"【禁止】"&E64 -> 【唯一交付文件】abn_nailong_combat_reference_01_walk_right.png 【对象】奶龙 右足支撑 原创二维地下工业收容设施游戏美术；怪诞手绘收容风，受手绘怪诞生存童话的表现原则启发。hand-drawn, ink-outline, slightly grotesque, whimsical horror, 2D cutout-friendly。粗细有变化的深墨轮廓，轻微不规则手绘线，大面积低饱和平涂，少量刻线阴影；剪影与动作优先于纹理。正交二维侧视角色/设施，UI为正视平面。保留对象身份，统一视觉语言，不复制其他作品具体资产。 【同组设计标准，仅作一致性约束】分别生成六个独立单姿：失控行走左右支撑 2 姿、前摇抬臂/后仰 1 姿、裂嘴前送命中 1 姿、收势 1 姿、短促受击回缩 1 姿。拉长颈部但脚底不瞬移；所有姿态使用同一裂嘴造型。 每个独立交付文件只能含一个姿势；按 「逐张提示词」本张范围 逐张生成。 【本次只画】本次只画完整失控 奶龙 对应的右侧足支撑姿，与左支撑姿保持体积相同；只交这一独立单元，不画其他零件、对照姿、sheet、文字或背景。保持主表指定造型、朝向与挂点。；本次只交付这一件/一个姿势，不把同组其他素材、姿势或裁切线画进本图，不拼成多格图集。 【状态】MOVING / WINDUP / IMPACT / HURT 【参考】附图 REF_N01_CALM / REF_N01_BREACH。奶龙 已批准失控定稿与实际 attackPhase/impactRemaining/hurt。如有前置定稿，必须保持同一造型、比例、线宽、服装和配色；拆件需另附已确认整身定稿图。 【画布】1024 × 1024 px，每张单独姿势/零件，共用 (512, 896) 根；尺寸不支持时保持比例生成，再后处理到目标尺寸。 【输出】本次仅一张单件 PNG，sRGB；真实 Alpha 透明背景；保持足够安全边距；尺寸修正、边缘清理、分层源文件及轴点记录由后处理制作。。只输出当前这一张；套组其余部分由其他任务分别完成。透明须为真实Alpha，禁止棋盘格。 【对齐】每个主要姿势保持同一脚底注册点；行走仅示足部接触关系，不烘焙移动距离。 【禁止】不做 3D、照片写实、厚涂油画、等距俯视、高饱和二次元、霓虹光污染、密集脏污；不加文字、数字、二维码、水印、游戏界面或棋盘格背景；不把动态状态、血条、范围、路径烘焙进图。 不要照片、3D 渲染、像素风、光滑矢量图标风或高饱和日漫；不要复制现成游戏的角色、脸型或官方 IP 素材；不要背景、文字、水印、UI、血条、黄色选中圈或攻击范围；不要以红色滤镜代替形变。 | E64: =生成规范!$B$9&CHAR(10)&素材需求!S19 -> 不做 3D、照片写实、厚涂油画、等距俯视、高饱和二次元、霓虹光污染、密集脏污；不加文字、数字、二维码、水印、游戏界面或棋盘格背景；不把动态状态、血条、范围、路径烘焙进图。 不要照片、3D 渲染、像素风、光滑矢量图标风或高饱和日漫；不要复制现成游戏的角色、脸型或官方 IP 素材；不要背景、文字、水印、UI、血条、黄色选中圈或攻击范围；不要以红色滤镜代替形变。 | F64: REF_N01_CALM / REF_N01_BREACH | G64: =素材需求!B19 -> P0 | H64: 1024 × 1024 px，每张单独姿势/零件，共用 (512, 896) 根 | I64: 本次只画完整失控 奶龙 对应的右侧足支撑姿，与左支撑姿保持体积相同；只交这一独立单元，不画其他零件、对照姿、sheet、文字或背景。保持主表指定造型、朝向与挂点。 | J64: 本次仅一张单件 PNG，sRGB；真实 Alpha 透明背景；保持足够安全边距；尺寸修正、边缘清理、分层源文件及轴点记录由后处理制作。 | K64: 每个主要姿势保持同一脚底注册点；行走仅示足部接触关系，不烘焙移动距离。 | L64: art_delivery/v1/abnormalities/ | M64: 待生成 | N64: ABN_N01_03 / ABN_N01_04
A65: ABN_N01_05 | B65: abn_nailong_combat_reference_01_windup.png | C65: 奶龙 攻击前摇 | D65: ="【唯一交付文件】"&B65&CHAR(10)&"【对象】"&C65&CHAR(10)&生成规范!$B$8&CHAR(10)&"【同组设计标准，仅作一致性约束】"&素材需求!G19&CHAR(10)&"【本次只画】"&I65&"；本次只交付这一件/一个姿势，不把同组其他素材、姿势或裁切线画进本图，不拼成多格图集。"&CHAR(10)&"【状态】"&素材需求!F19&CHAR(10)&"【参考】附图 "&F65&"。"&素材需求!H19&"。如有前置定稿，必须保持同一造型、比例、线宽、服装和配色；拆件需另附已确认整身定稿图。"&CHAR(10)&"【画布】"&H65&"；尺寸不支持时保持比例生成，再后处理到目标尺寸。"&CHAR(10)&"【输出】"&J65&"。只输出当前这一张；套组其余部分由其他任务分别完成。透明须为真实Alpha，禁止棋盘格。"&CHAR(10)&"【对齐】"&K65&CHAR(10)&"【禁止】"&E65 -> 【唯一交付文件】abn_nailong_combat_reference_01_windup.png 【对象】奶龙 攻击前摇 原创二维地下工业收容设施游戏美术；怪诞手绘收容风，受手绘怪诞生存童话的表现原则启发。hand-drawn, ink-outline, slightly grotesque, whimsical horror, 2D cutout-friendly。粗细有变化的深墨轮廓，轻微不规则手绘线，大面积低饱和平涂，少量刻线阴影；剪影与动作优先于纹理。正交二维侧视角色/设施，UI为正视平面。保留对象身份，统一视觉语言，不复制其他作品具体资产。 【同组设计标准，仅作一致性约束】分别生成六个独立单姿：失控行走左右支撑 2 姿、前摇抬臂/后仰 1 姿、裂嘴前送命中 1 姿、收势 1 姿、短促受击回缩 1 姿。拉长颈部但脚底不瞬移；所有姿态使用同一裂嘴造型。 每个独立交付文件只能含一个姿势；按 「逐张提示词」本张范围 逐张生成。 【本次只画】本次只画完整失控 奶龙 的攻击前摇姿：短臂抬起、头颈稍后收；脚底固定；只交这一独立单元，不画其他零件、对照姿、sheet、文字或背景。保持主表指定造型、朝向与挂点。；本次只交付这一件/一个姿势，不把同组其他素材、姿势或裁切线画进本图，不拼成多格图集。 【状态】MOVING / WINDUP / IMPACT / HURT 【参考】附图 REF_N01_CALM / REF_N01_BREACH。奶龙 已批准失控定稿与实际 attackPhase/impactRemaining/hurt。如有前置定稿，必须保持同一造型、比例、线宽、服装和配色；拆件需另附已确认整身定稿图。 【画布】1024 × 1024 px，每张单独姿势/零件，共用 (512, 896) 根；尺寸不支持时保持比例生成，再后处理到目标尺寸。 【输出】本次仅一张单件 PNG，sRGB；真实 Alpha 透明背景；保持足够安全边距；尺寸修正、边缘清理、分层源文件及轴点记录由后处理制作。。只输出当前这一张；套组其余部分由其他任务分别完成。透明须为真实Alpha，禁止棋盘格。 【对齐】每个主要姿势保持同一脚底注册点；行走仅示足部接触关系，不烘焙移动距离。 【禁止】不做 3D、照片写实、厚涂油画、等距俯视、高饱和二次元、霓虹光污染、密集脏污；不加文字、数字、二维码、水印、游戏界面或棋盘格背景；不把动态状态、血条、范围、路径烘焙进图。 不要照片、3D 渲染、像素风、光滑矢量图标风或高饱和日漫；不要复制现成游戏的角色、脸型或官方 IP 素材；不要背景、文字、水印、UI、血条、黄色选中圈或攻击范围；不要以红色滤镜代替形变。 | E65: =生成规范!$B$9&CHAR(10)&素材需求!S19 -> 不做 3D、照片写实、厚涂油画、等距俯视、高饱和二次元、霓虹光污染、密集脏污；不加文字、数字、二维码、水印、游戏界面或棋盘格背景；不把动态状态、血条、范围、路径烘焙进图。 不要照片、3D 渲染、像素风、光滑矢量图标风或高饱和日漫；不要复制现成游戏的角色、脸型或官方 IP 素材；不要背景、文字、水印、UI、血条、黄色选中圈或攻击范围；不要以红色滤镜代替形变。 | F65: REF_N01_CALM / REF_N01_BREACH | G65: =素材需求!B19 -> P0 | H65: 1024 × 1024 px，每张单独姿势/零件，共用 (512, 896) 根 | I65: 本次只画完整失控 奶龙 的攻击前摇姿：短臂抬起、头颈稍后收；脚底固定；只交这一独立单元，不画其他零件、对照姿、sheet、文字或背景。保持主表指定造型、朝向与挂点。 | J65: 本次仅一张单件 PNG，sRGB；真实 Alpha 透明背景；保持足够安全边距；尺寸修正、边缘清理、分层源文件及轴点记录由后处理制作。 | K65: 每个主要姿势保持同一脚底注册点；行走仅示足部接触关系，不烘焙移动距离。 | L65: art_delivery/v1/abnormalities/ | M65: 待生成 | N65: ABN_N01_03 / ABN_N01_04
A66: ABN_N01_05 | B66: abn_nailong_combat_reference_01_impact.png | C66: 奶龙 攻击释放 | D66: ="【唯一交付文件】"&B66&CHAR(10)&"【对象】"&C66&CHAR(10)&生成规范!$B$8&CHAR(10)&"【同组设计标准，仅作一致性约束】"&素材需求!G19&CHAR(10)&"【本次只画】"&I66&"；本次只交付这一件/一个姿势，不把同组其他素材、姿势或裁切线画进本图，不拼成多格图集。"&CHAR(10)&"【状态】"&素材需求!F19&CHAR(10)&"【参考】附图 "&F66&"。"&素材需求!H19&"。如有前置定稿，必须保持同一造型、比例、线宽、服装和配色；拆件需另附已确认整身定稿图。"&CHAR(10)&"【画布】"&H66&"；尺寸不支持时保持比例生成，再后处理到目标尺寸。"&CHAR(10)&"【输出】"&J66&"。只输出当前这一张；套组其余部分由其他任务分别完成。透明须为真实Alpha，禁止棋盘格。"&CHAR(10)&"【对齐】"&K66&CHAR(10)&"【禁止】"&E66 -> 【唯一交付文件】abn_nailong_combat_reference_01_impact.png 【对象】奶龙 攻击释放 原创二维地下工业收容设施游戏美术；怪诞手绘收容风，受手绘怪诞生存童话的表现原则启发。hand-drawn, ink-outline, slightly grotesque, whimsical horror, 2D cutout-friendly。粗细有变化的深墨轮廓，轻微不规则手绘线，大面积低饱和平涂，少量刻线阴影；剪影与动作优先于纹理。正交二维侧视角色/设施，UI为正视平面。保留对象身份，统一视觉语言，不复制其他作品具体资产。 【同组设计标准，仅作一致性约束】分别生成六个独立单姿：失控行走左右支撑 2 姿、前摇抬臂/后仰 1 姿、裂嘴前送命中 1 姿、收势 1 姿、短促受击回缩 1 姿。拉长颈部但脚底不瞬移；所有姿态使用同一裂嘴造型。 每个独立交付文件只能含一个姿势；按 「逐张提示词」本张范围 逐张生成。 【本次只画】本次只画完整失控 奶龙 的攻击释放姿：裂嘴与头颈前送；不含范围特效或额外位移；只交这一独立单元，不画其他零件、对照姿、sheet、文字或背景。保持主表指定造型、朝向与挂点。；本次只交付这一件/一个姿势，不把同组其他素材、姿势或裁切线画进本图，不拼成多格图集。 【状态】MOVING / WINDUP / IMPACT / HURT 【参考】附图 REF_N01_CALM / REF_N01_BREACH。奶龙 已批准失控定稿与实际 attackPhase/impactRemaining/hurt。如有前置定稿，必须保持同一造型、比例、线宽、服装和配色；拆件需另附已确认整身定稿图。 【画布】1024 × 1024 px，每张单独姿势/零件，共用 (512, 896) 根；尺寸不支持时保持比例生成，再后处理到目标尺寸。 【输出】本次仅一张单件 PNG，sRGB；真实 Alpha 透明背景；保持足够安全边距；尺寸修正、边缘清理、分层源文件及轴点记录由后处理制作。。只输出当前这一张；套组其余部分由其他任务分别完成。透明须为真实Alpha，禁止棋盘格。 【对齐】每个主要姿势保持同一脚底注册点；行走仅示足部接触关系，不烘焙移动距离。 【禁止】不做 3D、照片写实、厚涂油画、等距俯视、高饱和二次元、霓虹光污染、密集脏污；不加文字、数字、二维码、水印、游戏界面或棋盘格背景；不把动态状态、血条、范围、路径烘焙进图。 不要照片、3D 渲染、像素风、光滑矢量图标风或高饱和日漫；不要复制现成游戏的角色、脸型或官方 IP 素材；不要背景、文字、水印、UI、血条、黄色选中圈或攻击范围；不要以红色滤镜代替形变。 | E66: =生成规范!$B$9&CHAR(10)&素材需求!S19 -> 不做 3D、照片写实、厚涂油画、等距俯视、高饱和二次元、霓虹光污染、密集脏污；不加文字、数字、二维码、水印、游戏界面或棋盘格背景；不把动态状态、血条、范围、路径烘焙进图。 不要照片、3D 渲染、像素风、光滑矢量图标风或高饱和日漫；不要复制现成游戏的角色、脸型或官方 IP 素材；不要背景、文字、水印、UI、血条、黄色选中圈或攻击范围；不要以红色滤镜代替形变。 | F66: REF_N01_CALM / REF_N01_BREACH | G66: =素材需求!B19 -> P0 | H66: 1024 × 1024 px，每张单独姿势/零件，共用 (512, 896) 根 | I66: 本次只画完整失控 奶龙 的攻击释放姿：裂嘴与头颈前送；不含范围特效或额外位移；只交这一独立单元，不画其他零件、对照姿、sheet、文字或背景。保持主表指定造型、朝向与挂点。 | J66: 本次仅一张单件 PNG，sRGB；真实 Alpha 透明背景；保持足够安全边距；尺寸修正、边缘清理、分层源文件及轴点记录由后处理制作。 | K66: 每个主要姿势保持同一脚底注册点；行走仅示足部接触关系，不烘焙移动距离。 | L66: art_delivery/v1/abnormalities/ | M66: 待生成 | N66: ABN_N01_03 / ABN_N01_04
A67: ABN_N01_05 | B67: abn_nailong_combat_reference_01_recover.png | C67: 奶龙 攻击收势 | D67: ="【唯一交付文件】"&B67&CHAR(10)&"【对象】"&C67&CHAR(10)&生成规范!$B$8&CHAR(10)&"【同组设计标准，仅作一致性约束】"&素材需求!G19&CHAR(10)&"【本次只画】"&I67&"；本次只交付这一件/一个姿势，不把同组其他素材、姿势或裁切线画进本图，不拼成多格图集。"&CHAR(10)&"【状态】"&素材需求!F19&CHAR(10)&"【参考】附图 "&F67&"。"&素材需求!H19&"。如有前置定稿，必须保持同一造型、比例、线宽、服装和配色；拆件需另附已确认整身定稿图。"&CHAR(10)&"【画布】"&H67&"；尺寸不支持时保持比例生成，再后处理到目标尺寸。"&CHAR(10)&"【输出】"&J67&"。只输出当前这一张；套组其余部分由其他任务分别完成。透明须为真实Alpha，禁止棋盘格。"&CHAR(10)&"【对齐】"&K67&CHAR(10)&"【禁止】"&E67 -> 【唯一交付文件】abn_nailong_combat_reference_01_recover.png 【对象】奶龙 攻击收势 原创二维地下工业收容设施游戏美术；怪诞手绘收容风，受手绘怪诞生存童话的表现原则启发。hand-drawn, ink-outline, slightly grotesque, whimsical horror, 2D cutout-friendly。粗细有变化的深墨轮廓，轻微不规则手绘线，大面积低饱和平涂，少量刻线阴影；剪影与动作优先于纹理。正交二维侧视角色/设施，UI为正视平面。保留对象身份，统一视觉语言，不复制其他作品具体资产。 【同组设计标准，仅作一致性约束】分别生成六个独立单姿：失控行走左右支撑 2 姿、前摇抬臂/后仰 1 姿、裂嘴前送命中 1 姿、收势 1 姿、短促受击回缩 1 姿。拉长颈部但脚底不瞬移；所有姿态使用同一裂嘴造型。 每个独立交付文件只能含一个姿势；按 「逐张提示词」本张范围 逐张生成。 【本次只画】本次只画完整失控 奶龙 攻击后的身体收势，仍保持失控造型；只交这一独立单元，不画其他零件、对照姿、sheet、文字或背景。保持主表指定造型、朝向与挂点。；本次只交付这一件/一个姿势，不把同组其他素材、姿势或裁切线画进本图，不拼成多格图集。 【状态】MOVING / WINDUP / IMPACT / HURT 【参考】附图 REF_N01_CALM / REF_N01_BREACH。奶龙 已批准失控定稿与实际 attackPhase/impactRemaining/hurt。如有前置定稿，必须保持同一造型、比例、线宽、服装和配色；拆件需另附已确认整身定稿图。 【画布】1024 × 1024 px，每张单独姿势/零件，共用 (512, 896) 根；尺寸不支持时保持比例生成，再后处理到目标尺寸。 【输出】本次仅一张单件 PNG，sRGB；真实 Alpha 透明背景；保持足够安全边距；尺寸修正、边缘清理、分层源文件及轴点记录由后处理制作。。只输出当前这一张；套组其余部分由其他任务分别完成。透明须为真实Alpha，禁止棋盘格。 【对齐】每个主要姿势保持同一脚底注册点；行走仅示足部接触关系，不烘焙移动距离。 【禁止】不做 3D、照片写实、厚涂油画、等距俯视、高饱和二次元、霓虹光污染、密集脏污；不加文字、数字、二维码、水印、游戏界面或棋盘格背景；不把动态状态、血条、范围、路径烘焙进图。 不要照片、3D 渲染、像素风、光滑矢量图标风或高饱和日漫；不要复制现成游戏的角色、脸型或官方 IP 素材；不要背景、文字、水印、UI、血条、黄色选中圈或攻击范围；不要以红色滤镜代替形变。 | E67: =生成规范!$B$9&CHAR(10)&素材需求!S19 -> 不做 3D、照片写实、厚涂油画、等距俯视、高饱和二次元、霓虹光污染、密集脏污；不加文字、数字、二维码、水印、游戏界面或棋盘格背景；不把动态状态、血条、范围、路径烘焙进图。 不要照片、3D 渲染、像素风、光滑矢量图标风或高饱和日漫；不要复制现成游戏的角色、脸型或官方 IP 素材；不要背景、文字、水印、UI、血条、黄色选中圈或攻击范围；不要以红色滤镜代替形变。 | F67: REF_N01_CALM / REF_N01_BREACH | G67: =素材需求!B19 -> P0 | H67: 1024 × 1024 px，每张单独姿势/零件，共用 (512, 896) 根 | I67: 本次只画完整失控 奶龙 攻击后的身体收势，仍保持失控造型；只交这一独立单元，不画其他零件、对照姿、sheet、文字或背景。保持主表指定造型、朝向与挂点。 | J67: 本次仅一张单件 PNG，sRGB；真实 Alpha 透明背景；保持足够安全边距；尺寸修正、边缘清理、分层源文件及轴点记录由后处理制作。 | K67: 每个主要姿势保持同一脚底注册点；行走仅示足部接触关系，不烘焙移动距离。 | L67: art_delivery/v1/abnormalities/ | M67: 待生成 | N67: ABN_N01_03 / ABN_N01_04
A68: ABN_N01_05 | B68: abn_nailong_combat_reference_01_hit.png | C68: 奶龙 受击回缩 | D68: ="【唯一交付文件】"&B68&CHAR(10)&"【对象】"&C68&CHAR(10)&生成规范!$B$8&CHAR(10)&"【同组设计标准，仅作一致性约束】"&素材需求!G19&CHAR(10)&"【本次只画】"&I68&"；本次只交付这一件/一个姿势，不把同组其他素材、姿势或裁切线画进本图，不拼成多格图集。"&CHAR(10)&"【状态】"&素材需求!F19&CHAR(10)&"【参考】附图 "&F68&"。"&素材需求!H19&"。如有前置定稿，必须保持同一造型、比例、线宽、服装和配色；拆件需另附已确认整身定稿图。"&CHAR(10)&"【画布】"&H68&"；尺寸不支持时保持比例生成，再后处理到目标尺寸。"&CHAR(10)&"【输出】"&J68&"。只输出当前这一张；套组其余部分由其他任务分别完成。透明须为真实Alpha，禁止棋盘格。"&CHAR(10)&"【对齐】"&K68&CHAR(10)&"【禁止】"&E68 -> 【唯一交付文件】abn_nailong_combat_reference_01_hit.png 【对象】奶龙 受击回缩 原创二维地下工业收容设施游戏美术；怪诞手绘收容风，受手绘怪诞生存童话的表现原则启发。hand-drawn, ink-outline, slightly grotesque, whimsical horror, 2D cutout-friendly。粗细有变化的深墨轮廓，轻微不规则手绘线，大面积低饱和平涂，少量刻线阴影；剪影与动作优先于纹理。正交二维侧视角色/设施，UI为正视平面。保留对象身份，统一视觉语言，不复制其他作品具体资产。 【同组设计标准，仅作一致性约束】分别生成六个独立单姿：失控行走左右支撑 2 姿、前摇抬臂/后仰 1 姿、裂嘴前送命中 1 姿、收势 1 姿、短促受击回缩 1 姿。拉长颈部但脚底不瞬移；所有姿态使用同一裂嘴造型。 每个独立交付文件只能含一个姿势；按 「逐张提示词」本张范围 逐张生成。 【本次只画】本次只画完整失控 奶龙 短促受击回缩姿，局部缩肩/扭身，不含新增伤口和死亡；只交这一独立单元，不画其他零件、对照姿、sheet、文字或背景。保持主表指定造型、朝向与挂点。；本次只交付这一件/一个姿势，不把同组其他素材、姿势或裁切线画进本图，不拼成多格图集。 【状态】MOVING / WINDUP / IMPACT / HURT 【参考】附图 REF_N01_CALM / REF_N01_BREACH。奶龙 已批准失控定稿与实际 attackPhase/impactRemaining/hurt。如有前置定稿，必须保持同一造型、比例、线宽、服装和配色；拆件需另附已确认整身定稿图。 【画布】1024 × 1024 px，每张单独姿势/零件，共用 (512, 896) 根；尺寸不支持时保持比例生成，再后处理到目标尺寸。 【输出】本次仅一张单件 PNG，sRGB；真实 Alpha 透明背景；保持足够安全边距；尺寸修正、边缘清理、分层源文件及轴点记录由后处理制作。。只输出当前这一张；套组其余部分由其他任务分别完成。透明须为真实Alpha，禁止棋盘格。 【对齐】每个主要姿势保持同一脚底注册点；行走仅示足部接触关系，不烘焙移动距离。 【禁止】不做 3D、照片写实、厚涂油画、等距俯视、高饱和二次元、霓虹光污染、密集脏污；不加文字、数字、二维码、水印、游戏界面或棋盘格背景；不把动态状态、血条、范围、路径烘焙进图。 不要照片、3D 渲染、像素风、光滑矢量图标风或高饱和日漫；不要复制现成游戏的角色、脸型或官方 IP 素材；不要背景、文字、水印、UI、血条、黄色选中圈或攻击范围；不要以红色滤镜代替形变。 | E68: =生成规范!$B$9&CHAR(10)&素材需求!S19 -> 不做 3D、照片写实、厚涂油画、等距俯视、高饱和二次元、霓虹光污染、密集脏污；不加文字、数字、二维码、水印、游戏界面或棋盘格背景；不把动态状态、血条、范围、路径烘焙进图。 不要照片、3D 渲染、像素风、光滑矢量图标风或高饱和日漫；不要复制现成游戏的角色、脸型或官方 IP 素材；不要背景、文字、水印、UI、血条、黄色选中圈或攻击范围；不要以红色滤镜代替形变。 | F68: REF_N01_CALM / REF_N01_BREACH | G68: =素材需求!B19 -> P0 | H68: 1024 × 1024 px，每张单独姿势/零件，共用 (512, 896) 根 | I68: 本次只画完整失控 奶龙 短促受击回缩姿，局部缩肩/扭身，不含新增伤口和死亡；只交这一独立单元，不画其他零件、对照姿、sheet、文字或背景。保持主表指定造型、朝向与挂点。 | J68: 本次仅一张单件 PNG，sRGB；真实 Alpha 透明背景；保持足够安全边距；尺寸修正、边缘清理、分层源文件及轴点记录由后处理制作。 | K68: 每个主要姿势保持同一脚底注册点；行走仅示足部接触关系，不烘焙移动距离。 | L68: art_delivery/v1/abnormalities/ | M68: 待生成 | N68: ABN_N01_03 / ABN_N01_04
A69: ABN_N02_01 | B69: abn_maodie_idle_01_approved.png | C69: 耄耋 平静定稿 | D69: ="【唯一交付文件】"&B69&CHAR(10)&"【对象】"&C69&CHAR(10)&生成规范!$B$8&CHAR(10)&"【同组设计标准，仅作一致性约束】"&素材需求!G20&CHAR(10)&"【本次只画】"&I69&"；本次只交付这一件/一个姿势，不把同组其他素材、姿势或裁切线画进本图，不拼成多格图集。"&CHAR(10)&"【状态】"&素材需求!F20&CHAR(10)&"【参考】附图 "&F69&"。"&素材需求!H20&"。如有前置定稿，必须保持同一造型、比例、线宽、服装和配色；拆件需另附已确认整身定稿图。"&CHAR(10)&"【画布】"&H69&"；尺寸不支持时保持比例生成，再后处理到目标尺寸。"&CHAR(10)&"【输出】"&J69&"。只输出当前这一张；套组其余部分由其他任务分别完成。透明须为真实Alpha，禁止棋盘格。"&CHAR(10)&"【对齐】"&K69&CHAR(10)&"【禁止】"&E69 -> 【唯一交付文件】abn_maodie_idle_01_approved.png 【对象】耄耋 平静定稿 原创二维地下工业收容设施游戏美术；怪诞手绘收容风，受手绘怪诞生存童话的表现原则启发。hand-drawn, ink-outline, slightly grotesque, whimsical horror, 2D cutout-friendly。粗细有变化的深墨轮廓，轻微不规则手绘线，大面积低饱和平涂，少量刻线阴影；剪影与动作优先于纹理。正交二维侧视角色/设施，UI为正视平面。保留对象身份，统一视觉语言，不复制其他作品具体资产。 【同组设计标准，仅作一致性约束】原创怪诞手绘收容风：不均匀粗墨外轮廓、较细结构线、局部不对称、平涂和少量排线；轮廓在游戏缩小尺寸仍清楚。 灰绿猫形，头宽而不规则，两只高尖耳长短不同；迟钝且略怀疑的不等大眼、重眉、短口鼻；身躯紧凑、短爪、弯折尾。主色灰绿 #929b92、深灰绿 #65736e、旧纸腹部 #d6d0b4，小面积锈色耳内。 侧视略带正脸可读性，所有部位围绕单一脚底根节点，不画房间。 【本次只画】本次只画一只完整平静 耄耋，严格采用本行具体形状与三色群，不含动作对照或其他角色；只交这一独立单元，不画其他零件、对照姿、sheet、文字或背景。保持主表指定造型、朝向与挂点。；本次只交付这一件/一个姿势，不把同组其他素材、姿势或裁切线画进本图，不拼成多格图集。 【状态】CONTAINED / IDLE 【参考】附图 REF_N02_CALM。当前 耄耋 室内未作业形态。如有前置定稿，必须保持同一造型、比例、线宽、服装和配色；拆件需另附已确认整身定稿图。 【画布】1024 × 1024 px；尺寸不支持时保持比例生成，再后处理到目标尺寸。 【输出】1 个透明 RGBA PNG 定稿；主体完整、无底座、无环境阴影；附三色主色票说明。。只输出当前这一张；套组其余部分由其他任务分别完成。透明须为真实Alpha，禁止棋盘格。 【对齐】脚底地面中心；母版 (512, 896)，朝右；全部形态共享同一根节点。 【禁止】不做 3D、照片写实、厚涂油画、等距俯视、高饱和二次元、霓虹光污染、密集脏污；不加文字、数字、二维码、水印、游戏界面或棋盘格背景；不把动态状态、血条、范围、路径烘焙进图。 不要照片、3D 渲染、像素风、光滑矢量图标风或高饱和日漫；不要复制现成游戏的角色、脸型或官方 IP 素材；不要背景、文字、水印、UI、血条、黄色选中圈或攻击范围；不要以红色滤镜代替形变。 | E69: =生成规范!$B$9&CHAR(10)&素材需求!S20 -> 不做 3D、照片写实、厚涂油画、等距俯视、高饱和二次元、霓虹光污染、密集脏污；不加文字、数字、二维码、水印、游戏界面或棋盘格背景；不把动态状态、血条、范围、路径烘焙进图。 不要照片、3D 渲染、像素风、光滑矢量图标风或高饱和日漫；不要复制现成游戏的角色、脸型或官方 IP 素材；不要背景、文字、水印、UI、血条、黄色选中圈或攻击范围；不要以红色滤镜代替形变。 | F69: REF_N02_CALM | G69: =素材需求!B20 -> P0 | H69: 1024 × 1024 px | I69: 本次只画一只完整平静 耄耋，严格采用本行具体形状与三色群，不含动作对照或其他角色；只交这一独立单元，不画其他零件、对照姿、sheet、文字或背景。保持主表指定造型、朝向与挂点。 | J69: 1 个透明 RGBA PNG 定稿；主体完整、无底座、无环境阴影；附三色主色票说明。 | K69: 脚底地面中心；母版 (512, 896)，朝右；全部形态共享同一根节点。 | L69: art_delivery/v1/abnormalities/ | M69: 待生成 | N69: —
A70: ABN_N02_03 | B70: abn_maodie_breach_01_approved.png | C70: 耄耋 失控定稿 | D70: ="【唯一交付文件】"&B70&CHAR(10)&"【对象】"&C70&CHAR(10)&生成规范!$B$8&CHAR(10)&"【同组设计标准，仅作一致性约束】"&素材需求!G21&CHAR(10)&"【本次只画】"&I70&"；本次只交付这一件/一个姿势，不把同组其他素材、姿势或裁切线画进本图，不拼成多格图集。"&CHAR(10)&"【状态】"&素材需求!F21&CHAR(10)&"【参考】附图 "&F70&"。"&素材需求!H21&"。如有前置定稿，必须保持同一造型、比例、线宽、服装和配色；拆件需另附已确认整身定稿图。"&CHAR(10)&"【画布】"&H70&"；尺寸不支持时保持比例生成，再后处理到目标尺寸。"&CHAR(10)&"【输出】"&J70&"。只输出当前这一张；套组其余部分由其他任务分别完成。透明须为真实Alpha，禁止棋盘格。"&CHAR(10)&"【对齐】"&K70&CHAR(10)&"【禁止】"&E70 -> 【唯一交付文件】abn_maodie_breach_01_approved.png 【对象】耄耋 失控定稿 原创二维地下工业收容设施游戏美术；怪诞手绘收容风，受手绘怪诞生存童话的表现原则启发。hand-drawn, ink-outline, slightly grotesque, whimsical horror, 2D cutout-friendly。粗细有变化的深墨轮廓，轻微不规则手绘线，大面积低饱和平涂，少量刻线阴影；剪影与动作优先于纹理。正交二维侧视角色/设施，UI为正视平面。保留对象身份，统一视觉语言，不复制其他作品具体资产。 【同组设计标准，仅作一致性约束】原创怪诞手绘收容风：不均匀粗墨外轮廓、较细结构线、局部不对称、平涂和少量排线；轮廓在游戏缩小尺寸仍清楚。 躯干纵向抽长、头抬高、两前肢变成明显细长的多折角轮廓，爪伸到身体两侧和地面；眼睛撑开、嘴偏斜张开，头有小幅错位线。仍保留大尖耳、灰绿皮毛和折尾；不是只把毛炸开。 【本次只画】本次只画一只完整失控 耄耋 主体，严格体现本行眼口和轮廓变化；不含分身、重影、受控星标或范围；只交这一独立单元，不画其他零件、对照姿、sheet、文字或背景。保持主表指定造型、朝向与挂点。；本次只交付这一件/一个姿势，不把同组其他素材、姿势或裁切线画进本图，不拼成多格图集。 【状态】BREACHED 【参考】附图 REF_N02_CALM / REF_N02_BREACH。当前 耄耋 真实 enemy 形态，对照其平静定稿。如有前置定稿，必须保持同一造型、比例、线宽、服装和配色；拆件需另附已确认整身定稿图。 【画布】1024 × 1024 px；尺寸不支持时保持比例生成，再后处理到目标尺寸。 【输出】1 个透明 RGBA PNG 主体定稿；虚影/错帧效果仅放附属说明，实际主体不带不可拆多重残像。。只输出当前这一张；套组其余部分由其他任务分别完成。透明须为真实Alpha，禁止棋盘格。 【对齐】脚底地面中心；母版 (512, 896)，朝右；全部形态共享同一根节点。 【禁止】不做 3D、照片写实、厚涂油画、等距俯视、高饱和二次元、霓虹光污染、密集脏污；不加文字、数字、二维码、水印、游戏界面或棋盘格背景；不把动态状态、血条、范围、路径烘焙进图。 不要照片、3D 渲染、像素风、光滑矢量图标风或高饱和日漫；不要复制现成游戏的角色、脸型或官方 IP 素材；不要背景、文字、水印、UI、血条、黄色选中圈或攻击范围；不要以红色滤镜代替形变。 | E70: =生成规范!$B$9&CHAR(10)&素材需求!S21 -> 不做 3D、照片写实、厚涂油画、等距俯视、高饱和二次元、霓虹光污染、密集脏污；不加文字、数字、二维码、水印、游戏界面或棋盘格背景；不把动态状态、血条、范围、路径烘焙进图。 不要照片、3D 渲染、像素风、光滑矢量图标风或高饱和日漫；不要复制现成游戏的角色、脸型或官方 IP 素材；不要背景、文字、水印、UI、血条、黄色选中圈或攻击范围；不要以红色滤镜代替形变。 | F70: REF_N02_CALM / REF_N02_BREACH | G70: =素材需求!B21 -> P0 | H70: 1024 × 1024 px | I70: 本次只画一只完整失控 耄耋 主体，严格体现本行眼口和轮廓变化；不含分身、重影、受控星标或范围；只交这一独立单元，不画其他零件、对照姿、sheet、文字或背景。保持主表指定造型、朝向与挂点。 | J70: 1 个透明 RGBA PNG 主体定稿；虚影/错帧效果仅放附属说明，实际主体不带不可拆多重残像。 | K70: 脚底地面中心；母版 (512, 896)，朝右；全部形态共享同一根节点。 | L70: art_delivery/v1/abnormalities/ | M70: 待生成 | N70: ABN_N02_01
A71: ABN_N02_04 | B71: abn_maodie_parts_01_calm_body.png | C71: 耄耋常态躯干 | D71: ="【唯一交付文件】"&B71&CHAR(10)&"【对象】"&C71&CHAR(10)&生成规范!$B$8&CHAR(10)&"【同组设计标准，仅作一致性约束】"&素材需求!G22&CHAR(10)&"【本次只画】"&I71&"；本次只交付这一件/一个姿势，不把同组其他素材、姿势或裁切线画进本图，不拼成多格图集。"&CHAR(10)&"【状态】"&素材需求!F22&CHAR(10)&"【参考】附图 "&F71&"。"&素材需求!H22&"。如有前置定稿，必须保持同一造型、比例、线宽、服装和配色；拆件需另附已确认整身定稿图。"&CHAR(10)&"【画布】"&H71&"；尺寸不支持时保持比例生成，再后处理到目标尺寸。"&CHAR(10)&"【输出】"&J71&"。只输出当前这一张；套组其余部分由其他任务分别完成。透明须为真实Alpha，禁止棋盘格。"&CHAR(10)&"【对齐】"&K71&CHAR(10)&"【禁止】"&E71 -> 【唯一交付文件】abn_maodie_parts_01_calm_body.png 【对象】耄耋常态躯干 原创二维地下工业收容设施游戏美术；怪诞手绘收容风，受手绘怪诞生存童话的表现原则启发。hand-drawn, ink-outline, slightly grotesque, whimsical horror, 2D cutout-friendly。粗细有变化的深墨轮廓，轻微不规则手绘线，大面积低饱和平涂，少量刻线阴影；剪影与动作优先于纹理。正交二维侧视角色/设施，UI为正视平面。保留对象身份，统一视觉语言，不复制其他作品具体资产。 【同组设计标准，仅作一致性约束】常态躯干 1、伸长躯干 1、头含耳 1、平静眼口组 1、失控眼口组 1、短前肢 2、伸长前肢 2、后足 2、尾 1，共 12 件。伸长肢体为形态替换件，肩/髋根节点一致。 沿用两份已批准定稿的线宽与体积，关节背面补全；可复用部位只交一份，不为每个动作复制整身。完整定稿仅作组合校对，不额外计独立交付单位。 以上为整套构成；每次只生成 「逐张提示词」本张范围 指定的一个独立件，不画整套平铺图。 【本次只画】本次只画耄耋紧凑常态躯干和浅腹块，不含头与四肢尾；只交这一独立单元，不画其他零件、对照姿、sheet、文字或背景。保持主表指定造型、朝向与挂点。；本次只交付这一件/一个姿势，不把同组其他素材、姿势或裁切线画进本图，不拼成多格图集。 【状态】IDLE / WORKING / BREACHED 【参考】附图 REF_N02_CALM / REF_N02_BREACH。耄耋 已批准平静与失控定稿。如有前置定稿，必须保持同一造型、比例、线宽、服装和配色；拆件需另附已确认整身定稿图。 【画布】1024 × 1024 px，每张单独姿势/零件，共用 (512, 896) 根；尺寸不支持时保持比例生成，再后处理到目标尺寸。 【输出】本次仅一张单件 PNG，sRGB；真实 Alpha 透明背景；保持足够安全边距；尺寸修正、边缘清理、分层源文件及轴点记录由后处理制作。。只输出当前这一张；套组其余部分由其他任务分别完成。透明须为真实Alpha，禁止棋盘格。 【对齐】脚底地面中心；母版 (512, 896)，朝右；全部形态共享同一根节点。 另记录头颈、四肢、口部或钟针等实际旋转挂点。 【禁止】不做 3D、照片写实、厚涂油画、等距俯视、高饱和二次元、霓虹光污染、密集脏污；不加文字、数字、二维码、水印、游戏界面或棋盘格背景；不把动态状态、血条、范围、路径烘焙进图。 不要照片、3D 渲染、像素风、光滑矢量图标风或高饱和日漫；不要复制现成游戏的角色、脸型或官方 IP 素材；不要背景、文字、水印、UI、血条、黄色选中圈或攻击范围；不要以红色滤镜代替形变。 | E71: =生成规范!$B$9&CHAR(10)&素材需求!S22 -> 不做 3D、照片写实、厚涂油画、等距俯视、高饱和二次元、霓虹光污染、密集脏污；不加文字、数字、二维码、水印、游戏界面或棋盘格背景；不把动态状态、血条、范围、路径烘焙进图。 不要照片、3D 渲染、像素风、光滑矢量图标风或高饱和日漫；不要复制现成游戏的角色、脸型或官方 IP 素材；不要背景、文字、水印、UI、血条、黄色选中圈或攻击范围；不要以红色滤镜代替形变。 | F71: REF_N02_CALM / REF_N02_BREACH | G71: =素材需求!B22 -> P0 | H71: 1024 × 1024 px，每张单独姿势/零件，共用 (512, 896) 根 | I71: 本次只画耄耋紧凑常态躯干和浅腹块，不含头与四肢尾；只交这一独立单元，不画其他零件、对照姿、sheet、文字或背景。保持主表指定造型、朝向与挂点。 | J71: 本次仅一张单件 PNG，sRGB；真实 Alpha 透明背景；保持足够安全边距；尺寸修正、边缘清理、分层源文件及轴点记录由后处理制作。 | K71: 脚底地面中心；母版 (512, 896)，朝右；全部形态共享同一根节点。 另记录头颈、四肢、口部或钟针等实际旋转挂点。 | L71: art_delivery/v1/abnormalities/ | M71: 待生成 | N71: ABN_N02_01 / ABN_N02_03
A72: ABN_N02_04 | B72: abn_maodie_parts_01_breach_body.png | C72: 耄耋伸长躯干 | D72: ="【唯一交付文件】"&B72&CHAR(10)&"【对象】"&C72&CHAR(10)&生成规范!$B$8&CHAR(10)&"【同组设计标准，仅作一致性约束】"&素材需求!G22&CHAR(10)&"【本次只画】"&I72&"；本次只交付这一件/一个姿势，不把同组其他素材、姿势或裁切线画进本图，不拼成多格图集。"&CHAR(10)&"【状态】"&素材需求!F22&CHAR(10)&"【参考】附图 "&F72&"。"&素材需求!H22&"。如有前置定稿，必须保持同一造型、比例、线宽、服装和配色；拆件需另附已确认整身定稿图。"&CHAR(10)&"【画布】"&H72&"；尺寸不支持时保持比例生成，再后处理到目标尺寸。"&CHAR(10)&"【输出】"&J72&"。只输出当前这一张；套组其余部分由其他任务分别完成。透明须为真实Alpha，禁止棋盘格。"&CHAR(10)&"【对齐】"&K72&CHAR(10)&"【禁止】"&E72 -> 【唯一交付文件】abn_maodie_parts_01_breach_body.png 【对象】耄耋伸长躯干 原创二维地下工业收容设施游戏美术；怪诞手绘收容风，受手绘怪诞生存童话的表现原则启发。hand-drawn, ink-outline, slightly grotesque, whimsical horror, 2D cutout-friendly。粗细有变化的深墨轮廓，轻微不规则手绘线，大面积低饱和平涂，少量刻线阴影；剪影与动作优先于纹理。正交二维侧视角色/设施，UI为正视平面。保留对象身份，统一视觉语言，不复制其他作品具体资产。 【同组设计标准，仅作一致性约束】常态躯干 1、伸长躯干 1、头含耳 1、平静眼口组 1、失控眼口组 1、短前肢 2、伸长前肢 2、后足 2、尾 1，共 12 件。伸长肢体为形态替换件，肩/髋根节点一致。 沿用两份已批准定稿的线宽与体积，关节背面补全；可复用部位只交一份，不为每个动作复制整身。完整定稿仅作组合校对，不额外计独立交付单位。 以上为整套构成；每次只生成 「逐张提示词」本张范围 指定的一个独立件，不画整套平铺图。 【本次只画】本次只画耄耋失控伸长躯干，仍保留同一浅腹块和肩髋根；只交这一独立单元，不画其他零件、对照姿、sheet、文字或背景。保持主表指定造型、朝向与挂点。；本次只交付这一件/一个姿势，不把同组其他素材、姿势或裁切线画进本图，不拼成多格图集。 【状态】IDLE / WORKING / BREACHED 【参考】附图 REF_N02_CALM / REF_N02_BREACH。耄耋 已批准平静与失控定稿。如有前置定稿，必须保持同一造型、比例、线宽、服装和配色；拆件需另附已确认整身定稿图。 【画布】1024 × 1024 px，每张单独姿势/零件，共用 (512, 896) 根；尺寸不支持时保持比例生成，再后处理到目标尺寸。 【输出】本次仅一张单件 PNG，sRGB；真实 Alpha 透明背景；保持足够安全边距；尺寸修正、边缘清理、分层源文件及轴点记录由后处理制作。。只输出当前这一张；套组其余部分由其他任务分别完成。透明须为真实Alpha，禁止棋盘格。 【对齐】脚底地面中心；母版 (512, 896)，朝右；全部形态共享同一根节点。 另记录头颈、四肢、口部或钟针等实际旋转挂点。 【禁止】不做 3D、照片写实、厚涂油画、等距俯视、高饱和二次元、霓虹光污染、密集脏污；不加文字、数字、二维码、水印、游戏界面或棋盘格背景；不把动态状态、血条、范围、路径烘焙进图。 不要照片、3D 渲染、像素风、光滑矢量图标风或高饱和日漫；不要复制现成游戏的角色、脸型或官方 IP 素材；不要背景、文字、水印、UI、血条、黄色选中圈或攻击范围；不要以红色滤镜代替形变。 | E72: =生成规范!$B$9&CHAR(10)&素材需求!S22 -> 不做 3D、照片写实、厚涂油画、等距俯视、高饱和二次元、霓虹光污染、密集脏污；不加文字、数字、二维码、水印、游戏界面或棋盘格背景；不把动态状态、血条、范围、路径烘焙进图。 不要照片、3D 渲染、像素风、光滑矢量图标风或高饱和日漫；不要复制现成游戏的角色、脸型或官方 IP 素材；不要背景、文字、水印、UI、血条、黄色选中圈或攻击范围；不要以红色滤镜代替形变。 | F72: REF_N02_CALM / REF_N02_BREACH | G72: =素材需求!B22 -> P0 | H72: 1024 × 1024 px，每张单独姿势/零件，共用 (512, 896) 根 | I72: 本次只画耄耋失控伸长躯干，仍保留同一浅腹块和肩髋根；只交这一独立单元，不画其他零件、对照姿、sheet、文字或背景。保持主表指定造型、朝向与挂点。 | J72: 本次仅一张单件 PNG，sRGB；真实 Alpha 透明背景；保持足够安全边距；尺寸修正、边缘清理、分层源文件及轴点记录由后处理制作。 | K72: 脚底地面中心；母版 (512, 896)，朝右；全部形态共享同一根节点。 另记录头颈、四肢、口部或钟针等实际旋转挂点。 | L72: art_delivery/v1/abnormalities/ | M72: 待生成 | N72: ABN_N02_01 / ABN_N02_03
A73: ABN_N02_04 | B73: abn_maodie_parts_01_head_ears.png | C73: 耄耋头耳 | D73: ="【唯一交付文件】"&B73&CHAR(10)&"【对象】"&C73&CHAR(10)&生成规范!$B$8&CHAR(10)&"【同组设计标准，仅作一致性约束】"&素材需求!G22&CHAR(10)&"【本次只画】"&I73&"；本次只交付这一件/一个姿势，不把同组其他素材、姿势或裁切线画进本图，不拼成多格图集。"&CHAR(10)&"【状态】"&素材需求!F22&CHAR(10)&"【参考】附图 "&F73&"。"&素材需求!H22&"。如有前置定稿，必须保持同一造型、比例、线宽、服装和配色；拆件需另附已确认整身定稿图。"&CHAR(10)&"【画布】"&H73&"；尺寸不支持时保持比例生成，再后处理到目标尺寸。"&CHAR(10)&"【输出】"&J73&"。只输出当前这一张；套组其余部分由其他任务分别完成。透明须为真实Alpha，禁止棋盘格。"&CHAR(10)&"【对齐】"&K73&CHAR(10)&"【禁止】"&E73 -> 【唯一交付文件】abn_maodie_parts_01_head_ears.png 【对象】耄耋头耳 原创二维地下工业收容设施游戏美术；怪诞手绘收容风，受手绘怪诞生存童话的表现原则启发。hand-drawn, ink-outline, slightly grotesque, whimsical horror, 2D cutout-friendly。粗细有变化的深墨轮廓，轻微不规则手绘线，大面积低饱和平涂，少量刻线阴影；剪影与动作优先于纹理。正交二维侧视角色/设施，UI为正视平面。保留对象身份，统一视觉语言，不复制其他作品具体资产。 【同组设计标准，仅作一致性约束】常态躯干 1、伸长躯干 1、头含耳 1、平静眼口组 1、失控眼口组 1、短前肢 2、伸长前肢 2、后足 2、尾 1，共 12 件。伸长肢体为形态替换件，肩/髋根节点一致。 沿用两份已批准定稿的线宽与体积，关节背面补全；可复用部位只交一份，不为每个动作复制整身。完整定稿仅作组合校对，不额外计独立交付单位。 以上为整套构成；每次只生成 「逐张提示词」本张范围 指定的一个独立件，不画整套平铺图。 【本次只画】本次只画耄耋不规则宽头及两只不等高尖耳，预留眼口位置；只交这一独立单元，不画其他零件、对照姿、sheet、文字或背景。保持主表指定造型、朝向与挂点。；本次只交付这一件/一个姿势，不把同组其他素材、姿势或裁切线画进本图，不拼成多格图集。 【状态】IDLE / WORKING / BREACHED 【参考】附图 REF_N02_CALM / REF_N02_BREACH。耄耋 已批准平静与失控定稿。如有前置定稿，必须保持同一造型、比例、线宽、服装和配色；拆件需另附已确认整身定稿图。 【画布】1024 × 1024 px，每张单独姿势/零件，共用 (512, 896) 根；尺寸不支持时保持比例生成，再后处理到目标尺寸。 【输出】本次仅一张单件 PNG，sRGB；真实 Alpha 透明背景；保持足够安全边距；尺寸修正、边缘清理、分层源文件及轴点记录由后处理制作。。只输出当前这一张；套组其余部分由其他任务分别完成。透明须为真实Alpha，禁止棋盘格。 【对齐】脚底地面中心；母版 (512, 896)，朝右；全部形态共享同一根节点。 另记录头颈、四肢、口部或钟针等实际旋转挂点。 【禁止】不做 3D、照片写实、厚涂油画、等距俯视、高饱和二次元、霓虹光污染、密集脏污；不加文字、数字、二维码、水印、游戏界面或棋盘格背景；不把动态状态、血条、范围、路径烘焙进图。 不要照片、3D 渲染、像素风、光滑矢量图标风或高饱和日漫；不要复制现成游戏的角色、脸型或官方 IP 素材；不要背景、文字、水印、UI、血条、黄色选中圈或攻击范围；不要以红色滤镜代替形变。 | E73: =生成规范!$B$9&CHAR(10)&素材需求!S22 -> 不做 3D、照片写实、厚涂油画、等距俯视、高饱和二次元、霓虹光污染、密集脏污；不加文字、数字、二维码、水印、游戏界面或棋盘格背景；不把动态状态、血条、范围、路径烘焙进图。 不要照片、3D 渲染、像素风、光滑矢量图标风或高饱和日漫；不要复制现成游戏的角色、脸型或官方 IP 素材；不要背景、文字、水印、UI、血条、黄色选中圈或攻击范围；不要以红色滤镜代替形变。 | F73: REF_N02_CALM / REF_N02_BREACH | G73: =素材需求!B22 -> P0 | H73: 1024 × 1024 px，每张单独姿势/零件，共用 (512, 896) 根 | I73: 本次只画耄耋不规则宽头及两只不等高尖耳，预留眼口位置；只交这一独立单元，不画其他零件、对照姿、sheet、文字或背景。保持主表指定造型、朝向与挂点。 | J73: 本次仅一张单件 PNG，sRGB；真实 Alpha 透明背景；保持足够安全边距；尺寸修正、边缘清理、分层源文件及轴点记录由后处理制作。 | K73: 脚底地面中心；母版 (512, 896)，朝右；全部形态共享同一根节点。 另记录头颈、四肢、口部或钟针等实际旋转挂点。 | L73: art_delivery/v1/abnormalities/ | M73: 待生成 | N73: ABN_N02_01 / ABN_N02_03
A74: ABN_N02_04 | B74: abn_maodie_parts_01_calm_face.png | C74: 耄耋平静眼口 | D74: ="【唯一交付文件】"&B74&CHAR(10)&"【对象】"&C74&CHAR(10)&生成规范!$B$8&CHAR(10)&"【同组设计标准，仅作一致性约束】"&素材需求!G22&CHAR(10)&"【本次只画】"&I74&"；本次只交付这一件/一个姿势，不把同组其他素材、姿势或裁切线画进本图，不拼成多格图集。"&CHAR(10)&"【状态】"&素材需求!F22&CHAR(10)&"【参考】附图 "&F74&"。"&素材需求!H22&"。如有前置定稿，必须保持同一造型、比例、线宽、服装和配色；拆件需另附已确认整身定稿图。"&CHAR(10)&"【画布】"&H74&"；尺寸不支持时保持比例生成，再后处理到目标尺寸。"&CHAR(10)&"【输出】"&J74&"。只输出当前这一张；套组其余部分由其他任务分别完成。透明须为真实Alpha，禁止棋盘格。"&CHAR(10)&"【对齐】"&K74&CHAR(10)&"【禁止】"&E74 -> 【唯一交付文件】abn_maodie_parts_01_calm_face.png 【对象】耄耋平静眼口 原创二维地下工业收容设施游戏美术；怪诞手绘收容风，受手绘怪诞生存童话的表现原则启发。hand-drawn, ink-outline, slightly grotesque, whimsical horror, 2D cutout-friendly。粗细有变化的深墨轮廓，轻微不规则手绘线，大面积低饱和平涂，少量刻线阴影；剪影与动作优先于纹理。正交二维侧视角色/设施，UI为正视平面。保留对象身份，统一视觉语言，不复制其他作品具体资产。 【同组设计标准，仅作一致性约束】常态躯干 1、伸长躯干 1、头含耳 1、平静眼口组 1、失控眼口组 1、短前肢 2、伸长前肢 2、后足 2、尾 1，共 12 件。伸长肢体为形态替换件，肩/髋根节点一致。 沿用两份已批准定稿的线宽与体积，关节背面补全；可复用部位只交一份，不为每个动作复制整身。完整定稿仅作组合校对，不额外计独立交付单位。 以上为整套构成；每次只生成 「逐张提示词」本张范围 指定的一个独立件，不画整套平铺图。 【本次只画】本次只画耄耋迟钝怀疑的平静眉眼鼻口透明叠层，含胡须；只交这一独立单元，不画其他零件、对照姿、sheet、文字或背景。保持主表指定造型、朝向与挂点。；本次只交付这一件/一个姿势，不把同组其他素材、姿势或裁切线画进本图，不拼成多格图集。 【状态】IDLE / WORKING / BREACHED 【参考】附图 REF_N02_CALM / REF_N02_BREACH。耄耋 已批准平静与失控定稿。如有前置定稿，必须保持同一造型、比例、线宽、服装和配色；拆件需另附已确认整身定稿图。 【画布】1024 × 1024 px，每张单独姿势/零件，共用 (512, 896) 根；尺寸不支持时保持比例生成，再后处理到目标尺寸。 【输出】本次仅一张单件 PNG，sRGB；真实 Alpha 透明背景；保持足够安全边距；尺寸修正、边缘清理、分层源文件及轴点记录由后处理制作。。只输出当前这一张；套组其余部分由其他任务分别完成。透明须为真实Alpha，禁止棋盘格。 【对齐】脚底地面中心；母版 (512, 896)，朝右；全部形态共享同一根节点。 另记录头颈、四肢、口部或钟针等实际旋转挂点。 【禁止】不做 3D、照片写实、厚涂油画、等距俯视、高饱和二次元、霓虹光污染、密集脏污；不加文字、数字、二维码、水印、游戏界面或棋盘格背景；不把动态状态、血条、范围、路径烘焙进图。 不要照片、3D 渲染、像素风、光滑矢量图标风或高饱和日漫；不要复制现成游戏的角色、脸型或官方 IP 素材；不要背景、文字、水印、UI、血条、黄色选中圈或攻击范围；不要以红色滤镜代替形变。 | E74: =生成规范!$B$9&CHAR(10)&素材需求!S22 -> 不做 3D、照片写实、厚涂油画、等距俯视、高饱和二次元、霓虹光污染、密集脏污；不加文字、数字、二维码、水印、游戏界面或棋盘格背景；不把动态状态、血条、范围、路径烘焙进图。 不要照片、3D 渲染、像素风、光滑矢量图标风或高饱和日漫；不要复制现成游戏的角色、脸型或官方 IP 素材；不要背景、文字、水印、UI、血条、黄色选中圈或攻击范围；不要以红色滤镜代替形变。 | F74: REF_N02_CALM / REF_N02_BREACH | G74: =素材需求!B22 -> P0 | H74: 1024 × 1024 px，每张单独姿势/零件，共用 (512, 896) 根 | I74: 本次只画耄耋迟钝怀疑的平静眉眼鼻口透明叠层，含胡须；只交这一独立单元，不画其他零件、对照姿、sheet、文字或背景。保持主表指定造型、朝向与挂点。 | J74: 本次仅一张单件 PNG，sRGB；真实 Alpha 透明背景；保持足够安全边距；尺寸修正、边缘清理、分层源文件及轴点记录由后处理制作。 | K74: 脚底地面中心；母版 (512, 896)，朝右；全部形态共享同一根节点。 另记录头颈、四肢、口部或钟针等实际旋转挂点。 | L74: art_delivery/v1/abnormalities/ | M74: 待生成 | N74: ABN_N02_01 / ABN_N02_03
A75: ABN_N02_04 | B75: abn_maodie_parts_01_breach_face.png | C75: 耄耋失控眼口 | D75: ="【唯一交付文件】"&B75&CHAR(10)&"【对象】"&C75&CHAR(10)&生成规范!$B$8&CHAR(10)&"【同组设计标准，仅作一致性约束】"&素材需求!G22&CHAR(10)&"【本次只画】"&I75&"；本次只交付这一件/一个姿势，不把同组其他素材、姿势或裁切线画进本图，不拼成多格图集。"&CHAR(10)&"【状态】"&素材需求!F22&CHAR(10)&"【参考】附图 "&F75&"。"&素材需求!H22&"。如有前置定稿，必须保持同一造型、比例、线宽、服装和配色；拆件需另附已确认整身定稿图。"&CHAR(10)&"【画布】"&H75&"；尺寸不支持时保持比例生成，再后处理到目标尺寸。"&CHAR(10)&"【输出】"&J75&"。只输出当前这一张；套组其余部分由其他任务分别完成。透明须为真实Alpha，禁止棋盘格。"&CHAR(10)&"【对齐】"&K75&CHAR(10)&"【禁止】"&E75 -> 【唯一交付文件】abn_maodie_parts_01_breach_face.png 【对象】耄耋失控眼口 原创二维地下工业收容设施游戏美术；怪诞手绘收容风，受手绘怪诞生存童话的表现原则启发。hand-drawn, ink-outline, slightly grotesque, whimsical horror, 2D cutout-friendly。粗细有变化的深墨轮廓，轻微不规则手绘线，大面积低饱和平涂，少量刻线阴影；剪影与动作优先于纹理。正交二维侧视角色/设施，UI为正视平面。保留对象身份，统一视觉语言，不复制其他作品具体资产。 【同组设计标准，仅作一致性约束】常态躯干 1、伸长躯干 1、头含耳 1、平静眼口组 1、失控眼口组 1、短前肢 2、伸长前肢 2、后足 2、尾 1，共 12 件。伸长肢体为形态替换件，肩/髋根节点一致。 沿用两份已批准定稿的线宽与体积，关节背面补全；可复用部位只交一份，不为每个动作复制整身。完整定稿仅作组合校对，不额外计独立交付单位。 以上为整套构成；每次只生成 「逐张提示词」本张范围 指定的一个独立件，不画整套平铺图。 【本次只画】本次只画耄耋撑开双眼和偏斜张嘴的失控面部透明叠层，含胡须；只交这一独立单元，不画其他零件、对照姿、sheet、文字或背景。保持主表指定造型、朝向与挂点。；本次只交付这一件/一个姿势，不把同组其他素材、姿势或裁切线画进本图，不拼成多格图集。 【状态】IDLE / WORKING / BREACHED 【参考】附图 REF_N02_CALM / REF_N02_BREACH。耄耋 已批准平静与失控定稿。如有前置定稿，必须保持同一造型、比例、线宽、服装和配色；拆件需另附已确认整身定稿图。 【画布】1024 × 1024 px，每张单独姿势/零件，共用 (512, 896) 根；尺寸不支持时保持比例生成，再后处理到目标尺寸。 【输出】本次仅一张单件 PNG，sRGB；真实 Alpha 透明背景；保持足够安全边距；尺寸修正、边缘清理、分层源文件及轴点记录由后处理制作。。只输出当前这一张；套组其余部分由其他任务分别完成。透明须为真实Alpha，禁止棋盘格。 【对齐】脚底地面中心；母版 (512, 896)，朝右；全部形态共享同一根节点。 另记录头颈、四肢、口部或钟针等实际旋转挂点。 【禁止】不做 3D、照片写实、厚涂油画、等距俯视、高饱和二次元、霓虹光污染、密集脏污；不加文字、数字、二维码、水印、游戏界面或棋盘格背景；不把动态状态、血条、范围、路径烘焙进图。 不要照片、3D 渲染、像素风、光滑矢量图标风或高饱和日漫；不要复制现成游戏的角色、脸型或官方 IP 素材；不要背景、文字、水印、UI、血条、黄色选中圈或攻击范围；不要以红色滤镜代替形变。 | E75: =生成规范!$B$9&CHAR(10)&素材需求!S22 -> 不做 3D、照片写实、厚涂油画、等距俯视、高饱和二次元、霓虹光污染、密集脏污；不加文字、数字、二维码、水印、游戏界面或棋盘格背景；不把动态状态、血条、范围、路径烘焙进图。 不要照片、3D 渲染、像素风、光滑矢量图标风或高饱和日漫；不要复制现成游戏的角色、脸型或官方 IP 素材；不要背景、文字、水印、UI、血条、黄色选中圈或攻击范围；不要以红色滤镜代替形变。 | F75: REF_N02_CALM / REF_N02_BREACH | G75: =素材需求!B22 -> P0 | H75: 1024 × 1024 px，每张单独姿势/零件，共用 (512, 896) 根 | I75: 本次只画耄耋撑开双眼和偏斜张嘴的失控面部透明叠层，含胡须；只交这一独立单元，不画其他零件、对照姿、sheet、文字或背景。保持主表指定造型、朝向与挂点。 | J75: 本次仅一张单件 PNG，sRGB；真实 Alpha 透明背景；保持足够安全边距；尺寸修正、边缘清理、分层源文件及轴点记录由后处理制作。 | K75: 脚底地面中心；母版 (512, 896)，朝右；全部形态共享同一根节点。 另记录头颈、四肢、口部或钟针等实际旋转挂点。 | L75: art_delivery/v1/abnormalities/ | M75: 待生成 | N75: ABN_N02_01 / ABN_N02_03
A76: ABN_N02_04 | B76: abn_maodie_parts_01_calm_arm_left.png | C76: 耄耋左短前肢 | D76: ="【唯一交付文件】"&B76&CHAR(10)&"【对象】"&C76&CHAR(10)&生成规范!$B$8&CHAR(10)&"【同组设计标准，仅作一致性约束】"&素材需求!G22&CHAR(10)&"【本次只画】"&I76&"；本次只交付这一件/一个姿势，不把同组其他素材、姿势或裁切线画进本图，不拼成多格图集。"&CHAR(10)&"【状态】"&素材需求!F22&CHAR(10)&"【参考】附图 "&F76&"。"&素材需求!H22&"。如有前置定稿，必须保持同一造型、比例、线宽、服装和配色；拆件需另附已确认整身定稿图。"&CHAR(10)&"【画布】"&H76&"；尺寸不支持时保持比例生成，再后处理到目标尺寸。"&CHAR(10)&"【输出】"&J76&"。只输出当前这一张；套组其余部分由其他任务分别完成。透明须为真实Alpha，禁止棋盘格。"&CHAR(10)&"【对齐】"&K76&CHAR(10)&"【禁止】"&E76 -> 【唯一交付文件】abn_maodie_parts_01_calm_arm_left.png 【对象】耄耋左短前肢 原创二维地下工业收容设施游戏美术；怪诞手绘收容风，受手绘怪诞生存童话的表现原则启发。hand-drawn, ink-outline, slightly grotesque, whimsical horror, 2D cutout-friendly。粗细有变化的深墨轮廓，轻微不规则手绘线，大面积低饱和平涂，少量刻线阴影；剪影与动作优先于纹理。正交二维侧视角色/设施，UI为正视平面。保留对象身份，统一视觉语言，不复制其他作品具体资产。 【同组设计标准，仅作一致性约束】常态躯干 1、伸长躯干 1、头含耳 1、平静眼口组 1、失控眼口组 1、短前肢 2、伸长前肢 2、后足 2、尾 1，共 12 件。伸长肢体为形态替换件，肩/髋根节点一致。 沿用两份已批准定稿的线宽与体积，关节背面补全；可复用部位只交一份，不为每个动作复制整身。完整定稿仅作组合校对，不额外计独立交付单位。 以上为整套构成；每次只生成 「逐张提示词」本张范围 指定的一个独立件，不画整套平铺图。 【本次只画】本次只画耄耋常态左短前肢和爪掌，肩根补全；只交这一独立单元，不画其他零件、对照姿、sheet、文字或背景。保持主表指定造型、朝向与挂点。；本次只交付这一件/一个姿势，不把同组其他素材、姿势或裁切线画进本图，不拼成多格图集。 【状态】IDLE / WORKING / BREACHED 【参考】附图 REF_N02_CALM / REF_N02_BREACH。耄耋 已批准平静与失控定稿。如有前置定稿，必须保持同一造型、比例、线宽、服装和配色；拆件需另附已确认整身定稿图。 【画布】1024 × 1024 px，每张单独姿势/零件，共用 (512, 896) 根；尺寸不支持时保持比例生成，再后处理到目标尺寸。 【输出】本次仅一张单件 PNG，sRGB；真实 Alpha 透明背景；保持足够安全边距；尺寸修正、边缘清理、分层源文件及轴点记录由后处理制作。。只输出当前这一张；套组其余部分由其他任务分别完成。透明须为真实Alpha，禁止棋盘格。 【对齐】脚底地面中心；母版 (512, 896)，朝右；全部形态共享同一根节点。 另记录头颈、四肢、口部或钟针等实际旋转挂点。 【禁止】不做 3D、照片写实、厚涂油画、等距俯视、高饱和二次元、霓虹光污染、密集脏污；不加文字、数字、二维码、水印、游戏界面或棋盘格背景；不把动态状态、血条、范围、路径烘焙进图。 不要照片、3D 渲染、像素风、光滑矢量图标风或高饱和日漫；不要复制现成游戏的角色、脸型或官方 IP 素材；不要背景、文字、水印、UI、血条、黄色选中圈或攻击范围；不要以红色滤镜代替形变。 | E76: =生成规范!$B$9&CHAR(10)&素材需求!S22 -> 不做 3D、照片写实、厚涂油画、等距俯视、高饱和二次元、霓虹光污染、密集脏污；不加文字、数字、二维码、水印、游戏界面或棋盘格背景；不把动态状态、血条、范围、路径烘焙进图。 不要照片、3D 渲染、像素风、光滑矢量图标风或高饱和日漫；不要复制现成游戏的角色、脸型或官方 IP 素材；不要背景、文字、水印、UI、血条、黄色选中圈或攻击范围；不要以红色滤镜代替形变。 | F76: REF_N02_CALM / REF_N02_BREACH | G76: =素材需求!B22 -> P0 | H76: 1024 × 1024 px，每张单独姿势/零件，共用 (512, 896) 根 | I76: 本次只画耄耋常态左短前肢和爪掌，肩根补全；只交这一独立单元，不画其他零件、对照姿、sheet、文字或背景。保持主表指定造型、朝向与挂点。 | J76: 本次仅一张单件 PNG，sRGB；真实 Alpha 透明背景；保持足够安全边距；尺寸修正、边缘清理、分层源文件及轴点记录由后处理制作。 | K76: 脚底地面中心；母版 (512, 896)，朝右；全部形态共享同一根节点。 另记录头颈、四肢、口部或钟针等实际旋转挂点。 | L76: art_delivery/v1/abnormalities/ | M76: 待生成 | N76: ABN_N02_01 / ABN_N02_03
A77: ABN_N02_04 | B77: abn_maodie_parts_01_calm_arm_right.png | C77: 耄耋右短前肢 | D77: ="【唯一交付文件】"&B77&CHAR(10)&"【对象】"&C77&CHAR(10)&生成规范!$B$8&CHAR(10)&"【同组设计标准，仅作一致性约束】"&素材需求!G22&CHAR(10)&"【本次只画】"&I77&"；本次只交付这一件/一个姿势，不把同组其他素材、姿势或裁切线画进本图，不拼成多格图集。"&CHAR(10)&"【状态】"&素材需求!F22&CHAR(10)&"【参考】附图 "&F77&"。"&素材需求!H22&"。如有前置定稿，必须保持同一造型、比例、线宽、服装和配色；拆件需另附已确认整身定稿图。"&CHAR(10)&"【画布】"&H77&"；尺寸不支持时保持比例生成，再后处理到目标尺寸。"&CHAR(10)&"【输出】"&J77&"。只输出当前这一张；套组其余部分由其他任务分别完成。透明须为真实Alpha，禁止棋盘格。"&CHAR(10)&"【对齐】"&K77&CHAR(10)&"【禁止】"&E77 -> 【唯一交付文件】abn_maodie_parts_01_calm_arm_right.png 【对象】耄耋右短前肢 原创二维地下工业收容设施游戏美术；怪诞手绘收容风，受手绘怪诞生存童话的表现原则启发。hand-drawn, ink-outline, slightly grotesque, whimsical horror, 2D cutout-friendly。粗细有变化的深墨轮廓，轻微不规则手绘线，大面积低饱和平涂，少量刻线阴影；剪影与动作优先于纹理。正交二维侧视角色/设施，UI为正视平面。保留对象身份，统一视觉语言，不复制其他作品具体资产。 【同组设计标准，仅作一致性约束】常态躯干 1、伸长躯干 1、头含耳 1、平静眼口组 1、失控眼口组 1、短前肢 2、伸长前肢 2、后足 2、尾 1，共 12 件。伸长肢体为形态替换件，肩/髋根节点一致。 沿用两份已批准定稿的线宽与体积，关节背面补全；可复用部位只交一份，不为每个动作复制整身。完整定稿仅作组合校对，不额外计独立交付单位。 以上为整套构成；每次只生成 「逐张提示词」本张范围 指定的一个独立件，不画整套平铺图。 【本次只画】本次只画耄耋常态右短前肢和爪掌，肩根补全；只交这一独立单元，不画其他零件、对照姿、sheet、文字或背景。保持主表指定造型、朝向与挂点。；本次只交付这一件/一个姿势，不把同组其他素材、姿势或裁切线画进本图，不拼成多格图集。 【状态】IDLE / WORKING / BREACHED 【参考】附图 REF_N02_CALM / REF_N02_BREACH。耄耋 已批准平静与失控定稿。如有前置定稿，必须保持同一造型、比例、线宽、服装和配色；拆件需另附已确认整身定稿图。 【画布】1024 × 1024 px，每张单独姿势/零件，共用 (512, 896) 根；尺寸不支持时保持比例生成，再后处理到目标尺寸。 【输出】本次仅一张单件 PNG，sRGB；真实 Alpha 透明背景；保持足够安全边距；尺寸修正、边缘清理、分层源文件及轴点记录由后处理制作。。只输出当前这一张；套组其余部分由其他任务分别完成。透明须为真实Alpha，禁止棋盘格。 【对齐】脚底地面中心；母版 (512, 896)，朝右；全部形态共享同一根节点。 另记录头颈、四肢、口部或钟针等实际旋转挂点。 【禁止】不做 3D、照片写实、厚涂油画、等距俯视、高饱和二次元、霓虹光污染、密集脏污；不加文字、数字、二维码、水印、游戏界面或棋盘格背景；不把动态状态、血条、范围、路径烘焙进图。 不要照片、3D 渲染、像素风、光滑矢量图标风或高饱和日漫；不要复制现成游戏的角色、脸型或官方 IP 素材；不要背景、文字、水印、UI、血条、黄色选中圈或攻击范围；不要以红色滤镜代替形变。 | E77: =生成规范!$B$9&CHAR(10)&素材需求!S22 -> 不做 3D、照片写实、厚涂油画、等距俯视、高饱和二次元、霓虹光污染、密集脏污；不加文字、数字、二维码、水印、游戏界面或棋盘格背景；不把动态状态、血条、范围、路径烘焙进图。 不要照片、3D 渲染、像素风、光滑矢量图标风或高饱和日漫；不要复制现成游戏的角色、脸型或官方 IP 素材；不要背景、文字、水印、UI、血条、黄色选中圈或攻击范围；不要以红色滤镜代替形变。 | F77: REF_N02_CALM / REF_N02_BREACH | G77: =素材需求!B22 -> P0 | H77: 1024 × 1024 px，每张单独姿势/零件，共用 (512, 896) 根 | I77: 本次只画耄耋常态右短前肢和爪掌，肩根补全；只交这一独立单元，不画其他零件、对照姿、sheet、文字或背景。保持主表指定造型、朝向与挂点。 | J77: 本次仅一张单件 PNG，sRGB；真实 Alpha 透明背景；保持足够安全边距；尺寸修正、边缘清理、分层源文件及轴点记录由后处理制作。 | K77: 脚底地面中心；母版 (512, 896)，朝右；全部形态共享同一根节点。 另记录头颈、四肢、口部或钟针等实际旋转挂点。 | L77: art_delivery/v1/abnormalities/ | M77: 待生成 | N77: ABN_N02_01 / ABN_N02_03
A78: ABN_N02_04 | B78: abn_maodie_parts_01_breach_arm_left.png | C78: 耄耋左伸长前肢 | D78: ="【唯一交付文件】"&B78&CHAR(10)&"【对象】"&C78&CHAR(10)&生成规范!$B$8&CHAR(10)&"【同组设计标准，仅作一致性约束】"&素材需求!G22&CHAR(10)&"【本次只画】"&I78&"；本次只交付这一件/一个姿势，不把同组其他素材、姿势或裁切线画进本图，不拼成多格图集。"&CHAR(10)&"【状态】"&素材需求!F22&CHAR(10)&"【参考】附图 "&F78&"。"&素材需求!H22&"。如有前置定稿，必须保持同一造型、比例、线宽、服装和配色；拆件需另附已确认整身定稿图。"&CHAR(10)&"【画布】"&H78&"；尺寸不支持时保持比例生成，再后处理到目标尺寸。"&CHAR(10)&"【输出】"&J78&"。只输出当前这一张；套组其余部分由其他任务分别完成。透明须为真实Alpha，禁止棋盘格。"&CHAR(10)&"【对齐】"&K78&CHAR(10)&"【禁止】"&E78 -> 【唯一交付文件】abn_maodie_parts_01_breach_arm_left.png 【对象】耄耋左伸长前肢 原创二维地下工业收容设施游戏美术；怪诞手绘收容风，受手绘怪诞生存童话的表现原则启发。hand-drawn, ink-outline, slightly grotesque, whimsical horror, 2D cutout-friendly。粗细有变化的深墨轮廓，轻微不规则手绘线，大面积低饱和平涂，少量刻线阴影；剪影与动作优先于纹理。正交二维侧视角色/设施，UI为正视平面。保留对象身份，统一视觉语言，不复制其他作品具体资产。 【同组设计标准，仅作一致性约束】常态躯干 1、伸长躯干 1、头含耳 1、平静眼口组 1、失控眼口组 1、短前肢 2、伸长前肢 2、后足 2、尾 1，共 12 件。伸长肢体为形态替换件，肩/髋根节点一致。 沿用两份已批准定稿的线宽与体积，关节背面补全；可复用部位只交一份，不为每个动作复制整身。完整定稿仅作组合校对，不额外计独立交付单位。 以上为整套构成；每次只生成 「逐张提示词」本张范围 指定的一个独立件，不画整套平铺图。 【本次只画】本次只画耄耋失控左侧细长折角前肢和外伸爪，肩根与常态对齐；只交这一独立单元，不画其他零件、对照姿、sheet、文字或背景。保持主表指定造型、朝向与挂点。；本次只交付这一件/一个姿势，不把同组其他素材、姿势或裁切线画进本图，不拼成多格图集。 【状态】IDLE / WORKING / BREACHED 【参考】附图 REF_N02_CALM / REF_N02_BREACH。耄耋 已批准平静与失控定稿。如有前置定稿，必须保持同一造型、比例、线宽、服装和配色；拆件需另附已确认整身定稿图。 【画布】1024 × 1024 px，每张单独姿势/零件，共用 (512, 896) 根；尺寸不支持时保持比例生成，再后处理到目标尺寸。 【输出】本次仅一张单件 PNG，sRGB；真实 Alpha 透明背景；保持足够安全边距；尺寸修正、边缘清理、分层源文件及轴点记录由后处理制作。。只输出当前这一张；套组其余部分由其他任务分别完成。透明须为真实Alpha，禁止棋盘格。 【对齐】脚底地面中心；母版 (512, 896)，朝右；全部形态共享同一根节点。 另记录头颈、四肢、口部或钟针等实际旋转挂点。 【禁止】不做 3D、照片写实、厚涂油画、等距俯视、高饱和二次元、霓虹光污染、密集脏污；不加文字、数字、二维码、水印、游戏界面或棋盘格背景；不把动态状态、血条、范围、路径烘焙进图。 不要照片、3D 渲染、像素风、光滑矢量图标风或高饱和日漫；不要复制现成游戏的角色、脸型或官方 IP 素材；不要背景、文字、水印、UI、血条、黄色选中圈或攻击范围；不要以红色滤镜代替形变。 | E78: =生成规范!$B$9&CHAR(10)&素材需求!S22 -> 不做 3D、照片写实、厚涂油画、等距俯视、高饱和二次元、霓虹光污染、密集脏污；不加文字、数字、二维码、水印、游戏界面或棋盘格背景；不把动态状态、血条、范围、路径烘焙进图。 不要照片、3D 渲染、像素风、光滑矢量图标风或高饱和日漫；不要复制现成游戏的角色、脸型或官方 IP 素材；不要背景、文字、水印、UI、血条、黄色选中圈或攻击范围；不要以红色滤镜代替形变。 | F78: REF_N02_CALM / REF_N02_BREACH | G78: =素材需求!B22 -> P0 | H78: 1024 × 1024 px，每张单独姿势/零件，共用 (512, 896) 根 | I78: 本次只画耄耋失控左侧细长折角前肢和外伸爪，肩根与常态对齐；只交这一独立单元，不画其他零件、对照姿、sheet、文字或背景。保持主表指定造型、朝向与挂点。 | J78: 本次仅一张单件 PNG，sRGB；真实 Alpha 透明背景；保持足够安全边距；尺寸修正、边缘清理、分层源文件及轴点记录由后处理制作。 | K78: 脚底地面中心；母版 (512, 896)，朝右；全部形态共享同一根节点。 另记录头颈、四肢、口部或钟针等实际旋转挂点。 | L78: art_delivery/v1/abnormalities/ | M78: 待生成 | N78: ABN_N02_01 / ABN_N02_03
A79: ABN_N02_04 | B79: abn_maodie_parts_01_breach_arm_right.png | C79: 耄耋右伸长前肢 | D79: ="【唯一交付文件】"&B79&CHAR(10)&"【对象】"&C79&CHAR(10)&生成规范!$B$8&CHAR(10)&"【同组设计标准，仅作一致性约束】"&素材需求!G22&CHAR(10)&"【本次只画】"&I79&"；本次只交付这一件/一个姿势，不把同组其他素材、姿势或裁切线画进本图，不拼成多格图集。"&CHAR(10)&"【状态】"&素材需求!F22&CHAR(10)&"【参考】附图 "&F79&"。"&素材需求!H22&"。如有前置定稿，必须保持同一造型、比例、线宽、服装和配色；拆件需另附已确认整身定稿图。"&CHAR(10)&"【画布】"&H79&"；尺寸不支持时保持比例生成，再后处理到目标尺寸。"&CHAR(10)&"【输出】"&J79&"。只输出当前这一张；套组其余部分由其他任务分别完成。透明须为真实Alpha，禁止棋盘格。"&CHAR(10)&"【对齐】"&K79&CHAR(10)&"【禁止】"&E79 -> 【唯一交付文件】abn_maodie_parts_01_breach_arm_right.png 【对象】耄耋右伸长前肢 原创二维地下工业收容设施游戏美术；怪诞手绘收容风，受手绘怪诞生存童话的表现原则启发。hand-drawn, ink-outline, slightly grotesque, whimsical horror, 2D cutout-friendly。粗细有变化的深墨轮廓，轻微不规则手绘线，大面积低饱和平涂，少量刻线阴影；剪影与动作优先于纹理。正交二维侧视角色/设施，UI为正视平面。保留对象身份，统一视觉语言，不复制其他作品具体资产。 【同组设计标准，仅作一致性约束】常态躯干 1、伸长躯干 1、头含耳 1、平静眼口组 1、失控眼口组 1、短前肢 2、伸长前肢 2、后足 2、尾 1，共 12 件。伸长肢体为形态替换件，肩/髋根节点一致。 沿用两份已批准定稿的线宽与体积，关节背面补全；可复用部位只交一份，不为每个动作复制整身。完整定稿仅作组合校对，不额外计独立交付单位。 以上为整套构成；每次只生成 「逐张提示词」本张范围 指定的一个独立件，不画整套平铺图。 【本次只画】本次只画耄耋失控右侧细长折角前肢和外伸爪，肩根与常态对齐；只交这一独立单元，不画其他零件、对照姿、sheet、文字或背景。保持主表指定造型、朝向与挂点。；本次只交付这一件/一个姿势，不把同组其他素材、姿势或裁切线画进本图，不拼成多格图集。 【状态】IDLE / WORKING / BREACHED 【参考】附图 REF_N02_CALM / REF_N02_BREACH。耄耋 已批准平静与失控定稿。如有前置定稿，必须保持同一造型、比例、线宽、服装和配色；拆件需另附已确认整身定稿图。 【画布】1024 × 1024 px，每张单独姿势/零件，共用 (512, 896) 根；尺寸不支持时保持比例生成，再后处理到目标尺寸。 【输出】本次仅一张单件 PNG，sRGB；真实 Alpha 透明背景；保持足够安全边距；尺寸修正、边缘清理、分层源文件及轴点记录由后处理制作。。只输出当前这一张；套组其余部分由其他任务分别完成。透明须为真实Alpha，禁止棋盘格。 【对齐】脚底地面中心；母版 (512, 896)，朝右；全部形态共享同一根节点。 另记录头颈、四肢、口部或钟针等实际旋转挂点。 【禁止】不做 3D、照片写实、厚涂油画、等距俯视、高饱和二次元、霓虹光污染、密集脏污；不加文字、数字、二维码、水印、游戏界面或棋盘格背景；不把动态状态、血条、范围、路径烘焙进图。 不要照片、3D 渲染、像素风、光滑矢量图标风或高饱和日漫；不要复制现成游戏的角色、脸型或官方 IP 素材；不要背景、文字、水印、UI、血条、黄色选中圈或攻击范围；不要以红色滤镜代替形变。 | E79: =生成规范!$B$9&CHAR(10)&素材需求!S22 -> 不做 3D、照片写实、厚涂油画、等距俯视、高饱和二次元、霓虹光污染、密集脏污；不加文字、数字、二维码、水印、游戏界面或棋盘格背景；不把动态状态、血条、范围、路径烘焙进图。 不要照片、3D 渲染、像素风、光滑矢量图标风或高饱和日漫；不要复制现成游戏的角色、脸型或官方 IP 素材；不要背景、文字、水印、UI、血条、黄色选中圈或攻击范围；不要以红色滤镜代替形变。 | F79: REF_N02_CALM / REF_N02_BREACH | G79: =素材需求!B22 -> P0 | H79: 1024 × 1024 px，每张单独姿势/零件，共用 (512, 896) 根 | I79: 本次只画耄耋失控右侧细长折角前肢和外伸爪，肩根与常态对齐；只交这一独立单元，不画其他零件、对照姿、sheet、文字或背景。保持主表指定造型、朝向与挂点。 | J79: 本次仅一张单件 PNG，sRGB；真实 Alpha 透明背景；保持足够安全边距；尺寸修正、边缘清理、分层源文件及轴点记录由后处理制作。 | K79: 脚底地面中心；母版 (512, 896)，朝右；全部形态共享同一根节点。 另记录头颈、四肢、口部或钟针等实际旋转挂点。 | L79: art_delivery/v1/abnormalities/ | M79: 待生成 | N79: ABN_N02_01 / ABN_N02_03
A80: ABN_N02_04 | B80: abn_maodie_parts_01_hind_foot_left.png | C80: 耄耋左后足 | D80: ="【唯一交付文件】"&B80&CHAR(10)&"【对象】"&C80&CHAR(10)&生成规范!$B$8&CHAR(10)&"【同组设计标准，仅作一致性约束】"&素材需求!G22&CHAR(10)&"【本次只画】"&I80&"；本次只交付这一件/一个姿势，不把同组其他素材、姿势或裁切线画进本图，不拼成多格图集。"&CHAR(10)&"【状态】"&素材需求!F22&CHAR(10)&"【参考】附图 "&F80&"。"&素材需求!H22&"。如有前置定稿，必须保持同一造型、比例、线宽、服装和配色；拆件需另附已确认整身定稿图。"&CHAR(10)&"【画布】"&H80&"；尺寸不支持时保持比例生成，再后处理到目标尺寸。"&CHAR(10)&"【输出】"&J80&"。只输出当前这一张；套组其余部分由其他任务分别完成。透明须为真实Alpha，禁止棋盘格。"&CHAR(10)&"【对齐】"&K80&CHAR(10)&"【禁止】"&E80 -> 【唯一交付文件】abn_maodie_parts_01_hind_foot_left.png 【对象】耄耋左后足 原创二维地下工业收容设施游戏美术；怪诞手绘收容风，受手绘怪诞生存童话的表现原则启发。hand-drawn, ink-outline, slightly grotesque, whimsical horror, 2D cutout-friendly。粗细有变化的深墨轮廓，轻微不规则手绘线，大面积低饱和平涂，少量刻线阴影；剪影与动作优先于纹理。正交二维侧视角色/设施，UI为正视平面。保留对象身份，统一视觉语言，不复制其他作品具体资产。 【同组设计标准，仅作一致性约束】常态躯干 1、伸长躯干 1、头含耳 1、平静眼口组 1、失控眼口组 1、短前肢 2、伸长前肢 2、后足 2、尾 1，共 12 件。伸长肢体为形态替换件，肩/髋根节点一致。 沿用两份已批准定稿的线宽与体积，关节背面补全；可复用部位只交一份，不为每个动作复制整身。完整定稿仅作组合校对，不额外计独立交付单位。 以上为整套构成；每次只生成 「逐张提示词」本张范围 指定的一个独立件，不画整套平铺图。 【本次只画】本次只画耄耋灰绿左后足，短而扁；只交这一独立单元，不画其他零件、对照姿、sheet、文字或背景。保持主表指定造型、朝向与挂点。；本次只交付这一件/一个姿势，不把同组其他素材、姿势或裁切线画进本图，不拼成多格图集。 【状态】IDLE / WORKING / BREACHED 【参考】附图 REF_N02_CALM / REF_N02_BREACH。耄耋 已批准平静与失控定稿。如有前置定稿，必须保持同一造型、比例、线宽、服装和配色；拆件需另附已确认整身定稿图。 【画布】1024 × 1024 px，每张单独姿势/零件，共用 (512, 896) 根；尺寸不支持时保持比例生成，再后处理到目标尺寸。 【输出】本次仅一张单件 PNG，sRGB；真实 Alpha 透明背景；保持足够安全边距；尺寸修正、边缘清理、分层源文件及轴点记录由后处理制作。。只输出当前这一张；套组其余部分由其他任务分别完成。透明须为真实Alpha，禁止棋盘格。 【对齐】脚底地面中心；母版 (512, 896)，朝右；全部形态共享同一根节点。 另记录头颈、四肢、口部或钟针等实际旋转挂点。 【禁止】不做 3D、照片写实、厚涂油画、等距俯视、高饱和二次元、霓虹光污染、密集脏污；不加文字、数字、二维码、水印、游戏界面或棋盘格背景；不把动态状态、血条、范围、路径烘焙进图。 不要照片、3D 渲染、像素风、光滑矢量图标风或高饱和日漫；不要复制现成游戏的角色、脸型或官方 IP 素材；不要背景、文字、水印、UI、血条、黄色选中圈或攻击范围；不要以红色滤镜代替形变。 | E80: =生成规范!$B$9&CHAR(10)&素材需求!S22 -> 不做 3D、照片写实、厚涂油画、等距俯视、高饱和二次元、霓虹光污染、密集脏污；不加文字、数字、二维码、水印、游戏界面或棋盘格背景；不把动态状态、血条、范围、路径烘焙进图。 不要照片、3D 渲染、像素风、光滑矢量图标风或高饱和日漫；不要复制现成游戏的角色、脸型或官方 IP 素材；不要背景、文字、水印、UI、血条、黄色选中圈或攻击范围；不要以红色滤镜代替形变。 | F80: REF_N02_CALM / REF_N02_BREACH | G80: =素材需求!B22 -> P0 | H80: 1024 × 1024 px，每张单独姿势/零件，共用 (512, 896) 根 | I80: 本次只画耄耋灰绿左后足，短而扁；只交这一独立单元，不画其他零件、对照姿、sheet、文字或背景。保持主表指定造型、朝向与挂点。 | J80: 本次仅一张单件 PNG，sRGB；真实 Alpha 透明背景；保持足够安全边距；尺寸修正、边缘清理、分层源文件及轴点记录由后处理制作。 | K80: 脚底地面中心；母版 (512, 896)，朝右；全部形态共享同一根节点。 另记录头颈、四肢、口部或钟针等实际旋转挂点。 | L80: art_delivery/v1/abnormalities/ | M80: 待生成 | N80: ABN_N02_01 / ABN_N02_03
A81: ABN_N02_04 | B81: abn_maodie_parts_01_hind_foot_right.png | C81: 耄耋右后足 | D81: ="【唯一交付文件】"&B81&CHAR(10)&"【对象】"&C81&CHAR(10)&生成规范!$B$8&CHAR(10)&"【同组设计标准，仅作一致性约束】"&素材需求!G22&CHAR(10)&"【本次只画】"&I81&"；本次只交付这一件/一个姿势，不把同组其他素材、姿势或裁切线画进本图，不拼成多格图集。"&CHAR(10)&"【状态】"&素材需求!F22&CHAR(10)&"【参考】附图 "&F81&"。"&素材需求!H22&"。如有前置定稿，必须保持同一造型、比例、线宽、服装和配色；拆件需另附已确认整身定稿图。"&CHAR(10)&"【画布】"&H81&"；尺寸不支持时保持比例生成，再后处理到目标尺寸。"&CHAR(10)&"【输出】"&J81&"。只输出当前这一张；套组其余部分由其他任务分别完成。透明须为真实Alpha，禁止棋盘格。"&CHAR(10)&"【对齐】"&K81&CHAR(10)&"【禁止】"&E81 -> 【唯一交付文件】abn_maodie_parts_01_hind_foot_right.png 【对象】耄耋右后足 原创二维地下工业收容设施游戏美术；怪诞手绘收容风，受手绘怪诞生存童话的表现原则启发。hand-drawn, ink-outline, slightly grotesque, whimsical horror, 2D cutout-friendly。粗细有变化的深墨轮廓，轻微不规则手绘线，大面积低饱和平涂，少量刻线阴影；剪影与动作优先于纹理。正交二维侧视角色/设施，UI为正视平面。保留对象身份，统一视觉语言，不复制其他作品具体资产。 【同组设计标准，仅作一致性约束】常态躯干 1、伸长躯干 1、头含耳 1、平静眼口组 1、失控眼口组 1、短前肢 2、伸长前肢 2、后足 2、尾 1，共 12 件。伸长肢体为形态替换件，肩/髋根节点一致。 沿用两份已批准定稿的线宽与体积，关节背面补全；可复用部位只交一份，不为每个动作复制整身。完整定稿仅作组合校对，不额外计独立交付单位。 以上为整套构成；每次只生成 「逐张提示词」本张范围 指定的一个独立件，不画整套平铺图。 【本次只画】本次只画耄耋灰绿右后足，短而扁；只交这一独立单元，不画其他零件、对照姿、sheet、文字或背景。保持主表指定造型、朝向与挂点。；本次只交付这一件/一个姿势，不把同组其他素材、姿势或裁切线画进本图，不拼成多格图集。 【状态】IDLE / WORKING / BREACHED 【参考】附图 REF_N02_CALM / REF_N02_BREACH。耄耋 已批准平静与失控定稿。如有前置定稿，必须保持同一造型、比例、线宽、服装和配色；拆件需另附已确认整身定稿图。 【画布】1024 × 1024 px，每张单独姿势/零件，共用 (512, 896) 根；尺寸不支持时保持比例生成，再后处理到目标尺寸。 【输出】本次仅一张单件 PNG，sRGB；真实 Alpha 透明背景；保持足够安全边距；尺寸修正、边缘清理、分层源文件及轴点记录由后处理制作。。只输出当前这一张；套组其余部分由其他任务分别完成。透明须为真实Alpha，禁止棋盘格。 【对齐】脚底地面中心；母版 (512, 896)，朝右；全部形态共享同一根节点。 另记录头颈、四肢、口部或钟针等实际旋转挂点。 【禁止】不做 3D、照片写实、厚涂油画、等距俯视、高饱和二次元、霓虹光污染、密集脏污；不加文字、数字、二维码、水印、游戏界面或棋盘格背景；不把动态状态、血条、范围、路径烘焙进图。 不要照片、3D 渲染、像素风、光滑矢量图标风或高饱和日漫；不要复制现成游戏的角色、脸型或官方 IP 素材；不要背景、文字、水印、UI、血条、黄色选中圈或攻击范围；不要以红色滤镜代替形变。 | E81: =生成规范!$B$9&CHAR(10)&素材需求!S22 -> 不做 3D、照片写实、厚涂油画、等距俯视、高饱和二次元、霓虹光污染、密集脏污；不加文字、数字、二维码、水印、游戏界面或棋盘格背景；不把动态状态、血条、范围、路径烘焙进图。 不要照片、3D 渲染、像素风、光滑矢量图标风或高饱和日漫；不要复制现成游戏的角色、脸型或官方 IP 素材；不要背景、文字、水印、UI、血条、黄色选中圈或攻击范围；不要以红色滤镜代替形变。 | F81: REF_N02_CALM / REF_N02_BREACH | G81: =素材需求!B22 -> P0 | H81: 1024 × 1024 px，每张单独姿势/零件，共用 (512, 896) 根 | I81: 本次只画耄耋灰绿右后足，短而扁；只交这一独立单元，不画其他零件、对照姿、sheet、文字或背景。保持主表指定造型、朝向与挂点。 | J81: 本次仅一张单件 PNG，sRGB；真实 Alpha 透明背景；保持足够安全边距；尺寸修正、边缘清理、分层源文件及轴点记录由后处理制作。 | K81: 脚底地面中心；母版 (512, 896)，朝右；全部形态共享同一根节点。 另记录头颈、四肢、口部或钟针等实际旋转挂点。 | L81: art_delivery/v1/abnormalities/ | M81: 待生成 | N81: ABN_N02_01 / ABN_N02_03
A82: ABN_N02_04 | B82: abn_maodie_parts_01_tail.png | C82: 耄耋折尾 | D82: ="【唯一交付文件】"&B82&CHAR(10)&"【对象】"&C82&CHAR(10)&生成规范!$B$8&CHAR(10)&"【同组设计标准，仅作一致性约束】"&素材需求!G22&CHAR(10)&"【本次只画】"&I82&"；本次只交付这一件/一个姿势，不把同组其他素材、姿势或裁切线画进本图，不拼成多格图集。"&CHAR(10)&"【状态】"&素材需求!F22&CHAR(10)&"【参考】附图 "&F82&"。"&素材需求!H22&"。如有前置定稿，必须保持同一造型、比例、线宽、服装和配色；拆件需另附已确认整身定稿图。"&CHAR(10)&"【画布】"&H82&"；尺寸不支持时保持比例生成，再后处理到目标尺寸。"&CHAR(10)&"【输出】"&J82&"。只输出当前这一张；套组其余部分由其他任务分别完成。透明须为真实Alpha，禁止棋盘格。"&CHAR(10)&"【对齐】"&K82&CHAR(10)&"【禁止】"&E82 -> 【唯一交付文件】abn_maodie_parts_01_tail.png 【对象】耄耋折尾 原创二维地下工业收容设施游戏美术；怪诞手绘收容风，受手绘怪诞生存童话的表现原则启发。hand-drawn, ink-outline, slightly grotesque, whimsical horror, 2D cutout-friendly。粗细有变化的深墨轮廓，轻微不规则手绘线，大面积低饱和平涂，少量刻线阴影；剪影与动作优先于纹理。正交二维侧视角色/设施，UI为正视平面。保留对象身份，统一视觉语言，不复制其他作品具体资产。 【同组设计标准，仅作一致性约束】常态躯干 1、伸长躯干 1、头含耳 1、平静眼口组 1、失控眼口组 1、短前肢 2、伸长前肢 2、后足 2、尾 1，共 12 件。伸长肢体为形态替换件，肩/髋根节点一致。 沿用两份已批准定稿的线宽与体积，关节背面补全；可复用部位只交一份，不为每个动作复制整身。完整定稿仅作组合校对，不额外计独立交付单位。 以上为整套构成；每次只生成 「逐张提示词」本张范围 指定的一个独立件，不画整套平铺图。 【本次只画】本次只画耄耋灰绿弯折尾，折角清楚，补全尾根；只交这一独立单元，不画其他零件、对照姿、sheet、文字或背景。保持主表指定造型、朝向与挂点。；本次只交付这一件/一个姿势，不把同组其他素材、姿势或裁切线画进本图，不拼成多格图集。 【状态】IDLE / WORKING / BREACHED 【参考】附图 REF_N02_CALM / REF_N02_BREACH。耄耋 已批准平静与失控定稿。如有前置定稿，必须保持同一造型、比例、线宽、服装和配色；拆件需另附已确认整身定稿图。 【画布】1024 × 1024 px，每张单独姿势/零件，共用 (512, 896) 根；尺寸不支持时保持比例生成，再后处理到目标尺寸。 【输出】本次仅一张单件 PNG，sRGB；真实 Alpha 透明背景；保持足够安全边距；尺寸修正、边缘清理、分层源文件及轴点记录由后处理制作。。只输出当前这一张；套组其余部分由其他任务分别完成。透明须为真实Alpha，禁止棋盘格。 【对齐】脚底地面中心；母版 (512, 896)，朝右；全部形态共享同一根节点。 另记录头颈、四肢、口部或钟针等实际旋转挂点。 【禁止】不做 3D、照片写实、厚涂油画、等距俯视、高饱和二次元、霓虹光污染、密集脏污；不加文字、数字、二维码、水印、游戏界面或棋盘格背景；不把动态状态、血条、范围、路径烘焙进图。 不要照片、3D 渲染、像素风、光滑矢量图标风或高饱和日漫；不要复制现成游戏的角色、脸型或官方 IP 素材；不要背景、文字、水印、UI、血条、黄色选中圈或攻击范围；不要以红色滤镜代替形变。 | E82: =生成规范!$B$9&CHAR(10)&素材需求!S22 -> 不做 3D、照片写实、厚涂油画、等距俯视、高饱和二次元、霓虹光污染、密集脏污；不加文字、数字、二维码、水印、游戏界面或棋盘格背景；不把动态状态、血条、范围、路径烘焙进图。 不要照片、3D 渲染、像素风、光滑矢量图标风或高饱和日漫；不要复制现成游戏的角色、脸型或官方 IP 素材；不要背景、文字、水印、UI、血条、黄色选中圈或攻击范围；不要以红色滤镜代替形变。 | F82: REF_N02_CALM / REF_N02_BREACH | G82: =素材需求!B22 -> P0 | H82: 1024 × 1024 px，每张单独姿势/零件，共用 (512, 896) 根 | I82: 本次只画耄耋灰绿弯折尾，折角清楚，补全尾根；只交这一独立单元，不画其他零件、对照姿、sheet、文字或背景。保持主表指定造型、朝向与挂点。 | J82: 本次仅一张单件 PNG，sRGB；真实 Alpha 透明背景；保持足够安全边距；尺寸修正、边缘清理、分层源文件及轴点记录由后处理制作。 | K82: 脚底地面中心；母版 (512, 896)，朝右；全部形态共享同一根节点。 另记录头颈、四肢、口部或钟针等实际旋转挂点。 | L82: art_delivery/v1/abnormalities/ | M82: 待生成 | N82: ABN_N02_01 / ABN_N02_03
A83: ABN_N02_05 | B83: abn_maodie_combat_reference_01_walk_left.png | C83: 耄耋 左足支撑 | D83: ="【唯一交付文件】"&B83&CHAR(10)&"【对象】"&C83&CHAR(10)&生成规范!$B$8&CHAR(10)&"【同组设计标准，仅作一致性约束】"&素材需求!G23&CHAR(10)&"【本次只画】"&I83&"；本次只交付这一件/一个姿势，不把同组其他素材、姿势或裁切线画进本图，不拼成多格图集。"&CHAR(10)&"【状态】"&素材需求!F23&CHAR(10)&"【参考】附图 "&F83&"。"&素材需求!H23&"。如有前置定稿，必须保持同一造型、比例、线宽、服装和配色；拆件需另附已确认整身定稿图。"&CHAR(10)&"【画布】"&H83&"；尺寸不支持时保持比例生成，再后处理到目标尺寸。"&CHAR(10)&"【输出】"&J83&"。只输出当前这一张；套组其余部分由其他任务分别完成。透明须为真实Alpha，禁止棋盘格。"&CHAR(10)&"【对齐】"&K83&CHAR(10)&"【禁止】"&E83 -> 【唯一交付文件】abn_maodie_combat_reference_01_walk_left.png 【对象】耄耋 左足支撑 原创二维地下工业收容设施游戏美术；怪诞手绘收容风，受手绘怪诞生存童话的表现原则启发。hand-drawn, ink-outline, slightly grotesque, whimsical horror, 2D cutout-friendly。粗细有变化的深墨轮廓，轻微不规则手绘线，大面积低饱和平涂，少量刻线阴影；剪影与动作优先于纹理。正交二维侧视角色/设施，UI为正视平面。保留对象身份，统一视觉语言，不复制其他作品具体资产。 【同组设计标准，仅作一致性约束】分别生成六个独立单姿：失控快速追赶左右支撑 2 姿、近身扑前的前摇 1 姿、前爪伸出命中 1 姿、收爪回稳 1 姿、受击扭肩 1 姿。长肢体始终连在躯干上；只做原地身体倾斜和爪击，不添加实际跳跃位移或新攻击范围。 每个独立交付文件只能含一个姿势；按 「逐张提示词」本张范围 逐张生成。 【本次只画】本次只画完整失控 耄耋 快速追赶的左侧足支撑姿，另一足准备前摆；只交这一独立单元，不画其他零件、对照姿、sheet、文字或背景。保持主表指定造型、朝向与挂点。；本次只交付这一件/一个姿势，不把同组其他素材、姿势或裁切线画进本图，不拼成多格图集。 【状态】MOVING / WINDUP / IMPACT / HURT 【参考】附图 REF_N02_CALM / REF_N02_BREACH。耄耋 已批准失控定稿与实际 attackPhase/impactRemaining/hurt。如有前置定稿，必须保持同一造型、比例、线宽、服装和配色；拆件需另附已确认整身定稿图。 【画布】1024 × 1024 px，每张单独姿势/零件，共用 (512, 896) 根；尺寸不支持时保持比例生成，再后处理到目标尺寸。 【输出】本次仅一张单件 PNG，sRGB；真实 Alpha 透明背景；保持足够安全边距；尺寸修正、边缘清理、分层源文件及轴点记录由后处理制作。。只输出当前这一张；套组其余部分由其他任务分别完成。透明须为真实Alpha，禁止棋盘格。 【对齐】每个主要姿势保持同一脚底注册点；行走仅示足部接触关系，不烘焙移动距离。 【禁止】不做 3D、照片写实、厚涂油画、等距俯视、高饱和二次元、霓虹光污染、密集脏污；不加文字、数字、二维码、水印、游戏界面或棋盘格背景；不把动态状态、血条、范围、路径烘焙进图。 不要照片、3D 渲染、像素风、光滑矢量图标风或高饱和日漫；不要复制现成游戏的角色、脸型或官方 IP 素材；不要背景、文字、水印、UI、血条、黄色选中圈或攻击范围；不要以红色滤镜代替形变。 | E83: =生成规范!$B$9&CHAR(10)&素材需求!S23 -> 不做 3D、照片写实、厚涂油画、等距俯视、高饱和二次元、霓虹光污染、密集脏污；不加文字、数字、二维码、水印、游戏界面或棋盘格背景；不把动态状态、血条、范围、路径烘焙进图。 不要照片、3D 渲染、像素风、光滑矢量图标风或高饱和日漫；不要复制现成游戏的角色、脸型或官方 IP 素材；不要背景、文字、水印、UI、血条、黄色选中圈或攻击范围；不要以红色滤镜代替形变。 | F83: REF_N02_CALM / REF_N02_BREACH | G83: =素材需求!B23 -> P0 | H83: 1024 × 1024 px，每张单独姿势/零件，共用 (512, 896) 根 | I83: 本次只画完整失控 耄耋 快速追赶的左侧足支撑姿，另一足准备前摆；只交这一独立单元，不画其他零件、对照姿、sheet、文字或背景。保持主表指定造型、朝向与挂点。 | J83: 本次仅一张单件 PNG，sRGB；真实 Alpha 透明背景；保持足够安全边距；尺寸修正、边缘清理、分层源文件及轴点记录由后处理制作。 | K83: 每个主要姿势保持同一脚底注册点；行走仅示足部接触关系，不烘焙移动距离。 | L83: art_delivery/v1/abnormalities/ | M83: 待生成 | N83: ABN_N02_03 / ABN_N02_04
A84: ABN_N02_05 | B84: abn_maodie_combat_reference_01_walk_right.png | C84: 耄耋 右足支撑 | D84: ="【唯一交付文件】"&B84&CHAR(10)&"【对象】"&C84&CHAR(10)&生成规范!$B$8&CHAR(10)&"【同组设计标准，仅作一致性约束】"&素材需求!G23&CHAR(10)&"【本次只画】"&I84&"；本次只交付这一件/一个姿势，不把同组其他素材、姿势或裁切线画进本图，不拼成多格图集。"&CHAR(10)&"【状态】"&素材需求!F23&CHAR(10)&"【参考】附图 "&F84&"。"&素材需求!H23&"。如有前置定稿，必须保持同一造型、比例、线宽、服装和配色；拆件需另附已确认整身定稿图。"&CHAR(10)&"【画布】"&H84&"；尺寸不支持时保持比例生成，再后处理到目标尺寸。"&CHAR(10)&"【输出】"&J84&"。只输出当前这一张；套组其余部分由其他任务分别完成。透明须为真实Alpha，禁止棋盘格。"&CHAR(10)&"【对齐】"&K84&CHAR(10)&"【禁止】"&E84 -> 【唯一交付文件】abn_maodie_combat_reference_01_walk_right.png 【对象】耄耋 右足支撑 原创二维地下工业收容设施游戏美术；怪诞手绘收容风，受手绘怪诞生存童话的表现原则启发。hand-drawn, ink-outline, slightly grotesque, whimsical horror, 2D cutout-friendly。粗细有变化的深墨轮廓，轻微不规则手绘线，大面积低饱和平涂，少量刻线阴影；剪影与动作优先于纹理。正交二维侧视角色/设施，UI为正视平面。保留对象身份，统一视觉语言，不复制其他作品具体资产。 【同组设计标准，仅作一致性约束】分别生成六个独立单姿：失控快速追赶左右支撑 2 姿、近身扑前的前摇 1 姿、前爪伸出命中 1 姿、收爪回稳 1 姿、受击扭肩 1 姿。长肢体始终连在躯干上；只做原地身体倾斜和爪击，不添加实际跳跃位移或新攻击范围。 每个独立交付文件只能含一个姿势；按 「逐张提示词」本张范围 逐张生成。 【本次只画】本次只画完整失控 耄耋 对应的右侧足支撑姿，与左支撑姿保持体积相同；只交这一独立单元，不画其他零件、对照姿、sheet、文字或背景。保持主表指定造型、朝向与挂点。；本次只交付这一件/一个姿势，不把同组其他素材、姿势或裁切线画进本图，不拼成多格图集。 【状态】MOVING / WINDUP / IMPACT / HURT 【参考】附图 REF_N02_CALM / REF_N02_BREACH。耄耋 已批准失控定稿与实际 attackPhase/impactRemaining/hurt。如有前置定稿，必须保持同一造型、比例、线宽、服装和配色；拆件需另附已确认整身定稿图。 【画布】1024 × 1024 px，每张单独姿势/零件，共用 (512, 896) 根；尺寸不支持时保持比例生成，再后处理到目标尺寸。 【输出】本次仅一张单件 PNG，sRGB；真实 Alpha 透明背景；保持足够安全边距；尺寸修正、边缘清理、分层源文件及轴点记录由后处理制作。。只输出当前这一张；套组其余部分由其他任务分别完成。透明须为真实Alpha，禁止棋盘格。 【对齐】每个主要姿势保持同一脚底注册点；行走仅示足部接触关系，不烘焙移动距离。 【禁止】不做 3D、照片写实、厚涂油画、等距俯视、高饱和二次元、霓虹光污染、密集脏污；不加文字、数字、二维码、水印、游戏界面或棋盘格背景；不把动态状态、血条、范围、路径烘焙进图。 不要照片、3D 渲染、像素风、光滑矢量图标风或高饱和日漫；不要复制现成游戏的角色、脸型或官方 IP 素材；不要背景、文字、水印、UI、血条、黄色选中圈或攻击范围；不要以红色滤镜代替形变。 | E84: =生成规范!$B$9&CHAR(10)&素材需求!S23 -> 不做 3D、照片写实、厚涂油画、等距俯视、高饱和二次元、霓虹光污染、密集脏污；不加文字、数字、二维码、水印、游戏界面或棋盘格背景；不把动态状态、血条、范围、路径烘焙进图。 不要照片、3D 渲染、像素风、光滑矢量图标风或高饱和日漫；不要复制现成游戏的角色、脸型或官方 IP 素材；不要背景、文字、水印、UI、血条、黄色选中圈或攻击范围；不要以红色滤镜代替形变。 | F84: REF_N02_CALM / REF_N02_BREACH | G84: =素材需求!B23 -> P0 | H84: 1024 × 1024 px，每张单独姿势/零件，共用 (512, 896) 根 | I84: 本次只画完整失控 耄耋 对应的右侧足支撑姿，与左支撑姿保持体积相同；只交这一独立单元，不画其他零件、对照姿、sheet、文字或背景。保持主表指定造型、朝向与挂点。 | J84: 本次仅一张单件 PNG，sRGB；真实 Alpha 透明背景；保持足够安全边距；尺寸修正、边缘清理、分层源文件及轴点记录由后处理制作。 | K84: 每个主要姿势保持同一脚底注册点；行走仅示足部接触关系，不烘焙移动距离。 | L84: art_delivery/v1/abnormalities/ | M84: 待生成 | N84: ABN_N02_03 / ABN_N02_04
A85: ABN_N02_05 | B85: abn_maodie_combat_reference_01_windup.png | C85: 耄耋 攻击前摇 | D85: ="【唯一交付文件】"&B85&CHAR(10)&"【对象】"&C85&CHAR(10)&生成规范!$B$8&CHAR(10)&"【同组设计标准，仅作一致性约束】"&素材需求!G23&CHAR(10)&"【本次只画】"&I85&"；本次只交付这一件/一个姿势，不把同组其他素材、姿势或裁切线画进本图，不拼成多格图集。"&CHAR(10)&"【状态】"&素材需求!F23&CHAR(10)&"【参考】附图 "&F85&"。"&素材需求!H23&"。如有前置定稿，必须保持同一造型、比例、线宽、服装和配色；拆件需另附已确认整身定稿图。"&CHAR(10)&"【画布】"&H85&"；尺寸不支持时保持比例生成，再后处理到目标尺寸。"&CHAR(10)&"【输出】"&J85&"。只输出当前这一张；套组其余部分由其他任务分别完成。透明须为真实Alpha，禁止棋盘格。"&CHAR(10)&"【对齐】"&K85&CHAR(10)&"【禁止】"&E85 -> 【唯一交付文件】abn_maodie_combat_reference_01_windup.png 【对象】耄耋 攻击前摇 原创二维地下工业收容设施游戏美术；怪诞手绘收容风，受手绘怪诞生存童话的表现原则启发。hand-drawn, ink-outline, slightly grotesque, whimsical horror, 2D cutout-friendly。粗细有变化的深墨轮廓，轻微不规则手绘线，大面积低饱和平涂，少量刻线阴影；剪影与动作优先于纹理。正交二维侧视角色/设施，UI为正视平面。保留对象身份，统一视觉语言，不复制其他作品具体资产。 【同组设计标准，仅作一致性约束】分别生成六个独立单姿：失控快速追赶左右支撑 2 姿、近身扑前的前摇 1 姿、前爪伸出命中 1 姿、收爪回稳 1 姿、受击扭肩 1 姿。长肢体始终连在躯干上；只做原地身体倾斜和爪击，不添加实际跳跃位移或新攻击范围。 每个独立交付文件只能含一个姿势；按 「逐张提示词」本张范围 逐张生成。 【本次只画】本次只画完整失控 耄耋 的攻击前摇姿：长前肢收回并准备伸出；脚底固定；只交这一独立单元，不画其他零件、对照姿、sheet、文字或背景。保持主表指定造型、朝向与挂点。；本次只交付这一件/一个姿势，不把同组其他素材、姿势或裁切线画进本图，不拼成多格图集。 【状态】MOVING / WINDUP / IMPACT / HURT 【参考】附图 REF_N02_CALM / REF_N02_BREACH。耄耋 已批准失控定稿与实际 attackPhase/impactRemaining/hurt。如有前置定稿，必须保持同一造型、比例、线宽、服装和配色；拆件需另附已确认整身定稿图。 【画布】1024 × 1024 px，每张单独姿势/零件，共用 (512, 896) 根；尺寸不支持时保持比例生成，再后处理到目标尺寸。 【输出】本次仅一张单件 PNG，sRGB；真实 Alpha 透明背景；保持足够安全边距；尺寸修正、边缘清理、分层源文件及轴点记录由后处理制作。。只输出当前这一张；套组其余部分由其他任务分别完成。透明须为真实Alpha，禁止棋盘格。 【对齐】每个主要姿势保持同一脚底注册点；行走仅示足部接触关系，不烘焙移动距离。 【禁止】不做 3D、照片写实、厚涂油画、等距俯视、高饱和二次元、霓虹光污染、密集脏污；不加文字、数字、二维码、水印、游戏界面或棋盘格背景；不把动态状态、血条、范围、路径烘焙进图。 不要照片、3D 渲染、像素风、光滑矢量图标风或高饱和日漫；不要复制现成游戏的角色、脸型或官方 IP 素材；不要背景、文字、水印、UI、血条、黄色选中圈或攻击范围；不要以红色滤镜代替形变。 | E85: =生成规范!$B$9&CHAR(10)&素材需求!S23 -> 不做 3D、照片写实、厚涂油画、等距俯视、高饱和二次元、霓虹光污染、密集脏污；不加文字、数字、二维码、水印、游戏界面或棋盘格背景；不把动态状态、血条、范围、路径烘焙进图。 不要照片、3D 渲染、像素风、光滑矢量图标风或高饱和日漫；不要复制现成游戏的角色、脸型或官方 IP 素材；不要背景、文字、水印、UI、血条、黄色选中圈或攻击范围；不要以红色滤镜代替形变。 | F85: REF_N02_CALM / REF_N02_BREACH | G85: =素材需求!B23 -> P0 | H85: 1024 × 1024 px，每张单独姿势/零件，共用 (512, 896) 根 | I85: 本次只画完整失控 耄耋 的攻击前摇姿：长前肢收回并准备伸出；脚底固定；只交这一独立单元，不画其他零件、对照姿、sheet、文字或背景。保持主表指定造型、朝向与挂点。 | J85: 本次仅一张单件 PNG，sRGB；真实 Alpha 透明背景；保持足够安全边距；尺寸修正、边缘清理、分层源文件及轴点记录由后处理制作。 | K85: 每个主要姿势保持同一脚底注册点；行走仅示足部接触关系，不烘焙移动距离。 | L85: art_delivery/v1/abnormalities/ | M85: 待生成 | N85: ABN_N02_03 / ABN_N02_04
A86: ABN_N02_05 | B86: abn_maodie_combat_reference_01_impact.png | C86: 耄耋 攻击释放 | D86: ="【唯一交付文件】"&B86&CHAR(10)&"【对象】"&C86&CHAR(10)&生成规范!$B$8&CHAR(10)&"【同组设计标准，仅作一致性约束】"&素材需求!G23&CHAR(10)&"【本次只画】"&I86&"；本次只交付这一件/一个姿势，不把同组其他素材、姿势或裁切线画进本图，不拼成多格图集。"&CHAR(10)&"【状态】"&素材需求!F23&CHAR(10)&"【参考】附图 "&F86&"。"&素材需求!H23&"。如有前置定稿，必须保持同一造型、比例、线宽、服装和配色；拆件需另附已确认整身定稿图。"&CHAR(10)&"【画布】"&H86&"；尺寸不支持时保持比例生成，再后处理到目标尺寸。"&CHAR(10)&"【输出】"&J86&"。只输出当前这一张；套组其余部分由其他任务分别完成。透明须为真实Alpha，禁止棋盘格。"&CHAR(10)&"【对齐】"&K86&CHAR(10)&"【禁止】"&E86 -> 【唯一交付文件】abn_maodie_combat_reference_01_impact.png 【对象】耄耋 攻击释放 原创二维地下工业收容设施游戏美术；怪诞手绘收容风，受手绘怪诞生存童话的表现原则启发。hand-drawn, ink-outline, slightly grotesque, whimsical horror, 2D cutout-friendly。粗细有变化的深墨轮廓，轻微不规则手绘线，大面积低饱和平涂，少量刻线阴影；剪影与动作优先于纹理。正交二维侧视角色/设施，UI为正视平面。保留对象身份，统一视觉语言，不复制其他作品具体资产。 【同组设计标准，仅作一致性约束】分别生成六个独立单姿：失控快速追赶左右支撑 2 姿、近身扑前的前摇 1 姿、前爪伸出命中 1 姿、收爪回稳 1 姿、受击扭肩 1 姿。长肢体始终连在躯干上；只做原地身体倾斜和爪击，不添加实际跳跃位移或新攻击范围。 每个独立交付文件只能含一个姿势；按 「逐张提示词」本张范围 逐张生成。 【本次只画】本次只画完整失控 耄耋 的攻击释放姿：一条长前爪明确伸出；不含范围特效或额外位移；只交这一独立单元，不画其他零件、对照姿、sheet、文字或背景。保持主表指定造型、朝向与挂点。；本次只交付这一件/一个姿势，不把同组其他素材、姿势或裁切线画进本图，不拼成多格图集。 【状态】MOVING / WINDUP / IMPACT / HURT 【参考】附图 REF_N02_CALM / REF_N02_BREACH。耄耋 已批准失控定稿与实际 attackPhase/impactRemaining/hurt。如有前置定稿，必须保持同一造型、比例、线宽、服装和配色；拆件需另附已确认整身定稿图。 【画布】1024 × 1024 px，每张单独姿势/零件，共用 (512, 896) 根；尺寸不支持时保持比例生成，再后处理到目标尺寸。 【输出】本次仅一张单件 PNG，sRGB；真实 Alpha 透明背景；保持足够安全边距；尺寸修正、边缘清理、分层源文件及轴点记录由后处理制作。。只输出当前这一张；套组其余部分由其他任务分别完成。透明须为真实Alpha，禁止棋盘格。 【对齐】每个主要姿势保持同一脚底注册点；行走仅示足部接触关系，不烘焙移动距离。 【禁止】不做 3D、照片写实、厚涂油画、等距俯视、高饱和二次元、霓虹光污染、密集脏污；不加文字、数字、二维码、水印、游戏界面或棋盘格背景；不把动态状态、血条、范围、路径烘焙进图。 不要照片、3D 渲染、像素风、光滑矢量图标风或高饱和日漫；不要复制现成游戏的角色、脸型或官方 IP 素材；不要背景、文字、水印、UI、血条、黄色选中圈或攻击范围；不要以红色滤镜代替形变。 | E86: =生成规范!$B$9&CHAR(10)&素材需求!S23 -> 不做 3D、照片写实、厚涂油画、等距俯视、高饱和二次元、霓虹光污染、密集脏污；不加文字、数字、二维码、水印、游戏界面或棋盘格背景；不把动态状态、血条、范围、路径烘焙进图。 不要照片、3D 渲染、像素风、光滑矢量图标风或高饱和日漫；不要复制现成游戏的角色、脸型或官方 IP 素材；不要背景、文字、水印、UI、血条、黄色选中圈或攻击范围；不要以红色滤镜代替形变。 | F86: REF_N02_CALM / REF_N02_BREACH | G86: =素材需求!B23 -> P0 | H86: 1024 × 1024 px，每张单独姿势/零件，共用 (512, 896) 根 | I86: 本次只画完整失控 耄耋 的攻击释放姿：一条长前爪明确伸出；不含范围特效或额外位移；只交这一独立单元，不画其他零件、对照姿、sheet、文字或背景。保持主表指定造型、朝向与挂点。 | J86: 本次仅一张单件 PNG，sRGB；真实 Alpha 透明背景；保持足够安全边距；尺寸修正、边缘清理、分层源文件及轴点记录由后处理制作。 | K86: 每个主要姿势保持同一脚底注册点；行走仅示足部接触关系，不烘焙移动距离。 | L86: art_delivery/v1/abnormalities/ | M86: 待生成 | N86: ABN_N02_03 / ABN_N02_04
A87: ABN_N02_05 | B87: abn_maodie_combat_reference_01_recover.png | C87: 耄耋 攻击收势 | D87: ="【唯一交付文件】"&B87&CHAR(10)&"【对象】"&C87&CHAR(10)&生成规范!$B$8&CHAR(10)&"【同组设计标准，仅作一致性约束】"&素材需求!G23&CHAR(10)&"【本次只画】"&I87&"；本次只交付这一件/一个姿势，不把同组其他素材、姿势或裁切线画进本图，不拼成多格图集。"&CHAR(10)&"【状态】"&素材需求!F23&CHAR(10)&"【参考】附图 "&F87&"。"&素材需求!H23&"。如有前置定稿，必须保持同一造型、比例、线宽、服装和配色；拆件需另附已确认整身定稿图。"&CHAR(10)&"【画布】"&H87&"；尺寸不支持时保持比例生成，再后处理到目标尺寸。"&CHAR(10)&"【输出】"&J87&"。只输出当前这一张；套组其余部分由其他任务分别完成。透明须为真实Alpha，禁止棋盘格。"&CHAR(10)&"【对齐】"&K87&CHAR(10)&"【禁止】"&E87 -> 【唯一交付文件】abn_maodie_combat_reference_01_recover.png 【对象】耄耋 攻击收势 原创二维地下工业收容设施游戏美术；怪诞手绘收容风，受手绘怪诞生存童话的表现原则启发。hand-drawn, ink-outline, slightly grotesque, whimsical horror, 2D cutout-friendly。粗细有变化的深墨轮廓，轻微不规则手绘线，大面积低饱和平涂，少量刻线阴影；剪影与动作优先于纹理。正交二维侧视角色/设施，UI为正视平面。保留对象身份，统一视觉语言，不复制其他作品具体资产。 【同组设计标准，仅作一致性约束】分别生成六个独立单姿：失控快速追赶左右支撑 2 姿、近身扑前的前摇 1 姿、前爪伸出命中 1 姿、收爪回稳 1 姿、受击扭肩 1 姿。长肢体始终连在躯干上；只做原地身体倾斜和爪击，不添加实际跳跃位移或新攻击范围。 每个独立交付文件只能含一个姿势；按 「逐张提示词」本张范围 逐张生成。 【本次只画】本次只画完整失控 耄耋 攻击后的身体收势，仍保持失控造型；只交这一独立单元，不画其他零件、对照姿、sheet、文字或背景。保持主表指定造型、朝向与挂点。；本次只交付这一件/一个姿势，不把同组其他素材、姿势或裁切线画进本图，不拼成多格图集。 【状态】MOVING / WINDUP / IMPACT / HURT 【参考】附图 REF_N02_CALM / REF_N02_BREACH。耄耋 已批准失控定稿与实际 attackPhase/impactRemaining/hurt。如有前置定稿，必须保持同一造型、比例、线宽、服装和配色；拆件需另附已确认整身定稿图。 【画布】1024 × 1024 px，每张单独姿势/零件，共用 (512, 896) 根；尺寸不支持时保持比例生成，再后处理到目标尺寸。 【输出】本次仅一张单件 PNG，sRGB；真实 Alpha 透明背景；保持足够安全边距；尺寸修正、边缘清理、分层源文件及轴点记录由后处理制作。。只输出当前这一张；套组其余部分由其他任务分别完成。透明须为真实Alpha，禁止棋盘格。 【对齐】每个主要姿势保持同一脚底注册点；行走仅示足部接触关系，不烘焙移动距离。 【禁止】不做 3D、照片写实、厚涂油画、等距俯视、高饱和二次元、霓虹光污染、密集脏污；不加文字、数字、二维码、水印、游戏界面或棋盘格背景；不把动态状态、血条、范围、路径烘焙进图。 不要照片、3D 渲染、像素风、光滑矢量图标风或高饱和日漫；不要复制现成游戏的角色、脸型或官方 IP 素材；不要背景、文字、水印、UI、血条、黄色选中圈或攻击范围；不要以红色滤镜代替形变。 | E87: =生成规范!$B$9&CHAR(10)&素材需求!S23 -> 不做 3D、照片写实、厚涂油画、等距俯视、高饱和二次元、霓虹光污染、密集脏污；不加文字、数字、二维码、水印、游戏界面或棋盘格背景；不把动态状态、血条、范围、路径烘焙进图。 不要照片、3D 渲染、像素风、光滑矢量图标风或高饱和日漫；不要复制现成游戏的角色、脸型或官方 IP 素材；不要背景、文字、水印、UI、血条、黄色选中圈或攻击范围；不要以红色滤镜代替形变。 | F87: REF_N02_CALM / REF_N02_BREACH | G87: =素材需求!B23 -> P0 | H87: 1024 × 1024 px，每张单独姿势/零件，共用 (512, 896) 根 | I87: 本次只画完整失控 耄耋 攻击后的身体收势，仍保持失控造型；只交这一独立单元，不画其他零件、对照姿、sheet、文字或背景。保持主表指定造型、朝向与挂点。 | J87: 本次仅一张单件 PNG，sRGB；真实 Alpha 透明背景；保持足够安全边距；尺寸修正、边缘清理、分层源文件及轴点记录由后处理制作。 | K87: 每个主要姿势保持同一脚底注册点；行走仅示足部接触关系，不烘焙移动距离。 | L87: art_delivery/v1/abnormalities/ | M87: 待生成 | N87: ABN_N02_03 / ABN_N02_04
A88: ABN_N02_05 | B88: abn_maodie_combat_reference_01_hit.png | C88: 耄耋 受击回缩 | D88: ="【唯一交付文件】"&B88&CHAR(10)&"【对象】"&C88&CHAR(10)&生成规范!$B$8&CHAR(10)&"【同组设计标准，仅作一致性约束】"&素材需求!G23&CHAR(10)&"【本次只画】"&I88&"；本次只交付这一件/一个姿势，不把同组其他素材、姿势或裁切线画进本图，不拼成多格图集。"&CHAR(10)&"【状态】"&素材需求!F23&CHAR(10)&"【参考】附图 "&F88&"。"&素材需求!H23&"。如有前置定稿，必须保持同一造型、比例、线宽、服装和配色；拆件需另附已确认整身定稿图。"&CHAR(10)&"【画布】"&H88&"；尺寸不支持时保持比例生成，再后处理到目标尺寸。"&CHAR(10)&"【输出】"&J88&"。只输出当前这一张；套组其余部分由其他任务分别完成。透明须为真实Alpha，禁止棋盘格。"&CHAR(10)&"【对齐】"&K88&CHAR(10)&"【禁止】"&E88 -> 【唯一交付文件】abn_maodie_combat_reference_01_hit.png 【对象】耄耋 受击回缩 原创二维地下工业收容设施游戏美术；怪诞手绘收容风，受手绘怪诞生存童话的表现原则启发。hand-drawn, ink-outline, slightly grotesque, whimsical horror, 2D cutout-friendly。粗细有变化的深墨轮廓，轻微不规则手绘线，大面积低饱和平涂，少量刻线阴影；剪影与动作优先于纹理。正交二维侧视角色/设施，UI为正视平面。保留对象身份，统一视觉语言，不复制其他作品具体资产。 【同组设计标准，仅作一致性约束】分别生成六个独立单姿：失控快速追赶左右支撑 2 姿、近身扑前的前摇 1 姿、前爪伸出命中 1 姿、收爪回稳 1 姿、受击扭肩 1 姿。长肢体始终连在躯干上；只做原地身体倾斜和爪击，不添加实际跳跃位移或新攻击范围。 每个独立交付文件只能含一个姿势；按 「逐张提示词」本张范围 逐张生成。 【本次只画】本次只画完整失控 耄耋 短促受击回缩姿，局部缩肩/扭身，不含新增伤口和死亡；只交这一独立单元，不画其他零件、对照姿、sheet、文字或背景。保持主表指定造型、朝向与挂点。；本次只交付这一件/一个姿势，不把同组其他素材、姿势或裁切线画进本图，不拼成多格图集。 【状态】MOVING / WINDUP / IMPACT / HURT 【参考】附图 REF_N02_CALM / REF_N02_BREACH。耄耋 已批准失控定稿与实际 attackPhase/impactRemaining/hurt。如有前置定稿，必须保持同一造型、比例、线宽、服装和配色；拆件需另附已确认整身定稿图。 【画布】1024 × 1024 px，每张单独姿势/零件，共用 (512, 896) 根；尺寸不支持时保持比例生成，再后处理到目标尺寸。 【输出】本次仅一张单件 PNG，sRGB；真实 Alpha 透明背景；保持足够安全边距；尺寸修正、边缘清理、分层源文件及轴点记录由后处理制作。。只输出当前这一张；套组其余部分由其他任务分别完成。透明须为真实Alpha，禁止棋盘格。 【对齐】每个主要姿势保持同一脚底注册点；行走仅示足部接触关系，不烘焙移动距离。 【禁止】不做 3D、照片写实、厚涂油画、等距俯视、高饱和二次元、霓虹光污染、密集脏污；不加文字、数字、二维码、水印、游戏界面或棋盘格背景；不把动态状态、血条、范围、路径烘焙进图。 不要照片、3D 渲染、像素风、光滑矢量图标风或高饱和日漫；不要复制现成游戏的角色、脸型或官方 IP 素材；不要背景、文字、水印、UI、血条、黄色选中圈或攻击范围；不要以红色滤镜代替形变。 | E88: =生成规范!$B$9&CHAR(10)&素材需求!S23 -> 不做 3D、照片写实、厚涂油画、等距俯视、高饱和二次元、霓虹光污染、密集脏污；不加文字、数字、二维码、水印、游戏界面或棋盘格背景；不把动态状态、血条、范围、路径烘焙进图。 不要照片、3D 渲染、像素风、光滑矢量图标风或高饱和日漫；不要复制现成游戏的角色、脸型或官方 IP 素材；不要背景、文字、水印、UI、血条、黄色选中圈或攻击范围；不要以红色滤镜代替形变。 | F88: REF_N02_CALM / REF_N02_BREACH | G88: =素材需求!B23 -> P0 | H88: 1024 × 1024 px，每张单独姿势/零件，共用 (512, 896) 根 | I88: 本次只画完整失控 耄耋 短促受击回缩姿，局部缩肩/扭身，不含新增伤口和死亡；只交这一独立单元，不画其他零件、对照姿、sheet、文字或背景。保持主表指定造型、朝向与挂点。 | J88: 本次仅一张单件 PNG，sRGB；真实 Alpha 透明背景；保持足够安全边距；尺寸修正、边缘清理、分层源文件及轴点记录由后处理制作。 | K88: 每个主要姿势保持同一脚底注册点；行走仅示足部接触关系，不烘焙移动距离。 | L88: art_delivery/v1/abnormalities/ | M88: 待生成 | N88: ABN_N02_03 / ABN_N02_04
A89: ABN_N03_01 | B89: abn_big_dog_idle_01_approved.png | C89: 大狗 平静定稿 | D89: ="【唯一交付文件】"&B89&CHAR(10)&"【对象】"&C89&CHAR(10)&生成规范!$B$8&CHAR(10)&"【同组设计标准，仅作一致性约束】"&素材需求!G24&CHAR(10)&"【本次只画】"&I89&"；本次只交付这一件/一个姿势，不把同组其他素材、姿势或裁切线画进本图，不拼成多格图集。"&CHAR(10)&"【状态】"&素材需求!F24&CHAR(10)&"【参考】附图 "&F89&"。"&素材需求!H24&"。如有前置定稿，必须保持同一造型、比例、线宽、服装和配色；拆件需另附已确认整身定稿图。"&CHAR(10)&"【画布】"&H89&"；尺寸不支持时保持比例生成，再后处理到目标尺寸。"&CHAR(10)&"【输出】"&J89&"。只输出当前这一张；套组其余部分由其他任务分别完成。透明须为真实Alpha，禁止棋盘格。"&CHAR(10)&"【对齐】"&K89&CHAR(10)&"【禁止】"&E89 -> 【唯一交付文件】abn_big_dog_idle_01_approved.png 【对象】大狗 平静定稿 原创二维地下工业收容设施游戏美术；怪诞手绘收容风，受手绘怪诞生存童话的表现原则启发。hand-drawn, ink-outline, slightly grotesque, whimsical horror, 2D cutout-friendly。粗细有变化的深墨轮廓，轻微不规则手绘线，大面积低饱和平涂，少量刻线阴影；剪影与动作优先于纹理。正交二维侧视角色/设施，UI为正视平面。保留对象身份，统一视觉语言，不复制其他作品具体资产。 【同组设计标准，仅作一致性约束】原创怪诞手绘收容风：不均匀粗墨外轮廓、较细结构线、局部不对称、平涂和少量排线；轮廓在游戏缩小尺寸仍清楚。 五物中最厚重、横向最宽；背低肩厚，四足犬形的侧面读法，钝重口鼻向前突出；一只折耳一只竖耳，锈红项圈和旧金小牌。毛色灰褐绿 #6c7065、深影 #484d47、口鼻米灰 #b6ae8b。脚掌宽而不尖，不能画成长腿狼。 侧视略带正脸可读性，所有部位围绕单一脚底根节点，不画房间。 【本次只画】本次只画一只完整平静 大狗，严格采用本行具体形状与三色群，不含动作对照或其他角色；只交这一独立单元，不画其他零件、对照姿、sheet、文字或背景。保持主表指定造型、朝向与挂点。；本次只交付这一件/一个姿势，不把同组其他素材、姿势或裁切线画进本图，不拼成多格图集。 【状态】CONTAINED / IDLE 【参考】附图 REF_N03_CALM。当前 大狗 室内未作业形态。如有前置定稿，必须保持同一造型、比例、线宽、服装和配色；拆件需另附已确认整身定稿图。 【画布】1536 × 1024 px（横向宽体）；尺寸不支持时保持比例生成，再后处理到目标尺寸。 【输出】1 个透明 RGBA PNG 定稿；主体完整、无底座、无环境阴影；附三色主色票说明。。只输出当前这一张；套组其余部分由其他任务分别完成。透明须为真实Alpha，禁止棋盘格。 【对齐】根节点为身体支撑投影的地面中心；母版 (768, 896)，朝右；口鼻可前伸但不移动根。 【禁止】不做 3D、照片写实、厚涂油画、等距俯视、高饱和二次元、霓虹光污染、密集脏污；不加文字、数字、二维码、水印、游戏界面或棋盘格背景；不把动态状态、血条、范围、路径烘焙进图。 不要照片、3D 渲染、像素风、光滑矢量图标风或高饱和日漫；不要复制现成游戏的角色、脸型或官方 IP 素材；不要背景、文字、水印、UI、血条、黄色选中圈或攻击范围；不要以红色滤镜代替形变。 | E89: =生成规范!$B$9&CHAR(10)&素材需求!S24 -> 不做 3D、照片写实、厚涂油画、等距俯视、高饱和二次元、霓虹光污染、密集脏污；不加文字、数字、二维码、水印、游戏界面或棋盘格背景；不把动态状态、血条、范围、路径烘焙进图。 不要照片、3D 渲染、像素风、光滑矢量图标风或高饱和日漫；不要复制现成游戏的角色、脸型或官方 IP 素材；不要背景、文字、水印、UI、血条、黄色选中圈或攻击范围；不要以红色滤镜代替形变。 | F89: REF_N03_CALM | G89: =素材需求!B24 -> P0 | H89: 1536 × 1024 px（横向宽体） | I89: 本次只画一只完整平静 大狗，严格采用本行具体形状与三色群，不含动作对照或其他角色；只交这一独立单元，不画其他零件、对照姿、sheet、文字或背景。保持主表指定造型、朝向与挂点。 | J89: 1 个透明 RGBA PNG 定稿；主体完整、无底座、无环境阴影；附三色主色票说明。 | K89: 根节点为身体支撑投影的地面中心；母版 (768, 896)，朝右；口鼻可前伸但不移动根。 | L89: art_delivery/v1/abnormalities/ | M89: 待生成 | N89: —
A90: ABN_N03_03 | B90: abn_big_dog_breach_01_approved.png | C90: 大狗 失控定稿 | D90: ="【唯一交付文件】"&B90&CHAR(10)&"【对象】"&C90&CHAR(10)&生成规范!$B$8&CHAR(10)&"【同组设计标准，仅作一致性约束】"&素材需求!G25&CHAR(10)&"【本次只画】"&I90&"；本次只交付这一件/一个姿势，不把同组其他素材、姿势或裁切线画进本图，不拼成多格图集。"&CHAR(10)&"【状态】"&素材需求!F25&CHAR(10)&"【参考】附图 "&F90&"。"&素材需求!H25&"。如有前置定稿，必须保持同一造型、比例、线宽、服装和配色；拆件需另附已确认整身定稿图。"&CHAR(10)&"【画布】"&H90&"；尺寸不支持时保持比例生成，再后处理到目标尺寸。"&CHAR(10)&"【输出】"&J90&"。只输出当前这一张；套组其余部分由其他任务分别完成。透明须为真实Alpha，禁止棋盘格。"&CHAR(10)&"【对齐】"&K90&CHAR(10)&"【禁止】"&E90 -> 【唯一交付文件】abn_big_dog_breach_01_approved.png 【对象】大狗 失控定稿 原创二维地下工业收容设施游戏美术；怪诞手绘收容风，受手绘怪诞生存童话的表现原则启发。hand-drawn, ink-outline, slightly grotesque, whimsical horror, 2D cutout-friendly。粗细有变化的深墨轮廓，轻微不规则手绘线，大面积低饱和平涂，少量刻线阴影；剪影与动作优先于纹理。正交二维侧视角色/设施，UI为正视平面。保留对象身份，统一视觉语言，不复制其他作品具体资产。 【同组设计标准，仅作一致性约束】原创怪诞手绘收容风：不均匀粗墨外轮廓、较细结构线、局部不对称、平涂和少量排线；轮廓在游戏缩小尺寸仍清楚。 保持重背、厚腿和项圈；口部扩大为向前凸出的巨大黑色空腔，上下颌张开，边缘稀疏大三角齿。头前的咬合轮廓比常态明显更宽更高；口内以深墨平涂，不画写实咽喉。前导影仅另层视觉示意，不能成为第二只狗。 【本次只画】本次只画一只完整失控 大狗 主体，严格体现本行眼口和轮廓变化；不含分身、重影、受控星标或范围；只交这一独立单元，不画其他零件、对照姿、sheet、文字或背景。保持主表指定造型、朝向与挂点。；本次只交付这一件/一个姿势，不把同组其他素材、姿势或裁切线画进本图，不拼成多格图集。 【状态】BREACHED 【参考】附图 REF_N03_CALM / REF_N03_BREACH。当前 大狗 真实 enemy 形态，对照其平静定稿。如有前置定稿，必须保持同一造型、比例、线宽、服装和配色；拆件需另附已确认整身定稿图。 【画布】1536 × 1024 px（横向宽体）；尺寸不支持时保持比例生成，再后处理到目标尺寸。 【输出】1 个透明 RGBA PNG 主体定稿；虚影/错帧效果仅放附属说明，实际主体不带不可拆多重残像。。只输出当前这一张；套组其余部分由其他任务分别完成。透明须为真实Alpha，禁止棋盘格。 【对齐】根节点为身体支撑投影的地面中心；母版 (768, 896)，朝右；口鼻可前伸但不移动根。 【禁止】不做 3D、照片写实、厚涂油画、等距俯视、高饱和二次元、霓虹光污染、密集脏污；不加文字、数字、二维码、水印、游戏界面或棋盘格背景；不把动态状态、血条、范围、路径烘焙进图。 不要照片、3D 渲染、像素风、光滑矢量图标风或高饱和日漫；不要复制现成游戏的角色、脸型或官方 IP 素材；不要背景、文字、水印、UI、血条、黄色选中圈或攻击范围；不要以红色滤镜代替形变。 | E90: =生成规范!$B$9&CHAR(10)&素材需求!S25 -> 不做 3D、照片写实、厚涂油画、等距俯视、高饱和二次元、霓虹光污染、密集脏污；不加文字、数字、二维码、水印、游戏界面或棋盘格背景；不把动态状态、血条、范围、路径烘焙进图。 不要照片、3D 渲染、像素风、光滑矢量图标风或高饱和日漫；不要复制现成游戏的角色、脸型或官方 IP 素材；不要背景、文字、水印、UI、血条、黄色选中圈或攻击范围；不要以红色滤镜代替形变。 | F90: REF_N03_CALM / REF_N03_BREACH | G90: =素材需求!B25 -> P0 | H90: 1536 × 1024 px（横向宽体） | I90: 本次只画一只完整失控 大狗 主体，严格体现本行眼口和轮廓变化；不含分身、重影、受控星标或范围；只交这一独立单元，不画其他零件、对照姿、sheet、文字或背景。保持主表指定造型、朝向与挂点。 | J90: 1 个透明 RGBA PNG 主体定稿；虚影/错帧效果仅放附属说明，实际主体不带不可拆多重残像。 | K90: 根节点为身体支撑投影的地面中心；母版 (768, 896)，朝右；口鼻可前伸但不移动根。 | L90: art_delivery/v1/abnormalities/ | M90: 待生成 | N90: ABN_N03_01
